{
  "name": "Aerial Servant",
  "source_page": 8,
  "raw_text": "Aerial Servant\nCLIMATETERRAIN:\nPlane of elemental air; astral\nplane, and ethereal plane\nFREQUENCY:\nVery rare\nORGANIZATION:\nSolitary\nACTIVITY CYCLE:\nAny\nDIET:\nSee below\nINTELLIGENCE:\nSemi- (2-4)\nTREASURE:\nNil\nALIGNMENT:\nNeutral\nNO: APPEARING:\nARMOR CLASS:\nMOVEMENT:\nFl 24 (A)\nHIT DICE:\n16\nTHACO:\n5\nNO: OF ATTACKS:\nDAMAGEIATTACK:\n8-32\nSPECIAL ATTACKS:\nSurprise\nSPECIAL DEFENSES:\n+1 or better weapon to hit\nMAGIC RESISTANCE:\nNil\nSIZE:\nL (8' tall)\nMORALE:\nElite (14)\nXP VALUE:\n10,000\nThe aerial servant is a semi-intelligent form of an air elemental\nnative t0 the elemental plane of air, the ethereal\nand the as-\ntral plane. An encounter with an aerial servant in the prime mate-\ntheir native planes . As\nhave no permanent lairs, aerial ser -\nrial plane is usually the result of a conjuration by\ncleric\nvants have a virtually limitless range and are not tied to any spe-\nWhen encountered in the material plane, aerial servants nor-\ncific territory:\nare particularly drawn to areas of extreme\nmally are invisible\nare dimly visible in their native planes,\nweather; such as the ether cyclones of the ethereal plane (sinuous,\nresembling legless humanoids made of sparkling blue smoke:\nserpentine columns of force) , the psychic wind storms of the as-\nhave empty eye sockets, a thin slash for a mouth, and two\ntral plane (hurricane-like areas of darkness) , and the aerial mael-\narms with\nhands and four thick fingers.\nstroms\nof\nthe\nplane\nof   elemental\nair\n(doughnut-shaped\ntornadoes) . Generally; aerial servants are able to avoid the dan-\nCombat:\nAn aerial servant generally avoids combat in its native\ngers of these phenomena_\nHowever, if a careless aerial servant is\nplanes. However, if attacked\nOr\nthreatened, it responds by at-\nup in one of these storms, there is a 5 % chance it will be\ntempting to\nand strangle its opponent\nThe aerial servant's\nblown in two, with each half becoming a separate aerial servant\nfirst successful roll to hit means it has grabbed its victim; in each\nThis is the only way aerial servants reproduce,\nan\nextremely pain-\nsuccessive round that it holds its victim, the aerial servant, ifit de-\nful process the aerial servants strive to avoid_\nsires, automatically inflicts 8-32 hp of damage\nAn aerial servant\nAerial servants will not voluntarily leave their home plane and\nis very strong and can easily carry weights in excess of 10,000\nhave no interest in material plane affairs_\nresent\nbeing sum-\npieces. A character must have a Strength of 18 to have any\nmoned by clerics to the prime material plane and will attempt to\nchance of breaking free. For each percentage point score the char-\ntheir missions as soon as\npossible in order to return home.\nacter has, there is a like chance to break free of the aerial servant's\ngrasp; for instance,\ncharacter with an 18/50% Strength has a\nAerial servants do not consume food for nourishment\n50 % chance of breaking free, while a character with a 00 % or 19\nInstead, they are refreshed and energized by being buffeted in the\nautomatically\nbreaks\nfree\n(If the\ncreature\nhas\nno\nplanar winds .\nperiods of calm weather cause aerial servants\nStrength rating,roll the appropriate number of the creature's Hit\nto grow listless and weak. If an aerial servant is not exposed to a\nDice and 16 HD for the aerial servant; if the creature s total is\nplanar wind in excess of 30 miles per hour for 30 consecutive\nhigher, it breaks free.\nit risks suffering damage; beginning on\n31,it has a 10 %\nAn aerial servant in the command of a cleric will not fight for\nchance per\nof losing 1d8 hp of damage. Aerial servants re-\nhim, but will complete any other assigned\nusually finding\ncover lost hit points at the rate of 1d8 per hour of being buffeted\nand returning an object or victim. If assigned to return a victim,\nby planar winds in excess of 30 miles per hour:\nare unaf-\nthe aerial servant grabs the victim as described above_\nAddition-\nfected by winds of the prime material plane.\nally; those attacked by an aerial servant in the material plane have\nAerial servants have no natural enemies.\nrarely associate\na -5\nsurprise modifier: If the summoning cleric does not protect\nwith other creatures, although\ndo have an affinity for air ele-\nhimself by casting protection from evil or by standing inside\nmentals, occasionally tagging along after them. However, air ele-\nprotective symbol, the aerial servant\nattempt to crush and\nmentals   avoid\nand  discourage\ncontact\nwith\naerial  servants,\nkill him. If the aerial servant is prevented from completing its as-\nconsidering them an inferior species.\nsigned mission , it becomes insane, returns to the cleric, and at-\ntempts to kill him.\nHabitat Society:\nAerial servants are not organized into fami-\ncommunities, Or any other social units.\ndo not collect\ntreasure\nAerial servants pass the time by soaring on the elemen-\ntal, astral, and ethereal winds, exploring the infinite mysteries of\nplane,\nthey\nThey\nThey\nThey\nlong\nlarge\ncaught\ngrab\nThey\ngold\ncomplete\nEcology:\ngrasped\nLong\nday\ndays,\nday\nduty;\nThey\nThey\nthey\nwill\nThey\nlies ,",
  "climate_terrain": "Plane of elemental air; astral",
  "frequency": "Very rare",
  "organization": "Solitary",
  "activity_cycle": "Any",
  "diet": "See below",
  "intelligence": "Semi- (2-4)",
  "treasure_type": "Nil",
  "alignment": "Neutral",
  "movement": "Fl 24 (A)",
  "hit_dice": "16",
  "thac0": "5",
  "special_attacks": "Surprise",
  "special_defenses": "+1 or better weapon to hit",
  "magic_resistance": "Nil",
  "size": "L (8' tall)",
  "morale": "Elite (14)",
  "xp_value": "10,000",
  "id": "aerial_servant"
}