{
  "name": "Air/Earth Elementals Air Earth",
  "source_page": 45,
  "raw_text": "Air/Earth Elementals\nAir\nEarth\nCLIMATE TERRAIN:\nair\nland\nFREQUENCY:\nVery rare\nVery rare\nORGANIZATION:\nSolitary\nSolitary\nACTIVITY CYCLE:\nDIET:\nAir\nEarth, metal, or gem\nINTELLIGENCE:\nLow (5-7)\nLow (5-7)\nTREASURE:\nNil\nNil\nALIGNMENT:\nNeutral\nNeutral\nNO. APPEARING:\nARMOR CLASS:\nMOVEMENT:\nFI 30 (A)\nHIT DICE:\n8, 12, or 16\n8, 12\n0r\n16\nTHACO:\n8 Hit Dice: 12\n8 Hit Dice: [2\n12 Hit Dice; 9\n12 Hit Dice:\n16 Hit Dice: 7\n16 Hit Dice:\nNO. OF ATTACKS:\nDAMAGE ATTACK:\n2-20\n4-32\nSPECIAL ATTACKS:\nSee below\nSee below\nSPECIAL DEFENSES:\n+2 weapon or better to hit\n+2 weapon or better to hit\nMAGIC RESISTANCE:\nNil\nNil\nSIZE:\nLto H (8' t0 16' tall)\nL to H (8' to 16' tall)\nMORALE:\n8-12 Hit Dice: Champion\n8-12 Hit Dice: Champion\n(15-16)\n(15-16)\n16 Hit Dice; Fanatic (17)\n16 Hit Dice: Fanatic (17)\nXP VALUE:\n8 Hit Dice: 3,000\n8 Hit Dice: 2,000\n12 Hit Dice: 7,000\n12 Hit Dice: 6,000\n16 Hit Dice: 11,000\n16 Hit Dice: 10,000\nAir elementals can be conjured in any area of open air where gusts\nThis type of common elemental appears\non\nthe Prime Material\nof wind\nare\npresent: The\ncommon air elemental appears\nas an\nPlane a5 & very\nlarge humanoid made of whatever types of dirt,\namorphous, shifting cloud when it answers its summons to the\nstones\nprecious metals,\nand gems it was conjured from.\nIt has a\nPrime Material Plane. They rarely speak, but their language can\ncold, expressionless Face, and its\nEwo eyes\n~sparkle like brilliant\nbe heard in the high-pitched shriek of a tornado or the low moan\nmultifaceted\ngems\nThough it has\nmouth-like opening in its\nof a midnight storm.\nface\nan earth elemental will rarely speak;\nTheir voices can be\nheard\nsilence of deep tunnels\nthe rumblings\nofearth-\nCombat:\nWhile air elementals are not readily tangible to the in-\nquakes, and the grinding of stone on stone.\nhabitants of planes other than its own, they can strike an Oppo-\nThough earth elementals travel very slowly; they are relentless\nnent with & strong, focused blast of air that, like a giant, invisible\nin the fulfillment of their appointed tasks. An earth elemental can\nFist\ndoes 2-20 points of damage\nThe extremely\nrate at\ntravel through solid ground\nor stone with no penalty to move-\nwhich these creatures can\nmove make them very useful on vast\nment\nOr\ndexterity:\nHowever,\nthese\nelementals\ncannot\ntravel\nbattlefields or in extended aerial combat: In fact, the air elemen-\nthrough water: they must either g0 around the body of water in\ntals mastery of its natural element gives it a strong advantage in\ntheir path or go under it, traveling in the ground. Earth elemen -\ncombat above the ground. In aerial battles, they gain a +1 to hit\ntals prefer the latter as it keeps them moving, more or less,\nin &\nand a\n+4t0 the damage\ninflict _\n~straight line toward their\nThe most feared power of an air elemental is its ability to form\nwhirlwind upon command\nthis Form, the air elemental\nCombat:\nEarth elementals will always\nto fight on the ground\nappears as a truncated, reversed\ncone\nwith a 10 foot bottom di-\nand will only rarely be tricked into giving Up that advantage.\nBe-\nameter and 30 foot\ndiameter: The height of the whirlwind de-\ncause\nof their close alliance t0 the rock and earth; these elementals\non\nthe Hit Dice of the elemental.\nAn air elemental of 8 Hit\ndo 4-32\ndamage (4d8) whenever they strike a creature\nDice will produce a whirlwind standing 40 feet tall; a 12 Hit Dice\nthat rests on the ground:\nelemental produces\nwhirlwind standing 60 feet tall; anda 16 Hit\nAgainst constructions with foundations in earth or stone\nearth\nDice elemental produces\nwhirlwind standing 80 feet tall. It takes\nelementals do great damage, making them extremely useful for\none full turn to form and dissipate this cone.\narmies sieging\nfortification\nFor example\nreinforced door;\nThis whirlwind lasts for one melee round\nsweeps away and\nwhich might require\nrounds to shatter\nconventional\nkills all creatures under three Hit Dice in the area of its cone\nand\nmethods,\ncan be smashed with ease by an earth elemental.\nThey\ndoes 2-16 points of damage to all creatures it fails to kill outright:\ncan even\nlevel\nsmall cottage in & Few rounds_\nIC, because of overhead obstructions, the whirlwind fails to reach\nAn earth elemental s effectiveness against creatures in the air Or\nits full height, it can only sweep up creatures under two Hit Dice\nwater is limited; the damage done by the elemental's fists on air-\nand do 1-8\nof damage t0 all others in its cone\nborne or waterborne targets is lessened by 2 points per die (to a\nminimum of\nof damage per die) .\nEarth elementals can be conjured in any area of earth or stone_\nAny\nAny\nAny\nAny\nthe\nrapid\ngoal.\nthey\nUsing\nty\ntop\npoints\npends\nfew\nusing\npoints\npoint",
  "climate_terrain": "air",
  "frequency": "Very rare",
  "organization": "Solitary",
  "diet": "Air",
  "intelligence": "Low (5-7)",
  "treasure_type": "Nil",
  "alignment": "Neutral",
  "movement": "FI 30 (A)",
  "hit_dice": "8, 12, or 16",
  "thac0": "8 Hit Dice: 12",
  "damage": "2-20",
  "special_attacks": "See below",
  "special_defenses": "+2 weapon or better to hit",
  "magic_resistance": "Nil",
  "size": "Lto H (8' t0 16' tall)",
  "morale": "8-12 Hit Dice: Champion",
  "xp_value": "8 Hit Dice: 3,000",
  "id": "air_earth_elementals_air_earth"
}