{
  "name": "Behir",
  "source_page": 12,
  "raw_text": "Behir\nCLIMATE TERRAIN:\nland\nFREQUENCY:\nRare\nORGANIZATION:\nSolitary\nACTIVE TIME:\nDIET:\nCarnivore\nTREESURENCE:\nSee below\n9\nALIGNMENT:\nNeutral evil\nNOJ\nAPPEARING:\n1-2\nARMOR CLASS:\nMOVEMENT:\n15\nHIT DICE:\n12\nTHACO:\nNO.OF ATTACKS:\n2 or 7\nDAMAGEIATTACK:\n2-8 (2d4)/2-5 (1d4 + 1) or 2-8\n(2d4)/6 X 1-6\nSPECIAL ATTACKS:\nLightning bolt\nSPECIAL DEFENSES:\nImmune t0 electricity; poison\nMAGIC RESISTANCE:\nNil\nSIZE:\nG (40' long)\nMORALE:\nChampion (15)\nXP VALUE:\n10,000\nThe behir is a snake-like reptilian monster whose dozen\nallow\nit t0 move with considerable\nand climb at fully half its nor-\nmal movement rate. It can fold its limbs close to its\nnarrow\nBehir range over & territory of about 400 square miles, often\nbody and slither in snake-fashion if it desires_\nThe head looks\nhigh up\na cliff face in a cave_\nmore\ncrocodilian than snake-like, but has no difficulty in opening\nBehir are never friendly with dragonkind, and will\nnever be\nits mouth wide enough to swallow prey whole, the way a snake\nfound coexisting in the same\ngeographical area with any type of\ndoes .\ndragon. If a dragon should enter a behir's territory; the behir will\nBehir have band-like scales of great hardness.\nTheir color\ndo everything it can to drive the dragon out_\nIf the behir fails in\nranges from ultramarine t0\nblue with bands of gray-brown\nthis task;\nit will move off t0 find a new home. A behir will never\nThe belly is\nblue . The two\nhorns curving back over the\nknowingly enter the territory of a dragon.\nhead look dangerous enough but are actually used for preening\nthe creature $ scales and not for fighting.\nBehir are useful t0 mages, priests, and alchemists for a\nnumber of concoctions. The horns of a behir can be used to brew\nCombat:\nA behir will attack its prey by first biting and then\nthe ink necessary to inscribe a lightning bolt scroll, and the sharp\nlooping its body around the victim and squeezing: If the latter at-\ntalons can likewise be used by a cleric to make the ink for a neu-\ntack succeeds, the victim\nis subject\nto six talon attacks next\ntralize poison scroll. The heart of the behir is one of the more\nround:\ncommon ingredients for ink for a protection from poison scroll.\nA behir can discharge a 20-foot\nstroke of electrical energy\nAs behir sometimes swallow prey whole, there is a 10 % chance\nonce every 10 rounds. This lightning bolt will cause 24 points of\nthat there will be some small items of value inside the monster:\ndamage unless a saving throw versus breath weapon is made\nIn\nMore often than not (60 %\nthese will be gems (10 x Q1. Other-\nthe latter case , the target takes only half damage\nwise, there is & 30% chance that there will be from 1-8 pieces of\nOn\na natural attack roll of 20 the behir swallows man-sized\njewelry and a 10 % chance that a single small magical object of an\nprey whole.\ncreature swallowed will lose !/ of its starting hit\nindegistible nature may be found. Such objects are never found in\npoints each round until it dies at the end of the sixth round\nThe\nbehir's lair; because the creature expels this waste and buries it\nbehir will digest its meal in 12 turns, and at that time the victim is\nelsewhere .\ntotally gone and cannot be raised from the dead. Note\nhowever;\nThe scales are valued for their hardness and color; and are\nthat a creature swallowed can\nto cut its way out of the behir s\nworth up to 500 gp to an armorer who can use them to fashion a\nstomach_\nThe inner armor class of the behir is 7,\nbut each round\nhighly ornate set of scale mail armor:\nthe creature is in the behir it subtracts 1 from the damage each of\nits attacks does\nThis subtraction is cumulative\nSO on the second\nmelee round there is a -2, on the third & -3, and 50 on.\nHabitat Society:\nBehir are solitary creatures, meeting others of\ntheir kind only t0 mate and hatch a clutch of 1-4 eggs\nThe Female\nthese eggs For eight months while the male hunts for the\nWhen the young hatch, they are immediately turned out of\nthe nest t0 fend for themselves\nand the adults separate_\nNewly hatched behir are about two feet\nBehir grow at a\nrate of eight feet per year until fully mature. Interestingly enough_\nnewly hatched behir do not have all of their legs, having instead\nonly six or eight. Additional\nof\ngrow slowly over time un-\ntil the creature has its full complement when it reaches adulthood\nAny\nDay\nlegs\nspeed\nlong'\nliving\ndeep\nlarge\npale\nEcology:\nlong\nAny\ntry\nguards\npair;\nlong:\npairs\nlegs",
  "climate_terrain": "land",
  "frequency": "Rare",
  "organization": "Solitary",
  "diet": "Carnivore",
  "treasure_type": "See below",
  "alignment": "Neutral evil",
  "movement": "15",
  "hit_dice": "12",
  "attacks": "2 or 7",
  "damage": "2-8 (2d4)/2-5 (1d4 + 1) or 2-8",
  "special_attacks": "Lightning bolt",
  "special_defenses": "Immune t0 electricity; poison",
  "magic_resistance": "Nil",
  "size": "G (40' long)",
  "morale": "Champion (15)",
  "xp_value": "10,000",
  "id": "behir"
}