{
  "name": "Beholder Beholder of the",
  "source_page": 13,
  "raw_text": "Beholder\nBeholder\nof the\nCLIMATETERRAIN:\nSubterranean\nocean\nFREQUENCY:\nVery rare\nVery rare\nORGANIZATION:\nSolitary\nSolitary\nACTIVITY CYCLE:\nAny\nDIET:\nOmnivore\nOmnivore\nINTELLIGENCE:\nExceptional (15-16)\n(11-12)\nTREASURE:\nL,S, T\nR\nALIGNMENT:\nLawful evil\nLawful evil\nNO.\nAPPEARING:\nARMOR CLASS:\n0/2/7\nMOVEMENT:\nFl 3 (B)\nSw 6\nHIT DICE:\n45-75 hp\n10-12\nTHACO;\n45-49 hp;ll\n10 HD: 11\nAnti-Magic\n50-59 hp:\n11-12 HD:\n60-69 hp: 7\n70 + hp: 5\nNO: OF ATTACKS:\nDAMAGEIATTACK:\n2-8\n2-8/2-8/1-6\nSPECIAL ATTACKS:\nMagic\nSee below\nSPECIAL DEFENSES:\nAnti-magic ray\nNil\nMAGIC RESISTANCE:\nSpecial\nNil\nSIZE:\nM (4'-6' diameter)\nS to M (3'-5' diameter)\nMORALE:\nFanatic (18)\nChampion (15)\nXP VALUE:\n14,000\n4,000\nThe beholder (also known as the eye tyrant or sphere of many eyes) is\nBecause of its particular nature the beholder is able to withstand the\nmost frequently found underground, although it will lair in desolate\nloss of its eyestalks, each taking from 8 to 12 hit points before being\nwildernesses\ntime t0 time\nlost. These members are not computed as part of its hit point damage\nThe globular body of this monster is supported by levitation, al-\npotential, and lost eyestalks will eventually grow back (one week per\nlowing it to float slowly about as it wills_\nthe sphere are 10 eye-\nlost member) . The body of the monster can withstand two-thirds of\n~stalks, while in its central area are\ngreat eleventh eye and\nits total damage potential, while the great central eye can withstand\nmouth filled with pointed teeth_\none-third this total. Thus,\nbeholder with 45 hit points can withstand\nBeholders can , speak their own language and\nwill often know\n30 hit points of damage to its body before\nkilled and the elev-\ntongues of other lawful evil creatures\nenth eye could withstand 15 points before ceasing to function. The\nbody of a beholder represents 75 % of potential hit area, the central\nCombat:\nThe body is protected by a hard chitinous covering with\neye and the eyestalks 10% each, and the 10 small eyes 5 %\nan Armor Class of 0. The creature $ eyestalks and eyes are also pro-\ntected, although less well, having armor classes of 2 and\n7 respec-\nHabitat Society:\nThe beholder is hateful, aggressive, and avari-\ntively:\ncious. It will usually attack immediately. If confronted by a particu-\nThe various eyes of a beholder each have a different function. Typ-\nlarly powerful party there is a 50 % chance it will listen to negotiations\nically only the central eye, plus 1-4 ofthose on stalks; are able to func-\n(either\nbribed not to attack or paying\na ransom t0 not be at-\ntion considering that an attack usually comes from an arc 90\ntacked, depending on the strength of the opposing party) .\nbefore the monster: If attacks come from 180 degrees double the num-\nber of eyestalks able to function, and for 270\nor 360\ndegrees\nEcology:\nAn eye from a stalk is an important ingredient in some pO-\ntriple or quadruple the number: Attacks from above enable all 10 eye-\ntions of levitation, and as such can be sold t0 mages or alchemists for\nstalks to function, but the central eye cannot. Functions of the eyes\nas much as 50 gp each:\nare:\nEye of the\nCharm person\n2\nCharm monster\nThe evil eye of the\ndwells only at great depths, floating slowly\nSleep\nabout, and stalking prey:\nTelekinese 250 pound weight\nhave two crab-like pincers which inflict 2-8 (2d4) points of\nFlesh to stone ray (30 yard range)\ndamage each and a wide mouth full of\nteeth that does 1-6 points\nDisintegrate ray (20\nrange)\nof damage.\nFear (as a wand)\nIts primary weapons, however,\nare its eyes. The creature s\nSlow\ncentral eye emits a cone of\nblinding light 5' wide at its start, 30'\nCause serious wounds (50\nand 20' wide at its base. Those in this cone must save versus poison or\nbe stunned for 2-8 (2d4) rounds.\nrange)\n10\nDeath ray (40 yard range)\nThe eye of the deep also has two smaller eyes on\nstalks with\nCentral eye   Anti-magic ray (140\nrange)\nwhich it is able to create an illusion. Acting independently the small\neyes are able to cast hold person and hold monster spells respectively:\nThe anti-magic ray covers\na 90o arc.\nAll magic within the area\nThis monster has an Armor Class of 5 everywhere, including its\nceases t0 function as\nas it remains in the area, Spells cast from\neyes and eye stalks. If its eyestalks are severed\nwill grow back in\nwithin the area Or passing through it automatically fail.\nabout a week\nEye\nDeep\nAny\ndeep\nDay\nVery\nRay\nfrom\nAtop\nlarge\nbeing\nbeing\ndegrees\ndegrees\nDeep\ndeep\nThey\nsharp\nyard\nlarge\nlong'\nyard\nlong\nyard\nlong\nthey",
  "climate_terrain": "Subterranean",
  "frequency": "Very rare",
  "organization": "Solitary",
  "activity_cycle": "Any",
  "diet": "Omnivore",
  "intelligence": "Exceptional (15-16)",
  "treasure_type": "L,S, T",
  "alignment": "Lawful evil",
  "ac": "0/2/7",
  "movement": "Fl 3 (B)",
  "hit_dice": "45-75 hp",
  "thac0": "45-49 hp;ll",
  "special_attacks": "Magic",
  "special_defenses": "Anti-magic ray",
  "magic_resistance": "Special",
  "size": "M (4'-6' diameter)",
  "morale": "Fanatic (18)",
  "xp_value": "14,000",
  "id": "beholder_beholder_of_the"
}