{
  "name": "Bookworm",
  "source_page": 15,
  "raw_text": "Bookworm\nCLIMATE/TERRAIN:\nland\nFREQUENCY:\nRare\nORGANIZATION:\nSolitary\nACTIVE TIME:\nDIET:\nSpecial\nINTELLIGENCE:\nNon- (0)\nTREASURE:\nSee below\nALIGNMENT:\nNeutral\nNO.APPEARING:\n1-2 (10-40)\nARMOR CLASS:\nMOVEMENT:\n12 , Br 3\nHIT DICE:\n1/4 (2 hit points)\nTHACO:\n20\nNO: OF ATTACKS:\nNil\nDAMAGEIATTACK:\nNil\nSPECIAL ATTACKS:\nSee below\nSPECIAL DEFENSES:\nSee below\nMAGIC RESISTANCE:\nNil\nSIZE:\nT (1 inch long)\nMORALE:\nSpecial\nXP VALUE:\n15\nThis small worm, only one inch\nis greatly feared by mages\nbecause it is attracted t0 paper in all forms. It can smell scrolls,\nmaps, arcane tomes\nand\nbooks at a distance of 60 feet_\nNormally a dull gray color;\na bookworm's chameleon-like abil-\nWhen an adventurer is careless enough to encounter\na new\nities enable it to instinctively blend into any background. Its high\nbrood of bookworm larvae, he can inflict incredible damage by\nArmor Class is due to its speed and agility If found motionless the\ncarrying them unwittingly with him to other places\nA handful of\nbookworm is AC 9\nlarvae\nin a backpack\ntraveling\ncity street can find\nnew homes readily, destroying the libraries of sages, temples,\nCombat:\nThe bookworm initially imposes a -7 on the surprise\nmagic-users, and governments in the process.\nrolls of adventurers because of its color-changing ability If the\nvictim can see invisible\nthe bookworm s modifier is re-\nEcology:\nA bookworm will always be attracted to the largest\nduced to -4. Note that these chances apply even to creatures nor-\nvolume of paper in an area\nmally hard to surprise (like rangers and monks), because of its\nBecause of its unusual diet, the bookworm is a valuable\nsmall size ,\ngreat in proportion to its size), and inof-\ndient in various alchemical preparations. Chief among these is the\nfensive nature\nIf the bookworm does initially\nsurprise, it\nink used to inscribe protection from magic scrolls. Because it is\nmay then be discovered (25 %\non the outside of a victim s leg or\nthe residual ink in the bookworm s body that is the \"active ingre-\npack. Otherwise, it will remain unnoticed unless the victim bear-\ndient'\nin this case, the darker the bookworm, the better it is for\npaper hears the creature s noisy munching (base 50 % chance\nthis purpose.\nper round)\nA\nfeeding bookworm is motionless until attacked_\nThe bookworm itself can be a useful tool under the right cir-\nAfter any attack it will flee (if possible) by first jumping 10 feet\ncumstances. Releasing a bookworm in a mage s tower could exact\nand then crawling back to its lair at top\nrevenge of a most lasting sort: There are\nfew cases on record\nA bookworm can burrow through dead wood or leather at a\nalso, of criminals gaining release from prison when important\nrate of 3 inches per round and through\nleather scroll case or\ndocuments turned up missing during their trials. Such use of\npack in one segment but cannot digest living matter of any type_\nbookworm is both difficult and dangerous: difficult because it is\nIt will destroy spell books and scrolls at the rate of one\nlevel\nhard to\nbookworm alive under captivity and dangerous\nper round (i.e., five rounds for a scroll of a single Sth-level spell) _\nbecause the bookworm, once released\nmay not leave its owner;\nReleasing\nbookworm at an enemys hideout and then\nit\nHabitat Society:\nA bookworm lair is always a library or store-\nfollow you\nis an unpleasant experience at best.\nroom of some kind\nwhether in use Or\n~forgotten . When\nbookworm is encountered, there may be undamaged paper items\nremaining (30% chance) . In such cases, the surviving objects will\nbe as Follows:\na map (60 % ) , scroll (30% ) , or an arcane work of\nmage level 1-8 (10 % ) . If\nbooks are indicated,\nshould be\nappropriate for the level ofthe characters finding them but will be\n0-90 % (1d10-1) destroyed by the worms\nA\nbreeding\nof bookworms\n80 eggs; about half of these\nhatch a month later. The larvae have less than an hour to find pa-\nper nourishment, Or\ndie. When first hatched, the larvae are\npure white, but\ndevelop their dull gray color from ingesting\nthe ink on the paper that makes up their diet. Unfortunately the\nbuildup of ink in their systems eventually kills them. The average\nlifespan of\nbookworm is two\nor three years.\nA\nbookworm\nbreeds only once in its lifetime, after which it dies.\nAny\nAny\nlong'\nspell\nhiding\ndown\nthings.\ningre-\nspeed\n(very\ngain\ning\nspeed,\nspell\nkeep\nhaving\nhome\nlong-E\nspell\nthey\npair\nlays\nthey\nthey",
  "climate_terrain": "land",
  "frequency": "Rare",
  "organization": "Solitary",
  "diet": "Special",
  "intelligence": "Non- (0)",
  "treasure_type": "See below",
  "alignment": "Neutral",
  "number_appearing": "1-2 (10-40)",
  "movement": "12 , Br 3",
  "hit_dice": "1/4 (2 hit points)",
  "thac0": "20",
  "attacks": "Nil",
  "damage": "Nil",
  "special_attacks": "See below",
  "special_defenses": "See below",
  "magic_resistance": "Nil",
  "size": "T (1 inch long)",
  "morale": "Special",
  "xp_value": "15",
  "id": "bookworm"
}