{
  "name": "Brownie",
  "source_page": 16,
  "raw_text": "Brownie\nCLIMATE TERRAIN:\nTemperate rural\nFREQUENCY:\nRare\nORGANIZATION:\nTribal\nACTIVITY CYCLE:\nNight\nDIET:\nVegetarian\nINTELLIGENCE:\nHigh (13-14)\nTREASURE:\nO, R Q\nALIGNMENT:\nLawful\nNO: APPEARING:\n4-16\nARMOR CLASS:\nMOVEMENT:\n12\nHIT DICE:\n1/2\nTHACO:\n20\nNO:OF ATTACKS:\nDAMAGEIATTACK:\n1-2 (weapon)\nSPECIAL ATTACKS:\nSpells\nSPECIAL DEFENSES:\nSave as %th level cleric\nMAGIC RESISTANCE:\nAs above\nSIZE:\n(2')\nMORALE:\nSteady (11-12)\nXP VALUE:\n175\nBrownies are small, benign humanoids who may be very dis-\ntantly related to\nhalflings. Peaceful and friendly, brownies fre-\nquent pastoral areas, where\nlive by foraging and gleaning.\nBrownies stand no more than 2' tall and are exceedingly nim-\nmoral standards\nthe brownie will secretly enter the household,\nble_\nresemble small elves with brown hair and bright blue\nAt night\nwhile the residents are asleep, the brownie will perform\neyes. Brownies wear bright colored garments made from wool or\na variety of helpful tasks. He will spin, sweep, bake bread, repair\nlinen with\nornamentation\nBrownies normally carry leather\nFarm implements,\nfoxes out of the hen house , mend clothes,\npouches containing tools for the repair of leather;\nwood and\nand s0 forth. Ifa thief creeps into the house silently the brownie is\nmetal;\nsure to make enough noise to awaken the residents. Watchdogs\nBrownies\ntheir own language in addition to the common\nand domestic animals all consider brownies friendly and will\ntongue of men and those of elves, pixies, sprites, and halflings\nnever attack or bark at them.\nAll brownies ask in exchange for their labor is\nlittle milk\nCombat:\nBrownies prefer not to engage in combat, and will\nsome bread, and an occasional bit of fruit. Etiquette demands, in\nonly do so if threatened. Angry brownies\nrarely meet their\nfact, that other than the giving of such provisions, no notice be\nfoes in hand to hand combat, relying instead\non their\nmagical\ntaken of the brownie\nIf the residents boast about the presence of\nabilities.\nthe brownie , he will vanish.\nSince their senses are unusually keen it is impossible to surprise\nBrownies are not greedy, but\ndo have small hoards of\nbrownies.\nare\nsuperb at blending into their surroundings\ncoins and gems which\nhave taken from\nmonsters Or re =\nquickly and can thus become all but invisible when they choose to\nceived as gifts from grateful humans. A brownie will sometimes\ndo so. This, combined with their great agility gives them an Ar-\nleave his treasure in\na location where a\nperson in need is\nmor Class of 3.\nbound to find it.\nBrownies will use their magical\nt0 harass, confuse,\nOr\nStrangers and outsiders will be constantly watched by the\ndrive away their enemies. They can use the following\nonce\nbrownies of the community until their motives are ascertained. If\nper\nprotection from evil,\nventriloquism, dancing lights_\nthe brownies decide that the stranger is harmless, he will be left in\ncontinual light, mirror image (3 images) , confusion, and dimen-\npeace . If not, the brownies will unite and drive the intruder out.\nsion door.\nBrownies know every nook and cranny of the areas\nlive\nIf cornered and unable to employ their spells, brownies\nin, and thus make excellent guides. If asked politely; there is\nfight with their short swords.\n50 % chance that a brownie will agree t0 act as a\nguide for adven -\nturers\nHabitat Society:\nBrownies   dwell in rural\nareas,\noften\nliving\nclose to or on farms as they are fascinated by farm life. Brownies\nEcology:\nBrownies  are basically vegetarians,\nwho live   very\nmake their homes in small burrows Or abandoned buildings.\ncomfortably on the byproducts of agricultural life.\nmake ef -\nAlthough\nare\nsolitary creatures they will often meet to dis-\nficient use of leftovers too small for humans to notice.\nWhen\ncuss local affairs .\nare very particular about the communities\nbrownies glean from fields,\ndo so after harvest, gathering\nthey live in, and will set up their homes only in orderly; lawful\nand fruits which might otherwise be wasted,\nareasa\nBrownies live by harvesting wild fruits and gleaning\nfrom\nfarmer' s field. Being honest to the core;\na brownie\nwill always\nperform some service in exchange for what is taken. A brownie\nmight milk a farmer'$ cows and take &\nquantity of milk for\nhimself .\nSome brownies will g0 so far as to become house brownies. He\nwill observe the families in a given area, and if one meets his high\ngood\nTiny\nthey\nThey\nkeep\ngold\nspeak\nwill\nthey\nthey\nevil\nThey\ngood\nspells\nspells\nday:\nthey\nwill\nThey\nthey\nthey\nThey\ngrains\ngood\ngrain\nsmall",
  "climate_terrain": "Temperate rural",
  "frequency": "Rare",
  "organization": "Tribal",
  "activity_cycle": "Night",
  "diet": "Vegetarian",
  "intelligence": "High (13-14)",
  "treasure_type": "O, R Q",
  "alignment": "Lawful",
  "number_appearing": "4-16",
  "movement": "12",
  "hit_dice": "1/2",
  "thac0": "20",
  "special_attacks": "Spells",
  "special_defenses": "Save as %th level cleric",
  "magic_resistance": "As above",
  "size": "(2')",
  "morale": "Steady (11-12)",
  "xp_value": "175",
  "id": "brownie"
}