{
  "name": "Bugbear",
  "source_page": 17,
  "raw_text": "Bugbear\nCLIMATETERRAIN:\nsubterranean\nFREQUENCY:\nUncommon\nORGANIZATION:\nTribal\nACTIITY CYCLE:\nDIET:\nCarnivorous\nINTELLIGENCE:\nLow t0 average (5-10)\nTREASURE:\nIndividual: J, K, L; M; (B)\nALIGNMENT:\nChaotic evil\nNO: APPEARING:\n2-8 (2d4)\nARMOR CLASS:\n5 (10)\nMOVEMENT:\nHIT DICE:\n3+1\nTHACO:\n17\nNO. OF ATTACKS:\nDAMAGEJATTACK:\n2-8 (2d4) or by weapon\nSPECIAL ATTACKS:\nSurprise ,\n+2 to damage\nSPECIAL DEFENSES:\nNil\nMAGIC RESISTANCE:\nNil\nSIZE:\nL (7' tall)\nMORALE:\nSteady to Elite (11-13)\nXP VALUE:\n120\nBugbear leader:\n175\nBugbear chief:\n175\nBugbear shaman:\n175\nBugbears are giant,\ncousins of goblins who frequent the\nTheir great strength gives them a\n+3 to all damage inflicted in\nsame areas as their smaller relatives .\nmelee combat.\nBugbears are\nand very muscular; standing 7' tall. Their\nIE 24 or more bugbears are encountered,\nwill have a chief\nhides range from light yellow to yellow brown and their thick\nin addition to their leaders. Chiefs have between 28 and 30 hit\ncoarse hair varies in color from brown to brick red. Though\npoints, an Armor Class of 3, and attack as\n4 hit die monsters.\nvaguely humanoid in appearance, bugbears seem to contain the\nChiefs are so strong that\n+4 bonus to all damage\nblood of some\ncarnivore. Their eyes recall those of some\ncaused in melee . Each chief will also have a sub-chief who is iden -\nsavage bestial animal, being greenish white with red pupils, while\ntical to the leaders described above.\ntheir ears are wedge shaped, rising from the top of their heads. A\nIn\nlair, half of the bugbears\nbe females and young who\nbugbear' $ mouth is full of\nsharp fangs.\nwill not fight except in a life Or death situation. If\nare forced\nBugbears have a nose much like that of a bear with the same\ninto combat, the females attack as hobgoblins and the young as\nfine sense of smell. It is this feature which earned them their\nkobolds_\nname, despite the fact that\nare not actually related to bears in\nThe species survives primarily by hunting: They have no com-\nany way: Their tough leathery hide and\nsharp nails also look\npunctions about\nanything they can kill, including humans,\nsomething like those of a bear; but are far more dexterous.\ngoblins, and any monsters smaller than themselves .\nare also\nThe typical bugbears sight and hearing are exceptional,\nand\nfond of wine and strong ale, often drinking to excess.\ncan move with amazing agility when the need arises.\nBugbears are territorial, and the size of the domains vary with\nbear eyesight extends somewhat into the infrared, giving them\nthe size of the group and its location. It may be several square\ninfravision out to 60 feet_\nmiles in the wilderness, Or a narrow\nmore restricted area in an\nThe bugbear language is a foul sounding mixture of gestures,\nunderground region.\ngrunts, and snarls which leads many t0 underestimate the intelli-\nIntruders are considered\na valuable source of food and trea-\ngence of these creatures. In addition, most bugbears can speak the\nsure, and\nbugbears rarely negotiate. On occasion,\nwill par-\nlanguage of goblins and hobgoblins.\nif\nthink\ncan\nsomething exceptional by it.\nBugbears sometimes take prisoners to use as slaves.\nCombat:\nWhenever possible, bugbears prefer to ambush their\nExtremely greedy, bugbears love glittery;\nobjects and\nfoes. They impose a -3 on others' surprise rolls.\nweapons.\nare always on thelookout to increase their hoards\nIf a party looks\ndangerous, bugbear scouts will not hesitate to\nof coins, gems, and weapons through plunder and ambush\nfetch reinforcements. A bugbear attack will be tactically sound, if\nnot brilliant ,\nwill hurl small weapons, such as maces, ham-\nEcology:\nBugbears have two main goals in life: survival and\nmers, and spears before closing with their foes. If\nthink\ntreasure ,\nare\ncarnivores, winnowing out the weak\nare outnumbered or overmatched, bugbears will retreat, prefer-\nand careless adventurer; monster and animal. Goblins are always\nto\nto\nfight another\non their toes when\nbugbears are present, for the weak or stupid\nquickly end up in the stewpot.\nHabitat Society:\nBugbears prefer t0 live in caves and in under-\nground locations. A lair may consist of one\ncavern\nOr\ngroup of caverns\nare well-adapted to this life, since they\noperate equally well in daylight and darkness.\nIf a lair is uncovered and 12 or more bugbears are encountered\nwill have a leader. These individuals have between 22 and 25\nhit points, an Armor Class of 4, and attack as 4 hit die monsters\nAny\nAny\nhairy\nJarge\nthey\nthey\ngain\nlarge\nwill\nlong\nthey\nthey\nlong\neating\nThey\nthey\nBug-\nthey\nley\nthey\nthey\ngain\nshiny\nThey\nThey\nthey\nthey\nThey\nsuperb\nlive\nring\nday:\nlarge\nThey\nthey",
  "climate_terrain": "subterranean",
  "frequency": "Uncommon",
  "organization": "Tribal",
  "diet": "Carnivorous",
  "intelligence": "Low t0 average (5-10)",
  "treasure_type": "Individual: J, K, L; M; (B)",
  "alignment": "Chaotic evil",
  "number_appearing": "2-8 (2d4)",
  "ac": "5 (10)",
  "hit_dice": "3+1",
  "thac0": "17",
  "attacks": "DAMAGEJATTACK:",
  "special_attacks": "Surprise ,",
  "special_defenses": "Nil",
  "magic_resistance": "Nil",
  "size": "L (7' tall)",
  "morale": "Steady to Elite (11-13)",
  "xp_value": "120",
  "id": "bugbear"
}