{
  "name": "Carrion Crawler",
  "source_page": 18,
  "raw_text": "Carrion Crawler\nCLIMATETERRAIN:\nSubterranean\nFREQUENCY:\nUncommon\nORGANIZATION:\nSolitary\nACTIVITY CYCLE:\nDIET:\nCarnivorous\nINTELLIGENCE:\nNon - (0)\nTREASURE:\nB\nALIGNMENT:\nNeutral\nNO. APPEARING:\n1-6\nARMOR CLASS:\n3/7\nMOVEMENT:\n12\nHIT DICE:\n3+1\nTHACO:\n17\nNO:\nOF ATTACKS:\nDAMAGEIATTACK:\n1-2\nSPECIAL ATTACKS:\nParalysis\nSPECIAL DEFENSES:\nNil\nMAGIC RESISTANCE:\nNil\nSIZE:\nL (9' long)\nMORALE:\nSpecial\nXP VALUE:\n270\nThe carrion crawler is a scavenger of subterranean areas, feeding\nprimarily upon carrion. When such food becomes scarce,\never, it will attack and kill living creatures.\nThe crawler looks like & cross between a giant green cutworm\nfiercely for the same food. If 2 crawlers have made a kill or\nand a cephalopod. Like so many other hybrid monsters, the car-\ndiscovered carrion ,\nwill often fight over the food, sometimes\nrion crawler may well be the result of genetic experimentation by\nkilling one another in the process.\nmad, evil wizard.\nThe carrion crawler mates once a year. Several days after mat-\nThe monster's head\nwhich is covered with\ntough hide that\nthe female will g0 off in search of a\nkill. When she has\ngives it Armor Class 3, sprouts eight slender; writhing tentacles.\nfound or killed an adequate food supply she\nabout 100 eggs\nThe body of the carrion crawler is not well protected and has an\namong the carrion. The grubs hatch one week later and begin\narmor class of only 7\nThe monster is\naccompanied by\na rank\nfeeding:\nfetid odor which often gives warning of its approach.\nMaternal care ceases once the eggs have been laid and it is not\nuncommon for eggs to later be eaten by the female who laid them.\nCombat:\nThe carrion crawler can move along walls, ceilings\nFemales die a few weeks after laying their eggs, exhausted by the\nand passages very quickly; using its many clawed feet for trac-\neffort: Males live only a short time longer; having mated with as\ntion\nmany females as\npossible. Grubs have been known to consume\nWhen attacking, the monster lashes out with its 2'\ntenta-\none another in\nfeeding frenzies, and are a favorite food of adult\ncles, each of which produces a sticky secretion that can paralyze\ncarrion crawlers. Few of the grubs reach maturity;\nthose who\nits victims for 2-12 turns\nA save versus\nparalyzation is allowed to\ndo have eaten voraciously and will achieve their full size in a sin-\nescape these effects.\nkill paralyzed creatures with their bite\ngle\nWhen\nreach\nmaturity;\nthe mating cycle begins\nwhich inflicts 1-2 points of damage. The monster will always at-\nagain\ntack with all of its tentacles:\nThese monsters exist on the most basic instinctual level, having\nCarrion crawlers are non-intelligent, and will continue to at-\nno more intelligence than earthworms or most insects. The car-\ntack as\nas any of their opponents are unparalyzed. Groups of\nrion crawler is driven by two urges: food and reproduction. It has\ncrawlers attacking together will not fight in unison, but will each\nabsolutely no interest in the collection of treasure.\nconcentrate on paralyzing as many victims as\ncan;\nWhen\nseeking out prey;\nrely primarily on their keen senses of sight\nEcology:\nThe carrion crawler provides the same useful, if dis-\nand smell. Clever  travelers have been known\nto fool\nan\nap-\nagreeable, function that jackals, vultures, and crows perform_\nproaching carrion crawler with\nsight and smell illusion, thus\nLike so many other predators carrion crawlers instinctively prey\ngaining time t0 make\ntheir escape.\non the weak, sick, and foolish. In the\nrun, this has a benefi-\ncial effect on the prey, strengthening its gene pool. The carrion\nHabitatiSociety:\nCarrion crawlers are much-feared denizens of\ncrawler also works wonders in over crowded caverns, quickly\nthe\nunderground world.\nlive in lairs, venturing out in search\neliminating population problems among the weaker monsters.\nof carrion or food every few\nSome underground inhabit-\nThus, the life\nof the crawler is inextricably linked to those of\nants such as\ngoblins and trolls will make use of carrion crawlers\nits prey\nwhen the prey flourishes s0 does the crawler:\nby leaving the bodies of dead foes out in designated areas. This\nkeeps the creatures at a\ndistance from their own homes and\nencourages them to \"patrol\" certain areas: Some orcs have been\nknown to chain live prisoners near the lairs of these fearsome\nmonsters.\nCarrion crawlers will sometimes live with a mate Or in a small\ngroup numbering no more than 6. This does not mean that they\ncooperate in hunting, but merely share the same space and com-\nAny\nhow-\npete\nthey\nlarge\ning'\nlays\nlong\nbut\nthey\nThey\nyear:\nlong\nthey\nthey\nlong\ngood\nThey\ncycle\ndays.\ngood",
  "climate_terrain": "Subterranean",
  "frequency": "Uncommon",
  "organization": "Solitary",
  "diet": "Carnivorous",
  "intelligence": "Non - (0)",
  "treasure_type": "B",
  "alignment": "Neutral",
  "number_appearing": "1-6",
  "ac": "3/7",
  "movement": "12",
  "hit_dice": "3+1",
  "thac0": "17",
  "damage": "1-2",
  "special_attacks": "Paralysis",
  "special_defenses": "Nil",
  "magic_resistance": "Nil",
  "size": "L (9' long)",
  "morale": "Special",
  "xp_value": "270",
  "id": "carrion_crawler"
}