{
  "name": "Catoblepas `",
  "source_page": 19,
  "raw_text": "Catoblepas\n`\nCLIMATE/TERRAIN:\nswamp\nFREQUENCY:\nrare\nORGANIZATION:\nSolitary\nACTIVITY CYCLE:\nDay\nDIET:\nOmnivore\nINTELLIGENCE:\nSemi (2-4)\nTREASURE:\n(C)\nALIGNMENT:\nNeutral\nNO. APPEARING:\n1-2\nARMOR CLASS:\nMOVEMENT:\nHIT DICE:\n6 +2\nTHACO:\n15\nNO: OF ATTACKS:\nDAMAGEIATTACK:\n1-6 +stun\nSPECIAL ATTACKS:\nGaze causes death\nSPECIAL DEFENSES:\nNil\nMAGIC RESISTANCE:\nNil\nSIZE:\nL (6' tall at shoulder)\nMORALE:\nSteady (11-12)\nXP VALUE:\n975\nThe catoblepas is a bizarre, loathsome creature that inhabits dis-\nmal swamps and marshes. Its most terrifying features are its\nbloodshot eyes, from which emanate a deadly ray:\nThe body of the catoblepas is like that of a large, bloated buf-\ntall stand of reeds Or other marsh plants. The creature has little\nfalo, and its\nare\nstumpy; like those of a pygmy elephant or a\nfear of being disturbed in its lair, since it is frequently the most\nhippopotamus. Its\nsnakey tail is swift and strong, and can\nFeared carnivore in the swamp:\nmove with blinding speed. The head of the catoblepas is perched\nThe catoblepas mates for life and when more than one catoble-\nupon a\nweak neck\nand would be much like that of a wart-\npas is encountered\nwill be\nmated pair; There is\na 10 %\nexcept that the catoblepas is\nchance that the couple will have a single offspring with them_\nAn\nimmature catoblepas will have half the Hit Dice of an adult . It\nCombat:\nIn combat, the catoblepas relies on two forms of at-\ntakes almost nine years for the\noffspring to reach youthful matu-\ntack\nrity and an adult female will bear but one child every 10 or 12\nFirst, it will use its strong, snaky tail to strike and stun its foes.\nyears. Both the male and the female will cooperate in raising the\nAnyone struck by the tail suffers 1-6 points of damage and has a\noffspring\nbase 75 % chance of being stunned for 1-10 melee rounds. The\nWhen the catoblepas ventures forth to hunt it eats fish, marsh\nbase chance of\nstunned is lowered by 5% for every level\nbirds,   eels,\nwater\nrats,\namphibians,  snakes;\nand\nother\nabove first,\nor for each additional hit die in the case of monsters\nswamp animals. The catoblepas usually stuns its prey with\ntail\nand animals.\nand then kills it with its gaze\nDespite the\nof a tail strike, the catoblepas' second mode\nThe catoblepas is an opportunistic predator when it hunts and\nof attack is by far the more fearsome of the two, The gaze of the\nit is not above eating carrion_\nSince it is semi\n~intelligent,\nit will\ncatoblepas emanates & deathray, with a 60\nrange\ncrea-\ntreat parties of humans with respect, preferring to size them up\nture meeting its gaze dies without a saving throw. Ifa party is sur-\nfirst. Asa rule, it will not attack unless it is hunting or feels that its\nprised by & catoblepas, there isa 1 in 6 chance that someone in the\nmate or\noffspring is threatened. Being long-lived (150 t0 200 years\ngroup has met the creature $ gaze\nThose who close their eyes or\nor 50) and semi-intelligent, the catoblepas is capable of learning\nact with their eyes averted can still be affected by the deathray\nfrom the mistakes of earlier encounters and hunts.\nbut a saving throw versus death magic is allowed_\nThe catoblepas has no special interest in wealth, and the listed\nSince the neck of the creature is very weak\nit has only\na 25 %\ntreasure type is the result of victorious encounters with intruders\nchance of raising its head and\nthe deathray on subsequent\nIt attaches no value to the coins, gems, and occasional magical\nrounds. If the catoblepas and its target are both relatively still, this in-\nitems strewn about the lair;\ncreases\nby 15 % per melee round. If the catoblepas is forced to follow\nquick motions it has only a 10% chance of raising its head\nEcology:\nThe catoblepas has no natural enemies, since its gaze\nIf more than one catoblepas is attacking, the monsters will co-\nprovides it with more than adequate protection from even the\noperate with one another; attempting to herd their targets into a\nfiercest of predators\ncrosstire.\nHabitat Society:\nFor the most part, the catoblepas is a meander-\ncreature that wanders about its swamp\nnibbling on marsh\ngrasses and the like. Once & month; usually under the light of the\nfull moon , the catoblepas seeks out meat to round out its diet . It is\nat this time that the catoblepas is most likely to be encountered by\nadventurers ,\nThe lair of the catoblepas is usually some sort of sheltered place\nwhere the ground is Firm . More often than not it is surrounded by\nAny\nVery\nlarge\nlegs\nlong\"\nlong\nthey\nhog\nuglier;\nbeing\nlarge\nits\n'danger\nvard\nAny\nusing\ning",
  "climate_terrain": "swamp",
  "frequency": "rare",
  "organization": "Solitary",
  "activity_cycle": "Day",
  "diet": "Omnivore",
  "intelligence": "Semi (2-4)",
  "treasure_type": "(C)",
  "alignment": "Neutral",
  "number_appearing": "1-2",
  "hit_dice": "6 +2",
  "thac0": "15",
  "special_attacks": "Gaze causes death",
  "special_defenses": "Nil",
  "magic_resistance": "Nil",
  "size": "L (6' tall at shoulder)",
  "morale": "Steady (11-12)",
  "xp_value": "975",
  "id": "catoblepas"
}