{
  "name": "Cave Fisher",
  "source_page": 22,
  "raw_text": "Cave Fisher\nCLIMATE TERRAIN:\nSubterranean\nFREQUENCY:\nRare\nORGANIZATION:\nGroup\nACTIVITY CYCLE:\nNight\nDIET:\nCarnivorous\nINTELLIGENCE:\nSemi- (2-4)\nTREASURE:\nALIGNMENT:\nNeutral\nNO. APPEARING:\n1-4\nARMOR CLASS:\nMOVEMENT:\n1\nHIT DICE:\nTHACO:\n17 or 15 (see below)\nNO;\nOF ATTACKS:\nDAMAGEIATTACK:\n2-8 (2d41/2-8 (2d4)\nSPECIAL ATTACKS:\nAdhesive trapline\nSPECIAL DEFENSES:\nSee below\nMAGIC RESISTANCE:\nNil\nSIZE:\nM (7' long)\nMORALE:\nSteady (11-12)\nXP VALUE:\n175\nThe cave fisher is a\ninsectoid that has adapted to life below\nground: It combines many of the characteristics of a spider and a\nlobster;\nThe cave fisher has a hard, chitinous shell of overlapping plates\nIair: Their filaments are always strung before their lair, and\nand eight\nThe 6 rear\nare used for movement and traction\nattempt to kill anything\ntrap, often storing food for future\non\nstony walls and corridors\nBecause of these limbs, the fisher\nuse\nhas no difficulty in moving up and down vertical walls. The front\nTheir territories are very small, and never\nthan about\nof\nare equipped with powerful pincers, which are used\n300 feet to either side of the lair: Anything man-sized or smaller is\nfor\nkilling and dismembering prey: The most unusual feature of\nconsidered fair game by the cave fisher and halflings are thought\nthe cave fisher is its\nsnout, which can fire a strong, adhesive\nto be tasty treats\nA single cave fisher would never attack a\nfilament. The monster can also use\nadhesive to anchor itself in\nwell armed party for the sake of a single meal. Still,\nare cun\nplace on walls and ledges _\nning, anda group ofthe monsters might reel in their filaments and\nattempt an ambush if\nthought they could\naway with it. If\nCombat:\nThe cave fisher has two ways of hunting: Its preferred\nhunting in one area becomes scarce, the cave fisher will simply\nmethod is to string its\nfilament in the vicinity of its lair: The\nfind a new area t0 hunt\nwhere the small game is more\nplentiful\nfilaments are thin and strong, making them exceedingly difficult\nand careless .\nto detect or cut. There is only a 20 % chance of noticing the strand\nLike all predators, the cave Fisher is interested in survival. This\nat 10' , and no chance at all of seeing them at a greater distance. A\nmeans a steady supply of food and a mate. Females\neggs in the\ndetect snares and pits\nwill reveal\nstrand_\nThe filament is\nvicinity ofthe lair, which\nprotect from predators. The young\ncoated with an adhesive which can only be dissolved by liquids\nscatter when the eggs hatch, seeking lairs of their own .\nwith a\nhigh alcohol content (such as the cave fisher s blood)\nThe\nAlthough the cave fisher does not collect treasure, its lair is of-\nfilaments can only be cut by +1 or better edged weapons.\nten strewn with the possessions of its former victims.\nThe fishers favorite food are small, flying creatures like bats.\nEver opportunistic, they are constantly trying to vary their diet\nThe cave fisher preys primarily on small flying game;\nby trapping\ncareless adventurer; foolish goblin ,\nor orc (pro-\nand in the subterranean world this frequently means\na diet of\nvided that they think that\ncan get away with it) . If more than\nbats. It is not the top predator in its ecological niche, and has\none fisher inhabits a lair;\nwill frequently\ntheir resources\nlearned caution in dealing with other monsters\nThe cave fisher is\nto catch larger prey: Once the victim is trapped in the filament,\nsufficiently intelligent to know the dangers of preying on large,\nthe cave fisher draws\nprey\nreeling its filament in like a fish-\nwell-organized groups\nwho might grow tired of its depredations\ning line\nand hunt it to extinction. The monster instinctively\nthe easi-\nShould a tempting target escape the monster's neatly laid traps,\nest route for survival, and relies on stealth and cunning to trap its\nthe cave fisher will try another mode of attack: It will\none\nprey and avoid\neaten itself .\nround drawing its filament in and then shoot it at the prey; strik-\nThe filaments of the cave fisher are highly prized by many\nas a 6 Hit Die monster, It will\nto snare its prey in this man-\nthieves' guilds, for\ncan be made into thin and very strong\nner s0\nas it remains within the fisher $ established territory If\nrope which is nearly invisible. The Filaments are wound onto reels\nthe prey is hit by the filament, the monster can\nweight of up\nand then specially treated to dilute the adhesive. The resulting\nto 400 pounds at a movement rate of 15' per round. In the event\nstrands are made into ropes\nwhile the diluted adhesive is turned\nthat a\nof war\nbreaks out, the fisher has a strength of 18/00\ninto a special solution, which when applied to gloves and boots,\nwith its strand\ngreatly increases traction for climbing\nHabitat Society:\nCave fishers prefer\non ledges and caves\nlocated above well-traveled paths, sharing their lairs with others\nof their kind\nmore than four cave fishers will be found in one\nAny\nlarge\nthey\nthey\nlegs:\nlegs\nlarger\nlegs\npair\nlarge,\nlong\nthey\nits\nthey\nget\nlong\nlay\"\nthey\nspell\nEcology:\nthey\nthey\npool\nits\nin,\npicks\nspend\nbeing\nthey\ntry\ning\nlong\npull\n'tug\nliving\nNo",
  "climate_terrain": "Subterranean",
  "frequency": "Rare",
  "organization": "Group",
  "activity_cycle": "Night",
  "diet": "Carnivorous",
  "intelligence": "Semi- (2-4)",
  "alignment": "Neutral",
  "number_appearing": "1-4",
  "movement": "1",
  "thac0": "17 or 15 (see below)",
  "damage": "2-8 (2d41/2-8 (2d4)",
  "special_attacks": "Adhesive trapline",
  "special_defenses": "See below",
  "magic_resistance": "Nil",
  "size": "M (7' long)",
  "morale": "Steady (11-12)",
  "xp_value": "175",
  "id": "cave_fisher"
}