{
  "name": "Centaur; Sylvan",
  "source_page": 23,
  "raw_text": "Centaur; Sylvan\nCLIMATETERRAIN:\nTemperate Forest\nFREQUENCY:\nRare\nORGANIZATION:\nTribal\nACTIITY CYCLE:\nDIET:\nOmnivorous\nINTELLIGENCE:\nLow to average (5-10)\nTREASURE:\nM, Q (D, I, T)\nALIGNMENT:\nNeutral or chaotic\nNO. APPEARING:\n1-8\nARMOR CLASS:\n5 (4)\nMOVEMENT:\n18\nHIT DICE:\nTHACO;\n17\nNO: OF ATTACKS:\nDAMAGEIATTACK:\n1-6/1-6 and weapon\nSPECIAL ATTACKS:\nNil\nSPECIAL DEFENSES:\nNil\nMAGIC RESISTANCE:\nNil\nSIZE:\nL(8'-9' tall)\nMORALE:\nElite (13-14)\nXP VALUE:\n175\nCentaur leader\n270\nCentaur priest\n420\nCentaurs are woodland\nwho shun the company of\nmen.\ndwell in remote, secluded glades and pastures.\nagriculture and trade. Though they shun dealings with hu-\nThe appearance of a centaur is unmistakable:\nhave the up-\nmans, centaurs have been known to trade with elves, especially\nper torso, arms, and head of a human\nbeing and the lower body\nfor food and wine. The elves are\nfrom the group treasury;\nof a\npowerful horse.\nwhich comes from the booty of slain monsters.\nCentaurs speak their\nown\nlanguage and some among them\nThe territory of a centaur tribe varies with its size and the na-\n(about 10 %\ncan converse in the tongue of elves.\nture of the area it inhabits. Centaurs are also not above sharing a\nterritory with elves. The attitude ofa centaur toward a stranger in\nCombat: A band of centaurs is always armed, and the leaders\nits territory will vary with the visitor. Humans and dwarves will\ncarry shields. Half of the centaurs will be wielding oaken clubs\nusually be asked to\nin\npolite manner; while halflings or\n(the equivalent of morning stars) , one quarter will carry compos-\ngnomes will be tolerated, and elves will be welcomed\nMonsters\nite bows and have 10-30 arrows (either flight or sheaf, depending\nwill be dealt with in a manner according to the threat they repre-\non\nthe current state of affairs in the area). The remainder of the\nsent to the welfare and survival of the tribe.\na giant or\nband will be leaders using medium shields and medium horse\ndragon to enter the territory the centaurs would\nup stakes\nlances. Centaurs make 3 attacks each round in melee: once with\nand relocate, while trolls and orcs and their like will be killed_\ntheir weapons and twice with their hooves\nCentaurs will take the treasure of their fallen foes,\nare fully\naware of its value. Most male centaurs have a small coin\nsupply,\nHabitat/Society: Centaurs are sociable creatures, taking great\nwhile the tribe has a treasury which may well include some magi-\npleasure in the society of others of their kind, Their overall orga -\ncal items. Leaders will have twice the normal individual treasure .\nnization is tribal, with a tribe divided into family groups living to-\nThis treasure is used to\nfood for the group, Or t0 ransom\ngether in harmony: The size of the tribe varies, it range from 3-4\n(90 % likely) captured or threatened members of the tribe.\nfamilies to upwards of 20 families. Since males have the danger-\nWhile basically neutral or chaotic good, centaurs have been\nous roles of hunter and protector; females outnumber males by\nknown to become rowdy; boorish, and aggressive when under the\ntwo to one. The centaur mates for life, and the entire tribe partici-\ninfluence of alcohol\nare also extremely protective of their\nin the education of the young:\nfemales and young. Centaurs are basically pastoral, but will react\nThe lair is located\nwithin a forest, and consists of a\nwith violence if their lifestyle and survival is threatened\nhidden glade and pasture with a\nsupply of running water:\nDepending upon the climate, the lair may contain huts or lean-tos\nEcology: The centaur\nin close harmony with nature and\nto shelter the individual families. Centaurs are skilled in horticul-\nspends its lifetime carefully conserving the natural resources\nture, and have been known to cultivate useful plants in the vicin -\naround its lair. The race seems to have an innate knowledge of\nity of their lair. In dangerous\nmonster infested areas, centaurs\nhow to achieve this precious balance\nIE forced to\ndown\nwill sometimes plant a thick barrier of tough thorn bushes around\ntree,\na centaur will plant another t0 replace it. Centaurs never\ntheir lair and even set traps and snares_\nIn the open area, away\nover hunt or over fish an area as & human group might do, but\nfrom the trees, are hearths for cooking and warmth. If encoun-\nchoose their game with care, limiting the amount\neat,\ntered in their lair, there will be 1-6 additional males, females equal\nto twice the number of males, and 5-30 young: The females (3 Hit\nDice) and the young (1-3 Hit Dice) will fight only with their\nhooves, and only in a life or death situation.\nEach tribe will have a priest who is treated as a leader but has\nthe\nabilities of a 3rd level druid.\nCentaurs survive through a mixture of hunting, foraging, fish-\nDay\ngood\nbeings\nThey\ning;\nthey\npaid\nlarge,\nleave\nWere\npull\nand\nbuy\nThey\npates\nlarge,\ndeep\ngood\nlives\nchop\nthey\n~spell",
  "climate_terrain": "Temperate Forest",
  "frequency": "Rare",
  "organization": "Tribal",
  "diet": "Omnivorous",
  "intelligence": "Low to average (5-10)",
  "treasure_type": "M, Q (D, I, T)",
  "alignment": "Neutral or chaotic",
  "number_appearing": "1-8",
  "ac": "5 (4)",
  "movement": "18",
  "thac0": "17",
  "special_attacks": "Nil",
  "special_defenses": "Nil",
  "magic_resistance": "Nil",
  "size": "L(8'-9' tall)",
  "morale": "Elite (13-14)",
  "xp_value": "175",
  "id": "centaur_sylvan"
}