{
  "name": "Chimera Chimera Gorgimera",
  "source_page": 25,
  "raw_text": "Chimera\nChimera\nGorgimera\nCLIMATE TERRAIN:\ntemperate\ntemperate\nto\ntropical\nto\ntropical\nFREQUENCY:\nRare\nVery rare\nORGANIZATION:\nSolitary or pride\nSolitary\nACTIVITY CYCLE:\nDIET:\nOmnivore\nOmnivore\nINTELLIGENCE:\nSemi- (2-4)\nSemi- (2-4)\nTREASURE:\nF\nF\nALIGNMENT:\nChaotic evil\nNeutral\nNO. APPEARING:\n1-4\nARMOR CLASS:\n6/5/2\n5/2\nMOVEMENT:\n9, FI 18 (E)\n12\nFI 15 (E)\nHIT DICE:\n10\nTHACO:\n11\n11\nNO_\nOF ATTACKS:\nDAMAGEIATTACK;\n1-3/1-3/1-4/1-4/\n1-3/1-3/2-8 (2d4)\n2-8 (2d4) /\n/2-12 (2d6) /\n3-12 (3d4)\n3-12 (3d4)\nSPECIAL ATTACKS:\nBreath weapon\nBreath weapons\nSPECIAL DEFENSES:\nNil\nNil\nMAGIC RESISTANCE:   Nil\nNil\nSIZE:\nL (5\" tall at the\nL (5' tall at the\nshoulder)\nshoulder)\nMORALE:\nElite (13-14)\nElite (13-14)\nbe satisfied with flesh. The chimera hunts once every 3 or 4\nXP VALUE:\n5000\n6000\nusing its strength and limited intelligence to\nan\nadvantage\nover those it preys on\nHaving\na voracious\nappetite, it sometimes\nroams over territories as\nas 20 square miles.\nchimerae were created is a dark mystery better left unex-\nplored . The chimera has the hindquarters of a\nblack goat\nBeing chaotic evil in nature, the chimera enjoys preying upon\nhas\nmen, elves, dwarves, and halflings. It will\neven\ngladly attack\nand\nthe   forequarters   of\ntawny\nIts   body\nother monsters in its search for food. Anyone entering its terri-\nbrownish-black wings like those of a dragon.\nbecomes prey; and will be treated accordingly:\nThe monster has three heads, those of\ngoat,\nlion, and\nfierce\nThe\nhead is pitch black;\nwith glowing amber\nThe chimera\ncannot resist attacking groups of travelers or\nmonsters for another reason: its\nnature craves the treasure\neyes and\nochre horns\nThe lion head is framed by a brown\nmane and has green eyes. The dragon head is covered with orange\nthat its prey might be carrying: Although it has no earthly use for\nit; the chimera will gather the coins of its fallen foe\nscales and has black eyes\nThe chimera speaks a limited form of the foul language of red\nand roost on it like a\ndragon . Its hoard is nothing like that of &\ndragons. As a rule, however, it will only pause to communicate\ntrue\ndragon, however; and consists mainly of copper and silver\nwith those creatures who are more powerful than itsell.\ncoins, with perhaps some jewelry and a few magical items.\nCombat:\nIts\nheads and powerful physique make the chi-\nEcology:\nThe chimera fills the role of both omnivore and a\nmany\nmera a\ndeadly foe in combat: The monster prefers t0 surprise its\npredator in its ecosystem. It is very adaptable. During times when\nvictims, often swooping down upon them from the sky: It can at-\nits prey is scarce Or non-existent, the chimera can make do with a\ntack 6 times each round, clawing with\nforelegs, goring with its\nvegetarian diet.\ntwo horns, and biting with its lion and dragon heads. If it desires\nThe Gorgimera\nto do So, the dragon head can loose\na stream of flame some\nin lieu of biting. The dragon's fire causes 3-24 (3d8)\nThe gorgimera has the hindquarters of a gorgon, forequarters ofa\npoints damage, although\nsaving throw versus breath weapon\nand body and wings ofa red dragon. Like the chimera, it has\nwill cut the damage in half. The chimera will always attempt to\nthe heads of its three constituent creatures _\nbreathe if its opponents are in range. If more than 1 chimera is en-\nThe monster can attack with its claws, bite with its\nand\ncountered, they will attack in concert.\nheads, and butt with its gorgon head. In place of making\nThe armor classes are split as follows: Dragon, AC 2 (flank);\nits normal attack, the gorgon and dragon heads can employ their\nLion, AC 5 (front); Goat, AC 6 (rear).\nbreath weapons. While the dragon's attack is similar to that of the\nchimera, the gorgon s breath causes petrification to any caught in\nHabitatiSociety:\nThe chimera , being\nhybrid, combines the\nits area of effect. The gorgon head can use its breath weapon\npreferences of the lion , the goat, and the dragon in its habitat, s0-\ntwice per day to strike in a cone 3 feet\nwhich is 1 foot wide at\nciety and ecology: The dragonish\nof its nature gives the chi-\nits base and 3 feet wide at its mouth. The gorgimera will always\nmera a distinct\npreference for caves as lairs_\nThe dragon and lion\nuse one of its breath weapons if its foes are within 10\nA save\nseem\nto\nwar with\none another;\nfor some chimerae\nare\nversus\npetrification will allow a victim t0 avoid the effects of the\ndragon-like in their preference for solitude, while others live in\ngorgon'$ breath_\nsmall prides. Even if\nmate,\noffspring are rare.\nThe gorgon's head can see into both the Astral and Ethereal\nThe monster is an omnivore. The goat head will browse on the\nplanes, and its breath weapon extends therein.\ntoughest plants and shrubs and will derive nutrition from the\nLike its relative the chimera, the gorgimera can also speak\nmost barren vegetation while the lion and dragon heads can only\nlimited form of the language of red dragons.\nAny\nAny\nAny\nAny\ndays,\ngain\nlarge\nHow\nlarge ,\nlion .\nhuge ,\ntory\ndragon.\ngoat\ndragon\nlong\nheap\ninto\ntop\nits\nlong\nyards\nlion ,\nlion\ndragon\nlong\npart\nfeet.\nparts\nthey",
  "climate_terrain": "temperate",
  "frequency": "Rare",
  "organization": "Solitary or pride",
  "diet": "Omnivore",
  "intelligence": "Semi- (2-4)",
  "treasure_type": "F",
  "alignment": "Chaotic evil",
  "number_appearing": "1-4",
  "ac": "6/5/2",
  "movement": "9, FI 18 (E)",
  "hit_dice": "10",
  "thac0": "11",
  "damage": "1-3/1-3/1-4/1-4/",
  "special_attacks": "Breath weapon",
  "special_defenses": "Nil",
  "magic_resistance": "Nil",
  "size": "L (5\" tall at the",
  "morale": "Elite (13-14)",
  "xp_value": "5000",
  "id": "chimera_chimera_gorgimera"
}