{
  "name": "Cockatrice Cockatrice Pyrolisk",
  "source_page": 26,
  "raw_text": "Cockatrice\nCockatrice\nPyrolisk\nCLIMATETERRAIN:\nTemperate to\nTemperate to trop\nical;\nany terrain\nical; any terrain\nFREQUENCY:\nUncommon\nRare\nORGANIZATION:\nFlock\nFlock\nACTIVITY CYCLE:\nDIET:\nOmnivorous\nOmnivorous\nINTELLIGENCE:\nAnimal (1)\nLow (5)\nTREASURE:\nD\nD\nALIGNMENT:\nNeutral\nNeutral evil\nNO: APPEARING:\n1-6\n1-4\nARMOR CLASS:\nMOVEMENT:\n6, FI 18 (C)\n6, FI 18 (C)\nHIT DICE:\n6 +2\nTHACO:\n15\n13\nNO. OF ATTACKS:\nDAMAGEIATTACK:\n1-3\n1-4\nSPECIAL ATTACKS:\nPetrification\nGaze\nSPECIAL DEFENSES:\nNil\nImmune t0 fire\nMAGIC RESISTANCE:\nNil\nNil\nSIZE:\nS (3' tall)\n5 (3' tall)\nMORALE:\nSteady (11-12)\nSteady (11-12)\nXP VALUE:\n650\n1400\nThere is only a 25 % chance that any given egg will hatch . Those\nThe cockatrice is an eerie, repulsive hybrid of lizard,\ncock\nand\nthat are fertile will hatch in 11-19 days. The young reach maturity\nbat _\nIt is infamous for its ability to turn flesh to stone_\nand full power within 6 months_\nOnce\nachieve adulthood;\nThe cockatrice is about the size of a\ngoose or turkey; and\nthe hatchlings are driven away from the nesting site by their par-\nhas the head and body of a cock, with two bat-like wings and the\nents. Larger groups of cockatrices encountered will frequently be\nof a lizard tipped with\na few feathers. Its feathers are\nyoung driven from the nest who have temporarily united for sur-\ngolden brown, its beak yellow, its tail green, and its wings gray:\nvival.\nThe cockatrice $ wattles, comb, and eyes are bright red;\nFemales, which are much rarer than males, differ only in that\nEcology:\nThe cockatrice thrives in the wilderness. Its petrifica-\nthey have no wattles or comb\ntion power makes it immune to most predators, and enables it to\ncompete with other birds for food\nThe Feathers of the cockatrice\nCombat:\nThe cockatrice\nfiercely attack anything, human or\nare prized by certain wizards as many magical scrolls must be in-\notherwise, which it deems & threat t0 itself or its lair. When\nat=\nscribed with pens made from such quills. Many people also seek\ntacking; the cockatrice will attempt to grapple with its foe; touch-\nunhatched eggs,\nor even\nlive cockatrice ,\nas unusual pets or\nexposed flesh and turning it to stone. Flocks of cockatrices\nguardians_\ndo their utmost to overwhelm and confuse their opponents,\nand\nwill sometimes fly directly into their victims' faces_\nPyrolisk\nWhile the fatal touch of & cockatrice s beak will affect victims\nFrequently mistaken for its less malignant relative, the pyrolisk is\nclothed in leather or fabric, it will not work through metal armor;\nidentical t0 the cockatrice except for the single red\nThe touch will, however;, extend into the ethereal plane\nThe\nvirtually\nand\nfeather in its tail and the reddish cast of its wings. Whereas the\ncockatrice is somewhat aware of the limits of its powers\nnal-\ncockatrice is motivated by instinct alone, the pyrolisk revels in\nural selection has taught it to strike only at exposed flesh. If\nspreading mayhem. Any victims who fail to save versus death\nareas of the opponent s flesh are exposed, it should be assumed\nmagic when meeting its gaze will instantly burst into flames,\nthat the cockatrice automatically touches flesh: If the target is\ndying in\nIf the save is made, they are still burnt for 2-13\nreasonably well armored, the base chance of a cockatrice striking\nagony:\nan area which it can affect is equal to 10 % times the adjusted Ar-\n(1d12+1) points of damage:\ncreature innately or magically\nimmune t0 fire will not be affected by its gaze, and anyone who\nmor Class of the victim\nmakes their saving throw is thereafter immune to the gaze of that\nHabitat Society:\nThe cockatrice is immune t0 the petrification\nparticular pyrolisk.\nThe creature can cause any fire source within 30\nto\nex=\npowers of others of\nkind\nplode in fireworks (as a pyrotechnics\nonce per round\nThe diet of the cockatrice consists of insects, small lizards and\nThe pyrolisk is itself immune to all fire-based\nand at-\nthe like.\nWhen it hunts these animals, the creature does not em\ntacks.\nploy its power to petrify living things.\nThe pyrolisk's mortal enemy is the phoenix, although any crea-\nIt is distinguished from other avians\nits unusual habits and\nture which the monster encounters is likely to be attacked.\nnasty temperament: Since females are rare,\nare the dominant\nsex, and will often have more than one mate\nIn fact, males will\noften fight or strut for the privilege of joining\na female's harem_\nThese mated groups usually build their nests in caves: Nest sites\nare permanent, and the cockatrice constantly seeks to decorate its\nnesting site by lining it with shining objects like coins and gems.\nFemales\n1 or 2 brownish red\nrust\nspeckled eggs per month.\ntrop-\nAny\nAny\nthey\nlarge\ntail\nlong\nwill\ning\nwill\nthey\nlarge\nAny\nyards\nits\n~spell)\nspells\nby\nthey\nlay",
  "climate_terrain": "Temperate to",
  "frequency": "Uncommon",
  "organization": "Flock",
  "diet": "Omnivorous",
  "intelligence": "Animal (1)",
  "treasure_type": "D",
  "alignment": "Neutral",
  "number_appearing": "1-6",
  "movement": "6, FI 18 (C)",
  "hit_dice": "6 +2",
  "thac0": "15",
  "damage": "1-3",
  "special_attacks": "Petrification",
  "special_defenses": "Nil",
  "magic_resistance": "Nil",
  "size": "S (3' tall)",
  "morale": "Steady (11-12)",
  "xp_value": "650",
  "id": "cockatrice_cockatrice_pyrolisk"
}