{
  "name": "Couatl",
  "source_page": 27,
  "raw_text": "Couatl\nCLIMATE TERRAIN:\nTropical and subtropical jungles\nFREQUENCY:\nVery rare\nORGANIZATION:\nSolitary\nACTIITY CYCLE:\nDIET:\nCarnivorous\nINTELLIGENCE:\nGenius (17-18)\nTREASURE:\nB, [\nALIGNMENT:\nLawful\nNO. APPEARING:\n1-4\nARMOR CLASS:\nMOVEMENT:\n6, FI 18 (A)\nHIT DICE:\nTHACO:\n11\nNO. OF ATTACKS:\nDAMAGEIATTACK:\n1-3/2-8 (2d4)\nSPECIAL ATTACKS:\nPoison , magic use\nSPECIAL DEFENSES:\nEtherealness\nMAGIC RESISTANCE:\nNil\nSIZE:\nL (12'\nMORALE:\nElite (13-14)\nXP VALUE:\n6000\nThe couatl are feathered serpents of\nand lore. It is believed\nthat\nare distant relatives of\ndragons, although this remains\nunproven.\nSo rare as to be considered almost legendary; the couatl is one\nof mankind and the bestower of such precious\nas\nagriculture\nof the most beautiful creatures in existence. It has the body of a\nand medicine. There are even shrines in certain areas dedicated to\nserpent and feathered\nthe color of the rainbow. Since\nthe couatl, and any who attack or harm\na couatl are automati-\nit has the ability to polymorph; the couatl will sometimes appear\ncally viewed as the blackest of villains.\nin the form of other creatures (always of\nalignment)\nAlthough solitary in nature, couatl think of themselves as a sin -\nCouatl are able to communicate via telepathy with almost any\ngle, extended clan. This clan is led by the oldest and wisest of their\nintelligent creature which they encounter. In addition, they can\nnumbers but assembles only in dire emergencies.\nspeak common and most serpent and avian languages\nMost couatl dwell alone, making their lairs in caves and aban-\ndoned buildings in remote, uninhabited regions_\nhunt jun-\nCombat:\nA\ncouatl will  seldom attack\nwithout provocation,\ngle animals for food\nonce every fortnight or\nSO.\nMany enjoy\nthough it will always attack evildoers caught red-handed. When-\ntraveling, often undertaking\njourneys of exploration.\never\npossible,\na couatl will attack from the air;\nOn rare occasions; a\nwill mate for life and establish a joint\nSince it is highly intelligent\nthe couatl will frequently use its\nlair. Unlike many other reptiles, the couatl bear live young. Births\nfrom\na distance before\nclosing with its foes. If more than\nare rare, averaging only one per couple each century: Both par-\none couatl is involved;\nwill discuss their strategy before\nents participate in the\nand education of the single off-\nbattle. The couatl will also not hesitate to polymorph into\nan-\nspring, and will fight to the death if their child is threatened\nother; more effective form in combat.\nreach maturity in thirty or\nyears and, though\nThe couatl have a variety of abilities which make them more\nsome will elect to remain with their parents for as\nas & cen-\nthan a match for most other creatures. In addition to being able to\ntury; will eventually set off in search of the couatls never-ending\npolymorph themselves at will, a couatl can use\nmagic: Fully 45 %\nquest for wisdom\nwill be Sth level wizards, while 35 % can act as 7th level priests.\nIntellectually curious, all couatl have vast stores of informa-\nThe remaining 20% are able to use both types of abilities.\ntion and enjoy learning more. When one of them learns some new\nIn addition to their other magical abilities, couatl can render\nand fascina\nfact he will inevitably set out in search of his\nthemselves and up to 450 pounds of additional matter ethereal at\nbrethren t0 share and discuss it.\nwill . Further,\ncan detect\n'evil, detect magic, turn invisi-\nCouatl can sometimes be persuaded to\nadventurers\nble, and employ ESP whenever they desire to do so\nThe oldest\nor give sound council. If\nfeel that\nare\nbeing sought for\nand most powerful of couatl can also use & plane shift on them-\nfrivolous reasons, they will simply fly away: They are not greedy\nselves and up t0 8 others. This ability has a 90% chance of reach-\nand do not seek treasure for\nown sake. Aid from a couatl may\nthe desired plane\ntake the form of a magical item from its hoard.\nThe couatl uses its poisonous bite and constriction when forced\ninto melee combat\nWhen it bites it does 1-3 points of damage and\nEcology:\nThe couatl usually reigns supreme in its jungle, having\ninjects a deadly toxin. If the victim fails a save versus\npoison it is\nlittle t0 fear from most other monsters\nkilled instantly;\nIC the constriction attack succeeds, the victim\ntakes 2-8 points damage each round untilit or the couatl is killed\nHabitat Society:\nThis winged serpent is native to warm, jungle-\nlike regions but can also be Found flying through the ether: Their\nintelligence and goodness has made them objects of reverence by\nthe natives of the regions which they inhabit. Considered to be di-\nvine, there are many legends in which the couatl is the benefactor\nAny\ngood\nlong)\nmyth\nthey\ngifts\nlong\nwings\ngood\nThey\nlong\npair\nspells\nthey\nrearing\nYoung\ncouatl\nforty\nlong\nting\nthey\ngood/\nhelp\ngood\nthey\nthey\nits\ning\nwell",
  "climate_terrain": "Tropical and subtropical jungles",
  "frequency": "Very rare",
  "organization": "Solitary",
  "diet": "Carnivorous",
  "intelligence": "Genius (17-18)",
  "treasure_type": "B, [",
  "alignment": "Lawful",
  "number_appearing": "1-4",
  "movement": "6, FI 18 (A)",
  "thac0": "11",
  "damage": "1-3/2-8 (2d4)",
  "special_attacks": "Poison , magic use",
  "special_defenses": "Etherealness",
  "magic_resistance": "Nil",
  "size": "L (12'",
  "morale": "Elite (13-14)",
  "xp_value": "6000",
  "id": "couatl"
}