{
  "name": "Displacer Beast Temperate mountains",
  "source_page": 28,
  "raw_text": "Displacer Beast\nCLIMATEITERRAIN:\nTemperate mountains\nFREQUENCY:\nTare\nORGANIZATION:\nPack\nACTIVITY CYCLE:\nAny\nDIET:\nCarnivorous\nINTELLIGENCE:\nSemi- (2-4)\nTREASURE:\n(D)\nALIGNMENT:\nNeutral\nNO: APPEARING:\n2-5 (1d4+1)\nARMOR CLASS:\n\"#6)\nMOVEMENT:\n15\nHIT DICE:\nTHACO:\n15\nNO: OF ATTACKS:\n4\nDAMAGEIATTACK:\n2-8 (2d4)/2-8 (2d4)\nSPECIAL ATTACKS:\nNil\nSPECIAL DEFENSES:\n~2 on opponents attack roll\nMAGIC RESISTANCE:\nSave as a 12th level fighter\n(+2)\nSIZE:\nL (8' - 12' long)\nMORALE:\nElite (13-14)\nXP VALUE:\n975\nThe displacer beast is a magical creature which resembles a puma\nwith two powerful black tentacles growing from its shoulders.\nare very rare, and inhabit spots far from human lands.\nbeen known to make a meal of orcs, goblins, and bands of men_\nThe displacer beast has the blue-black coloring of a dark pan-\nbeing entering their terrain is viewed as potential prey:\nther with\ncat-like body and head_\nFemales range in size\nDisplacer beasts mate in the autumn, and the young are born in\nfrom 8\nto 9'\nand weigh 450 pounds. Males can vary in size from\nthe spring. A mated\nof displacer beasts makes its home in a\n10' to 12'\nand weigh up to 500 Ibs. Unlike the panther, however,\ncave, producing litters of 1-4 young. The cubs, about the size of\nthe displacer beast has 6\nIts black tentacles are tipped with\ndomestic cats, are born without tentacles and reach maturity but\nrough horny edges which can inflict terrible wounds upon its\nnot full size, within 4 months.\nremain in the cave until their\nfoes. The eyes of a displacer beast glow bright green even after the\ndisplacement abilities\nfully developed\nThis is followed by a 2\ndeath of the creature itself.\nmonth period during which the cubs are taught how to hunt by\ntheir parents. When this is completed, the family group disbands\nCombat:\nThe displacer beast is a\nsavage creature which\nand the monsters wander off to join separate packs. While raising\nhates all forms of life. Highly aggressive, the displacer beast will\nyoung, however; the monsters are fiercely protective of their lair:\nattack on sight, using its tentacles to inflict 2-8 (2d4) points of\nOne adult will always remain with the cubs, usually the female\ndamage to its victims.\nwhile the other goes off to hunt: Dead prey will be dragged back\nTheir main advantage in combat, however, stems from their\nto the lair to be devoured by the entire family. The lair of a dis-\nmagical power of displacement,\nwhich causes them to appear to\nplacer beast Family is littered with the bones, equipment, and\nbe some 3' from their actual location. Anyone attacking\ndis-\ntreasures of its victims,\nplacer beast receives\na -2 on his attack roll. In addition, these\nNaturally vicious and almost evil at times, the displacer beast\nmonsters make their saving throws as 12th level fighters, gaining\nhas an undying hatred of the blink\nMany theories abound to\nan additional +2 t0 their die roll.\naccount for this enmity. Some say it springs from antipathy in\nTo determine the true position ofthe displacer beast and\nillu-\ntemperaments, and that the lawful\nblink\nwould natu-\nsionary\nroll 1d1o. On a result of 1-5 the illusion is in front of\nrally be the enemy of a creature as savage and destructive as the\nthe creature, 6-7 to the creature s left, 8-9, to the right, and 10 the\ndisplacer beast. Some argue that it is the displacement and blink-\nthe illusion is behind the actual position of the beast. Although\nabilities which are the cause for this antipathy and that the\nthe displacement ability is magical , the location of the animal will\ntwo abilities, when in close proximity somehow stimulate the\nnot be revealed by a dispel or detect\nOnly true seeing will\nnervous system and produce\nhostile reaction . Encounters be-\nreveal the true position of the displacer beast.\ntween the two kinds are rare however, since they do not share the\nDisplacer beasts will not use their claws or teeth unless near\nsame\nterritory:\ndeath or when fighting a very\nopponent\nIf\ndo employ\nthese secondary weapons each claw does 1-3 points of damage,\nEcology:\nThe displacer beast has little to fear from other\nand each bite does 1-8 points of damage-\npredators, save perhaps\ntrolls or giants. Some wizards and\nalchemists value the hide of displacer beasts for use in certain\nHabitatiSociety:\nDisplacer beasts are carnivores who survive\nmagical preparations, and will offer generous rewards for them\nby hunting: Unless\nare in the process of raising young;\nThe eyes of a displacer beast are a highly prized, if uncommon,\ngenerally run in packs, carving a savage swath of destruction as\nluck charm among thieves who believe that\nwill pro-\ng0.\nhate all life, and will sometimes kill purely for plea-\ntect the bearer\ndetection _\nsure. Fierce and vicious as they are, however, displacer beasts\nnever\nfight among themselves. The\nis a well-run and\nhighly\nefficient killing machine. When encountered en masse, displacer\nbeasts are more than a match for many\ncreatures and have\nVery\n2\nThey\nAny\nlong\npair\nlegs.\nThey\nare\nfierce ,\ndog-\ndog\nits\ngood\nform\ning\nmagic.\nthey\nlarge\nlarge\nlarge\nthey\nthey\nthey\ngood\nfrom\nthey\nThey\npack\nlarge",
  "frequency": "Tare",
  "organization": "Pack",
  "activity_cycle": "Any",
  "diet": "Carnivorous",
  "intelligence": "Semi- (2-4)",
  "treasure_type": "(D)",
  "alignment": "Neutral",
  "number_appearing": "2-5 (1d4+1)",
  "ac": "\"#6)",
  "movement": "15",
  "thac0": "15",
  "attacks": "4",
  "damage": "2-8 (2d4)/2-8 (2d4)",
  "special_attacks": "Nil",
  "special_defenses": "~2 on opponents attack roll",
  "magic_resistance": "Save as a 12th level fighter",
  "size": "L (8' - 12' long)",
  "morale": "Elite (13-14)",
  "xp_value": "975",
  "id": "displacer_beast_temperate_mountains"
}