{
  "name": "Dragon, Black",
  "source_page": 32,
  "raw_text": "Dragon, Black\nCLIMATETERRAIN:\nswamp, jungle, and\nsubterranean\nFREQUENCY:\nRare\nORGANIZATION:\nSolitary\nor clan\nACTIVE TIME:\nAny\nDIET:\nSpecial\nINTELLIGENCE:\nAverage (8-10)\nTREASURE:\nSpecial\nALIGNMENT:\nChaotic evil\nNO: APPEARING:\n(2-5)\nARMOR CLASS:\n1 (base)\nMOVEMENT:\n12 , Fl 30 (Ch Sw 12\nHIT DICE:\n12 (base)\nTHACO:\n(base)\nNO. OF ATTACKS:\n3 +\nDAMAGEIATTACK:\n1-6/1-6/3-18\nSPECIAL ATTACKS:\nSpecial\nSPECIAL DEFENSES:\nVariable\nMAGIC RESISTANCE:\nVariable\nSIZE:\nG (30' base)\nMORALE:\nFanatic (16 base)\nXP VALUE:\nVariable\nAge\nBody Lgt:\nTail Lgt: ()\nAC\nBreath Weapon\nSpells Wizard Priest\nMT\nTreas: Type\nXP Value\n3-6\n2-5\n2d4 +1\nNil\nNil\nNil\n7400\n6-15\n5-12\n4d4 + 2\nNil\n2,000\n15-24\n12-19\n6d4 + 3\nNil\nNil\nNil\n3,000\n24-33\n19-27\n8d4 +4\nNil\n1/2H\n6,000\n33-42\n27-35\n0d4 + 5\n2\n10 %\n8,000\n42-51\n35-43\n-1\n2d4 +6\n15 %\n#\n9,000\n51-60\n43-50\n4d4 + 7\n20%\n10,000\n60-69\n50-57\n3\nod4 + 8\n25 %\nHxz\n11,000\n69-78\n57-64\n8d4 + 9\n309\nHx2\n13,000\n10\n78-87\n64-73\n0d4 +10\n35 %\nHx2\n14,000\n11\n87-96\n73-80\n-6\n2d4+11\n40 %\nHx3\n15,000\n12\n96-105\n80-87\n-7\n4d4 +12\n45 %\nHx3\n16,000\nBlack dragons are abusive,\nto anger, and resent intrusions of any\nJuvenile: darkness three times a\nin a 10' radius per age category ofthe\nkind . They like dismal surroundings\nvegetation, and prefer dark-\ndragon _\nAdult: corrupt water once a\nFor every age category a dragon\nness to daylight: Although not as intelligent as other dragons, black\nattains, it can stagnate 10 cubic feet of water, making it become still , foul,\ndragons are instinctively cunning and malevolent\ninert, and unable to support animal life\nWhen this ability is used against\nAt birth,\nblack dragon s scales are thin, small , and glossy: But as the\npotions and elixirs, they become useless if\nrolla 15 or better on 1dzo.\n~dragon ages, its scales become\nthicker; and duller, which helps it cam-\nOld: plant growth once a day: Venerable: summon insects once a day:\nouflage itself in swamps and marshes. Black dragons\ntheir own tongue,\nGreat wyrm: charm\nreptiles three times & day: This operates as & charm\ntongue common to all evil dragons, and 10% of hatchling black dragons\nmammals spell , but is applicable only to reptiles.\nhave an ability to communicate with any intelligent creature. The chance to\npossess this ability increases 5 % per age category of the dragon:\nHabitat Society:\nBlack dragons are found in swamps, marshes, rain for-\nests, and jungles. They revel in & steamy environment where canopies of\nCombat:\nBlack dragons prefer to ambush their targets, using their\ntrees filter out most of the sunlight\nswarms of insects fill the air, and\nroundings as cover. Their favorite targets are men, who\nwill some-\nnant moss-covered\nponds lie in abundance. Black dragons are excellent\ntimes stalk for several minutes in an attempt t0 gauge their strength and\nswimmers and enjoy lurking in the gloomy depths of swamps and\nwealth before attacking. Against a band of men or a formidable creature\nalso are\ngraceful in flight, however; they prefer to fly at night when\nolder black dragons\nuse their special abilities first s0 the very forces of\ntheir great forms are hidden by the darkness of the sky: Black dragons are\nthe marsh can weaken the targets before the dragon joins the fight. Black\nextremely selfish, and the majority of those encountered will be alone\ndragons also will use their breath weapon before closing in melee:\nWhen\nWhen a family of black dragons is encountered, the adults will protect\nfighting in heavily vegetated swamps and marshes, black dragons attempt\ntheir young. However, if it appears the adults\nare in jeopardy they\nto stay in the water\nalong the ground; the numerous trees and leafy can-\nwill abandon their young t0 save themselves_\nopies limit their flying maneuverability: When faced with an opponent\nlair in\ncaves and multi-chambered subterranean caverns.\nwhich poses too much ofa threat\na black dragon will attempt to fly out of\nOlder dragons are able to hide the entrance to their lairs with their plant\nsight, s0 it will not leave tracks, and hide in a\nor\nability. Black  dragons\nare\nespecially fond of coins.\nOlder   black\ndragons sometimes capture humans and question them before\nthem to\nBreath weapon/special abilities:\nA black dragon's breath weapon is a 5'\nfind out where\nstockpiles of\nsilver; and platinum coins are kept.\nwide stream of acid that extends 60' in & straight line from the dragon'$\nhead. All creatures caught in this stream must save Vs. breath weapon for\nEcology:\nBlack dragons can eat almost anything, although they prefer\nhalf damage. A black dragon casts\nand uses its magical abilities at\nto dine primarily on fish, mollusks, and other aquatic creatures_\nare\nSth level, plus its combat modifier.\nfond of eels, especially the giant varieties. They also hunt for red meat,\nBlack dragons are born with an innate water breathing ability and an\nbut they like to \"pickle\" it by letting it lie in ponds within their lair for\nimmunity to acid\nAs\nage, they\nthe following additional powers:\nbefore eating it.\nAny\nspecial\nday\nquick\nday:\nheavy\nthey\nlarger,\nspeak\nstag\nsur-\nthey\nbogs .\nThey\nwill\nlives\nOr .\nThey\nlarge,\ndamp\ngrowth\npond\nbog:\ndeep\nkilling\ngold,\nThey\nspells\ndays\nthey\ngain",
  "climate_terrain": "swamp, jungle, and",
  "frequency": "Rare",
  "organization": "Solitary",
  "activity_cycle": "Any",
  "diet": "Special",
  "intelligence": "Average (8-10)",
  "treasure_type": "Special",
  "alignment": "Chaotic evil",
  "number_appearing": "(2-5)",
  "ac": "1 (base)",
  "movement": "12 , Fl 30 (Ch Sw 12",
  "hit_dice": "12 (base)",
  "thac0": "(base)",
  "attacks": "3 +",
  "damage": "1-6/1-6/3-18",
  "special_attacks": "Special",
  "special_defenses": "Variable",
  "magic_resistance": "Variable",
  "size": "G (30' base)",
  "morale": "Fanatic (16 base)",
  "xp_value": "Variable",
  "id": "dragon_black"
}