{
  "name": "Dragon,_Silver_",
  "source_page": 40,
  "raw_text": "Dragon,_Silver_\nCLIMATETERRAIN:\nTropical, sub-tropical, and\ntemperate mountains and\nclouds\nFREQUENCY:\nrare\nORGANIZATION:\nSolitary or clan\nACTMITY CYCLE:\nDIET:\nSpecial\nINTELLIGENCE:\nExceptional (15-16)\nTREASURE:\nSpecial\nALIGNMENT:\nLawful\nNO. APPEARING:\n1 (2-5)\nARMOR CLASS:\n~3 (base)\nMOVEMENT:\nFl 30 (C) Jp 3\nHIT DICE:\n15 (base)\nTHACO:\n5 (at 15 HD)\nNO.OF ATTACKS:\n3 +\nDAMAGEIATTACK:\n1-8/1-8/5-30 (5d6)\nSPECIAL ATTACKS:\nSpecial\nSPECIAL DEFENSES:\nVariable\nMAGIC RESISTANCE:\nVariable\nSIZE:\nG (48' base)\nMORALE:\nFanatic (17-18)\nXP VALUE:\nVariable\nAge\nBody Lgt (')\nTail Lgt:\nAC\nBreath Weapon\nSpells Wizard Priest\nMR\nTreasure Type\nXP Value\n8-18\n3=\n2d10 + 1\nNil\nNil\nNil\n3,000\n18-30\n6-12\n4d10+2\nNil\nNil\nNil\n4,000\n30-42\n12-16\n6d10+3\nNil\nNil\nNil\n0,000\n42-52\n16-21\n8d10 +4\nNil\nE; R\n8,000\n52-63\n21-27\n10d10 + 5\n2 2\n25 %\nH; R\n10,000\n63-74\n27-32\n12d10 +6\n2 2 1\n30 %\nH R\n13,000\n74-85\n32-37\n14d10 +7\n2 2 2\n35 %\nH;R\n14,000\n85-90\n37-43\nIod1o + 8\n2 2 2 1/2\n40 %\nA; Rxz\n15,000\n90-108\n43-48\n18d10+0\n2 2 2 2/2 2\n45 %\nA; Rx2\n17,000\n10\n108-120\n48-54\n20d10 +10\n2 2 2 2 1/2 21\n50 %\nH; Rx2\n18,000\n11\n120-134\n54-60\n10\n22d10 +11\n2 2 2 2 2/2 2 2\n55 %\nH, Rx3\n19,000\n12\n134-148\n60-67\n11\n24d10 + 12\n2 2 2 2 2 1/2 2 2 1\n60 %\nH, Rx3\n20,000\nSilver dragons are kind and helpful. They\ncheerFully assist\ncred=\nlevel, plus its combat modifier;\ntures if their need is genuine. They often take the forms of kindly old men\nAt birth, silver\n~dragons\nare immune t0 cold, and can polymorph self\nor fair damsels when associating with people\nthree times a\nEach change in form lasts until the dragon chooses a dif-\nAt birth,\na silver\ndragon'$ scales are blue-gray with silver highlights. As\nferent form and revertingto their normal form does not count asa\nchange.\nthe dragon approaches adulthood, its color slowly lightens to brightly\nalso can cloud walk: This allows the dragon to tread on clouds or\ngleaming silver. An adult or older silver dragon has scales s0 fine that the\nas\nthough\nwere solid ground. The ability functions continuously\nindividual scales are scarcely visible. From a distance, these dragons look\nbut can be negated or resumed at will. As they age,\nthe follow-\nas if\nhave been sculpted from pure metal.\nadditional powers: Young: feather fall twice &\nJuvenile: wall of\nSilver\ntheir\nOwn\ntongue,\ntongue common to all\nfog once a\nAdult: control winds three times &\nMature adult: con-\ndragons, and 16 % of hatchling silver dragons have an ability to commu-\ntrol weather once a\nday: Old: reverse gravity once a\nnicate with any intelligent creature\nThe chance t0 possess this ability in-\ncreases 5 % per age category of the dragon.\nHabitat Society:\nSilver dragons prefer aerial lairs on secluded mountain\npeaks, or amid the clouds themselves. When\nlair in clouds there al-\nCombat:\nSilver dragons are not violent and avoid combat except when\nways\nbe an enchanted area with a solid floor for laying eggs and stor-\nfaced with highly evil or aggressive foes . If necessary; they use feather\ntreasure.\nto stop any missiles fired at them. They use wall of\nOr control weather\nSilver dragons seem to prefer human form t0 their OWn, and often have\nto blind or confuse opponents before making melee attacks. If angry;\nmortal companions. Frequently they share\nfriendships with mortals.\nwill use reverse gravity to\nenemies helplessly into the air; where they\nInevitably however, the dragon reveals its true form and takes its leave to\ncan be snatched. When faced with flying opponents,\na silver\ndragon will\nlive a\ndragon s life fOr &\nhide in clouds (often creating some with control weather on clear days) ,\nremain there using cloud walking then jump to the attack when they have\nEcology:\nSilver dragons prefer human food, andcan live on such fare in-\nthe advantage.\ndefinitely:\nBecause they lair in similar territories, silver dragons come into conflict\nBreath Weapon Special Abilities:\nA silver dragon has two breath weap-\nwith red dragons. Duels between the two species are furious and deadly,\nons: & cone of cold 80'\n5' wide at the dragon $ mouth, and 30' wide at\nbut silver dragons generally\nthe upper hand since\nare more capa-\nthe end or a cloud of paralyzation\n50\"\n40' wide, and 20' high:\nble of working together against their foes and often have human allies_\nCreatures caught in the gas must save versus breath weapon or become\nparalyzed for one minute per age level of the dragon, plus 1-8 minutes_\nCreatures caught in the cold are allowed a save versus breath weapon for\nhalf damage. A silver dragon casts its\nand uses its magical abilities at\nVery\nAny\ngood\nspecial\nwill\ngood\noth\nday\nThey\nfog =\nthey\nthey\n~gain\nday:\nthey\ning\nday:\nday:\ndragons\nspeak\ngood\n'day:\nthey\nwill\nfall\ning\nfog\nthey\ndeep\nfling\ntime\nlong\nthey\nget\nlong'\ngas\nspells",
  "climate_terrain": "Tropical, sub-tropical, and",
  "frequency": "rare",
  "organization": "Solitary or clan",
  "diet": "Special",
  "intelligence": "Exceptional (15-16)",
  "treasure_type": "Special",
  "alignment": "Lawful",
  "number_appearing": "1 (2-5)",
  "ac": "~3 (base)",
  "movement": "Fl 30 (C) Jp 3",
  "hit_dice": "15 (base)",
  "thac0": "5 (at 15 HD)",
  "attacks": "3 +",
  "damage": "1-8/1-8/5-30 (5d6)",
  "special_attacks": "Special",
  "special_defenses": "Variable",
  "magic_resistance": "Variable",
  "size": "G (48' base)",
  "morale": "Fanatic (17-18)",
  "xp_value": "Variable",
  "id": "dragon_silver"
}