{
  "name": "Dragon;_Copper_",
  "source_page": 36,
  "raw_text": "Dragon;_Copper_\nCLIMATETERRAIN:\nArid and temperate hills and\nmountains\nFREQUENCY:\nRare\nORGANIZATION:\nSolitary or clan\nACTIVE TIME:\nDIET:\nSpecial\nINTELLIGENCE:\nHigh (13-14)\nTREASURE:\nSpecial\nALIGNMENT:\nChaotic\nNO: APPEARING:\n1 (2-5)\nARMOR CLASS:\n1 (base)\nMOVEMENT:\n9, Fl 30 (C) Jp 3\nHIT DICE:\n13 (base)\nTHACO:\nNO. OF ATTACKS:\n3 + special\nDAMAGEIATTACK:\n1-6/1-6/5-20\nSPECIAL ATTACKS:\nSpecial\nSPECIAL DEFENSES:\nVariable\nMAGIC RESISTANCE:\nVariable\nSIZE:\nG (36' base)\nMORALE:\nElite (16 base)\nXP VALUE:\nVariable\nAge\nBody Lgt:\nTail Lgt:\nAC\nBreath Weapon\nSpells Wizard Priest\nMR\nTreas. Type\nXP Value\n3-8\n2-6\nZd6 + 1\nNil\nNil\nNil\n1,400\n8-16\n4-12\n4d6 +2\nNil\nNil\nNil\n2,000\n16-27\n12-20\n6d6 +3\nNil\nNil\nNil\n4,000\n27-38\n20-30\nF 1\n8d6 +4\nNil\n1/2HS\n6,000\n38-50\n30-40\n1Od6 + 5\n10 %\nHS\n9,000\n50-59\n40-50\n12d6 + 6\n15 %\nHS\n10,000\n50-73\n50-60\n14d6 + 7\n3 1\n20 %\nHS\n11,000\n73-86\n60-70\nlod6 + 8\n3 2/1\n25 %\nHSxz\n12,000\n86-100\n70-80\n18d6 +9\n3 3/2\n30 %\nHSx2\n14,000\n10\n100-114\n80-90\n20d6 +10\n3 3 1/3\n35 %\nHSx2\n16,000\n11\n114-130\n90-100\n22d6 +11\n3 3 2/3 2\n40 %\nHSx3\n17,000\n12\n130-147\n100-110\n24d6 +12\n3 3 2 1/3 3\n45 %\nHSx3\n18,000\nCopper dragons are incorrigible pranksters, joke tellers, and riddlers_\ntures caught in the acid take damage, save Vs. breath weapon for half: A\nThey are prideful and are not\nlosers, although\nare reasonably\ncopper dragon casts its\nand uses its magical abilities at 7th level, plus\ngood winners. They are particularly selfish and greedy for their align-\nits combat modifier;\nment, and have an almost neutral outlook where wealth is concerned.\nAt birth , copper dragons can spider climb (stone surfaces only) and are\nAt birth, a copper dragon's scales have a ruddy brown color with a cop-\nimmune t0 acid, As\nage,\nthe following additional powers:\nper tint. As the dragon\nolder, the scales become finer and more cop-\nYoung: neutralize poison three times a day: Juvenile: stone shape twice a\npery, assuming a soft,\nwarm\ngloss by the time the dragon becomes\nAdult: forget once a day. Mature adult: rock to mud once a day. Old:\nyoung adult: Beginning at the venerable stage, the dragons' scales pick up\nmove earth once a\nday: Great wyrm: wall of stone once a day: A copper\na green tint.\ndragon can jump 30 yards forward or sideways, reaching heights up to 20'\nCopper dragons\ntheir own tongue, a tongue common to all\nat mid jump\ncan\njump 30' straight up.\ndragons, and 14% of hatchling copper dragons have an ability to commu-\nnicate with any intelligent creature. The chance to possess this ability in-\nHabitat/Society:\nCopper dragons like\nrocky uplands and\nmoun-\ncreases 5 % per age category of the dragon.\ntains.\nlair in narrow\ncaves and often conceal the entrances\nmove earth and stone shape. Within the lair,\nconstruct\ntwisting\nCombat:\nCopper dragons\nto taunt and annoy their opponents,\nmazes with open tops. These allow the dragons to fly or jump over in-\nthey will give up or become angry and act foolishly. Early in\nan\ntruders struggling through the maze_\nencounter; a copper\n'dragon will jump from one side of an opponent to an-\nCopper dragons appreciate wit, and will usually leave\nOr neutral\nother, landing on inaccessible\nOT\nvertical stone surfaces\nIf there are no\ncreatures alone if they can relate a joke, humorous story; or riddle the\nsuch places around a dragon s lair; the dragon will create them ahead of\ndragon has not heard before:\nquickly\nannoyed with creatures\ntime\nstone shape, move earth\nand wall of stone, An angry copper\nwho don't laugh at their jokes Or do not accept the dragon $ tricks and an-\ndragon will mire its opponents\nrock to mud, and will force victims\ntics with good humor:\nwho escape the mud into it with kicks. Once opponents are trapped in the\nBecause\noften inhabit hills in sight of red dragons' lairs conflicts be-\nmud, the dragon will crush them with a wall of stone or snatch them and\ntween the\ntwo subspecies often\noccur\nCopper dragons usually run for\ncarry them aloft. When fighting airborne opponents, a dragon\ndraw\ncover until\ncan\nthe odds\nits enemies into narrow, stony gorges where it can use its spider climb\nability in an attempt to maneuver the enemy into colliding with the walls.\nEcology:\ndragons are determined hunters, the\nsport a hunt\nprovides is at least as important as\nfood\nare known t0\nBreath weapon/special abilities:\nA copper dragon's breath weapon is ei-\neat almost anything, including metal ores. However; they prize giant scor-\nther a cloud of slow\n30' long, 20' wide, and 20' high\nspurt of acid\npions and other\npoisonous creatures\nsay the venom sharpens\n70'\nand 5' wide. Creatures caught in the gas must save vs. breath\ntheir wit) . The dragon $ digestive system can handle the venom safely, al-\nweapon or be slowed\nthree minutes per age level of the dragon. Crea-\nthough injected venoms affect them normally:\nAny\ngood\nspells\nthey\ngood\nthey\nthey\ngain\ngets\nday:\nThey\ngood\nspeak\ndry;\nThey\nusing\nthey\nhop-\nlike\ning\ngood\nThey\nget\nusing\nusing\nthey\nwill\nthey\nequal\nCopper\ngood\nthey\nthey\nThey\nget,\nlarge\n(they\nOr\ngas\nJong\nfor",
  "climate_terrain": "Arid and temperate hills and",
  "frequency": "Rare",
  "organization": "Solitary or clan",
  "diet": "Special",
  "intelligence": "High (13-14)",
  "treasure_type": "Special",
  "alignment": "Chaotic",
  "number_appearing": "1 (2-5)",
  "ac": "1 (base)",
  "movement": "9, Fl 30 (C) Jp 3",
  "hit_dice": "13 (base)",
  "attacks": "3 + special",
  "damage": "1-6/1-6/5-20",
  "special_attacks": "Special",
  "special_defenses": "Variable",
  "magic_resistance": "Variable",
  "size": "G (36' base)",
  "morale": "Elite (16 base)",
  "xp_value": "Variable",
  "id": "dragon_copper"
}