{
  "name": "Dragon;_Green_",
  "source_page": 38,
  "raw_text": "Dragon;_Green_\nCLIMATE TERRAIN:\nSub-tropical and temperate\nforest and subterranean\nFREQUENCY:\nrare\nORGANIZATION:\nSolitary or clan\nACTIVITY CYCLE:\nDIET:\nSpecial\nINTELLIGENCE:\n(11-12)\nTREASURE:\nSpecial\nALIGNMENT:\nLawful evil\nNO.APPEARING:\n1 (2-5)\nARMOR CLASS:\n0 (base)\nMOVEMENT:\n9, Fl 30 (C) Sw\nHIT DICE:\n13 (base)\nTHACO:\n7 (at 13 HD)\nNO. OF ATTACKS:\n3 + special\nDAMAGEIATTACK:\n1-8/1-8/2-20 (2d10)\nSPECIAL ATTACKS:\nSpecial\nSPECIAL DEFENSES:\nVariable\nMAGIC RESISTANCE:\nVariable\nSIZE:\nG (36' base)\nMORALE:\nElite (15-16)\nXP VALUE:\nVariable\nAge\nBody Lgt (\")\nTail Lgt: ()\nAC\nBreath\nWeapon\nSpells Wizard Priest\nMR\nTreasure Type\nXP Value\n2-7\n2-5\n2d6 + [\nNil\nNil\nNil\n1,400\n7-16\n5-15\n4d6 + 2\nNil\nNil\n2,000\n16-35\n15-31\nod6 + 3\nNil\nNil\nNil\n3,000\n35-44\n31- 40\n8d6 +4\nNil\n1/2H\n6,000\n44-53\n40-48\n=1\n10d6 +5\n15 %\n8,000\n53-62\n48-56\n12d6 + 6\n20 %\n#\n9,000\n62-71\n56-64\n14d6 +7\n25 %\n10,000\n71-80\n64-72\nTod6 + 8\n4\n30 %\nHx2\n11,000\n80-89\n72-80\n4\n18d6 + 9\n4 2\n40 %\nHx2\n13,000\n10\n80-98\n80-86\nF0\n20d6 +10\n4 3\n45 %\nHxz\n14,000\n11\n08-107\n86-96\n-7\n22d6 +11\n4 4\n50 %\nHx3\n16,000\n12\n107-116\n96-104\n-8\n24d6 + 12\n5 4\n55 %\nHx3\n17,000\nGreen dragons are bad tempered, mean, cruel , and rude.\nhate\nBreath weapor/special abilities:\nA green dragon'$ breath weapon is & cloud\nness and\n-aligned creatures. They love intrigue and seek to enslave\nof poisonous chlorine gas that is 50'\n40' wide, and 30 feet high. Creatures\nother woodland creatures,\nkilling those who cannot be controlled\nOI In-\nwithin the cloud may save versus breath weapon for half damage. A green\ntimidated:\ncasts its\nat 6th level, adjusted by its combat modifier:\nA\nhatchling green dragon's scales are thin,\nsmall, and a\nshade\nFrom birth, green dragons are immune t0 gasses. As\nage,\nof green that appears nearly black. As the dragon ages, the scales grow\nthe following additional powers: Juvenile: water breathing. Adult: sug-\nlarger and become lighter, turning shades of forest, emerald, and olive\ngestion once a day. Mature adult: warp wood three times a day: Old; plant\ngreen, which helps it blend in with its wooded\nsurroundings. A green\ngrowth once a\nold: entangle once a day Wyrm:\nwithout\ndragon'$   scales\nnever become\nas thick\nJs\nother   dragons\"\nremaining\ntrace three times a day:\nsmooth and flexible.\nGreen dragons\ntheir own tongue,\ntongue common t0 all evil\nHabitat Society:\nGreen dragons are found in sub-tropical and temperate\ndragons, and 12 % of hatchling green dragons have an ability to commu-\nforests, the older the forest and bigger the trees, the better; The sights and\nnicate with any intelligent creature. The chance t0 possess this ability in-\nsmells of the woods are pleasing to the\nand it considers the entire\ncreases 5 % per age category of the dragon:\nforest or woods its territory: Sometimes the dragon will enter into a relation-\nship with other evil forest-dwelling creatures, which keep the dragon in-\nCombat:\nGreen dragons initiate fights with little Or no provocation,\nformed about what is going\non in the forest and surrounding area in\npicking on creatures of any size. If the target creature intrigues the dragon\nexchange for their lives. If a green dragon lives in a forest on a hillside, it will\nOr\nappears t0 be difficult to deal with; the dragon will stalk the creature;\nseek to enslave hill giants, which the dragon considers its greatest enemy: A\nits environment for cover, until it determines the best time t0 strike\ngreen dragon makes its lair in underground chambers far beneath its forest\nand the most appropriate tactics t0 use. If the target appears formidable\nThe majority of green dragons encountered will be alone. However;\nthe dragon will first attack with its breath weapon , magical abilities, and\nwhen a mated\nof dragons and their young are encountered, the fe-\nHowever, if the target appears weak, the dragon\nmake its pres-\nmale\nto the attack\nThe male will take the young to a place of\nence known quickly for it enjoys evoking terror in its targets. When the\nsafety before joining the fight. The parents are extremely protective of\ndragon has tired of this game, it will\ndown the creature using its\ntheir young, despite their evil nature, and will sacrifice their own\nto\nphysical attacks s0 the fight lasts longer and the creature s agony is prO-\nsave their offspring.\niongrdetimes , the dragon elects to control a creature such as a human or\nEcology:\nAlthough green dragons have been known to eat practically\ndemi-human , through intimidation and suggestion. Green dragons like to\nanything, including shrubs and small trees when they are hungry enough,\nquestion\nmen;\nespecially adventurers, t0 learn more about their society;\nespecially prize elves . If the forest is on a hillside, hill giants hunt the\nabilities ,\nwhat is going on in the countryside, and if there is treasure\nyounger dragons, the meat of which\nconsider a delicacy;\nnearby.\nVery\nAny\nVery\nThey\ngood-\ngood-\nlong'\ndragon\nspells\ndeep\nthey\nthey\nvery\ngain\nday:\nVery\npass\nspeak\ndragon,\n~using\npair\nspells.\nwill\nwill\nleap\nbring\nlives\nthey\nthey",
  "climate_terrain": "Sub-tropical and temperate",
  "frequency": "rare",
  "organization": "Solitary or clan",
  "diet": "Special",
  "intelligence": "(11-12)",
  "treasure_type": "Special",
  "alignment": "Lawful evil",
  "number_appearing": "1 (2-5)",
  "ac": "0 (base)",
  "movement": "9, Fl 30 (C) Sw",
  "hit_dice": "13 (base)",
  "thac0": "7 (at 13 HD)",
  "attacks": "3 + special",
  "damage": "1-8/1-8/2-20 (2d10)",
  "special_attacks": "Special",
  "special_defenses": "Variable",
  "magic_resistance": "Variable",
  "size": "G (36' base)",
  "morale": "Elite (15-16)",
  "xp_value": "Variable",
  "id": "dragon_green"
}