{
  "name": "Dragon, Gold",
  "source_page": 37,
  "raw_text": "Dragon, Gold\nCLIMATE TERRAIN:\nFREQUENCY:\nVery rare\nORGANIZATION:\nSolitary\nOr\nclan\nACTIITY CYCLE:\nDIET:\nSpecial\nINTELLIGENCE:\nGenius (17-18)\nTREASURE:\nSpecial\nALIGNMENT:\nLawful\nNO: APPEARING:\n1 (2-5)\nARMOR CLASS:\n-4\n(base)\nMOVEMENT:\n12 , Fl 40 (C) Jp 3, Sw 12 (15)\nHIT DICE:\n16 (base)\nTHACO:\n5 (at 16 HD)\nNO.OF ATTACKS:\n3 +\nspecial\nDAMAGEIATTACK:\n1-10/1-10/6-36 (6d6)\nSPECIAL ATTACKS:\nSpecial\nSPECIAL DEFENSES:\nVariable\nMAGIC RESISTANCE:\nVariable\nSIZE:\nG (54' base)\nMORALE:\nFanatic (17-18)\nXP VALUE:\nVariable\nAge\nBody Lgt ()\nTail Lgt (')\nAC\nBreath\nWeapon\nSpells Wizard Priest\nMR\nTreasure Type\nXP Value\n7-19\n6-16\n2d12\nNil\nNil\nNil\n3,000\n10-31\n16-28\n4d12+2\nNil\nNil\nNil\n4,000\n31-43\n28-38\n6d12 +3\nNil\nNil\nNil\n6,000\n43-55\n38-50\n8d12 +4\nNil\nE; R T\n8,000\n55-67\n50-60\n10d12 +5\n35 %\nH, R T\n10,000\n67-80\n60-70\n12d12 +6\n2 2\n40 %\nH R T\n13,000\n80-93\n70-84\n14d12 + 7\n2 2 2\n45 %\nA;RT\n14,000\n93-100\n84-95\n1od1z + 8\n22 2 2/1\n50 %\nH R Tx2\n15,\n106-120\n95-108\n18d12 +0\n2 22 2 2/2\n55 %\nH; R Txz\n17,000\n10\n120-134\n108-120\n10\n20d12 +10\n2 2 2 2 2 2/2 2\n60 %\nA R; Tx2\n18,000\n11\n134-148\n121-133\n11\n22d12 +11\n2 2 2 2 2 2 2/2 2 2\n65 %\nH; R; Tx3\n19,000\n12\n148-162\n133-146\n12\n24d12 +12\n2 2 2 2 2 2 2 1/2 2 2 2\n70 %\nH; R; Tx3\n20,000\nGold dragons are wise, judicious, and benevolent.\noften embark on self-\nferent form; reverting to the dragon s normal form does not count as\nappointed quests to promote goodness\nare not easily distracted from\nchange: A\ndragon $ natural form has wings. However,\nsome=\nthem\nhate injustice and foul play. A\ndragon frequently assumes hu-\ntimes choose & wingless form t0 facilitate swimming, gaining the higher\nman or animal\nguise and usually will be encountered disguised.\nswimming rate listed above. A\ndragon in any wingless form can flyat\nAt birth,\ndragon'$ scales are dark yellow with golden metallic\nof 6 (MC E)\nflecks. The flecks get larger as the dragon matures until, at the adult stage\nAs\nage;\nthe following additional powers;\nbless three\nthe scales grow completely golden .\ntimes a\nday; Juvenile: detect lie three times a\nAdult: animal summoning\nGold dragons\ntheir own tongue,\na tongue common t0 all\nonce &\nMature adult: luck bonus once a\nOld: quest once a day; and\ndragons, and 18% of hatchling\ndragons have an ability to communi-\ndetect gems three times & day: (This allows the dragon to know the number\ncate with any intelligent creature_\nThe chance to possess this ability in-\nand kind of precious stones within a 30' radius, duration is one minute.\ncreases 5 % per age category of the dragon.\nThe luck bonus power of mature adults is used to aid\nadventurers,\nBy touch, the dragon can enchant one gem to\ngood luck. The gem is\nCombat:\nGold dragons usually parley before combat\nWhen conversing\nusually one which has been embedded in the dragon's hide. When the\nwith intelligent creatures\nuse detect lie and detect gems\nto\ndragon carries the gem, it and every\ncreature in a 10' radius per age\nthe upper hand: In combat,\nquickly use bless and luck bonus. Older\ncategory of the dragon receives a + 1 bonus to all Saving Throws and sim -\ndragons use luck bonus at the start of each day if the duration is a\nOr\nilar dice rolls, cf. stone of\nluck: If the dragon gives a gem to another\nmore ,\nThey make\nuse of\nin combat. Among their favorites\ncreature\nonly the bearer\nthe bonus\nThe enchantment lasts three\nare\nsleep, stinking cloud, slow, fire shield, cloudkill, globe of invulnera-\nhours per age category of the dragon, plus 1-3 hours. The enchantment\nbility, delayed blast fireball, and maze_\nends if the gem is destroyed before its duration expires.\nBreath weapon/special abilities:\nhas two breath weap-\nHabitat Society:\nGold dragons can live anywhere. Their lairs are se-\nons: a cone\nof fire 90'\n5' wide at the dragon s mouth, and 30' wide at\ncluded and always made of solid stone, either caves Or castles. These usu -\nthe end or & cloud of potent chlorine gas 50\"\n40' wide, and 30' high.\nally have loyal guards: either animals appropriate to the terrain, Or storm\nCreatures\nin either effect are entitled to\nsave\nversus breath\nOr\ncloud giants. The giants usually serve as guards through a mutual\nweapon for half damage.\ndefensive agreement.\nA\ndragon casts its\nand uses its magical abilities at Ilth level\nplus its combat modifier. Unlike other dragons,\nmost\ndragons seek\nEcology:\nGold dragons can eat almost anything. However,\nusually\nformal magical training: These dragons own\nbooks and always have\nsustain themselves on pearls or small gems_\nGold dragons who receive\nuseful\npearls and gems from\nOr neutral creatures usually will be favorably\nAt birth;\ndragons have water breathing ability; can speak with ani-\ninclined toward the\nbringers ,,as long as the\nis not presented as a\nmals freely; and are immune t0 fire and gas. They can also polymorph self\ncrass bribe. In thelatter case, the dragon will accept the gift, but react cyn -\nthree times a day: Each change in form lasts untilthe dragon chooses a dif-\nically to any requests the giver makes\nAny\nAny\ngood\nCales\nT1\n00O\nThey\ngold\nthey\nand\ngold,\nThey\ngold\nspeed\ngold\nthey\nthey\nYoung:\ngain\n~day:\nday:\nday:\ngood\nspeak\ngold\ngood\nbring\n~spells\nthey\ngain\ngood\nthey\nday\ngood\nheavy\nspells\ngets\ngold\ndragon\nlong;\nlong\"\ncaught\ngood\ngold\nspells\ngold\nthey\n'spell\ngood\nspells .\ngift\ngift\ngold",
  "frequency": "Very rare",
  "organization": "Solitary",
  "diet": "Special",
  "intelligence": "Genius (17-18)",
  "treasure_type": "Special",
  "alignment": "Lawful",
  "number_appearing": "1 (2-5)",
  "ac": "-4",
  "movement": "12 , Fl 40 (C) Jp 3, Sw 12 (15)",
  "hit_dice": "16 (base)",
  "thac0": "5 (at 16 HD)",
  "attacks": "3 +",
  "damage": "1-10/1-10/6-36 (6d6)",
  "special_attacks": "Special",
  "special_defenses": "Variable",
  "magic_resistance": "Variable",
  "size": "G (54' base)",
  "morale": "Fanatic (17-18)",
  "xp_value": "Variable",
  "id": "dragon_gold"
}