{
  "name": "Dragon; Brass",
  "source_page": 34,
  "raw_text": "Dragon; Brass\nCLIMATETERRAIN:\nArid desert and plain\nFREQUENCY;\nRare\nORGANIZATION:\nSolitary or clan\nACTIVE TIME:\nAny\nDIET:\nSpecial\nINTELLIGENCE:\nHigh (13-14)\nTREASURE:\nSpecial\nALIGNMENT:\nChaotic\n(neutral)\nNO: APPEARING:\n1 (2-5)\nARMOR CLASS:\n0 (base)\nMOVEMENT:\nFL 30 (C); Br 6\nHIT DICE:\n12 (base)\nTHACO:\nNO: OF ATTACKS:\n3 + special\nDAMAGEIATTACK:\n1-6/1-6/4-16\nSPECIAL ATTACKS:\nSpecial\nSPECIAL DEFENSES:\nVariable\nMAGIC RESISTANCE:\nVariable\nSIZE:\nG (30' base)\nMORALE:\nFanatic (17 base)\nXP VALUE:\nVariable\nAge\nBody Lgt:\nTail Lgt:\nAC\nBreath Weapon\nSpells Wizard Priest\nMR\nTreas. Type\nXP Value\n3-6\n2d4 +1\nNil/Nil\nNil\nNill\n400\n2\n6-14\n4-12\n4d4 +2\nNil/Nil\nNil\nNil\n2,000\n14-22\n12-18\n6d4 + 3\nNil/Nil\nNil\nNil\n4,000\n22-31\n18-24\n8d4 +4\nNil\n1/2H\n7,000\n31-41\n24-34\n10d4 +5\n11\n15 %\nH\n9,00o\n41-52\n34-44\n~2\n12d4\n2 1\n20%\nH\n10,000\n52-64\n44-54\n14d4 + 7\n2 2\n25 %\nH\n11,000\n8\n64-77\n54-64\nJod4 + 8\n3 2/1\n30%\nHx2\n13,000\n77-91\n64-74\n18d4 +9\n3 3/11\n3500\nHxz\n14,000\n10\n91-105\n74-84\n20d4 + 10\n4 3/2 1\n40 %\nHx2\n15,000\n11\n105-121\n84-94\n~7\n22d4 +11\n4 4/2 2\n45 %\nHx3\n16,000\n12\n121-138\n94-104\n24d4+12\n5 4/3 2\n50 %\nHx3\n17,000\nBrass dragons are great talkers, but not particularly\nconversational-\nYoung: create or destroy water three times a day: luvenile: dust devil once\nists. They are egotistical and often boorish. They often have useful infor-\nday. Adult: suggestion once a\nMature adult: control temperature 3\nmation, but will divulge it only after drifting off the subject many times\ntimes a\nin a 10' radius per age level\nOld; control winds once a day:\nand after hints that a gift would be appreciated,\nGreat wyrm; Summon djinni once a week_\nThe dragon usually asks the\nAt birth,\nbrass dragon $ scales are dull. Their color\nbrassy; mottled\ndjinni to preform some service. Although the djinni serves willingly, the\nbrown . As the dragon gets older; the scales become more brassy;\ndragon will order it into combat only in extreme circumstances, as the\nthey reach a warm , burnished appearance_\ndragon would be dismayed and embarrassed if the djinni were killed.\nCombal:\nBrass dragons would rather talk than fight: If an intelligent\nHabitat Society:\nBrass dragons are found in arid, warm climates; rang-\ncreature tries t0 take its\nof a brass\ndragon without talking to it at\nfrom sandy deserts t0\nsteppes\nlove intense,\nheat and\nlength, the dragon might have a fit of pique and\nto force & conversa -\nmost of their time basking in the sun_\nlair in high caves\ntion with\nsuggestion or by giving the victim a dose of_\ngas. If the vic-\nerably facing east where the sun can warm the rocks, and their territories\ntim falls asleep it will awaken to find itself pinned under the dragon\nOr\nalways contain several spots where they can bask and trap unwary trav-\nburied to the neck in the sand until the dragon $ thirst for small talk is\nelers into conversation.\nslaked . Before melee, brass dragons create a cloud of dust with dust devil\nBrass dragons are very social. They usually are on\nterms with\nOr control winds, then\nOr\nsnatch . Brass dragons often use control\nneighboring brass dragons and sphinxes\nBrass dragons are dedicated par-\ntemperature to create heat to discomfort their opponents_\nWhen faced\nents. If their young are attacked they will try to slay the enemy; using their\nwith real danger, younger brass dragons will fly out of sight, then hide by\nheat breath weapons and taking full advantage of their own immunity:\nburrowing. Older dragons spurn this ploy:\nBecause they share the same habitat, blue dragons are brass dragons\nworst enemies. Brass dragons usually get the worst of a ne-on-one con-\nBreath weapon/special abilities:\nA brass dragon has two breath weap-\nfrontation, mostly because of the longer reach of the blue dragon's breath\nons: a cone of\ngas 70'\n5' wide at the dragon's mouth; and 20'\nweapon . Because of this, brass dragons usually try to evade blue dragons\nwide at its end; or a cloud of blistering desert heat 50'\n40' wide, and\nuntil they can rally their neighbors for a mass attack.\n20' high. Creatures caught in the gas, regardless of Hit Dice or level , must\nsave VS . breath weapon or fall\nasleep for 10 minutes per age level of the\nEcology:\nLike other dragons, brass dragons can, and will,\neat almost\ndragon. Creatures caught in the heat take damage;\nsave\nVS .\nbreath\nanything if the need arises. In practice, however, they eat very little.\nweapon for half. A brass dragon casts its\nand uses its magical abili-\nare able to\nnourishment from morning dew, a rare commodity in their\nties at 6th level, plus its combat modifier.\nhabitat, and have been seen carefully\nit off plants with their\nAt birth, brass dragons can speak with animals freely, and are immune\ntongues\nto fire and heat. As\nage,\nthe following additional powers:\ngood\n12,\n2-5\nF6\n4\ngood\nday;\nday\nTis a\nuntil\ndry\nThey\n~dry\ning\nleave\nThey\npref-\nspend\ntry\n~sleep\ngood\ncharge\nlong\nsleep\nlong'\nThey\nspells\nget =\nlifting\nlong\nthey\nthey\n~gain",
  "climate_terrain": "Arid desert and plain",
  "frequency": "Rare",
  "organization": "Solitary or clan",
  "activity_cycle": "Any",
  "diet": "Special",
  "intelligence": "High (13-14)",
  "treasure_type": "Special",
  "alignment": "Chaotic",
  "number_appearing": "1 (2-5)",
  "ac": "0 (base)",
  "movement": "FL 30 (C); Br 6",
  "hit_dice": "12 (base)",
  "attacks": "3 + special",
  "damage": "1-6/1-6/4-16",
  "special_attacks": "Special",
  "special_defenses": "Variable",
  "magic_resistance": "Variable",
  "size": "G (30' base)",
  "morale": "Fanatic (17 base)",
  "xp_value": "Variable",
  "id": "dragon_brass"
}