{
  "name": "Dragon; Red",
  "source_page": 39,
  "raw_text": "Dragon; Red\nCLIMATETERRAIN:\nTropical, sub-tropical , and\ntemperate hills and mountains\nFREQUENCY:\nrare\nORGANIZATION:\nSolitary or clan\nACTIVITY CYCLE:\nDIET:\nSpecial\nINTELLIGENCE:\nExceptional (15-16)\nTREASURE:\nSpecial\nALIGNMENT:\nChaotic evil\nNO.APPEARING:\n1 (2-5)\nARMOR CLASS:\n~3 (base)\nMOVEMENT:\n9, Fl 30 (C), Jp 3\nHIT DICE:\n13 (base)\nTHACO:\n7 (at 9 HD)\nNO: OF ATTACKS:\n3 +\nDAMAGEATTACK:\n1-10/1-10/3-30 (3d10)\nSPECIAL ATTACKS:\nSpecial\nSPECIAL DEFENSES:\nVariable\nMAGIC RESISTANCE:\nVariable\nSIZE:\nG (48' base)\nMORALE:\nFanatic (17-18)\nXP VALUE:\nVariable\nAge\nBody Lgt (')\nTail Lgt:\nAC\nBreath Weapon\nSpells Wizard Priest\nMR\nTreasure\nXP Value\n1-12\n3- 12\n2d10 + 1\nNil\nNil\nNil\n3,000\n12-23\n12-21\n4d10 +2\nNil\nNil\nNil\n4,000\n21-30\n6d10 +3\nNil\nNil\nNil\n6,000\n23-42\n8d10 +4\nNil\nEST\n8,000\n42-61\n30-49\n61-80\n49-68\n10d10 +5\n30 %\nHST\n10,000\n80-90\n68-87\n12d10+6\n2 1\n35 %\nHST\n11,000\n99-118\n87-106\n14d10 +7\n2 2\n40 %\nHST\n12,000\n118-137\n106-125\n1od10 + 8\n2 2 1\n45 %\nHSTx2\n15,000\n8\n125-144\n18d10+9\n2 2 2\n50 %\nHSTx2\n17,000\n137-156\n10\n156-165\n144-153\n20d10+10\n2 2 2 1/1\n55 %\nHSTx2\n18,000\n11\n165-174\n153-162\n10\n22d10+11\n2 2 2 2/2\n60 %\nHSTx3\n19,000\n12\n174-183\n162-171\n11\n24d10 +12\n2 2 221/2 1\n65 %\nHSTx3\n20,000\nRed dragons are the most covetous and greedy of all dragons, forever\nCreatures struck by the flames must save versus breath weapon for half\nseeking to increase their treasure hoards. They are obsessed with their\ndamage. Red dragons cast\nat %th level, adjusted by their combat\nwealth and memorize an inventory accurate t0 the last copper\nare\nmodifiers_\nexceptionally vain and self confident, considering themselves superior not\nRed dragons are born immune to fire: As they age, they\nthe follow-\nonly to other dragons, but to all other life in general,\nadditional powers: Young: affect normal fires three times per day Ju-\nWhen red dragons hatch, their small scales are & bright glossy scarlet. Be-\nvenile: pyrotechnics three times per\nAdult: heat metal once per day:\ncause of this, they can be quickly spotted by predators and men hunting for\nOld: suggestion once\nday;\nold: hypnotism once per day. Venera-\nskins, 50 they are hidden in deep underground lairs and not permitted to ven-\nble: detect gems\nkind and number in a 100' radius three times a day:\nture outside until toward the end of their young stage when their scales\nturned a\ndeeper red, the glossy texture has been replaced by a smooth, dull fin-\nHabitat Society:\nRed dragons can be found on great hills or on soaring\nish, and\nare more able to take care of themselves.\nAs the dragon con-\nmountains. From a high\nthey haughtily survey their territory; which\ntinues to age, the scales become large, thick, and as strong as metal:.\nthey consider to be everything that can be seen from their position. They\nRed dragons\ntheir own tongue;\na tongue common to all evil\nprefer to lair in\ncaves that extend deep into the earth.\ndragons, and 16% of hatchling red dragons have an ability to communi-\nA red dragon enjoys its own company; not associating with other crea-\ncate with any intelligent creature_\nThe chance to possess this ability in-\ntures\nor even other red dragons, unless the dragon's aims can be fur-\ncreases 5% per age category of the dragon\nthered . For example, some\nwho have charm\nwill order\nmen to act as the dragon's eyes and ears, gathering information about\nCombat:\nBecause red dragons are s0 confident, they never pause to ap-\nnearby settlements and sources of treasure. When\nred dragons's off=\nan adversary When\nnotice a target they make & snap decision\nspring reach the young adult stage, they are ordered from the lair and the\nwhether to attack, using one of many\n'perfect\" strategies worked out\nsurrounding territory, as\nare viewed as\ncompetition.\nahead of time in the solitude of their lairs_\nIf the creature appears small\nRed dragons are\nto fight all creatures which encroach on their ter-\nand\ninsignificant, such as an unarmored man, the dragon\nland to at-\nritory; especially copper and silver dragons which sometimes share the\ntack with its claws and bite, not wanting to obliterate the creature with its\nsame environment\nhate\ndragons above all else because\nbreath weapon, as any treasure might be consumed by the flames; How-\nbelieve\ndragons are \"nearly'\naS\npowerful as themselves _\never; if a red dragon encounters & group of armored men, it will use its\nbreath weapon, special abilities, and\n(if it is old enough to have\nRed dragons are meat eaters, although\nare\n'capable of di-\nthem) before landing\ngesting almost anything. Their favorite food is a maiden of any human or\ndemi-human race. Sometimes the dragons are able to charm key villagers\nBreath\nweapor/special abilities:\nAred dragon $ breath weapon is & sear-\ninto\nregularly sacrificing maidens to them.\ncone of fire 00'\n5' wide at the dragon s mouth and 30' at the base.\nVery\nAny\nspecial\nType\nspells\nThey\nBain\ning\nday:\nVery\nper\nhave\nperch\nthey\nlarge\nspeak\nspells\ndragons\nred\nthey\npraise\nthey\nquick\nwill\nthey\ngold\nThey\ngold\nEcology:\nthey\n~spells\nlong,\ning \"",
  "climate_terrain": "Tropical, sub-tropical , and",
  "frequency": "rare",
  "organization": "Solitary or clan",
  "diet": "Special",
  "intelligence": "Exceptional (15-16)",
  "treasure_type": "Special",
  "alignment": "Chaotic evil",
  "number_appearing": "1 (2-5)",
  "ac": "~3 (base)",
  "movement": "9, Fl 30 (C), Jp 3",
  "hit_dice": "13 (base)",
  "thac0": "7 (at 9 HD)",
  "attacks": "3 +",
  "damage": "1-10/1-10/3-30 (3d10)",
  "special_attacks": "Special",
  "special_defenses": "Variable",
  "magic_resistance": "Variable",
  "size": "G (48' base)",
  "morale": "Fanatic (17-18)",
  "xp_value": "Variable",
  "id": "dragon_red"
}