{
  "name": "Dragon Turtle",
  "source_page": 42,
  "raw_text": "Dragon Turtle\nCLIMATETERRAIN:\nSubtropical and temperate fresh\nand salt water\nFREQUENCY:\nrare\nORGANIZATION:\nSolitary\nACTIVITY CYCLE:\nAny\nDIET:\nCarnivore\nINTELLIGENCE:\nVery (11-12)\nTREASURE:\nB,R,S,TV\nALIGNMENT:\nNeutral\nNO. APPEARING:\nARMOR CLASS:\nMOVEMENT:\n3, Sw 9\nHIT DICE:\n12-14\nTHACO:\n12 Hit Dice: 9\n13-14 Hit Dice: 7\nNO. OF ATTACKS:\nDAMAGEIATTACK:\n2-12/2-12/4-32\nSPECIAL ATTACKS:\nBreath weapon , capsize ships\nSPECIAL DEFENSES:\nNil\nMAGIC RESISTANCE:\nNil\nSIZE:\nG (30' diameter shell)\nMORALE:\nFanatic (17)\nXP VALUE:\n12 Hit Dice: 10,000\n13 Hit Dice: 11,000\n14 Hit Dice: 12,000\ncreatures\nmaking\nsaving throw versus breath weapon take half\nturtles are one of the most beautiful,\nawesome;\nand feared\ndamage\nLike true dragons\ndragon turtles\ncan\nuse\nthis deadly\ncreatures of the water: With their deadly jaws and breath weapon\nbreath weapon three times a\nand their penchant for capsizing ships, dragon turtles are dreaded\nby mariners on\nbodies of water, both fresh and salt.\nHabitat Society:\nDragon\nturtles\nare\nextremely  solitary\ncred-\nWhen a\ndragon turtle surfaces, it is sometimes mistaken for the\ntures\ndesolate sea caves and secret underground caverns\nreflection of the sun\nor moon on the water;\nturtle's rough,\nthat\ncan\nbe accessed only through the water are their favorite\ndeep green shell is much the\nsame color as the deep water the\nlairs. These lairs are difficult to find, but adventurers locating\nmonster favors, and the silver highlights that line the shell\nare\ndragon turtle s cave will find it filled with treasures of all types.\npatterned like light dancing on open water: The turtle s legs and\nThe turtle gathers this treasure, which it will protect to the death,\ntail are of a lighter green,\nand they are flecked with\ngolden high-\nfrom the ships sunk in its territory:\nlights. The coloration of the creature s head is similar to the\nA dragon turtle s territory is well-defined and may\ncover a5\nand tail, but its crest spines are\ngolden with dark green webbing\nmuch as\nfifty square miles of open water: Other dragon turtles are\nconnecting them: A dragon turtle's shell can reach to 30 feet in di-\nallowed into this area only during mating season, though turtles\nameter;\nand\nan\nadult turtle can measure\nover 40 feet from its\nof the same sex will always fight to the death upon meeting. It is\nsnout to the tip of its tail. Dragon turtles speak their own highly-\nthis hostility toward their\nown\nkind that\nthe number of\ndeveloped language.\ndragon turtles relatively low.\nMariners of any experience recognize the territorial claims of\nCombat:   Though dragon turtles may be mistaken for the pleas-\ndragon turtles and will often make extravagant tributes to the tur-\nant\nsight of light glinting off of water, that illusion is never main-\ntle controlling areas necessary for safe and speedy trade.\ntained for long: Dragon turtles are fierce fighters and will generally\nattack any creature that threatens its territory Or presents itself as a\nEcology:   Dragon turtles\nare carnivorous and will eat almost\npotential meal. In combat, dragon turtles will usually (90 % ) attack\nany creature\nincluding humans or other dragon turtles\nto satisfy\nwith their formidable claws and teeth first. Its shell provides the\ntheir voracious appetite. Large fish seem to be the prefered food\nturtle with\nexcellent protection,  though\nonce the dragon\nturtle\nfor\nturtles\nand the turtles can often be found\nlurking in\nstrikes\nvictim, it rarely needs to rely upon this safeguard.\nthe weeds and muck at the bottom of a lake or sea waiting for fish\nThe dragon turtles shell also provides the creature with\nto pass. In particularly poor years for fish,\ndragon turtles have\nweapon to attack ships that foolishly pass through\nIts\nterritory\nbeen known to use their breath weapon to kill large groups of sea\nuninvited. Sinking as deep as necessary the dragon turtle will\nbirds that stray too close t0 the water for food\nwait for the ship to pass over it and then rise Up underneath the\nConflict often arises between dragon turtles and the many in-\nvessel;\nusing all of its considerable bulk to capsize the unlucky\ntelligent aquatic races , like the locathah or mermen\nbecause of\ntarget. Ships under 20 feet in length will be capsized by this attack\ncompetition for ideal lairs. Like many of their land-based rela-\n95 9 of the time, vessels from 20 t0 60 feet\nwill be capsized\ntives, dragon turtles are considered treacherous and selfish by all\n50% of the time, and ships over 60 feet will be capsized 20 % of\ncreatures that share their domain_\nthe time. Ships not capsized will sustain some damage.\nDragon turtle shells make outstanding shields and armor:\nBe=\nIn\ncombat\nwhen\nneither its bite\nnor its capsizing\nattack is\ncause of the shell's\nstrength and natural resistance to the dragon\nenough\ndefeat\nan enemy\ndragon turtle will use its breath\nturtle's own breath weapon,\narmor\nOr 4\nshield made out of this\nweapon . The turtle can belch forth a cloud of scalding steam that\nmaterial\n+1t0 its defensive rating: The shield Or armor will\nwill cover an area 60 feet\n40 feet wide, and 40 feet high. This\nalso save as an item\nagainst destruction by fire or steam-based at-\nattack causes 20-120 points of damage (20d6), and characters Or\ntacks at +4\nVery\nDragon\nday:\nlarge\nLarge,\nThe\nlegs\nkeeps\ndragon\nJong\ngains\nlong;",
  "climate_terrain": "Subtropical and temperate fresh",
  "frequency": "rare",
  "organization": "Solitary",
  "activity_cycle": "Any",
  "diet": "Carnivore",
  "intelligence": "Very (11-12)",
  "treasure_type": "B,R,S,TV",
  "alignment": "Neutral",
  "movement": "3, Sw 9",
  "hit_dice": "12-14",
  "thac0": "12 Hit Dice: 9",
  "damage": "2-12/2-12/4-32",
  "special_attacks": "Breath weapon , capsize ships",
  "special_defenses": "Nil",
  "magic_resistance": "Nil",
  "size": "G (30' diameter shell)",
  "morale": "Fanatic (17)",
  "xp_value": "12 Hit Dice: 10,000",
  "id": "dragon_turtle"
}