{
  "name": "Dragon, Blue",
  "source_page": 33,
  "raw_text": "Dragon, Blue\nCLIMATETERRAIN:\nArid deserts\nFREQUENCY:\nVery rare\nORGANIZATION:\nSolitary or clan\nACTIVE TIME:\nDIET:\nSpecial\nINTELLIGENCE:\n(11-12)\nTREASURE:\nSpecial\nALIGNMENT:\nLawful evil\nNO. APPEARING:\n1 (2-5)\nARMOR CLASS:\n0 (base)\nMOVEMENT:\n9, Fl 30 (Ch Br 4\nHIT DICE:\n14 (base)\nTHACO:\n8 (base)\nNO: OF ATTACKS:\n3 + special\nDAMAGE/ATTACK:\n1-8/1-8/3-24\nSPECIAL ATTACKS:\nSpecial\nSPECIAL DEFENSES:\nVariable\nMAGIC RESISTANCE:\nVariable\nSIZE:\nG (42' base)\nMORALE:\nFanatic (10 base)\nXP VALUE:\nVariable\nAge\nBase Lgt:\nTail Lgt: (')\nAC\nBreath Weapon\nSpells Wizard Priest\nMR\nType\nXP Value\n3-9\n2-7\n2d8\nNil\nNil\nNIl\n1,400\n0-20\n7-L6\nAd8 + 2\nNil\nNil\nNil\n2,000\n20-31\n16-25\n6d8 + 3\nNil\nNil\nNil\n4,000\n31-50\n25-34\n8d8 + 4\nNil\n1/2H, $\n7,000\n50-69\n34-43\nFl\n10d8 + 5\n20 %\nH; S\n9,000\n69-88\n43-52\n-2\n12d8 + 6\n25 %\nH; S\n10,000\n88407\n52-61\n~3\n14d3 + 7\n30 %\nA;S\n11,000\n97-106\n01-70\n=4\nlod8 + 8\n3 2\n35 %\nH; Sx2\n12,000\n106-115\n70-79\n18d8 +0\n3 3\n40%0\nH; Sx2\n14,000\n10\n115-124\n70-80\nF0\n20d8 +10\n3 3 1/1\n45 %\nH; Sx2\n15,000\n11\n124-133\n80-89\nF7\n22d8 + 11\n3 3 2/2\n50 %\nH; Sx3\n16,000\n12\n133-142\n89-98\n-8\n24d8 + 12\n3 3 3/3\n55 %\nH; Sx3\n17,000\nBlue dragons are extremely territorial and voracious. They love to spend\nfor half damage. Blue dragons cast\nand use their magical abilities at\nhours preparing ambushes for herd animals and unwary travelers,\n7th level, adjusted by their combat modifier:\nand\nequally\nhours dwelling on their success and admiring\nBlue dragons are born with an immunity to electricity As they age,\ntheir trophies\nthe following additional powers;\ncreate Or destroy water\nThe size of a blue dragon $ scales increases little as the dragon ages, al-\nthree times per day: Juvenile: sound imitation at will.\nAdult: dust devil\nthough they do become thicker and harder: The scales vary in color from\nonce &\nday: Old: ventriloquism once a\nVenerable: control winds once\nan\niridescent azure t0 a deep indigo, retaining a glossy finish through all of\nGreat wyrm: hallucinatory terrain once & day:\nthe dragon's stages because the blowing desert sands polish them\nThis\nHabitat Society:\nmakes blue dragons easy to spot in barren desert surroundings. However;\nBlue dragons are found in deserts; arid,  windswept\nthe dragons often conceal themselves, burrowing into the sand s0 only\nplains; and hot, humid badlands_\nthe bleak terrain\npart of their heads are exposed.\nthere are few obstacles\nonly an occasional rock outcropping Or dune\nBlue dragons love to soar in the hot desert air; usually flying in the daytime\nto interrupt the view of their territories.\nhours looking out\nwhen temperatures are the highest. Some blue dragons nearly match the color\nover their domains, watching for trespassers and admiring their property:\nof the desert sky and use this coloration t0 their advantage in combat:\nMost of the blue dragons encountered will be alone because\ndo not\nBlue dragons\ntheir own tongue,\ntongue common to all evil\nwant to share their territories with others. However; when a family is en-\ndragons, and 12% of hatchling blue dragons have an ability to communi-\ncountered the male  dragon\nwill\naltack ferociously;\nprotecting his\ncate with any intelligent creature. The chance to possess this ability in-\nproperty\nhis\nand young: The female\nalso will join in the at-\ncreases 5 % per age category of the dragon.\ntack if the threat proves significant.\nBlue dragons' enemies are men, who kill the dragons for their skin and\nCombat:\nBlue dragons prefer to fight from & distance s0 their opponents\ntreasure, and brass dragons, which share the same environment. If a blue\ncan clearly witness the full force of their breath weapon and s0 little or no\ndragon discovers a brass dragon in the same region, it will not rest until\nthreat is posed to themselves. Often blue dragons will attack from directly\nthe trespassing dragon is killed or driven away:\nabove Or\nburrow beneath the sands until opponents come within 100\nBlue dragons lair in vast underground caverns in which\nstore their\nfeet. Older blue dragons will use their special abilities, such as hallucina-\ntreasure\nAlthough blue dragons will collect anything which looks valu-\ntory terrain, in concert with these tactics t0 mask the land and aid in their\nable;\nare fond of gems\nespecially sapphires\nchances to surprise. Blue dragons will only run\nfight if they are se-\nverely damaged\nas\nalso view retreat as cowardly.\nEcology:\nBlue dragons are able to consume nearly anything; and some-\ntimes are forced to eat snakes, lizards, and desert plants to help sate their\nBreath weapon/special abilities:\nA blue dragon $ breath weapon is a 5'\ngreat hunger: However;\nare\nparticularly fond of herd animals, such\nwide bolt of lightning that streaks 100' in a straight line from the dragon $\nas\ncamels, and\nwill gorge themselves on caravans of the creatures\nmouth. All creatures caught in this stream must save Vs. breath weapon\nwhich\nhave cooked with a lightning bolt:\nAny\nVery\nTreas.\n1\nspells\nlong\nthey\nspend\nlong\nthey\nYoung:\ngain\nday:\nday:\nThey\nenjoy\nbecause\nThey\nspend\nthey\nspeak\ndragon\nmate\nwill\nthey\nthey\nfrom\nthey\nthey\nthey\nthey",
  "climate_terrain": "Arid deserts",
  "frequency": "Very rare",
  "organization": "Solitary or clan",
  "diet": "Special",
  "intelligence": "(11-12)",
  "treasure_type": "Special",
  "alignment": "Lawful evil",
  "number_appearing": "1 (2-5)",
  "ac": "0 (base)",
  "movement": "9, Fl 30 (Ch Br 4",
  "hit_dice": "14 (base)",
  "thac0": "8 (base)",
  "attacks": "3 + special",
  "damage": "1-8/1-8/3-24",
  "special_attacks": "Special",
  "special_defenses": "Variable",
  "magic_resistance": "Variable",
  "size": "G (42' base)",
  "morale": "Fanatic (10 base)",
  "xp_value": "Variable",
  "id": "dragon_blue"
}