{
  "name": "Dragon,_White",
  "source_page": 41,
  "raw_text": "Dragon,_White\nCLIMATETERRAIN:\nArctic plains, hills,\nmountains\nand subterranean\nFREQUENCY:\nRare\nORGANIZATION:\nSolitary or clan\nACTIVITY CYCLE:\nAny\nDIET:\nSpecial\nINTELLIGENCE:\nLow (5-7)\nTREASURE:\nSpecial\nALIGNMENT:\nChaotic evil\nNO. APPEARING:\n(2-5)\nARMOR CLASS:\n(base )\nMOVEMENT:\n12, Fl 40 (C), Br 6, Sw 12\nHIT DICE:\n11 (base)\nTHACO:\n(at 11 HD)\nNO. OF ATTACKS:\n3 +\n~special\nDAMAGEIATTACK:\n1-6/1-6/2-16 (2d8)\nSPECIAL ATTACKS:\nSpecial\nSPECIAL DEFENSES:\nVariable\nMAGIC RESISTANCE:\nVariable\nSIZE:\nH (24\nbase)\nMORALE:\nElite (15-16)\nXP VALUE:\nVariable\nAge\nBody Lgt.(')\nLgt:\nAC\nBreath Weapon\nSpells Wizard Priest\nMR\nTreasure\nXP Value\nId\nNil\nNil\n400\n5-14\n4- 12\n2d6\nNil\nNil\nNil\n2,000\n14-23\n12 -21\n3do\nNil\nNil\nNil\n3,000\n23-32\n21 - 28\n4d6 + 4\nNil\nNil\n5,000\n32-41\n28- 36\nSd6\nNil\n5 %\nE; 0, 5\n7,000\n41-50\n30-45\nodo +6\n10%0\nE; 0, S\n000\n50-59\n45-54\n7do\n15 %0\nE; 0 $S\n10,000\n50-08\n54-02\n8d6\n20%0\nE; 0, Sx2\n11,000\n68-77\n62-70\n9do\n25 00\nE; 0,\n5x2\n13,000\n77-86\n70-78\n1Odo + 10\n30%0\nE; 0, Sx2\n14,000\n80-05\n78-85\nLdo + 11\n35 %0\nE; 0,Sx3\n15,000\n12\n05-104\n85-94\n12d6 + 12\n40%0\nE; 0, Sx3\n16,000\nWhite dragons, the smallest and weakest of the\ndragons\nare slow\nwhich allows the dragon t0 walk across ice as easily as creatures walk\nted but efficient hunters. They are impulsive\nvicious\nand animalistic,\nacross\ndry ground,\nMature adult: gust of wind three times\nday: Very\ntending t0 consider only the needs and emotions of the moment and hav-\nold: wall of fog three times\nthis produces snow or hail rather than\ning\nno foresight\nor regrel.\nDespite their low intelligence;\nthey are as\nTain\nWyrm: freezing fog three times\nday: This obscures vision in a 100'\ngreedy and\nas the other\ndragons -\nradius and causes Frost t0 form; creating\nthin\nof glare ice on the\nThe scales of\nhatchling\ndragon\nare\nmirror-like glistening\nground and on all surfaces within the radius.\nwhite, which makes them virtually invisible against\nsnowy background:\nAs the dragon ages,\nthe sheen disappears\nand by the time\nreaches the\nHabitat Society:\nWhite dragons live in chilly or cold regions\npreferring\nvery old stage; scales of pale blue and light gray are mixed in with the\nlands where the temperature rarely rises above freezing\nice and snow\nwhite.\nalways\ncover the\nground.\nWhen temperatures become t0o warm\nthe\nWhite dragons\ntheir own tongue\ntongue common t0 all\ndragons become lethargic_\nWhite dragons bask in the frigid winds that\ndragons,\n790 of hatchling white dragons have an ability to communi-\nwhip over the landscape\nand they wallow and play in\nsnow banks\ncate\nwith any intelligent creature: The chance to possess this ability in-\nWhite dragons are lackadaisical parents\nAlthough the young remain\ncreases 5 % per age category of the dragon;\nwith the parents from hatchling to juvenile or young adult stage, they are\nnot protected. Once\ndragon passes\nils\nhatchling stage,\nmust Fend\nCombat:\nRegardless of\ntarget $ size ,\nwhite dragon's favorite method\nfor itself , learning how to hunt and defend itself by watching the parents.\nof attack is to use its breath weapon and\nabilities before closing to\nWhite dragons\nlairs\nare usually icey\ncaves and deep subterranean\nmelee. This tactic sometimes works t0 the dragon $ detriment,\na5 It can ex-\nchambers;\nselect caves that open away from the warming rays of the\nhaust its breath weapon on\nsmaller prey and then be faced with\nlarger\nsun\nWhite dragons store all of their treasure within their lair; and prefer\ncreature it must attack\nphysically If a white dragon is pursuing creatures\nkeeping\nin caverns coated in ice\nwhich reflect the gems and coins and\nin the water; such as\nbears Or seals, it will melee them in their ele-\nmake the treasure appear even\nThey are fond of gems, especially\nment; fighting with its claws and bite.\ndiamonds\nbecause they are pretty t0 look at\nBreath\nabilities:\nA white dragon $ breath weapon is\nEcology:\nAlthough white dragons\nall other dragons\nare\nable t0 eat\ncone of\n{FeosozosForia =\nFrost 70\"\nwide at the dragon's mouth;\nand 25' wide al the\nnearly anything\nthey are very particular and will consume only food\nbase\nCreatures caught in the blast may Save versus Breath\nfor\nwhich has\nfrozen\nUsuallv after\ndragon has killed\ncreature with its\nhalf damage_\nA white dragon casts its spells and uses its magical abilities\nbreath weapon it will fall to devouring it while the carcass is\nstiff and\nat Sth level, plus its combat modifier:\nfrigid. It will\nother kills in snow banks until they are suitably frozen.\nFrom their birth, white dragons are immune to cold_\nAs they grow\nWhite dragons natural enemies are frost giants who kill\ndragons for\nolder; they gain the following additional abilities: Juvenile: ice walking,\nfood and armor and subdue them t0 use for guards and mounts;\nType\nTail\nevil\nWvit=\nFlal ,\nday:\nJayer\nevil\nevil\nwhite\nand\nevil\nspeak\ndeep\nand\nfrom\nspecial .\nthey\nlarger:\npolar\nWeapon\nbeen\nstill\nbury\nthe ,",
  "climate_terrain": "Arctic plains, hills,",
  "frequency": "Rare",
  "organization": "Solitary or clan",
  "activity_cycle": "Any",
  "diet": "Special",
  "intelligence": "Low (5-7)",
  "treasure_type": "Special",
  "alignment": "Chaotic evil",
  "number_appearing": "(2-5)",
  "ac": "(base )",
  "movement": "12, Fl 40 (C), Br 6, Sw 12",
  "hit_dice": "11 (base)",
  "thac0": "(at 11 HD)",
  "attacks": "3 +",
  "damage": "1-6/1-6/2-16 (2d8)",
  "special_attacks": "Special",
  "special_defenses": "Variable",
  "magic_resistance": "Variable",
  "size": "H (24",
  "morale": "Elite (15-16)",
  "xp_value": "Variable",
  "id": "dragon_white"
}