{
  "name": "Elf",
  "source_page": 48,
  "raw_text": "Elf\nCLIMATETERRAIN:\nTemperate to subtropical forest\nFREQUENCY:\nUncommon\nORGANIZATION:\nBands\nACTIITY CYCLE:\nAny\nDIET:\nOmnivore\nINTELLIGENCE:\nHigh to Supra- (14-20)\nTREASURE:\nIndividual: N; G,S,T in lair\nALIGNMENT:\nChaotic good\nNO. APPEARING:\n20-200\nARMOR CLASS:\n5 (10)\nMOVEMENT:\n12\nHIT DICE:\nt1\nTHACO:\n10 (18)\nNO. OF ATTACKS:\nDAMAGE ATTACK:\n1-10 (weapon)\nSPECIAL ATTACKS:\n+1to hit with bow or sword\nSPECIAL DEFENSES:\nSee below\nMAGIC RESISTANCE:\n90 % resistance t0 sleep and all\ncharm-related\nSIZE:\nM (5\ntall)\nMORALE:\nElite (13)\nXP VALUE:\n420\nThough their lives span several human generations,\nelves appear\nat first glance to be frail when compared to man\nHowever; elves\nhave a number of special talents that more than make up for their\nAlthough their constitutions\nare\nweak\nelves have extremely\nslightly weaker constitutions.\nstrong wills. Elves have such strong wills,\nfact, that they are\nHigh elves\nthe most common type f elf, are somewhat shorter\n90 % immune to all charm and sleep\nAnd even if their natu-\nthan men,\nnever growing much over than 5 feet tall. Male elves\nral resistance to these\nfails,  they get\nnormal saving\nusually weigh between 90 and 120 pounds,\nand female elves only\nthrow\n~making it unlikely an elf will fall victim to these\nweigh between 70 and 100 pounds. High elves are dark-haired;\nvery often_\nand their eyes are always & beautiful, deep shade of green\nand\nElves live in the wild ,\nso weapons are used for everything from\nhave infravision up to 60 feet. The features of an elf are delicate\ndealing with the hostile creatures that live around their camps,\n#0\nand finely chiseled.\nsuch mundane tasks as hunting dinner: The elves' rigorous train-\nElves are very\nof complexion , which is odd because they\ning with bows and swords,\nin addition to their great dexterity,\nspend\ndeal of time outdoors. They also tend to be slim;\ngives them\nnatural bonus of\n+1 to hit when fighting with\nlooking almost  fragile.\nBoth their\ncomplexion\nand slight\nshort\nlong sword,\na bow of any kind other than\nbuild are the results of a constitution that is weaker than man's_\ncrossbow. Elves are especially proficient in the use of the bow.\nElves, therefore, always subtract one point from their initial Con-\nBecause of their agility,\nelves can move, fire\nbow, then\nmove\nstitution ability score. Though they are not as sturdy as humans\nagain, all in the same round, making their archers extremely mo-\nelves are much more\nand they always\none\nto their\nbile\nand therefore dangerous.\ninitial Dexterity ability score_\nBecause of horses' limitations in forest combat; elves do not fa-\nElvish clothing tends to be colorful, but not\nThey often\nvor their use. Elves prefer to fight as foot soldiers and are generally\nwear\npastel colors,  especially blues and\ngreens\nBecause they\narmed as such: Most elves wear scale, ring,\nchain mail;\nand al-\ndwell in forests, however, high elves will often\nwear\ngreenish-\nmost all high elves carry shields. And although elves have natural\ngrey cloaks to afford them quick camouflage.\nbonuses when\n'they use bows and swords, their bands carry a vari-\nElves have learned that it is\nimportant t0 understand the\nety of weapons. The composition of a band of elves by weaponry\ncreatures-\n~both good and evil\n-that share their forest home\nBe=\niS: spear\n30 % ; sword\n20\nsword and spear\n20 % ; sword and\ncause of this\nelves may speak the tongue of goblins,\norcs, hob-\nbow\n-10% ; bow_15 % ; two-handed sword-\n5 %\ngoblins\ngnomes, and halflings,\naddition to common\nElvish fighters and multi-class fighters have a 10 % chance per\nand their\nown\nhighly-developed language\nThey   will  always\nlevel to possess\nmagical item of use to his or her class. This per-\nshow an interest in anything that will allow them to communicate\ncentage is cumulative and can be applied\neach major type of\nwith, and learn from, their forest-dwelling neighbors_\nmagical item that character could possibly use__for each class in\nthe case of multi-class characters. (For example\nFighter / E\nCombat: Elves\nare cautious fighters and will always\nusC\ntheir\nof level 4/5 would have a 40 % chance to have a magical item use-\nstrengths to an advantage if possible: One of the greatest strengths\nful to fighters and\n50 %\nhaving\nan item useful to\nelves have is their ability to pass through natural surroundings,\npriests.\nIn addition, if above 4th level, elvish mages\nthe\nsuch as a wood or forest, silently and almost invisibly By moving\nsame percentage chance t0\nitems\nbut\n2-5 magical items\nquietly and blending into the vegetation for cover; elves can often\nuseful to them if & successful roll is made\nsurprise\nperson Or party (opponents have & surprise modifier of\nFor every twenty elves in a group, there will be one Znd or 3rd\n-5)\nAlso, as long as they are not\nattacking, the elves\nhiding in the\nlevel fighter (50% chance of either)\nFor every forty elves in a\nforest can only be spotted by someone or something with the abil-\ngroup\naddition to the group's higher level fighter, there will be\nity to see invisible objects. The military value of this skill is im-\nIst or Znd level mage (again, 50 % chance of either). If one hun-\nmense, and elven armies will always send\nscouts to spy on the\ndred or more elves are encountered, the\nfollowing additional fig-\nenemy since such spies are rarely caught\nOr even seen.\nures\nwill be present: a 4th level fighter / 8th level mage; two 4th\nspells\n'spells.\nspells\n~spells\npale\ngreat\npale\nusing\nadd\nagile,\npoint\ngarish;\nvery\nOjo ;\ngnolls,\npriest\nchance\ngain\nGain\ngain",
  "climate_terrain": "Temperate to subtropical forest",
  "frequency": "Uncommon",
  "organization": "Bands",
  "diet": "Omnivore",
  "intelligence": "High to Supra- (14-20)",
  "treasure_type": "Individual: N; G,S,T in lair",
  "alignment": "Chaotic good",
  "number_appearing": "20-200",
  "ac": "5 (10)",
  "movement": "12",
  "hit_dice": "t1",
  "thac0": "10 (18)",
  "damage": "1-10 (weapon)",
  "special_attacks": "+1to hit with bow or sword",
  "special_defenses": "See below",
  "magic_resistance": "90 % resistance t0 sleep and all",
  "size": "M (5",
  "morale": "Elite (13)",
  "xp_value": "420",
  "id": "elf"
}