{
  "name": "Fire/Water Elementals Fire Water",
  "source_page": 46,
  "raw_text": "Fire/Water Elementals\nFire\nWater\nCLIMATE TERRAIN:\ndry land\nLarge areas of water\nFREQUENCY:\nVery rare\nFare\nORGANIZATION:\nSolitary\nSolitary\nACTIVITY CYCLE:\nDIET:\nAny combustible\nliquid\nINTELLIGENCE:\nLow (5-7)\nLow (5-7)\nTREASURE:\nNil\nNil\nALIGNMENT:\nNeutral\nNeutral\nNO. APPEARING:\nARMOR CLASS:\nMOVEMENT:\n12\nSw 18\nHIT DICE:\n8, 12, or 16\n8 , 12\nor 16\nTHACO:\n8 Hit Dice: 13\n8 Hit Dice: 12\n12 Hit Dice:\n12 Hit Dice:\nlo Hit Dice:\n16 Hit Dice: 7\nNO. OF ATTACKS:\nDAMAGEIATTACK:\n3-24\n5-30\nSPECIAL ATTACKS:\nSee below\nSee below\nSPECIAL DEFENSES:\n+2 weapon\nor better to hit\n+2 weapon or better to hit\nMAGIC RESISTANCE:\nNil\nNil\nSIZE:\nL to H (8' to 16' tall)\nLto H (8' t0 16' tall)\nMORALE:\n8-12 Hit Dice: Champion\n8-12 Hit Dice: Champion\n(15-16)\n(15-16)\n16 Hit Dice: Fanatic (17)\n16 Hit Dice: Fantatic (17)\nXP VALUE:\n8 Hit Dice; 2,000\n8 Hit Dice: 2,000\n12 Hit Dice: 6,000\n12 Hit Dice: 6,000\n16 Hit Dice; 10,000\n16 Hit Dice: 10,000\nFire elementals\ncan\nbe conjured in any area\ncontaining\nWater elementals can be conjured in any area containing a large\nopen flame_\nTo\nprovide\nfire elemental with an adequate shell of\namount of water Or watery\nliquid. At least one thousand cubic\nPrime Material flame,\nfire built to house an elemental should\nfeet of liquid is required to create a shell for the water elemental to\nhave a diameter of at least six feet and reach\nminimum of four\ninhabit: Usually a large pool serves this purpose, but several large\nfeet into the air;\nkegs of wine or ale will do just as well;\nOn the Prime Material plane,\nfire elemental appears as a tall\nThe water elemental appears on the Prime Material Plane as a\nsheet of flame. The fire elemental will always appear to have two\nhigh-crested\nWave\nThe\nelementals\narms\nappear\nsmaller\narmlike appendages\none\non each side of its body These\narms\nwaves\none\nthrust out on each side of its main body The arms ebb\nseem to flicker back into the\ncreature\nflaming body, only to\nand flow, growing longer or shorter as the elemental moves .\nTwo\nspring out from its sides seconds later: The only facial features of\norbs of\ngreen peer out of the front of the wave and serve the\nfire elemental are two large glowing patches of brilliant blue\nelemental as eyes. Like all other common elementals,\nwater ele=\nfire\nwhich seem to function\nfor the elemental. Like all\nmental rarely speak on the Prime Material\nbut their voices\ncommon\nelementals;\nfire elementals rarely speak on the Prime\ncan be heard in the crashing of waves on rocky shores and the\nMaterial Plane, though their voices can be heard in the crackle\nhowl of an ocean\nand hiss of a large fire.\nCombat:\nIn combat, the water elemental is a dangerous adver-\nCombat:\nBecause they resent being conjured to this plane, fire\nsary. It\nprefers to fight in a large body of water where it can con-\nelementals are fierce opponents who will attack their enemies di -\nstantly disappear\nbeneath the\nwaves\nand  suddenly\nswell  up\nrectly and savagely; taking what joy they can in burning the weak\nbehind its opponent:\nWhen the elemental strikes\nit lashes\nout\ncreatures\nand objects of the Prime Material to ashes. In combat,\nwith a huge wave-like arm, doing 5-30 points of damage_\nfire elemental lashes out with one of its ever-moving limbs, doing\nWater elementals\nare also\na serious threat t0 ships that cross\n3-24 points of damage\nflammable object struck by the fire\ntheir path: A water elemental can easily overturn small craft (one\nelemental must save versus\nmagical fire at a -2 or immediately be-\nton of\nship per hit die of the elemental) and stop or slow almost\ngin to burn .\nany vessel (one ton of ship per hit point of the elemental) . Ships\nFire elementals do have some limitations on their actions in the\nnot\ncompletely stopped by an elemental will be slowed by a per-\nPrime Material Plane\nare unable to\ncross water Or\nnon-\ncentage equal to the ratio of ship's tons over the hit points of the\nflammable liquids. Often ,\nquick dive into a nearby lake or stream\nattacking elemental.\nis the only thing that can save\npowerful party from certain death\nThough the water elemental is most effective in\nareas\nof\nfrom\na fire elemental;\nAlso\nbecause their\nnatural\nabilities give\nopen water; it can be called upon to serve in a battle on dry land,\nthem  some built-in  resistance to flame-based attacks\ncreatures\nclose to the body of water from which it arose\nHowever, the\nwith innate fire-using abilities, like red dragons,\ntake less damage\nmovement ofthe water elemental on land is the most restricted of\nfrom a fire elementals attack. The elemental subtracts 1\nfrom\nany elemental type: a water elemental cannot move more than 60\neach die of damage it does to these creature (to a minimum of 1\naway from the water it was conjured from\nand 1 point of\nof damage\ndie) .\ndamage is subtracted from each die of damage\ninflict out of\nthe water (t0 a minimum of 1\nof damage per die).\nAny\nVery\nAny\nAny\nAny\nlarge\ndeep\nPlane,\neyes\ngale;\nAny\nThey\nlarge\npoint F\nyards\nthey\npoint\nper\npoint",
  "climate_terrain": "dry land",
  "frequency": "Very rare",
  "organization": "Solitary",
  "diet": "Any combustible",
  "intelligence": "Low (5-7)",
  "treasure_type": "Nil",
  "alignment": "Neutral",
  "movement": "12",
  "hit_dice": "8, 12, or 16",
  "thac0": "8 Hit Dice: 13",
  "damage": "3-24",
  "special_attacks": "See below",
  "special_defenses": "+2 weapon",
  "magic_resistance": "Nil",
  "size": "L to H (8' to 16' tall)",
  "morale": "8-12 Hit Dice: Champion",
  "xp_value": "8 Hit Dice; 2,000",
  "id": "fire_water_elementals_fire_water"
}