{
  "name": "Ghost",
  "source_page": 52,
  "raw_text": "Ghost\nCLIMATETERRAIN:\nAny\nFREQUENCY:\nVery rare\nORGANIZATION:\nSolitary\nACTIVE TIME:\nNight\nDIET:\nNone\nINTELLIGENCE:\nHighly (13-14)\nTREASURE:\nE; S\nALIGNMENT:\nLawful evil\nNO. APPEARING:\nARMOR CLASS:\n0 or 8 (see below)\nMOVEMENT:\nHIT DICE:\n10\nTHACO:\n11\nNO. OF ATTACKS:\nDAMAGEATTACK:\nAge 10-40 years\nSPECIAL ATTACKS:\nSee below\nSPECIAL DEFENSES:\nSee below\nMAGIC RESISTANCE:\nNil\nSIZE:\nM (5'-6' tall)\nMORALE:\nSpecial\nXP VALUE:\n7,000\nGhosts are the spirits of humans who were either so greatly\nlife or whose deaths were so unusually emotional they have been\ncursed with the gift of undead status. Thus, they roam about at\nnight or in places of darkness\nThese spirits hate goodness and\nThe ghost, in its resentment toward all life, becomes an evil crea-\nlife , hungering to draw the living essences from the\nture intent on destruction and\nsuffering-\nIn rare circumstances,\nmore than one\nghost will haunt the same\nCombat:\nAs ghosts are non-corporeal (ethereal) , they are USU-\nlocation . The classic example of this is the haunted ship, a vessel\nally encountered only by creatures in a like state, although they\nlost at sea\nnow\nethereal and crewed entirely by ghosts. These\ncan be seen by non-ethereal creatures. The supernatural power of\nships are most often encountered in the presence of St. Elmo's fire,\nghost is such\nhowever; that the mere sight of one causes any hu-\nan electrical\ndischarge that causes mysterious lights to appear in\nmanoid being to age 10 years and flee in panic for 2-12 (2d6) turns\nthe rigging of a ship.\nunless\na saving throw versus\nis made. Priests above 6th\nIn many cases;\nghost can be overcome by those who might be\nlevel are immune to this effect and all other humanoids above 8th\nno\nmatch for it in combat simply by setting right whatever events\nlevel may add +2 t0 their saving throws\nled to the attainment of the ghost's undead status. For example,\ncreatures within 60\nof a ghost is subject to attack by\nyoung woman who was betrayed and murdered by someone who\nmagic jar.\nIf the ghost fails to magic jar its chosen victim,\npretended to love her might be freed from her curse if the cad\nwill then semi-materialize in order t0 attack by touch (in which\nwere humiliated and ruined. In many cases\nhowever, a ghost s re-\ncase the ghost is Armor Class 0) . Semi-materialized ghosts can be\nvenge will be far more demanding, often ending in the death of\nstruck only by silver (half damage) or magical weapons (full dam-\nthe offender.\nage) . If they strike an opponent it ages him 10-40 (1d4xlO) years\nNote that ghosts can be attacked with\nonly by creatures\nEcology:\nThe dreadful fear caused by the ghost, which ages\nwho are in an ethereal state. Any human or demi-human killed by\nvictim 10 years, is not well understood by the common man, who\nghost is drained of its life essence and is forever dead.\noften ascribes it to the fact that a ghost is \"dead:\" If this were the\nIf the ghost Fails to become\n~material it can only be com-\ncase, then certainly skeletons and zombies would have the same\nbatted by another in the Ethereal plane (in which\ncase\nthe ghost\neffect, which they do not_\nhas an Armor Class of 8) _\nCommon folklore further confuses this fact by relating details\nGhosts can be turned by clerics after reaching 7th level and can\nof the ghosts physical form: the classic example of which is the\nbe damaged by holy water while in their semi-material form.\nheadless horseman , thought by many to be particularly frighten-\ning simply because he had no head. Under this belief ,\none\ncould\nHabitat Society:\nIn most cases\nghost is confined to a small\nface a\nghost if only one had the courage to stand up to him. Such a\nphysical area, which the ghost haunts.\nThose who have heard\nmistaken impression has cost many lives over the years. Actually\nstories of a haunted\narea\ncan\nthus attempt to\nit for their\nthe fear is caused by the supernatural power of the ghost, and has\nown\nsafety:\nnothing whatsoever to do with courage.\nA ghost often has a specific purpose in its haunting, sometimes\ntrying\n'get even\nfor something that happened during the\nghost s life. Thus a woman who was jilted by a lover; and then\ncommitted suicide, might become a ghost and haunt the couple's\nsecret trysting place. Similarly\nman\nwho failed\nat business\nmight appear each night at his storefront Or, perhaps\nat that of a\nformer competitor:\nAnother common reason for an individual to become a ghost is\nthe denial of a proper burial. A ghost might inhabit the area near\nits body; waiting for a passerby to promise to\nthe remains\nevil.\nliving:\n~spells\nyards ,\nAny\n~spells\nsemi\navoid\nbury",
  "climate_terrain": "Any",
  "frequency": "Very rare",
  "organization": "Solitary",
  "activity_cycle": "Night",
  "diet": "None",
  "intelligence": "Highly (13-14)",
  "treasure_type": "E; S",
  "alignment": "Lawful evil",
  "ac": "0 or 8 (see below)",
  "hit_dice": "10",
  "thac0": "11",
  "damage": "Age 10-40 years",
  "special_attacks": "See below",
  "special_defenses": "See below",
  "magic_resistance": "Nil",
  "size": "M (5'-6' tall)",
  "morale": "Special",
  "xp_value": "7,000",
  "id": "ghost"
}