{
  "name": "Giant, Fire",
  "source_page": 55,
  "raw_text": "Giant, Fire\nCLIMATETERRAIN:\ntemperate, subtropical,\ntropical\nFREQUENCY:\nRare\nORGANIZATION:\nTribal\nACTIVITY CYCLE:\nAny\nDIET:\nOmnivorous\nINTELLIGENCE:\nLow to average (5-10)\nTREASURE:\nALIGNMENT:\nLawful evil\nNO: APPEARING:\n1-8\nARMOR CLASS:\n-1 (5)\nMOVEMENT:\n12 (15)\nHIT DICE:\n15 +2-5 hit points\nTHACO:\nNO. OF ATTACKS:\nDAMAGEIATTACK:\n1-8.\nby weapon (2-20+10)\nSPECIAL ATTACKS:\nHurling rocks for 2-20 (2d10)\nSPECIAL DEFENSES:\nResistant to fire\nMAGIC RESISTANCE:\nNil\nSIZE:\nH (18' )\nMORALE:\nChampion (15-16)\nXP VALUE:\n8,000\nInfant\nNil\nJuvenile;\n120\nJuvenile\n3,400\nJuvenile,\n5,000\nroll of 4 indicates an infant with no combat\nand hit\nShaman/Witch doctor, Ist\n9,000\nof an ogre while rolls of 1-3 indicate older progeny with hit dice,\nShaman/Witch doctor, Znd\n10,000\ndamage\nand attack rolls equal to that of & frost giant.\nShaman/ Witch doctor; 3rd\n10,000\nTheir lairs are always protected by vigilant watchmen,\nand\nShaman/ Witch doctor; 4th\n12,000\nsometimes by traps. Fire giants favor deadfalls that can crush in-\ntruders for 5-30 (5d6)\nof damage,\nand large crossbow de-\nFire giants are brutal, ruthless,\nand militaristic.\nvices that fire one\nLWo,\nthree huge bolts for 2-16 (2d8) points\nare\ntall, but squat; resembling\ndwarves . An adult\nof\ndamage each:\nmale is 18' tall, has a 12'\nchest,\nand weighs about 7,500 pounds\nParticularly intelligent fire giant leaders will command groups\nFire giants have\nblack skin , flaming red or bright orange hair,\nthree or four times normal size . One who commands 30 or more\nand prognathous jaws that reveal dirty ivory\nyellow teeth.\ngiants usually will call himself a\nKings always will have bet-\nThey can live to be 350 years old:\nter than normal armor and a magical weapon of\n+1 t0\nA fire giants natural Armor Class is 5\nWarriors USually wear\nThere is\n20% chance that any band of fire giants will have &\nbanded mail and round metal helmets (AC -1) They carry their\nshaman (80%) or witch doctor (20-\nIf the group is lead by\nbelongings in huge sacks_\nA typical fire giant's sack contains 2-5\nthere is an 80 % chance of &\ncaster: Fire giant shamans\n(1d4 +1) throwing rocks, the giant's wealth, a tinderbox, and 3-12\nare\npriests of up to 7th level.\nshaman\ncan cast normal Or re=\n(3d4) common items. Everything they own is battered, filthy; and\nversed spells from the Elemental, Healing, Charm, Protection ,\nsmelly; making it difficult to identify valuable items\nDivination;\nor Combat spheres\nFire   giant witch\ndoctors\nare\nAII\ngiants can\nthe language of all giants and their own\npriest /wizards of up to Zth/ 3rd level; they prefer\nthat can\ntongue\ndetect r thwart intruders.\nFire giants often capture and tame other creatures\nguards\nCombat:\nFire giants are immune to nonmagical fire and heat,\n45\nThere is a 50 % chance that\nfire giant lair will contain 1-4 hell\nwell as red\ndragon breath. They are resistant to all types of magi-\nhounds. Larger than normal groups check once for every 10 gi-\ncal\nfire; such attacks inflict -1 hit\nper die of damage. Adult\nants\nBands with 30 or more giants have a additional 30 % chance\nfire giants can hurl rocks for 2-20 (2d10) points of damage. Their\nto have 2-5 (1d4 +1) trolls, larger groups check once for every 20\nminimum range is 3 yards while their maximum is 200 yards.\ngiants\nA king $ group has a 20 % chance to have 1-2 red dragons\nThey can catch similar large missiles 50 % of the time\nUSU-\nof age category 2-5 (1d4+1) in addition to other guards. Fire gi\nally fight in disciplined groups, throwing rocks until they run out\nants frequently take captives to hold for ransom Or use as slaves\nof ammunition or the opponent closes. Fire giants often wait in\nThere is a 25 % chance that a lair will contain 1-2 captives, larger\nambush at lava\nhot springs, hurling heated rocks at\nbands check once per 10 giants_\ntims for an extra 1-6 points of damage\nWarriors favor\ntwo-handed swords_\nA fire giant' $ over-\nEcology:\nFire giants live wherever there is a lot of heat:\nsized weapons do double normal (man-sized) damage to all oppO-\nprefer volcanic regions Or areas with hot springs. Frequently they\nnents\nplus\nthe   giant's   strength\nbonus_\nThus,\nfire   giant\nshare their lairs with other fire-dwelling creatures\nas sala-\ntwo-handed sword does 2-20 (2d10)\n10\nof damage.\nmanders or fire elementals.\nFire giants\nto eat meat and bread, they can hunt and kill\nHabitat Society:\nFire   giants   live\nin\nwell\norganized   military\ntheir own meat, but raid human and demi-human settlements for\ngroups, occupying large castles or caverns. When encountered in\ngrain, captives, and treasure\ntheir lair there will be 13-20 (1d8 +12) giants, half of whom will\nbe immature giants. To determine a giants maturity roll 1d4_\nAny\n~ability\npoints\npoints\n'huge\nThey\ncoal\nking.\nOlo ) .\nking,\nspell\n~spells\nfire\nspeak\npoint\nThey\npools\nvic=\nThey\nhuge\nsuch\npoints\nprefer",
  "climate_terrain": "temperate, subtropical,",
  "frequency": "Rare",
  "organization": "Tribal",
  "activity_cycle": "Any",
  "diet": "Omnivorous",
  "intelligence": "Low to average (5-10)",
  "alignment": "Lawful evil",
  "number_appearing": "1-8",
  "ac": "-1 (5)",
  "movement": "12 (15)",
  "hit_dice": "15 +2-5 hit points",
  "damage": "1-8.",
  "special_attacks": "Hurling rocks for 2-20 (2d10)",
  "special_defenses": "Resistant to fire",
  "magic_resistance": "Nil",
  "size": "H (18' )",
  "morale": "Champion (15-16)",
  "xp_value": "8,000",
  "id": "giant_fire"
}