{
  "name": "Giant, Stone",
  "source_page": 58,
  "raw_text": "Giant, Stone\nCLIMATETERRAIN:\nSub-tropical and temperate\nmountains\nFREQUENCY:\nRare\nORGANIZATION:\nTribal\nACTIITY CYCLE:\nAny\nDIET:\nOmnivorous\nINTELLIGENCE:\nAverage (8-10)\nTREASURE:\nALIGNMENT:\nNeutral\nNO. APPEARING:\n1-10\nARMOR CLASS:\nMOVEMENT:\n12\nHIT DICE:\n14\n1-3 hit points\nTHACO:\nNO. OF ATTACKS:\nDAMAGEIATTACK:\n1-8 or by weapon (2-12 + 8)\nSPECIAL ATTACKS:\nHurling rocks for 3-30 (3d10)\nSPECIAL DEFENSES:\nSee below\nMAGIC RESISTANCE:\nNil\nSIZE:\nH (18' tall)\nMORALE:\n16\nXP VALUE:\nInfant\nNil\nJuvenile;\n1,400\nJuvenile\n4,000\nJuvenile\n7,000\neach other; however, for\nsense of community and protection\nElder\n0,00o\nmountain range commonly has 2-8 clans lairing there_\nSpell caster\n000\nStone giants are crude artists, painting scenes of their lives on\nthe walls of their lairs and on tanned hide scrolls. Some giants are\nStone giants are lean, but muscular Their hard, hairless flesh is\nfond of music and play stone flutes and drums. Others make sim-\nsmooth and gray; making it easy for them to blend in with their\nple jewelry; fashioning painted stone beads into necklaces.\nmountainous surroundings. Their gaunt Facial features and\nIf eight or more giants are encountered in a clan $ lair, one quar-\nsunken black eyes make them seem perpetually grim;\nter will be female;\none\nquarter male, and the remainder offspring:\nThe typical stone giant is 18' tall and weighs 9,000 pounds be-\nTo determine a\n'giant's maturity; roll 1d4\nA roll of 4 indicates an\ncause of its dense flesh_\nFemales are & little shorter and lighter:\ninfant with no combat ability and hit points of an ogre; rolls of 1-\nThe giants' natural Armor Class is 0. They do not wear armor to\n3 indicate older progeny with hit dice, damage, and attack rolls\naugment that, preferring to wear stone-colored garments.\nStone\nequal to those of a hill giant.\ngiants can live to be 800 years old.\nOne in 20 stone giants develop\nabilities related to their\nStone giants, like several other giant races,\ncarry some of their\nenvironment_\nThese giant elders\nable to stone shape, stone\nbelongings with them: They leave their more valuable items in\ntell, and transmute rock to mud (Or mud to rock) once per day as\ntheir lairs, however:\nA typical stone\n'giant's bag will contain 2-24\nifthey were Sth level mages. One in 10 of these exceptional giants\n(2d12) throwing rocks,\nportion ofthe giant s wealth; and 1-8 ad-\ncan also cast\nspells as if he\nwere\n3rd level wizard . Their spells\nditional common items\ncan\nbe determined randomly or\nFit a\n'specific encounter\nStone giants speak their own language,\nas well as those of hill\n4S\ndesired . Frequently these giants are able to rise to positions of\ngiants\ncloud giants\nand storm giants. In addition, 50 % of the gi-\npower and are considered the leaders of several clans.\nants also\nthe common language of man\nStone giants are usually found in mountain ranges in temperate\nand sub-tropical areas. Stone giants are fond of cave bears and\nCombat:\nWhen  possible,\nstone giants fight From\ndistance\n75 % of their lairs will\n1-8 of them as guards. The few stone\nThey are able t0 hurl rocks\nminimum distance of 3 yards to a\n~giants living in cold areas use\nbears as guards\nmaximum distance of 300 yards, doing 3-30 (3d10) points of dam-\nStone giants are playful, especially at night. They are fond of\nage with each rock. These giants are able to catch stones and simi-\nrock throwing contests and other games that test their might:\nlar missiles 90% of the time\nA favorite tactic of stone giants is t0\nTribes of giants will often\nto toss rocks at each other; the\nstand nearly motionless against rocks, blending in with the back-\nlosing side being the giants who are hit more often.\nground, then moving forward to throw rocks, surprising their\nfoes. Many giants set up\nof rocks near their lair which can be\nEcology:\nStone giants are omnivorous\nbut\nwill\neal\nonly\ntriggered like an avalanche when intruders get too close\nfresh food. They cook and eat their meat quickly after it has been\nWhen stone giants are forced into melee combat, they use\nkilled . They use the skins of the animals for blankets and trade\nclubs chiseled out of stone which do 2-12 (2d6) + 8 points of dam-\nwhat they do not need with nearby human communities in\nex-\nage; double\nnormal\n(man-sized) club damage plus the giants\nfor bolts of cloth or herd animals which they use for food.\nstrength bonus.\nstone\ngiant bands keep giant goats in and near their lairs s0\nthey will have a continuous supply of milk, cheese, and butter.\nHabitat Society:\nStone giants prefer to dwell in deep caves high\non rocky;\nstorm-swept mountains\nThey normally live in the\ncompany of their relatives, though\na clans usually include\nno more than 10 giants. Clans of giants do locate their lairs near\n000\ndeep,\nspecial\nare\nchosen\nspeak\nhave\npolar\ngather\npiles\nthey\nlarge\nchange\nMany\nsuch",
  "climate_terrain": "Sub-tropical and temperate",
  "frequency": "Rare",
  "organization": "Tribal",
  "diet": "Omnivorous",
  "intelligence": "Average (8-10)",
  "alignment": "Neutral",
  "number_appearing": "1-10",
  "movement": "12",
  "hit_dice": "14",
  "damage": "1-8 or by weapon (2-12 + 8)",
  "special_attacks": "Hurling rocks for 3-30 (3d10)",
  "special_defenses": "See below",
  "magic_resistance": "Nil",
  "size": "H (18' tall)",
  "morale": "16",
  "xp_value": "Infant",
  "id": "giant_stone"
}