{
  "name": "Giant, Hill",
  "source_page": 57,
  "raw_text": "Giant, Hill\nCLIMATETERRAIN:\nAny hills and mountains\nFREQUENCY:\nRare\nORGANIZATION:\nTribal\nACTIITY CYCLE:\nAny\nDIET:\nOmnivorous\nINTELLIGENCE:\nLow (5-7)\nTREASURE:\nALIGNMENT:\nChaotic evil\nNO. APPEARING:\n1-12\nARMOR CLASS:\n3 (5)\nMOVEMENT:\n12\nHIT DICE:\n12+1-2 hit\nTHACO:\nNO; OF ATTACKS:\nDAMAGEATTACK:\n1-0 Or\nby weapon (2-12 + 7)\nSPECIAL ATTACKS:\nHurling rocks for 2-16 (2d8)\nSPECIAL DEFENSES:\nNil\nMAGIC RESISTANCE:\nNil\nSIZE:\nH (16' tall)\nMORALE:\nElite (13-14)\nXP VALUE:\n3,000\nInfant\nNil\nJuvenile\n270\nJuvenile, -2\n650\nJuvenile, -1\n2,000\nmale,\nand the remainder will be immature giants. To determine\nHill giants are selfish , cunning brutes who survive through hunt-\ngiant's maturity; roll 1d4\nA roll of 4 indicates an infant with no\ning and by terrorizing and raiding nearby communities. Despite\ncombat ability and hit\nof\nrolls of 1-3 indicate older\ntheir low intelligence, they are capable fighters.\nprogeny with hit dice, damage, and attack rolls equalto that ofan\nHill giants are oddly simian and barbaric in appearance, with\nogre\noverly\narms\nstooped shoulders, and low foreheads. Even\nOccasionally a hill giant with an average intelligence can be\nthough they are the smallest of the giants, their limbs are more\nfound: Such a giant is\nrallying bands of his peers s0 2,\nmuscular and massive than those of the other giant races. The av-\nor 4 times the number of giants usually appearing can be en-\nerage hill giant is 16 feet tall and weighs about 4,500 pounds\nFe-\ncountered=\nThese\n'giant\nthey call themselves, stage\nmales have the same builds as males. Their skin color ranges from\nraids on human towns Or against other races of giants.\nlight tan to a deep ruddy brown. Their hair is brown\nblack ,\nAlthough hill giants prefer temperate areas,\ncan be found\nand their eyes are black. Hill giants can\nto be 200 years old.\nin practically any climate where there is an abundance of hills and\nHill giants' natural Armor Class is 5. This is reduced to an Ar-\nmountains\nThey lair in\ncaves\nexcava\nted\ndens\nr crude huts_\nmor Class of 3 when they wear crudely-sewn animal hides, which\nThose who live in colder climates have developed\nmore\nskills\nare the equivalent of leather\narmor\nNearly all hill giants\nwear\nwith preparing and using skins to\nthemselves warm and t0\nthese hides, which\nare\na symbol of esteem in\nsome\nhill giant\nkeep the harsh winds out of their lairs.\ncommunities\nthe more hides a giant has, the more large kills to\nThere is a 50 % chance a band of hill giants will have guards in\nhis credit. Only\na few (5 % ) of the giants fashion metal\narmor\ntheir  lairs_\nand the\nguarding\ncreatures will be 2-8 (2d4) dire\nfrom the armor of men they have defeated. These giants have an\nwolves (50 % ) , 1-3 giant lizards (30% ) ,\na group of 2-8 (2d4)\nArmor Class of 0. Like other races of giants, hill giants carry their\nogres (20 %\nbelongings with them in huge hide sacks_\ntypical hill giants\nThe majority of hill giants are suspicious of magic and will seek\nwill contain 2-8 (2d4) throwing rocks, the giants wealth, and 1-8\nto destroy magic items\nacquire as treasure.\nceremoni=\nadditional common items_\nally kill mages _\nHill giants speak their own language and a tongue common to\nall giants. In addition , 50 % also speak ogre.\nEcology:\nHill giants' main diet consists of meat, which they ob-\ntain by hunting. The flesh of young green dragons is considered a\nCombat:\nHill giants prefer to fight their opponents from high\ndelicacy; and frequently giants who live on hills and mountains\nrocky outcroppings where they can\ntheir targets with rocks\ncovered with forests will organize hunting parties in search of\nand boulders while limiting the risks posed to themselves_\ngreen\ndragon lairs. In turn,\ndragons have been known\nHill giants' favorite weapons are oversized clubs which do 2-12\nhunt hill giants:\n7 points of damage (double the damage ofa man-sized club plus\nSometimes bands of hill giants will trade with each other Or\ntheir strength bonus) . They hurl rocks for 2-16 (2d8) points of\nwith bands of ogres to get foodstuffs and trinkets\ndamage. Their targets for such attacks must be between 3 and 200\n~yards away from the giant: They can catch rocks Or other similar\nmissiles 30 % of the time.\nHabitat Society:\nA hill giant lair will have 9-16 (1d8 + 8) giants;\nusually an extended family. Sometimes these families will accept\nlone hill giants into their folds. If six or more giants are encoun-\ntered in a lair; half of them will be male,\none\nquarter will be fe-\npoints\ngnoll;\npoints\nlong\ncapable\nkings,\nthey\nlive\nkeep\nbag\nthey\nThey\nPelt\ngreen",
  "climate_terrain": "Any hills and mountains",
  "frequency": "Rare",
  "organization": "Tribal",
  "diet": "Omnivorous",
  "intelligence": "Low (5-7)",
  "alignment": "Chaotic evil",
  "number_appearing": "1-12",
  "ac": "3 (5)",
  "movement": "12",
  "hit_dice": "12+1-2 hit",
  "damage": "1-0 Or",
  "special_attacks": "Hurling rocks for 2-16 (2d8)",
  "special_defenses": "Nil",
  "magic_resistance": "Nil",
  "size": "H (16' tall)",
  "morale": "Elite (13-14)",
  "xp_value": "3,000",
  "id": "giant_hill"
}