{
  "name": "Giant; Storm",
  "source_page": 59,
  "raw_text": "Giant; Storm\nCLIMATE TERRAIN:\nSpecial (see below)\nFREQUENCY:\nVery rare\nORGANIZATION:\nSolitary or Tribal\nACTIVITY CYCLE:\nAny\nDIET:\nOmnivorous\nINTELLIGENCE:\nExceptional (15-16)\nTREASURE:\nE; QxlO;\nALIGNMENT:\nChaotic good\nNO. APPEARING:\n(2-4)\nARMOR CLASS:\n0 (-6)\nMOVEMENT:\n15, Sw 15\nHIT DICE:\n19 +2-7 hit points\nTHACO:\nNO. OF ATTACKS:\nDAMAGEIATTACK:\n1-10 or by\nweapon\n(3-30 +12)\nSPECIAL ATTACKS:\nSee below\nSPECIAL DEFENSES:\nImpervious t0\nelectricity\nMAGIC RESISTANCE:\nNil\nSIZE:\nG (26' tall)\nMORALE:\nFanatic (17-18)\nXP VALUE:\n13,000\nInfant\nNil\nJuvenile;\n1,400\nJuvenile\n4,000\nJuvenile\n7,000\nSpell caster, Ist\n14,000\nto all opponents, plus the giant s strength bonus. Thus\na storm\nSpell caster, Znd\n14,000\ngiant' $\n(WO-\n-handed sword does 3-30 (3d10)\n+12\npoints of dam-\nSpell caster, 3rd\n14,000\nage-\nalso\nuse massive composite bows which have a 300\nSpell caster, 4th +\n16,000\n~yard range and do 3-18 (3d6) points of damage. There is a 10%\nchance that any storm giant will\nenchanted weapons\nStorm giants are\nand reclusive\nare usually tolerant of\nA storm\n'giant's natural Armor Class is 0. In battle, storm giants\nothers\nbut can be very dangerous when angry:\nusually wear elaborate bronze plate mail (AC -6).\nStorm giants resemble\nformed humans of gargantuan prO-\nportions. Adult males and females are about 26' tall and weigh\nHabitat Society:\nStorm giants are retiring and solitary; but not\nabout 15,000 pounds_\nStorm giants have\nlight green\nshy: They live in castles built on cloud islands (60 % ) , mountain\n(rarely) violet skin . Green-skinned storm giants have dark green\npeaks (20% ) ,\nor underwater (10 %\nThey live quiet, reflective\nhair and glittering emerald\neyes\nViolet-skinned\nstorm  giants\nlives and spend their time musing about the world, composing\nhave deep violet or blue-black hair with\ngray or\npurple\nand playing music, and tilling their land or gathering food. Land-\neyes. Storm giants can live to be 600 years old.\nand\nair-dwelling storm giants usually\nare\non\ngood terms with\nA storm giant's\nusually is a short, loose tunic belted at the\nneighboring silver dragons and\ncloud giants, and cooperate\nwaist, sandals or bare feet, and\nheadband. They wear\na few\nwith them For mutual defense. Aquatic storm giants have similar\npieces of simple, but finely crafted jewelry: anklets (favored by\nrelationships with mermen and bronze dragons:\nbare-footed giants), rings\nOr\ncirclets being most common.\nWhen two or more storm giants are encountered in lair they\nStorm giants usually\ncarry pouches attached to their belts\nwill be\nmated\ncouple and their children.\nTo determine each\nThese hold only\na few tools;\nnecessities;\nand\na simple musical\nyoung\ngiants maturity roll 1d4_\nA roll of 4 indicates an infant\ninstrument-\nusually\npanpipe\nharp. Other than the jewelry\nwith no combat ability and hit points of ogre; rolls of 1-3 indicate\nthey wear; they prefer to leave their wealth in their lairs .\nolder progeny with hit dice, damage,\nand attack rolls equal to\nThey speak their own language as well as cloud giant,\nthe tongue\nthat of a cloud giant.\ncommon to all giants,\nand the common tongue of humankind:\nThere is a 20 % chance that an adult storm giant is also a priest\n(70 %\nwizard (30 % ) . Storm giants can attain %h level\nCombat:\nAll storm giants are immune to electricity and light-\nas priests and 7th level as wizards.\nStorm giant priests can cast\nning: They use weapons and special abilities instead of hurling\nfrom  the Animal,\nCharm,\nCombat,\nCreation;\nrocks, but can catch large missiles 65 % of the time_\nGuardian, Healing, Plant, Weather, and Sun spheres\nStorm giant\nStorm giants\nare born\nWith water\nbreathing ability and can\nwizards are generalists,\nand typically know spells from the Alter\nmove\nattack\nand use magic under water as if they were on land:\nation\nInvocation/ Evocation,\nConjuration / Summoning;\nand\nJuvenile and adult storm giants can cast control weather and levi-\nAbjuration schools.\ntate\n~spells lifting their own weight and as much as 4,000 addi-\nStorm giant lairs are always protected by guards. Land Or aer-\ntional pounds twice a\nAdult storm giants also can predict\nial lairs have 1-2 rocs (70 % ) , which also serve\nmounts\nor 1-4\nweather; call lightning (3 bolts of 15 8-sided dice each), lightning\ngriffons (30%) . Underwater lairs have 2-8 (2d4) sea lions_\nbolt (1 bolt of 15 6-sided dice) , control winds, and use weather\nsummoning once a day A storm giant uses its magical abilities at\nEcology:\nStorm giants live off the land in the immediate vicinity\nI5th level,\nAn angry storm giant usually will\nsummon\n4 storm\nof their lairs. If the natural harvest is not enough t0 sustain them\nand call lightning:\nthey create and carefully till large areas of gardens, fields, and\nThey employ gigantic two-handed swords in battle;\nA storm\nvineyards. They do not keep animals for food, preferring to hunt.\ngiant s oversized weapons do triple normal (man-sized) damage\nThey\nhave\nThey\ngentle=\nwell-,\nPale;\nsilvery\ngood\ngarb\npriest,\nregular\nspells\nday:",
  "climate_terrain": "Special (see below)",
  "frequency": "Very rare",
  "organization": "Solitary or Tribal",
  "activity_cycle": "Any",
  "diet": "Omnivorous",
  "intelligence": "Exceptional (15-16)",
  "treasure_type": "E; QxlO;",
  "alignment": "Chaotic good",
  "number_appearing": "(2-4)",
  "ac": "0 (-6)",
  "movement": "15, Sw 15",
  "hit_dice": "19 +2-7 hit points",
  "damage": "1-10 or by",
  "special_attacks": "See below",
  "special_defenses": "Impervious t0",
  "magic_resistance": "Nil",
  "size": "G (26' tall)",
  "morale": "Fanatic (17-18)",
  "xp_value": "13,000",
  "id": "giant_storm"
}