{
  "name": "Giant, Frost Arctic lands",
  "source_page": 56,
  "raw_text": "Giant, Frost\nCLIMATEITERRAIN:\nArctic lands\nFREQUENCY:\nVery rare\nORGANIZATION:\nTribal\nACTIITY CYCLE:\nDIET:\nOmnivorous\nINTELLIGENCE:\nLow to average (5-10)\nTREASURE:\nALIGNMENT:\nChaotic evil\nNO. APPEARING:\n1-8\nARMOR CLASS:\n0 (5\nMOVEMENT:\n12 (15)\nHIT DICE:\n14\n1-4 hit points\nTHACO:\n7 or 5\nNO. OF ATTACKS:\nDAMAGEIATTACK:\n1-8,\nby weapon (2-16 +9)\nSPECIAL ATTACKS:\nHurling rocks for 2-20 (2d10)\nSPECIAL DEFENSES:\nImpervious to cold\nMAGIC RESISTANCE:\nNil\nSIZE:\nH (21\")\nMORALE:\nVery Steady (13-14)\nXP VALUE:\n7,000\nInfant\nNil\nJuvenile\n270\nJuvenile\n975\nJuvenile\n4,000\nShaman /Witch doctor, Ist\n8,000\nHabitat Society:\nFrost giants live in\nbands consisting of a\nShaman/ Witch doctor; Znd\n8,000\nchief , his henchmen ,\nand their camp followers_\nA band usually\nShaman/Witch doctor; 3rd\n8,000\noccupy\ncrude castle or\nfrigid cavern . When encountered in\nShaman/Witch doctor, 4th + 10,000\ntheir lair there will be 9-16 1d8 + 8) giants; half of whom will be\nimmature\nTo determine a giant's maturity roll 1d4\nAroll of 4 in-\nLike all evil giants, frost giants have a reputation for crudeness\ndicates an\ninfant with no combat ability and hit points of ogre;\nand stupidity. This reputation is deserved, but frost giants are\nrolls of 1-3 indicate older progeny with hit dice, damage,\nand at=\ncrafty fighters.\ntack rolls equal to that of a stone giant.\nFrost giants have muscular; roughly human builds. The typical\nParticularly strong or intelligent frost giant chieftains will com-\nadult male is 21' tall and weighs about 8,000 pounds\nFemales are\nmand bands three\nfour times normal size .\nA chieftain who\nslightly shorter and lighter; but otherwise identical to males. Frost\ncommands 20 or more giants is called a jarl. Jarls always will have\ngiants have snow-white or ivory skin. Their hair is light blue or\nbetter than normal armor and\nweapon of +1 to\n+3 enchant-\nyellow, with matching eyes_\ncan\nlive to be 250 years\nment.\nold.\nThere is a 20 % chance that any band of frost giants will have a\nA frost giants natural Armor Class is 5.\nWarriors usually wear\nshaman (80 % ) or witch doctor (20\nIf the group is lead by a\nchain mail and metal helmets decorated with\nOr\nfeathers\njarl, there is an 80% chance for a\ncaster Frost giant shamans\n(AC 0) . They also wear skins and pelts\nwith any jewelry\nare\npriests of up to Zth level.\nA shaman can cast normal Or re=-\nthey own .\nversed spells from the healing, charm, protection, divination;\nOr\nFrost giants carry their belongings in\nsacks.\ntypical\nweather spheres_\nFrost giant witch doctors are priest/ wizards of\nfrost giant'$\ncontains 2-5 (1d4 +1) throwing rocks, the giant's\nup to 7th/ 3rd level; they prefer spells that can bewilder and con-\nwealth, and 3-12 (3d4) mundane items. Everything in\ngiant's\nfound\nother   giants_\nFavorite   spells   include:\nunseen\nservant\nbag is old, worn , dirty, and smelly, making the identification of\n~shocking grasp , detect magic, ventriloquism, deeppockets, ESP\nany\nvaluable items difficult .\nmirror image,\nand invisibility:\nFrost giants speak their own language and the language com-\nFrost giants often capture and tame other creatures as guards;\nmon to all giants.\nThere is a 50 % chance that\nfrost giant lair will contain 1-6 win-\nter wolves. Larger than normal groups check once for every eight\nCombat:\nFrost giants are immune to cold. Adult frost giants can\ngiants\nBands with 20\nmore giants have\nadditional 30 %\nhurl rocks for 2-20 (2d10) points of damage_\nTheir minimum\nchance to have 1-4 yeti, larger groups check once for every 16 gi-\nrange is 3 yards while their maximum is 200 yards_\nThey\ncan\nants\nA jarls band has\n20 % chance to have 1-2 subdued white\ncatch similar\nmissiles 40 %\nof the time\nThey usually will\ndragons in addition to other guards. The dragons will be age cate-\nstart combat at a distance;\nthrowing rocks until they run out of\ngory 2-5 (1d4 +1). Frost giants also take captives to hold for ran-\nammunition,\nor the opponent closes. One of their favorite strate-\nsom Or use as slaves. There is a 15 % chance that a lair will contain\ngies is to ambush victims by hiding buried in the snow at the\n1-2 captives, larger bands check\nonce\nper eight giants. Captives\nof an icy\nor snowy\nslope where opponents will have difficulty\ncan\nbe of any race.\nreaching them.\nWarriors favor huge battle axes.\nA frost giants oversized weap-\nEcology:\nFrost giants live in frigid, arctic lands with glaciers and\nons\ndo double normal (man-sized) damage to all opponents, plus\nheavy snowfall. Frost giants eat mostly\nmeat, which they can\nthe giant's strength bonus. Thus,\ngiant battle axe\n2-16\nhunt and kill themselves. They raid human and demi-human\n(2d8) +9\nof damage:\nsettlements for foodstuffs and other booty.\nAny\nsmall\nwill\n~dirty\nThey\n1 %0 ) .\nhorns\nspell\nalong\n'huge\nsack\nlarge\ntop\nfrost\ndoes\npoints",
  "frequency": "Very rare",
  "organization": "Tribal",
  "diet": "Omnivorous",
  "intelligence": "Low to average (5-10)",
  "alignment": "Chaotic evil",
  "number_appearing": "1-8",
  "ac": "0 (5",
  "movement": "12 (15)",
  "hit_dice": "14",
  "thac0": "7 or 5",
  "damage": "1-8,",
  "special_attacks": "Hurling rocks for 2-20 (2d10)",
  "special_defenses": "Impervious to cold",
  "magic_resistance": "Nil",
  "size": "H (21\")",
  "morale": "Very Steady (13-14)",
  "xp_value": "7,000",
  "id": "giant_frost_arctic_lands"
}