{
  "name": "Gnome",
  "source_page": 61,
  "raw_text": "Gnome\nCLIMATETERRAIN:\nwoods or hills\nFREQUENCY:\nORGANIZATION:\nClans\nACTIVITY CYCLE:\nDIET:\nOmnivore\nINTELLIGENCE:\n(11-12)\nTREASURE:\nC,Qx2o (Mx3)\nALIGNMENT:\nNeutral\nNO. APPEARING:\n4-12 (3d4)\nARMOR CLASS:\n5 (10)\nMOVEMENT:\nHIT DICE:\nTHACO:\n19\nNO. OF ATTACKS:\nDAMAGE ATTACK:\n1-6 (by weapon)\nSPECIAL ATTACKS:\nNil\nSPECIAL DEFENSES:\nSee below\nMAGIC RESISTANCE:\nSpecial\nSIZE:\nSmall (3' tall)\nMORALE:\nSteady (12)\nXP VALUE:\n65\nLeaders\n120\nSmaller relatives of the dwarves, gnomes are shy\nrarely seen\nby other demi-humans. They tend to dwell near secluded Forests\nand live peaceful lives .\nHabitat Society:\nGnomes live in underground burrows in\nre -\nShort and stout, the gnome looks like\ncompact version of the\nmote woods. They are clannish\nwith\nFriendly rivalry between\ndwarf, although\ntwo\nmajor facial features help to distinguish\nnearby clans. They\ntheir lives mining, tunneling and enjoy -\nthem. Gnomes do not let their beards grow longer than half\ning the peaceful quiet of the woods.\nGnomes work hard, and play\nfoot, and they have long, broad\nnoses\nfully twice the size of any\nhard. They observe many festivals and holidays, which usually\ndwarfs\nThe skin of\ngnome is any shade of wooden brown,\ninvolve games and swapping of\ntales. Their society is well\nsometimes with a hint of gray: Their hair is white, and their eyes\norganized, with many levels of responsibility culminating in\nare shades of blue.\nGnomish\nclothing tends toward leather and\nsingle chief. The clerics share leadership with the chief, but only\nearth tones, with jewelry to match:\nfor those matters directly relating to their calling. Internal strife in\nGnomes\ntheir own\nlanguage and\nare often able to con-\ngnome tribe is uncommon, although not unheard of.\nverse\nwith kobolds\ngoblins, halflings,and\ndwarves\nFurther;\nA gnomish lair will be home\nt0 some\n40-400 (4d1OxIO) adult\nmany are able to communicate with burrowing mammals via\nmales -\nFor every 40 gnomes there is & fighter of Znd to 4th level\nbasic language of signs and animal sounds_\n(1d3+1) . If 160 or more are encountered there is also a Sth level\nchiel and a 3rd level lieutenant. If 200 or more are met,\nthere iS &\nCombat:\nGnomes are likely to use any strategy in combat that is\ncleric or illusionist of 4th t0 6th level (d3 + 3) . If 320 or more are\nnot blatantly treacherous. Their great hatred of kobolds and\nmet, add a 6th level fighter; 2 Sth level fighters,\nZth level cleric;\nlins gives them a +1 on their attack rolls when fighting them. All\n3rd level clerics\nSth level illusionist and 2 Znd level illusionists .\ngiant class creatures (gnolls, bugbears\nogres, trolls, giants, etc.)\nAlso in the lair, there will be a number of females equal to the\nmust subtract 4 from their attack rolls when fighting gnomes\nnumber of males and children\nto 1/4 the total number of\nGnomes can use any weapon that matches their size, and al-\nadults . Gnomes\nuse animals t0\ntheir homes\n5-30 (5d6)\nways carry\nsecond (or even third) weapon .\nare\nFond of\nbadgers (70 % ) , 3-12 (3d4) giant badgers (20% ) , or 2-8 (2d4) wol-\nstudded leather armor and small shields (AC 6). Their leaders will\nverines\n(10%0 ) . These creatures are not bound or caged, but are\nhave chain mail (AC 4) and any gnome above Sth level has plate\nfree creatures that have chosen to\nnear\nthe tribe\nmail (AC 2) . There is a 10% chance for each level above Sth that\nthe gnome s\narmor\nOrweapon\n(roll separately for\nEcology:\nGnomes are very much a\nmagical part of nature, exist-\neach) . Roll percentile dice two or three times (DM's discretion) on\ning in harmony with the land they inhabit: They choose to live\nthe table below to determine their weapons.\nunderground for protection and to avoid marring the works of\nnature\nGnomes eat meat only if no other food source is availa-\nClub (or war hammer)\n01-40 %\nble. They have an average life\nof around 600 years and are\nShort sword\n41-70 %\nof detecting\nand other underground constructions\nSpear\n71-85 %\ndescribed in the Player s Handbook.\nShort bow (or crossbow)\n80-90 %\nSling\n01-95 %\nDagger\n06-00 %\nGnomes are\nhighly resistant to magic or poison and save as if\nthey\nwere 4 levels higher than they really\nare\nGnomes can be\npriests or fighters, but prefer being thieves and illusionists. Spell\ncasters have a 10% chance per level of having 1-3 magical items\n(not weapons or armor) usable by their character class\nAny\nRare\nAny\nVery\ngood\nand\n'spend\ngrand\nspeak\ngob-\nequal\nguard\nThey\nstay\nmagical\nspan\ncapable\nslopes",
  "climate_terrain": "woods or hills",
  "organization": "Clans",
  "diet": "Omnivore",
  "intelligence": "(11-12)",
  "treasure_type": "C,Qx2o (Mx3)",
  "alignment": "Neutral",
  "number_appearing": "4-12 (3d4)",
  "ac": "5 (10)",
  "thac0": "19",
  "damage": "1-6 (by weapon)",
  "special_attacks": "Nil",
  "special_defenses": "See below",
  "magic_resistance": "Special",
  "size": "Small (3' tall)",
  "morale": "Steady (12)",
  "xp_value": "65",
  "id": "gnome"
}