{
  "name": "Goblin",
  "source_page": 62,
  "raw_text": "Goblin\nCLIMATETERRAIN:\nAny non-arctic land\nFREQUENCY:\nUncommon\nORGANIZATION:\nTribe\nACTIVITY CYCLE:\nNight\nDIET:\nCarnivore\nINTELLIGENCE:\nLow to average (5-10)\nTREASURE:\nC (K)\nALIGNMENT:\nLawful evil\nNO. APPEARING:\n4-24 (4d6)\nARMOR CLASS:\n6 (10)\nMOVEMENT:\nHIT DICE:\n1-1\nTHAC:\n20\nNO. OF ATTACKS:\nDAMAGEATTACK:\n1-6 (by weapon)\nSPECIAL ATTACKS:\nNil\nSPECIAL DEFENSES:\nNil\nMAGIC RESISTANCE:\nNil\nSIZE:\nSmall (4' tall)\nMORALE:\nAverage (10)\nXP VALUE:\n15\nChief & sub-chiefs\n35\nThese small, evil humanoids would be merely pests, if not for\ntheir great numbers\nGoblins have  flat\nfaces\nbroad\nnoses\npointed\nears\nwide\nthere will be & sub-chief and 2-8 (2d4) bodyguards, each of which\nmouths and small, sharp fangs. Their foreheads slope back,\nand\nhas 1 +1 Hit Dice (8 hit points) , is Armor Class 5, and armed with\ntheir eyes are usually dull and glazed. They always walk upright,\nbattle axe. The tribe has\nsingle goblin chief and 2-8 (2d4)\nbut their arms hang down almost to their knees. Their skin colors\nbodyguards each of 2 Hit Dice, Armor Class 4, and armed with\nrange trom\nyellow through any shade of orange to\nred_\ntwo weapons\nUsually\nsingle tribe has members all of about the same color\nThere is a 25 % chance that 10% of their force will be mounted\nskin. Their eyes vary from bright red to a gleaming lemon yellow.\nupon\nworgs, and have another 10-40 (1d4xlO) unmounted\nThey wear\nclothing of dark leather, tending toward dull soiled-\nworgs with them. There is & 60% chance that the lair is guarded\nlooking colors.\nby 5-30 (Sd6) such wolves, and a 20% chance of 2-12 (2d6)\nGoblin speech is harsh, and pitched higher than that of hu-\nbears . Goblin shamans are rare;\nbut have been known t0 reach\nmans. In addition to their own language, some\ngoblins\ncan\nspeak\n7th level. Their spheres include: Divination , Healing (reversed)\nin the kobold, orc, and hobgoblin tongues\nProtection, and Sun (reversed)_\nIn addition t0 the males\nthere will be adult females equal to\nCombat:\nGoblins hate bright sunlight, and fight with a -1\non\n60 % of their number and children equal to the total number of\ntheir attack rolls when in it. this unusual sensitivity to light, how-\nadults in the lair. Neither will fight in battles\never;\nserves the\ngoblins well underground, giving them infra-\ntribe has an exact pecking order; each member knows\nvision out to 60 feet. They can use any sort of weapon\npreferring\nwho is above him and\nwho is below him. They fight amongst\nthose that take little\ntraining, like spears and\nmaces_\nThey are\nthemselves constantly to move up this social ladder.\nknown to carry short swords as & second weapon. They are uSu-\nThey often take slaves for both food and labor: The tribe will\nally armored in leather, although the leaders may have chain\nhave slaves of several races numbering 10-40 % of the size of the\neven\nplate mail.\ntribe . Slaves are always kept shackled, and are staked to a com-\nGoblin strategies and tactics are simple and crude.\nare\nmon\nchain when sleeping:\ncowardly and will usually avoid a face-to-face fight; More often\nGoblins hate most other humanoids\ngnomes and dwarves in\nthan not,\nthey will attempt to arrange an ambush of their foes\nparticular; and work to exterminate them whenever possible.\nHabitat Society:\nHumans would consider the caves and under-\nEcology:\nGoblins live only 50 years or so. They do not need to\nground dwellings of goblins to be dank and dismal\nThose few\neat much, but will kill just for the pleasure of it. They eat any\ntribes that live above ground are found in ruins,\nand are only ac-\ncreature from rats and snakes t0 humans. In lean times they will\ntive at night or on very dark, cloudy days: They use no form of\neat carrion. Goblins usually\ntheir habitat, driving game\nsanitation, and their lairs have a foul stench. Goblins seem to be\nfrom it and depleting the area of all resources. They are decent\nsomewhat resistant t0 the diseases that breed in such filth.\nminers, able to note new or unusual construction an an under-\nThey live a communal life , sharing large common areas for eat-\nground area 25 % of the time;\nand any habitat will soon be\nex=\nand sleeping. Only leaders have separate living spaces_\nAlI\npanded by a maze-like network of tunnels.\ntheir possessions are carried with them . Property of the tribe is\nkept with the chief and sub-chiefs. Most of their goods are stolen ,\nalthough\ndo manufacture their own garments and leather\nThe concept of privacy is largely foreign to goblins.\ntypical goblin tribe has 40-400 (4d10 x 10) adult male war-\nriors. For every 40\ngoblins there will be a leader and his 4 assist-\nants, each having 1 hit die\nhit points) . For every 200 goblins\n'deep\nhuge\nbug=\ngoblin\nThey\nspoil\ning\nthey\ngoods.",
  "climate_terrain": "Any non-arctic land",
  "frequency": "Uncommon",
  "organization": "Tribe",
  "activity_cycle": "Night",
  "diet": "Carnivore",
  "intelligence": "Low to average (5-10)",
  "treasure_type": "C (K)",
  "alignment": "Lawful evil",
  "number_appearing": "4-24 (4d6)",
  "ac": "6 (10)",
  "hit_dice": "1-1",
  "damage": "1-6 (by weapon)",
  "special_attacks": "Nil",
  "special_defenses": "Nil",
  "magic_resistance": "Nil",
  "size": "Small (4' tall)",
  "morale": "Average (10)",
  "xp_value": "15",
  "id": "goblin"
}