{
  "name": "Golems, Greater Stone Tron",
  "source_page": 65,
  "raw_text": "Golems, Greater\nStone\nTron\nCLIMATE TERRAIN:\nFREQUENCY:\nrare\nrare\nORGANIZATION:\nSolitary\nSolitary\nACTIITY CYCLE\nAny\nDIET:\nNil\nNil\nINTELLIGENCE:\nNon- (0)\nNon- (0)\nTREASURE;\nNil\nNil\nALIGNMENT:\nNeutral\nNeutral\nNO. APPEARING:\nARMOR CLASS:\nMOVEMENT:\nHIT DICE:\n14\nhp)\n18 (80 hp)\nTHACO:\nNO: OF ATTACKS:\nDAMAGEIATTACK:\n3-24 (3d8)\n4-40 (4d10)\nSPECIAL ATTACKS:\nSee below\nSee below\nSPECIAL DEFENSES:\nSee below\nSee below\nMAGIC RESISTANCE:\nNil\nNil\nSIZE:\nL (91/2' tall)\nL (12\" tall)\nMORALE:\nFearless (19-201\nFearless (19-20)\nXP VALUE:\n10,000\n15,000\nA greater\nis an\nartificial humanoid body which has been\nmake poor servants_\ngiven task could take several separate\nanimated by an elemental spirit but remains under the complete\ncommands t0 direct the\nto its completion\ncontrol of its creator;\nEcology:\nGolems are not natural creatures,\nand play no part in\nStone Golem\nthe ecology of the world. They neither eat\nnor\nand \"live'\nA stone\nis 91/2 feet tall, and weighs around 2000 pounds\nuntil they are destroyed,\nusually\nin combal\nCertain spells (see\nIts body is of roughly chiseled stone, frequently stylized to suit its\nabove) can be used to heal or repair any damage done to them in\ncombat: This is usually done by their creators t0 insure\nand\ncreator: For example it might be carved to to look like it is wear-\nvaluable service.\ning armor with a particular symbol on the chest plate. Sometimes\ndesigns are worked into the stone of its limbs. The head may be\nIron Golem\nchiseled to resemble a helmet or other head piece. Regardless of\nthese elements, it always has the basic humanoid parts\n2 arms\nAn iron golem is twice the height of a normal man\nand\nweighs\nhead with 2 eyes_\nnose;\nmouth etc.) . It is always weaponless\naround 5000 pounds .\nIt can be fashioned in any stylized manner;\nand never wears\nclothing:\njust like the stone golems, although it almost always is built dis-\nplaying armor of some sort. Its features are much smoother in\nCombat:\nGreater\ngolems are mindless in combat, only follow-\ncontrast to the stone\ngolem . Iron golems are sometimes found\ning the simple tactics of their masters. They are completely emo-\nwith\nshort sword (relative to their size) in\none\nhand. On ex-\ntionless and cannot be swayed in any way from their instructions_\ntremely rare occasions this sword will be magical.\nThey will not pick up and use weapons in combat,\neven if ordered\nThe iron\ncannot\n~speak\nOr\nmake any vocal noise,\nnor\nto, always preferring their fists. Stone golems have a strength of\ndoes it have any distinguishable odor: It moves with\nponder-\n22, for purposes of breaking\nthrowing things.\nously smooth gait at half the speed of & normal\nman;\nEach step\nThe stone\nis immune t0 any weapon\nexcept those of +2\ncauses\nthe floor to tremble, unless it is on a thick, solid founda-\nor better enchantment_\nArock to mud\nslows a\nfor 2-12\ntion\n(2d6) rounds\nIts reverse , mud t0 rock acts to heal the\ngolem ,\nre=\nstoring all lost hit points_\nA flesh to stone spell does not actually\nCombat:\nThe iron\nconforms to the strategies listed for the\nchange the golem s structure, but does make it vulnerable to any\nstone\nexcept as described here: It has a strength of 24 for\nnormal attack\nthe following round.\nThis does not include\nthe purposes of lifting, throwing or breaking objects. The iron g0-\nspells,\nexcept those that will cause direct damage. All other spells\nlem is immune t0 any weapon,\nexcept those of\n3 or better en-\nare\nignored. Once every other round, the stone golem can cast &\nchantment. Magical electrical attacks will slow it for 3 rounds,\nslow\nupon any opponent with 10 feet of it.\nand magical fire attacks actually repair 1 hit point of damage for\neach hit die of damage it would have caused . All other\nare\nHabitat Society:\nGolems\nare automatons\nartificially\ncreated\nignored:\ngolems\nare\nsubject to the damage inflicted by\nrust\nand under the direct control of their creator: They have no society\nmonster\nOnce every 7 rounds, beginning either the first or sec-\nand are not associated with any particular habitat:\nare fre=\nond round of combat; the iron golem breathes out & cloud of\nquently used to guard valuable items or places. Unlike the lesser\nsonous gas_\nIt does this automatically\nwith\nno\nregard\nto the\ngolems, the greater golems are always under the complete control\neffects it might have. The gas cloud fills a 10 foot cube directly in\nof their master: A greater golem can obey simple instructions in-\nfront of it, which dissipates by the following round, assuming\nvolving direct actions with simple conditional phrases. Although\nthere is somewhere for the gas to g0.\nthis is better than a lesser\nis capable of following, they still\nAny\nAny\nVery\nVery\nAny\n(60\nAny\ngolem\ngolem\nsleep,\ngolem\nlong\nlegs ,\ngolem\ngolem\nIspell\ngolem\ngolem\ngolem\nfor\nspell\n~spells\nIron\nThey\npoi=\n'golem",
  "frequency": "rare",
  "organization": "Solitary",
  "diet": "Nil",
  "intelligence": "Non- (0)",
  "treasure_type": "Nil",
  "alignment": "Neutral",
  "hit_dice": "14",
  "special_attacks": "See below",
  "special_defenses": "See below",
  "magic_resistance": "Nil",
  "size": "L (91/2' tall)",
  "morale": "Fearless (19-201",
  "xp_value": "10,000",
  "id": "golems_greater_stone_tron"
}