{
  "name": "Golem, General",
  "source_page": 63,
  "raw_text": "Golem, General\nCLIMATE TERRAIN:\nFREQUENCY:\nrare\nORGANIZATION:\nSolitary\nACTIVITY CYCLE:\nDIET:\nNil\nINTELLIGENCE:\nNon- (0)\nTREASURE:\nNil\nALIGNMENT:\nNeutral\nGolems are magically created automatons of great power. The\nconstruction of one involves mighty magics and elemental forces_\nBackground:\nGolems predate any known writings. The wizard\nwho discovered the process, if indeed there was only one\n1S not\nknown\nSome of the rediscoverers have written down their se -\ncrets in various arcane manuals, enchanted to aid the reader in\nconstructing the golem . It is thought that the first golem created\nwas ]\nflesh\npossibly an accident of some great wizard ex-\nperimenting with reanima\nhuman bodies. Flesh golems\neasier to make than any other sort because they are made of 0r-\nganic material that once lived\nLater, the process was generalized\nto suit certain earthen materials, which produces much stronger\ngolems. Strangely enough, the\ncan\nonly be animated\nby priests.\nTheory:\nGolems are all made from some sort of elemental mate-\nrial. So far; the great wizards have only discovered how to\nuse\nvarious earthen materials\nsuch as\nstone and iron;\nto make\nClay Golems\ngolems. The sole exception is the flesh\ndue to the special\nOnly a lawful good priest of at least 17th level can create a\nproperties of its organic body. The animating force of the golem is\ngolem. The body is sculpted from a single block of\nweighing\nan elemental spirit from the elemental plane of earth. Since the\nleast 1000 pounds, which takes about & month. The other ma-\nspirit is not a natural part of the body\nit is not affected by most\nterials and spell components cost roughly 20,000\npieces, The\n~spells or even by most weapons (see individual descriptions) . The\nvestments\nwhich\nare not consumed and\ncan\nbe reused,\ncost\nprocess of creating the golem binds the unwilling spirit to the arti-\n30,000 gold pieces. The spells used are resurrection,\nanimate 0b-\nficial body; and enslaves it to the will of the golem s creator: The\nject;\ncommune, prayer; and bless.\nnature of this spirit is unknown\nand has so far eluded the grasp of\nall researchers. What is known is that it is hostile to all prime ma-\nStone Golems\nterial plane life forms, especially\ntoward the\ncaster that\nbound it to the golem.\nOnly a wizard of at least Ioth level can create a stone golem. The\nThe carving or assembling of the golem s physical body is an\nbody is chiseled from\nsingle block of hard stone, such as granite;\nexacting task: Most\ncasters end up\nhiring skilled labor to do\nweighing at least 3000 pounds,\nwhich takes 2 months. The mate=\nit for them, such as a stone mason or dwarf for stone golems\netc;\nrials and\ncomponents cost 60,000\npieces and the spells\nIF the maker has no experience\nworking in that material, the con -\nused are wish, polymorph any object,\nand slow.\nstruction time is doubled. The known\nfor crea\ngolems\nspecify the size of the creature. Anything bigger or smaller won't\nIron Golems\nwork, although it might be worth investigating a new\nthat;\nOnly a wizard of at least 18th level can create an iron golem\nwould. The material costs listed do not include the base physical\ntakes 3 months,\nand 5000 pounds of iron,\nto build the body;\nbody itself , only the unusual materials and\ncomponents that\nwhich must be done by\nskilled\nsmith\nThe materials and\nare consumed Or become\npermanent part of the golem. The rit-\ncomponents cost 80,000\npieces. The\nused in the\nuals used t0 animate the\ngolem require a full uninterrupted month\nritual are wish\npolymorph any object,\ngeas\nand cloud kill;\nCon-\nto complete\nIn all\ncases the\nspells used\ncan\ncome from devices;\nstruction of the body requires an ornate sword which is incorpo-\nsuch as wands or scrolls. If a magical tome is used to make the g0-\nrated into the monster: A magical sword\ncan\nbe used,\nin which\nlem ;\nno\n'spells are needed,\nand the level of the\ncaster can be\ncase\nthere is a 50 %\nthat it is drained of magic when the g0-\nsignificantly lower.\nlem is animated_\nThe\ncan only use those abilities of the\nsword that are automatic\nproperty that requires & command\nFlesh Golems\nword,\nor any sentient\nability of the sword are lost. If the sword is\nOnly a wizard of at least I4th level can create a flesh golem. The\never removed from the golem, it\nall of its magic.\npieces of the golem must be sewn together from the dead bodies of\nnormal humans that have not decayed significantly This requires\nFull month to complete_\nA minimum of 6 different bodies must\n'be used,\none for each limb,\none\nfor the torso (with head),\nand\ndifferent one for the brain. In some cases,\nmore\nbodies may be\nnecessary t0 form a complete\ngolem. Other materials and ceremo-\nnial items for the\ncost 40,000 gold pieces\nand are consumed\nin the casting. The spells needed are wish, polymorph any object,\nprotection from normal missiles\nand strength.\nAny\nVery\nAny\ngolem ,\n1ting\nare\nclay\ngolem\nclay;\ngolem ,\nclay\nclay\ngold\nspell\nspell\nspell\ngold\ngeas,\nspells\nting\n~spell\nspell ,\niron\n~spell\ngold\nspells\nspell\nchance\ngolem\nAny\nJoses\n'spells ,\ngeas,",
  "frequency": "rare",
  "organization": "Solitary",
  "diet": "Nil",
  "intelligence": "Non- (0)",
  "treasure_type": "Nil",
  "alignment": "Neutral",
  "id": "golem_general"
}