{
  "name": "Harpy",
  "source_page": 67,
  "raw_text": "Harpy\nCLIMATE TERRAIN:\nTemperate, tropical land or\ncoast\nFREQUENCY:\nRare\nORGANIZATION:\nFlock\nACTIVITY CYCLE:\nDay\nDIET:\nCarnivore\nINTELLIGENCE:\nLow (5-7)\nTREASURE:\nR (C)\nALIGNMENT:\nChaotic evil\nNO. APPEARING:\n2-12 (2d6)\nARMOR CLASS:\nMOVEMENT:\n6, Fl 15 (C)\nHIT DICE:\nTHACO:\n13\nNO. OF ATTACKS:\nDAMAGEIATTACK:\n1-3/1-3/1-6 or 1-3/1-3/weapon\nSPECIAL ATTACKS:\nSinging and charm\nSPECIAL DEFENSES:\nNil\nMAGIC RESISTANCE:\nNil\nSIZE:\nM (6')\nMORALE:\nElite (13-14)\nXP VALUE:\n1400\nHarpies are wicked avian beasts that prey upon nearly all crea-\ntures but prefer the flesh of humans and demihumans\nHarpies have the bodies of vultures but the upper torsos and\nanimal dare approach it. Here they remain unless hunting. Har-\nheads of women . Their human features are\nyouthful, but hid-\npies often carry victims back to their lair to devour them in more\neous\nwith frayed unkempt hair and decaying teeth: A foul odor\nfamiliar surroundings_\nsurrounds all\nharpies and that which they touch. Harpies never\nHarpies have little use for treasure, other than the shiny bau-\nbathe nor clean themselves in any way: Their dress, if .\nanything, is\nbles which they often attach to their clothes. Other items, such as\nlimited to tattered rags and shiny trinkets taken from previous\nand weapons;\nare\nfrequently interspersed amongst the filth\nvictims\nand bones that litter the\ncave:\nThis refuse can reach\ndepth of\nThe language of harpies , in contrast to their enticing song, is a\nseveral feet in the oldest of harpy lairs_\nhorrible collection of cackles and shrieks. Although there are in-\nA typical   harpy   lair\nhouses\nabout\nhalf-dozen   of\nthese\nstances of harpies which could speak the languages of other crea-\nwretched creatures. No male harpies have ever\nseen and it\ntures, these are few and far between.\nseems\nthat harpies can reproduce at will by laying\nsingle egg\nevery other year: Harpies take no care of their young, which live\nCombat:\nThe song of the harpies has the ability to charm all hu-\noff carcasses and\ncave\nvermin\nuntil they  themselves\nare   old\nmans and demihumans who hear it (elves are resistant to the\nenough to sing and hunt.\ncharm) . Those who fail their saving throw\nversus\nwill pro-\nHarpies have\nno social structure, frequently\nquarreling\nover\nceed towards the\nwith all possible speed, only to stand en-\nwho gets what part ofa victim and when to stop the torturing and\ntranced while the\nslays them at its leisure. This charm\nstart the feasting. Occasionally these quarrels will turn violent, so\nlast as\nas\nthe\ncontinues t0\nHarpies\ncan\nsing even\nthat more than one harpy feast has begun with the last minute ad-\nwhile engaged in melee\ndition of the losing harpy to the menu.\nIt is\nimpossible to fend off a harpy song simply by clasping\nHarpies will occassionally agree to cooperate in\nacts with\nhands over ears because the charm takes effect the moment the\nother humanoids.\nfirst note is heard\nCharacters making\npreparations to block\nout the sound; (wax in ears;\netc:)\nare immune t0 the effects of the\nEcology:\nHarpies hunt all\nmanner\nof beasts, remaining in\nan\nsong: In addition, characters who make their saving throw are\narea for as\nas the food supply lasts. They are despised and\nthereafter immuneto\neffect, until such time as\nencounter a\ngreatly feared by all creatures weaker than themselves.\ndifferent group of harpies.\nHarpies have\nvoracious\nappetite, devouring all\nmanner of\nIf forced to fight, harpies can do so quite effectively by deliver-\nman and beast. They take great delight in torture, and frequently\ning\nvicious bite and raking simultaneously with their talons\nkill for pleasure. Slain victims which harpies do not eat are simply\nAbout 50 % of all harpies encountered will use weapons, usually\nleft to rot\na bone club\n(damage 1-8) which they wield surprisingly well.\nTheir life span is unknown but seems to be about 50 years.\nThe touch of a harpy upon a charmed individual has a similar;\nthough somewhat less potent, effect. Those who are touched\nmiss their saving throw\nversus\nwill stand mesmerized for\n20 + Id10 hours\nThe effect of either charm is broken if the\nis slain\nHabitat Society:\nHarpies make their home upon coastlines in\nregions near shipping lanes and by well-traveled\nThere\n~they use their song to lure travelers to their doom:\nTheir lair is usually a shallow cave, which they defile until no\ngold\nbeen\nspell\nharpy\nwill\nharpy\nlong\nharpy\nsing:\nevil\nprior\nJong\nthey\nits =\nand\nspell\nharpy\npaths,",
  "climate_terrain": "Temperate, tropical land or",
  "frequency": "Rare",
  "organization": "Flock",
  "activity_cycle": "Day",
  "diet": "Carnivore",
  "intelligence": "Low (5-7)",
  "treasure_type": "R (C)",
  "alignment": "Chaotic evil",
  "number_appearing": "2-12 (2d6)",
  "movement": "6, Fl 15 (C)",
  "thac0": "13",
  "damage": "1-3/1-3/1-6 or 1-3/1-3/weapon",
  "special_attacks": "Singing and charm",
  "special_defenses": "Nil",
  "magic_resistance": "Nil",
  "size": "M (6')",
  "morale": "Elite (13-14)",
  "xp_value": "1400",
  "id": "harpy"
}