{
  "name": "Hobgoblin",
  "source_page": 68,
  "raw_text": "Hobgoblin\nCLIMATETERRAIN:\nnon-arctic\nFREQUENCY:\nUncommon\nORGANIZATION:\nTribal\nACTIVITY CYCLE:\nAny\nDIET:\nOmnivore\nINTELLIGENCE:\nAverage (8-10)\nTREASURE:\nJ, M; D; (Qx5)\nALIGNMENT:\nLawful evil\nNO. APPEARING:\n2-20 (2d10)\nARMOR CLASS:\n5 (10)\nMOVEMENT:\nHIT DICE:\n1+1\nTHACO:\n19\nNO: OF ATTACKS:\nDAMAGEATTACK:\nby weapon\nSPECIAL ATTACKS:\nNil\nSPECIAL DEFENSES:\nNil\nMAGIC RESISTANCE:\nNil\nSIZE:\nM (6 1/2' tall)\nMORALE:\nSteady (11-12)\nXP VALUE: Hobgoblin\n35\nSub-chief\n65\nChief\n120\nHobgoblins are\nhumanoid race that wage a perpetual war\nwith the other humanoid races\nare\nintelligent, organized,\ncombat to inspire the troops. If the tribal chief is leading the bat-\nand aggressive\ntle, he will carry the standard with him, otherwise it will be held\nThe typical hobgoblin is a burly humanoid standing 61/2' tall.\nby one of his sub-chiefs.\nTheir hairy hides range from dark reddish-brown to dark gray:\nIn addition to the warriors present in a hobgoblin tribe, there\nTheir faces show dark red or red-orange skin. Large males have\nwill be half again that many females and three times as many chil-\nblue or red noses. Hobgoblin eyes are either yellowish or dark\ndren as\nadult males.\nbrown while their teeth\nare\nyellow_\nTheir garments tend to be\nFully 80 % of all known hobgoblin lairs are subterranean com-\nbrightly colored,\noften bold, blood red_\nAny leather is always\nplexes. The remaining 20 % are surface villages which are fortified\ntinted black . Hobgoblin weaponry is kept polished and repaired.\nwith a ditch, fence\n2 gates\nand 3-6 guard towers\nare of-\nHobgoblins have their\nOwn\nlanguage and\noften speak with\nten\nbuilt upon ruined humanoid settlements and may incorporate\nOrCS ,\ngoblins ,\nand carnivorous apes\nRoughly 20% of them can\ndefensive features already present in the ruins\nthe common tongue of man\nHobgoblin\npossess artillery in the form of 2 heavy cata-\n2 light catapults\nand a ballista for each 50 warriors. Under-\nCombat:\nHobgoblins in & typical force will be equipped with\nground complexes may be guarded by 2-12\ncarnivorous apes\npolearms (30\nmorningstars (20 % ) , swords and bows (20% ) ,\n(60 % ).\nspears (10% ), swords and spears (10 %),\nswords and morning\nThey are highly adept at mining and can detect new construc-\nstars (5 % ) ,\nor swords and whips (5 % )\ntion , sloping passages, and shifting walls 40 % of the time.\nHobgoblins fight equally well in bright light or virtual dark-\nness\nhaving infravision with a range of 60 feet.\nEcology:\nHobgoblins feel superior to goblins or orcs and may\nHobgoblins hate elves and always attack them first\nact as leaders for them. In such cases, the\nlesser races\nare used as\nbattle Fodder: Hobgoblin mercenaries may work for powerful or\nHabitat Society:\nHobgoblins are nightmarish mockeries of the\nrich evil humanoids\nhumanoid races who\nmilitary society organized in tribal\nbands . Each tribe is intensely jealous of its status. Chance meet-\nKoalinth\nings with other tribes will result in verbal abuse (85 %) or open\nThis marine species of hobgoblin is similar to the land dwelling\nfighting (15 % ) . Hobgoblin tribes are found in almost any climate\nvariety in\nrespects. Koalinth dwell in shallow fresh or salt\nmany\nor subterranean realm\nwater and make their homes in caves\nA typical tribe of hobgoblins will have between 20 and 200\n(2d10 x 10) adult male warriors_\nIn addition , for every 20 male\nTheir bodies have adapted t0 marine environments via\nevo=\nand\nlution of gills. Their webbed\nand toes give them a move-\nhobgoblins there\nbe a leader (known\nas &\nsergeant)\n[WO\nment rate of 12 when swimming: Their bodies are sleeker than\nassistants. These have 9 hit\neach but still fight as 1 +1 Hit\n100\nled by\nsub-chief\nthose of hobgoblins and\nhave light green skin. They speak an\nDie monsters_\nGroups numbering over\nare\nunusual dialect of the hobgoblin tongue.\nwho has 16 hit points and an Armor Class of 3. The great =\n'strength\nThey tend to employ thrusting weapons like spears and pole\nof a\n~chief gives it a\n+2 on its\ndamage rolls and allows it to\nKoalinth\nbit\nfight as a 3 Hit Die monster: If the hobgoblins are encountered in\narms\nare every\ndisagreeable as hobgoblins,\nprey-\ntheir lair; they will be led by\nchief with AC 2, 22 hit points, and\non every\nthing they come across, especially aquatic humanoid\nand demi-human races. They detest aquatic elves.\n+3\npoints of damage\nattack\nwho fights as a 4 Hit Die mon-\nster, The chief has 5-20 (5d4) sub-chiefs acting\nbodyguards_\nLeaders and chiefs always carry two weapons\nEach tribe has a distinctive battle standard which is carried into\nAny\nfierce\nThey\nVillages\nvillages\nspeak\npults,\n%jo )\nhave\nthe e\nfingers\nwill\npoints\nthey\nsub-(\ning\nper",
  "climate_terrain": "non-arctic",
  "frequency": "Uncommon",
  "organization": "Tribal",
  "activity_cycle": "Any",
  "diet": "Omnivore",
  "intelligence": "Average (8-10)",
  "treasure_type": "J, M; D; (Qx5)",
  "alignment": "Lawful evil",
  "number_appearing": "2-20 (2d10)",
  "ac": "5 (10)",
  "hit_dice": "1+1",
  "thac0": "19",
  "special_attacks": "Nil",
  "special_defenses": "Nil",
  "magic_resistance": "Nil",
  "size": "M (6 1/2' tall)",
  "morale": "Steady (11-12)",
  "xp_value": "Hobgoblin",
  "id": "hobgoblin"
}