{
  "name": "Homonculous",
  "source_page": 69,
  "raw_text": "Homonculous\nCLIMATEITERRAIN:\nFREQUENCY:\nVery rare\nORGANIZATION:\nSolitary\nACTIVITY CYCLE:\nAny\nDIET:\nOmnivore\nINTELLIGENCE:\nSee below\nTREASURE:\nNil\nALIGNMENT:\nSee below\nNO. APPEARING:\nARMOR CLASS:\nMOVEMENT:\nFL 18 (B)\nHIT DICE:\nTHACO:\n16\nNO. OF ATTACKS:\nDAMAGEIATTACK:\nSPECIAL ATTACKS:\nBite causes\nSPECIAL DEFENSES:\nSee below\nMAGIC RESISTANCE:\nSee below\nSIZE:\nT(18\" tall)\nMORALE:\nElite (13-14)\nXP VALUE:\n420\nHomonculi are\nmystical\ncreated by magicians for\nspying and other special tasks.\nThe average homonculous is vaguely humanoid in form . It is\n18 inches tali and its greenish, reptilian skin may have spots Or\nforce. As soon as it loses contact with its master, the creature pan-\nwarts\nThey have leathery; bat-like wings with a span of 24 inches\nics and will do anything to regain contact. Contact between the\nand\nfilled with\npointed teeth that can inject\npO -\ntwo cannot be maintained across planar or dimensional barriers_\ntent\nsleeping venom.\nIf either the creator or homonculous is on another plane, the ho-\nCombat;\nThe homonculous is a quick and agile flyer which uses\nmonculous will remain near the point where it was last in contact\nthis ability to great advantage in combat. It can dart to and fro s0\nwith its master;\nquickly that any attempt to capture it short ofa net or web\nHomonculi are a reflection of their creator: They have the crea-\nalmost\nimpossible.\ntor's alignment,\nbasic\nintelligence,\neven\nphysical\nmanner-\nIn combat, the homonculous will land on its chosen victim\nisms. They are mute but can write if the creator is literate. They\nbite with its needle-like fangs. In addition to\n1-3\npoints of\nmay assist their creator in & variety of tasks including magical en-\ndamage, the creature injects a powerful venom. Anyone bitten by\ndeavors;\nalthough they cannot themselves cast\nthe homonculous must save versus poison or fall into a comatose\nHomonculi lairs are in the homes of their creators. Indulgent\nsleep for 5-30 (Sd6) minutes.\nwizards may\nprovide\nspecially built bed,\nneste\nOr\n'living cham-\nThe creature $ saving throws are the same as those of its crea-\nber: Otherwise, the homonculous simply perches wherever it can.\ntor. While most attacks against either the homonculous Or creator\ndo not affect the other; there is one exception. Any attack which\nEcology:\nHomonculi are nothing more than tools.\nhave\ndestroys the homonculous causes its creator to suffer 2-20 (2d10)\nno place in the natural world and\nare not\npart of any ecological\ndamage.\nConversely; if the creator is slain, the homon-\nsystem. They provide the wizard who created them with a variety\nculous also dies and its body swiftly melts away into a\nof\nof useful services\nCommonly;\na homonculous is called upon to\nichor;\nact as a spY; scout, messenger;\nemissary: Because of the\ntial harm which the death of a homonculous inflicts on its master;\nHabitat Society:\nHomonculi are artificial creatures created by\nthey are seldom employed as body guards or living weapons_\nwizards as\nliving tools. The process by which one is created is\nAlthough they are magical creations, homonculi possess the\nlong, complicated, and expensive.\nwizard who desires a ho-\nsame\nbiological functions as non-magical creatures. They must\nmonculous servant must first locate and hire an alchemist. The\nrest and require food and drink in order to survive. When eating;\nwizard\nmust\nprovide one pint of his own blood and 500-2,000\nthey share the\ntastes of their  masters and generally consume\n(1d4 x 500)\npieces. The blood becomes the basis for the crea-\nabout as much as & typical cat.\nture s body while the money pays for & variety of other\nThere are rumors of magical means by which non-wizards can\nand the alchemist's time. The alchemist requires 1-4\nweeks\nacquire their own form of homonculous. Although these are not\ntransform the blood into the necessary magical base. The wizard\nwidely believed to be valid, there are those who report having\nis then sent for and required to cast mending, mirror image, and\nseen the process Or its results first hand. If such a procedure exists,\nwizard eye\n~spells upon the fluids.\nAs the last of these spells is\nbe\nvaluable to its discoverer;\nworked, the fluids spontaneously coagulate and form the body of\nthe homonculous\nThe homonculous is telepathically linked\nto its\ncreator\nknows everything that its master knows and transmits everything\nit sees and hears t0 him. The creator can telepathically control the\nactions of the homonculous at a range of up to 480 yards. The ho-\nmonculous will never willingly travel beyond the limits of contact\nwith its master, though it can be removed from that region by\nAny\n1-3\nsleep\nsmall\nbeings\nlong\"\nmouth\n'spell\nand\nand\ndoing\nspells,\nThey\npoints\npool\npoten-\nAny\ngold\n'supplies\nwould\nquite",
  "frequency": "Very rare",
  "organization": "Solitary",
  "activity_cycle": "Any",
  "diet": "Omnivore",
  "intelligence": "See below",
  "treasure_type": "Nil",
  "alignment": "See below",
  "movement": "FL 18 (B)",
  "thac0": "16",
  "special_attacks": "Bite causes",
  "special_defenses": "See below",
  "magic_resistance": "See below",
  "size": "T(18\" tall)",
  "morale": "Elite (13-14)",
  "xp_value": "420",
  "id": "homonculous"
}