{
  "name": "Hornet Hornet",
  "source_page": 70,
  "raw_text": "Hornet\nHornet\nCLIMATE TERRAIN:\nforest\nforest\nOF cave\nOr cave\nFREQUENCY:\nUncommon\nRare\nORGANIZATION:\nSolitary\nHive\nACTIITY CYCLE:\nDIET:\nOmnivore\nOmnivore\nINTELLIGENCE:\nSemi- (2-4)\nNon- (0)\nTREASURE:\nNil\nQ(xzo)\nALIGNMENT:\nNeutral\nNeutral\nNO. APPEARING:\n1-20\nARMOR CLASS:\n2 (4)\nMOVEMENT:\n6, Fl 24 (B)\n6, Fl 21 (B)\nHIT DICE:\nTHACO:\n15\n17\nNO: OF ATTACKS:\nDAMAGEIATTACK:\n1-4\n2-8 (2d4)/1-4\nSPECIAL ATTACKS:\nPoison and\nPoison and\nparalysis\nparalysis\nSPECIAL DEFENSES:\nNil\nNil\nMAGIC RESISTANCE:   Nil\nNil\nSIZE:\nM (5' long)\nM (5' long)\nMORALE:\nAverage (8-10)\nAverage (8-10)\nXP VALUE:\n650\n420\nGiant hornets are nothing more than fantastically enlarged ver-\ntion . The female leaves the chamber in search of a victim which it\nsions of normal insects. Unlike their more common cousins,\nparalyzes and carries back to the chamber. Once in the chamber,\nare often hostile and aggressive\nthe hornet uses its mud-like compound to bind its prey and injects\nThe giant hornet has a 5'\nbody and a 10' wingspan. Their\nit with 2-4 (2d8) eggs. It leaves promptly thereafter; pausing only\nchitinous exoskeleton is marked by shiny; parallel stripes of black\nto seal the egg chamber (which takes 1-6 hours) . Mere hours later;\nand yellow\nThe abdomen is tipped by a retractable stinger:\nthe eggs hatch and the larvae within begin to feed on the body\naround them. The six inch\nlarvae do 1 point of damage each\nCombat:\nGiant hornets are solitary creatures who will attack\nper turn. After devouring the body the young hornets break\non\nsight: It swoops\nonto its prey and takes hold with\nthrough the wall of the egg chamber by dissolving it with their sa -\nwhile its stinger stabs into the victim's body In addition to inflict-\nliva and fly off to begin their lives in the wild.\n1-4 points of damage, the stinger also injects a potent toxin . If\nAlthough hornets do not keep treasure troves, their egg cham -\nsaving throw\nversus\npoison is not made, the toxin does 5-30\nbers may be a source of valuables in the form of victims' posses-\npoints of damage and paralyzes the victim for 2-12 (2d6) hours.\nsions\nSmoke and flame are powerful weapons in any battle against\nthese giant insects. Smoke causes them to become somewhat tran-\nEcology:\nThe giant hornets are the result of deliberate tamper-\nquilized , invoking a -2 penalty on its attack rolls. Flame frightens\nwith nature\nroam the world mindlessly following their\nthem greatly; and\nwill suffer a -4 on their attack rolls against\nprimal instinct to reproduce_\nanyone who is using it to defend himself.\nThe hornet's\nare\nHornet toxin decays quickly when removed from the body: It\nespecially vulnerable to flame and will be consumed by any form\ncan be used to coat blades and such only if the toxin is less than\nof fire-based attack in one round. Although this does no physical\ntwo\nold. The toxin\nalso be used in the preparation of\nharm to the hornet, it does render it flightless until its\ngrow\nanti-paralysis potions and antidotes\nback in 2-12 (2d6) weeks.\nThe giant hornet is\na very noisy flier and the buzzing of\nGiant\nwings can be heard up to 150' away: Underground, this range is\nThese insects are very similar to giant hornets but\nin swarms\nhalved by each wall or closed door between the monster and the\nof as many as 20 individuals. Giant wasps are cooperative insects\nlistener;\nwho build and maintain immense hives . Constructed of a thick\npaper-like   substance,\ngiant\nwasp\nhives\nare\nhome\nto\n21-40\nHabitatiSociety:\nGiant hornets are believed to be the result of\n(1d20 +20) adults and 100-400 (1d4xlOO) eggs, larvae, and pupae\nmagical experiments gone awry. Save for the fact that\nare\nTheir hives may surround a\ntree or fill a vast chamber in the\nmuch more\naggressive than the common hornet, their gigantic\nearth.\nsize has not changed their instinctual behavior:\nA giant wasp first attacks with its powerful bite (2d4 points of\nOnce per month,; female hornets will prepare a nest and attract\ndamage) , then stabs with its stinger (1-4 points) . Failure to make a\nmale for mating: Together, the two create an egg chamber in\nsave\nagainst poison means that any victim hit\nthe stinger has\nsome out of the way place. Egg chambers can be established in\nbeen injected with a poison similar to that employed by the giant\npits, abandoned buildings, caves, Or any similar area. The walls\nhornet. Paralyzed victims are carried back to the hive and placed\nof the chamber are coated with a mixture of mud\ncellulose, and\nin the communal egg chamber where\nare quickly consumed\nhornet saliva which hardens into rock\nThe construction of the\nby the hungry young:\nchamber takes between 1 and 6\ndepending on its size.\nWhen the chamber is completed, the couple mates. The male\ndeparts shortly afterwards, but dies within\nday From exhaus-\nWasp\nAny\nAny\nDay\nDay\nthey\nlong\nlong\ndown\nlegs\nits\ning\ning\nThey\nthey\nwings\ndays\nmay\nwings\nWasp:\nits\nlive\nthey\nlarge\nby\nthey\ndays,",
  "climate_terrain": "forest",
  "frequency": "Uncommon",
  "organization": "Solitary",
  "diet": "Omnivore",
  "intelligence": "Semi- (2-4)",
  "treasure_type": "Nil",
  "alignment": "Neutral",
  "number_appearing": "1-20",
  "ac": "2 (4)",
  "movement": "6, Fl 24 (B)",
  "thac0": "15",
  "special_attacks": "Poison and",
  "special_defenses": "Nil",
  "magic_resistance": "Nil",
  "size": "M (5' long)",
  "morale": "Average (8-10)",
  "xp_value": "650",
  "id": "hornet_hornet"
}