{
  "name": "Hyena Hyena Hyaenodon",
  "source_page": 73,
  "raw_text": "Hyena\nHyena\nHyaenodon\nCLIMATETERRAIN:\nWarm plains\nWarm plains\nFREQUENCY:\nCommon\nVery rare\nORGANIZATION:\nPack\nPack\nACTIVITY CYCLE:\nDay\nDIET:\nScavenger\nScavenger\nINTELLIGENCE:\nAnimal (1\nAnimal\nTREASURE:\nNil\nNil\nALIGNMENT:\nNeutral\nNeutral\nNO. APPEARING:\n2-12 (2d6)\n2-8 (2d4)\nARMOR CLASS:\nMOVEMENT:\n12\n12\nHIT DICE:\nTHACO:\n17\n15\nNO. OF ATTACKS:\nDAMAGEATTACK:\n2-8 (2d4)\n3-12\nSPECIAL ATTACKS:\nNil\nNil\nSPECIAL DEFENSES:\nNil\nNil\nMAGIC RESISTANCE:   Nil\nNil\nSIZE:\nS (4' long)\nL (8' long)\nMORALE:\nUnsteady\nAverage\n(5-7)\n(8-10)\nXP VALUE:\n65\n175\nHyenae are canines who roam warm\ngrasslands and plains\nDuring their first year of life cubs will not attack. They are one\nare\nprimarily scavangers,\nbut will hunt small game on occasion.\nof\nHit Die animals who run for the protection\ntheir parents and\nTheir powerful jaws give them & nasty bite.\nthe\nif threatened. During the second year; the cubs\nan\nHyenae are ugly animals. Roughly the size of a large.\nthe hye-\nadditional Hit Die\nbegin to hunt alongside the adults. Hyenae\nnas body is covered with a light brown or\nfur; Its feet , mark-\nings, and belly are black: The hyena s shorter rear legs make it look\nbecome fully mature in three years\nclumsy\nan illusion which is quickly\ndispelled when it attacks:\nEcology:\nHyenae are active scavengers who feed on the carrion\nHyenae are cowards. They do not attack unless their\nleft behind by other, larger predators. They are also able to take\nCombat:\nliving prey,  although they normally\nrestrict  their hunting to\nprey is helpless;,\noutnumbered,\nor\ndead already:\nsmall, young, old,\nor sick animals\nThey have strong constitu-\nHyenae surround\na victim and rush in at it from all sides\nat-\nenable\nsafely\ntions and digestive tracts that\nthem t0\ndigest even\ntacking with a strong bite that does 2-8 (2d4) points of damage.\ndiseased meat\nnatural attack roll of 20 indicates that the hyena has locked its\nHyenae produce few useful byproducts. The skins make\njaws onto the victim . Once this happens, the animal will not let\npoor\nleather; the fur tends to fall out, and the meat has a decidedly ran-\ngo until it suffers 2 or more points of damage: Such holding bites\ncid taste . Cubs are difficult to domesticate as they usually revert\ndo\ndo additional damage but can slow the victim down be-\nto the wild upon\nmaturity However; they may be found as\ncause of the hyena's extra weight. Each hyena reduces a victim'$\nmovement rate by 6. The number of hyenae which can lock onto\ncompanions of nomadic, aboriginal people:\nvictim is determined by its size . One hyena can lock onto a\nanimal;\ntwo t0 & small one;\n~and s0 forth.\nHyaenodon\nAlthough the hyaenodon resembles a giant hyena it is actually\nHabitat Society:\nHyenae roam the open plains of warm,\ngrassy\nnot\nrelated at all. It is a survivor of\nprehistoric times ,\npredator\nregions. They are usually found within sight of a herd of animals\nthat evolved into a canine-like form\nHyaenodon markings are\nlike zebra and antelope. Generally; there will be L hyena for every\nsimilar to those of hyenae, although the dominant fur color is a\n10 herd animals being followed. A typical hyena\ncan survive\nlion-like gold. Despite their genetic differences, they are very sim-\non one man-sized animal every three days . If\nattack and kill\nilar to hyenae in temperament and behavior: Hyaenodon females\nan\nanimal, they will strip it to the bones in short order:\ncar-\ngive birth to litters of 1-4 cubs. These mature within 4 years_\nrion which they encounter will also be consumed.\nIts savage bite does 3-12 (3d4) points of damage and it can lock\nHyenae are instinctively aware of their place in the animal hier-\nonto its victims just as smaller hyenae do. If the hyaenodon does\narchy: They defer to larger or more powerful predators like lions\nthis, the victim'$ movement rate is cut by 12 for each hyaenodon\nIf such an animal makes a kill\nwill sit 50' to 100' away and\nthat attaches itself. Hyaenodon\nwill devour one man-sized\npatiently wait for the predator to finish and leave: If given the\nvictim per\nBecause of their larger size, they are able to take\nchance, they have been known to\nto snatch portions of the\nprey such as elephants\noxen\nand buffalo. If a giant hyena\ncarcass and run\nmay\nopenly challenge other; less powerful\nsuffers 2 Or more points of burning damage\nit immediately flees\nor numerous\npredators.\nthe area in search of a spot to tend its wounds.\nHyenae travel in\ncomposed of an even mixture of adult\nmales, females, and young. Although they do not mate for life,\nhyena couple will remain together for several years. The male as-\nsists in caring for the 2-4 cubs which are born in each litter: The\nyoung do not nurse, but are fed regurgitated food in\nmanner\nsimilar t0 that employed by many avian\nDay\nThey\npack\n~gain\ndog\nand\ngolden\nnot\nhitting`\ntiny\npack\nthey\nAny\nthey\npacks\nday:\nlarge\ntry\nThey\npacks\nspecies",
  "climate_terrain": "Warm plains",
  "frequency": "Common",
  "organization": "Pack",
  "activity_cycle": "Day",
  "diet": "Scavenger",
  "intelligence": "Animal (1",
  "treasure_type": "Nil",
  "alignment": "Neutral",
  "number_appearing": "2-12 (2d6)",
  "movement": "12",
  "thac0": "17",
  "damage": "2-8 (2d4)",
  "special_attacks": "Nil",
  "special_defenses": "Nil",
  "magic_resistance": "Nil",
  "size": "S (4' long)",
  "morale": "Unsteady",
  "xp_value": "65",
  "id": "hyena_hyena_hyaenodon"
}