{
  "name": "Imp Quasit",
  "source_page": 74,
  "raw_text": "Imp\nQuasit\nCLIMATETERRAIN:\nAny\nFREQUENCY:\nrare\nrare\nORGANIZATION:\nSolitary\nSolitary\nACTIVITY CYCLE:\nAny\nDIET:\nCarnivore\nCarnivore\nINTELLIGENCE:\nAverage\nLow\nTREASURE:\nQx3\nALIGNMENT:\nLawful evil\nChaotic\nNO. APPEARING:\nARMOR CLASS:\nMOVEMENT:\n6 , Fl 18 (A)\n15\nHIT DICE:\n2+2\nTHACO:\n19\n17\nNO: OF ATTACKS:\nDAMAGEIATTACK:\n1-4\n1-2/1-2/1-4\nSPECIAL ATTACKS:\nSee below\nSee below\nSPECIAL DEFENSES:\nSee below\nSee below\nMAGIC RESISTANCE:   25 %\n25 %\nSIZE:\nT (2' tall)\nT (2' tall)\nMORALE:\nAverage (8-10)\nAverage (8-10)\nXP VALUE:\n650\n650\nImps are diminutive creatures of an evil nature who roam the\nand act as familiars for lawful evil wizards and priests_\nThe average imp is a 2' humanoid with leathery; bat-like wings,\nvaluables encountered during their travels\nbarbed tail;\nand sharp, twisted horns. Its skin is & dark red and\nThe imp confers some of its powers upon its master: A tele-\npathic link connects the two whenever they are within one mile of\nits horns and jagged teeth are & gleaming white\nother; This enables the master to receive all of the imp's sen -\nThe imp can polymorph itself into two other animal forms_\nThe most commonly encountered alternate forms are those of &\nsory impressions, including its infravision. The master also gains\nspider,\nral\nOr\ngoat. In such forms the\nthe\ninherent 25 % magical resistance and is able to regener-\nraven; giant\nate just as the imp does. If the imp is within telepathic range, the\nphysically identical to\nnormal animal-\nmaster acts as if he were one level higher than he actually is. Con -\nCombat:\nIn its natural form, the imp attacks with the wicked\nversely; if the imp is more than\nmile away; the master acts as if\nhe\nwere one\nlevel of ability below his actual rank. If the imp is\nstinger on its tail_\nIn addition to\ninflicting 1-4 points of damage_\nthese\nthis stinger injects a powerful poison which is s0 deadly that those\nkilled , the master instantly\nby four levels, though\ncan\nwho fail their save versus poison are instantly slain by it. When it\nbe regained in the usual manner:\nis polymorphed, the imp attacks with the natural weaponry of its\nEcology:   Imps are the errand\nof the powerful evil beings\nadopted form, though the goat and raven forms lack damaging\nwho command the darkest planes. They often act as emissaries\nattacks\nand agents, but their primary task is to enhance the spread of evil\nThe imp can use its\n~special magical abilities no matter what its\nform . All imps are able to detect\ndetect magic, or become\nin our world.\ninvisible at will . Once per\nthey can\nuse 4\nsuggestion.\nImps are immune t0 attacks based\non\ncold,\nfire , Or\nelectricity\nQuasit\nand resist all other\nattacks as if\nwere 7 Hit Die creatures\nQuasits are chaotic\ncounterparts to imps. The chaotic evil\nThey can be harmed only by silver or magical weapons and are\npriests and wizards which quasits\nserve\ngain the same benefits\nable to regenerate one hit\nper melee round.\nand disadvantages that\nan\nimp's master does. Like imps\neach\nquasit can assume two other forms_\nThose most commonly cho-\nHabitat Society:\nImps are beings of a very evil nature who orig-\nsen\nby quasits are bats, giant centipedes, frogs,\nOr wolves\nThey\ninate on the darkest of evil planes\nTheir main purpose on the\ncan use their magic in any of their forms.\nPrime Material plane is to spread evil by assisting lawful evil wiz-\nThe quasit attacks with its\nclawed hands (doing 1-2 points\nards and priests. When such a person is judged worthy of an imp's\neach) and its deadly bite (doing 1-4 points) . The quasit s claws are\nservice , the imp comes in answer to a find familiar\ncoated in a toxin which causes anyone struck by them to save ver-\nOnce they have contacted their new\nmaster\nimps begin at\npoison\nor lose\none\nof dexterity for 2-12 (2d6) rounds\nonce to take control of his actions. Although imps maintain the il-\nThe effects of multiple wounds are cumulative_\nlusion that the summoner is in charge, the actual relationship is\nQuasits can turn invisible, detect\nOr\ndetect magic at will.\ncloser t0 that of a workman (the imp) and his tools (the master) .\nThey regenerate 1 hit\nper round and can unleash & blast of\nAlthough\nan imp's body can be destroyed on the Prime Mate-\nfear with a 30 foot range radius once per\nOnce each week the\nrial plane, it is not s0 easily slain . When its physical form is lost,\nquasit can commune with the lower planes\n(asking up to 6 ques-\nits corrupt spirit instantly returns to its home plane where it is re-\ntions) .\nformed and; after\na time, returned t0\nouI\nworld to resume its\nQuasits can only be harmed by cold iron or magical weapons.\nwOrK\nare able to resist magic 25 % of the time, save as if they were\nWhile they are technically in the service of their master, imps re-\n7 Hit Die monsters and are immune t0 cold, fire, and lightning:\ntain a basic independence and ambition to become more\npowerful\nsomeday: They may acquire treasure from those\nslay; and will\nImp\nAny\nVery\nVery\nAny\nevil\nworld\npilfer\noften\neach\nimp\nimp\nlarge\ndrops\n'boys\ngood,\nday\n\"spell ,\nthey\nevil\npoint\nspell.\npoint\nSuS\ngood,\npoint\nday:\nThey\nthey",
  "climate_terrain": "Any",
  "frequency": "rare",
  "organization": "Solitary",
  "activity_cycle": "Any",
  "diet": "Carnivore",
  "intelligence": "Average",
  "treasure_type": "Qx3",
  "alignment": "Lawful evil",
  "movement": "6 , Fl 18 (A)",
  "hit_dice": "2+2",
  "thac0": "19",
  "special_attacks": "See below",
  "special_defenses": "See below",
  "magic_resistance": "25 %",
  "size": "T (2' tall)",
  "morale": "Average (8-10)",
  "xp_value": "650",
  "id": "imp_quasit"
}