{
  "name": "Invisible Stalker",
  "source_page": 75,
  "raw_text": "Invisible Stalker\nCLIMATE TERRAIN:\nAny\nFREQUENCY:\nrare\nORGANIZATION:\nSolitary\nACTIVITY CYCLE:\nDIET:\nSpecial\nINTELLIGENCE:\nHigh (13-14)\nTREASURE:\nNil\nALIGNMENT:\nNeutral\nNO. APPEARING:\nARMOR CLASS:\nMOVEMENT:\n12, Fl 12 (A)\nHIT DICE:\nTHACO:\n13\nNO. OF ATTACKS:\nDAMAGEATTACK:\n4-16 (4d4)\nSPECIAL ATTACKS:\nSurprise\nSPECIAL DEFENSES:\nInvisibility\nMAGIC RESISTANCE:\n30 %\nSIZE:\nL (8' tall)\nMORALE:\nElite (13-14)\nXP VALUE:\n5000\nThe invisible stalker is a creature from the elemental plane of air:\nbe seen as\nsomething of a diversion and thus undertaken with lit-\nThose encountered\non the Prime Material plane have almost al-\ntle resentment. Tasks that require a week Or more of its time will\nways been summoned by wizards to Fulfill\nspecific task:\ndrive the invisible stalker to pervert the stated intent of the com-\nThe true form of the invisible stalker is unknown . On the\nmand. Such commands must be carefully worded and come from\nrial, Astral;\nor\nEthereal planes, the invisible stalker can only be\npowerful wizard. An invisible stalker may look for a\nhole\nperceived as\nshimmering air mass which looks much like the re-\nin the command as\nmeans of striking back at its master. For ex-\nfraction effect caused by hot air passing in front of cold.\nample, a simple command such as \"keep me safe from all harm\"\nInvisible stalkers understand the common speech of men, but\nmay result in the stalker carrying the conjurer back to the elemen-\ncan not\nspeak it: They can converse only in their own language,\ntal plane of air and leaving him there in a well hidden location.\nwhich sounds much like the roaring and\nwhooshing of & great\nEach\nof the invisible stalker s indenturedness there is a 1 %\nwind storm:\ncumulative chance that the creature will seek a means to pervert\nits commands and free itself of servitude. If no option is open, the\nCombat:\nInvisible stalkers attack by using the air itself as\ncreature must continue t0 serve.\nweapon . It is\ncapable of creating\nsudden , intense vortex that\nbatters a victim for 4-16 (4d4) points of damage. Such attacks af-\nEcology:\nInvisible   stalkers\nare\nspecies   unwillingly\ntrans-\nfect\nsingle victim\non the same\nplane as the invisible stalker:\nplanted to the Prime Material plane: They are slaves whose terms\nDue to their invisibility these creatures impose a\npenalty\nof servitude dominate their brief stays. Those who have been\non the surprise rolls of those they choose to attack: Similarly; all\njected\nto great hardship, assigned very difficult tasks,\nOr\nwho\nopponents who are unable to see or detect invisible foes are at a\nhave faced death at the hands of humanoids, tend t0 retain a dis-\n2 on their attack rolls. Although they are fully invisible on the\ntrust Or\noutright hatred of them. Those that have had an easy time\nPrime Material plane, their outlines can be dimly perceived on\nduring\nperiods of service or who are first time arrivals on the\nthe Astral or Ethereal planes_\nPrime Material plane may be easier to deal with. Such\nfeelings\nInvisible stalkers can only be killed on the elemental plane of\nmay carry over t0 influence encounters with humanoids traveling\nair;\nIf attacked on another plane, they automatically return\nin the\naerial plane. Anyone who has befriended\nan\ninvisible\ntheir home plane when their total hit points are exceeded by the\nstalker in the\nfind that voyages through the plane of Ele-\ndamage they suffered .\nmental Air are far less hazardous than they might otherwise have\nbeen .\nHabitat Society:\nLittle is known about the lives of these crea-\nInvisible stalkers only obey those who actually summon them\ntures on their home plane. It is assumed that they are similar to\nfew wizards can be commissioned to summon such a\non\nnormal air elementals when encountered there.\nanother's behalf. Some mercenary wizards have been able to con-\nThose present on the material plane are there as the result of a\nstruct the necessary summons onto scrolls that are usable by oth-\nconjuration by some wizard. This magic causes the creature to\ners. These sell for between\n5,000 and 10,000 gp and are very\nserve its summoner for a time. The conjurer retains full command\ndangerous to use. Even the slightest error can cause users of such\nof the stalker until it either fulfills its duties or is defeated and\nscrolls to come to a tragic end\ndriven back to its home plane: Once given a task;\nan\ninvisible\n~stalker is relentless. They are faultless trackers who\ncan detect\nany trail less than a day old. If ordered to attack, they will do so\nwith great\nand will cease their efforts only upon their own\ndestruction or the direct orders of their master:\nOnce their mis-\nsion iS\naccomplished, the creature is free to return to its home\nplane\nThe invisible stalker is,\nbest, an unwilling servant: It resents\nany task assigned to it, although brief, uncomplicated labors may\nVery\nAny\nMate-\nloop\nday\nsub-\npast\nwill\npast\nand\nbeing\nfury",
  "climate_terrain": "Any",
  "frequency": "rare",
  "organization": "Solitary",
  "diet": "Special",
  "intelligence": "High (13-14)",
  "treasure_type": "Nil",
  "alignment": "Neutral",
  "movement": "12, Fl 12 (A)",
  "thac0": "13",
  "damage": "4-16 (4d4)",
  "special_attacks": "Surprise",
  "special_defenses": "Invisibility",
  "magic_resistance": "30 %",
  "size": "L (8' tall)",
  "morale": "Elite (13-14)",
  "xp_value": "5000",
  "id": "invisible_stalker"
}