{
  "name": "Jackalwere Any temperate",
  "source_page": 77,
  "raw_text": "Jackalwere\nCLIMATEITERRAIN:\nAny temperate\nFREQUENCY:\nORGANIZATION:\nPack\nACTIVITY CYCLE:\nAny\nDIET:\nCarnivore\nINTELLIGENCE:\nVery (11-12)\nTREASURE:\nALIGNMENT:\nChaotic evil\nNO. APPEARING:\n1-4\nARMOR CLASS:\nMOVEMENT:\n12\nHIT DICE:\nTHACO:\n17\nNO. OF ATTACKS:\nDAMAGEIATTACK:\n2-8 (2d4)\nSPECIAL ATTACKS:\nGaze causes sleep\nSPECIAL DEFENSES:\nHit only by iron and +1 Or\nbetter magical weapons\nMAGIC RESISTANCE:\nNil\nSIZE:\nS (3'\nas 4\njackal\nM (6' tall) as a human or hy-\nbrid\nMORALE:\nSteady (11-12)\nXP VALUE:\n420\nThe jackalwere is a terrible and savage creature which preys on\nerwise in need;\nuntil it can employ its gaze attack. If this fails and\nunsuspecting travelers and other demihumans that it\ncan\nam-\nthe jackalwere is confronted with forceful resistance it will decide\nbush. Its ability to alter its shape at\nmakes it a most danger-\nwhether to flee or press the attack based on\nestimation of its\nous foe.\nvictim $ strength:\nThe jackalwere can be found in any of three forms, showing no\nThe jackalwere spends its life hunting and killing those humans\npreference for any one over the others. The first of these is that of\nand demihumans which it comes across. They roam the world in\na normal\nIjackal. In this form it will often run and hunt with jackal\neither the jackal or human forms, seeking humanoids to kill;\neat,\nIts second form is a six foot tall, half-human /half-jackal\nand rob;\nare sly creatures and masters of deceit\nhybrid which stands erect. In its third form, the jackalwere is\nJackalweres are able to mate only in their jackal form. They\nphysically indistinguishable from normal human beings. The ex-\nmay\nproduce offspring either by mating with true jackals or other\nact\nphysical characteristics of the jackalwere's human form varies\njackalweres, but only those young who were not of mixed blood\naccording to the desires of the monster:\nwill be jackalweres themselves. The children of\njackal\nand\njackalwere mating will be jackals, although they will be unnatu-\nCombat:\nIn its jackal form, the monster conforms to the statis-\nrally aggressive\ntics presented elsewhere in this volume\nA careful observer\nhow-\nFemale jackalweres give birth in five months to a litter of 1-4\never;\nwill find that the creature does not act in the manner\ntypical\npups\nThese are identical to jackal pups although they initially\nof\nnormal\njackal, for it is far more aggressive.\nhave 1 Hit Die. The pups grow quickly and\nan additional Hit\nIn its hybrid form, the jackalwere can attack with either its bite\nDie each year: Their jackal forms reach Full growth at three years\nor with any weapons in hand\nBecause it has\ngreat thirst for the\nand pups are locked in that form for their first two years_\nAt age\nblood of humans and demihumans\nthe jackalwere will use its bite\ntwo they\nthe ability t0 assume their hybrid form and at age\nwhenever possible. Still, it will not\nthe use of weapons that\nthree they gain the ability to assume a human form which is ap-\nwill insure\nvictory in combat:\nparently nine years of age. The human form grows at triple the\nIn its human form, the jackalwere can only attack with weap -\nnormal human rate. If a parent in human form is discovered with\nons\nAlthough it may employ any manner of weapon, it greatly\nits pups\nit will often try\nto pass them off as pets.\nenjoys those which will cut and tear the flesh of its victims_\nIn\nJackalweres may (20%\ntravel in the company of 1-6 normal\nsome cases\njackalwere has been known to feed on the bodies of\njackals. Although these jackals are normal in every regard, the in-\nfallen enemies without reverting to its jackal or hybrid form.\nfluence of the jackalwere tends to make them\nmore fierce than\nIn all forms, the jackalwere possesses\nmagical gaze. If an un-\nnormal\nJackals   under the\ninfluence   of\njackalwere  will be\nsuspecting victim meets the monster's gaze, the victim must save\nhunters instead of scavengers\nversus\nspell or fall deeply asleep; the effect is identical to that of\nthe sleep\nNote that hostile\nscared\nOr excited\npeople are not\nEcology:\nJackalweres will not serve any but the most evil of hu-\nconsidered t0 be unsuspecting:\nmanoids, and even then only if they have the opportunity to\nThe jackalwere s\ndefenses also function in all three\nmore humans and demihumans than they could on their own.\nforms. Only\n1or better\nmagical weapons Or those forged from\ncold iron will cause any damage to the jackalwere\nJackalweres\nrevert to their jackal form after death:\nHabitat Society:\nWhen the jackalwere locates a victim it will as-\nsume its human shape and\napproach its prey: It will seek to ease\nthe suspicions of its target;\noften pretending to be injured or oth-\nRare\nlong)\nWill\nits\nThey\nPacks.\nadd;\ngain\navoid\nits\n'spell.\nslay\nspecial",
  "organization": "Pack",
  "activity_cycle": "Any",
  "diet": "Carnivore",
  "intelligence": "Very (11-12)",
  "alignment": "Chaotic evil",
  "number_appearing": "1-4",
  "movement": "12",
  "thac0": "17",
  "damage": "2-8 (2d4)",
  "special_attacks": "Gaze causes sleep",
  "special_defenses": "Hit only by iron and +1 Or",
  "magic_resistance": "Nil",
  "size": "S (3'",
  "morale": "Steady (11-12)",
  "xp_value": "420",
  "id": "jackalwere_any_temperate"
}