{
  "name": "Jackal",
  "source_page": 76,
  "raw_text": "Jackal\nCLIMATETERRAIN:\nWarm plains and deserts\nFREQUENCY:\nCommon\nORGANIZATION:\nPack\nACTIVITY CYCLE:\nNight\nDIET:\nScavenger\nINTELLIGENCE:\nSemi- (2-4)\nTREASURE;\nNil\nALIGNMENT:\nNeutral\nNO. APPEARING:\n1-6\nARMOR CLASS:\nMOVEMENT:\n12\nHIT DICE:\n1/2 (1-4 hp)\nTHACO:\n20\nNO. OF ATTACKS:\nDAMAGEIATTACK:\n172\nSPECIAL ATTACKS:\nNil\nSPECIAL DEFENSES:\nNil\nMAGIC RESISTANCE:\nNil\nSIZE:\nS (3'\nMORALE:\nUnreliable (2-4)\nXP VALUE:\nJackals are small,\ncanine scavengers that roam the warm grass-\nlands of the world. They\nare\nneither fierce nor brave, but are\nquite common. There are three known species of jackal in the\nworld: asian , black-backed,\nand side-striped. Except for their\nand mysterious role in the mythoi of various human cultures_\nmarkings\nthese animals are very similar:\nTheir place\nas carrion\neaters and killers of the defenseless has\nThe typical jackal has\nnarrow\nhead and\nsharp, pointed\nearned them\nreputation for cruelty and evil deeds which is\nsnout which looks very similar to that of a fox. In its other char-\nwholly undeserved . Jackal attacks\non\nmen\nand other demihu-\nacteristics\nhowever; the animal is much like\nwolf Or\nIts fur\nmans are few and far between. In many regions which are fre-\ntypically\na tawny buff in color and quite grizzled. The tip of the\nquented by jackals, numerous horror stories will be told about\nanimals bushy tail is much darker; often shading to black:\nthe doings of jackals but, oddly enough, further investigation\nusually show that these are second hand reports of questionable\nCombat:\nAs a rule, any jackal will flee if charged or threatened\norigin.\nby another predator: In fact, they will even abandon their efforts\nhunting if their prey turns out to have more life left in it than\nEcology:\nJackals are reluctant predators and their position in\nthey expected.\nthe food chain is that of a scavenger rather than\nhunter. By\nWhen a jackal does attack, it will do so by biting. Although this\nhunting and\nSick or weak animals, they play an important\nis not an\nespecially fierce attack, it serves the animal well enough\nin the process of natural selection. In addition, the carrion\nOften , jackals will dart in to bite a victim and then quickly retreat\nwhich they consume\nwould otherwise rot and become a potential\nto a safe distance t0 examine the effects of their attack_\nIf more\nhealth hazard and breeding ground for disease_\nthan one jackal is trying to bring down a particular animal,\nJackal pups mature quickly and in just over a year they are able\nwill attack in a haphazard manner with little Or no coordination\nto fend for themselves\nwell .\n'live\n12 to 15 years in\nof their efforts_\nthe wild\nIn those places where\nshare\nterritory with men, it is quite\nHabitat Society:\nJackals inhabit plains, deserts,\ngrasslands\ncommon for\njackals to interbreed with domesticated dogs:\nFur-\nthroughout the warmer regions of the world. During the\nther; both the pups born to such a mating and adult wild jackals\nwhen the sun is too hot for their tastes\nthey remain in holes\nare   easily\ndomesticated\nThus\nalthough\nare\nnot\nFierce\nwhich they have\nin the ground:\nenough to act as\nguards or hunting animals, they are often found\nAt night, they come out to hunt. Although they usually search\nin human communities near their lands as pets.\nfor prey in\nthey can be encountered in small groups of up to\nYoung, wild,\nor domesticated jackals are seldom available on\nsix individuals. Jackals are loath to attack healthy animals who\nthe commercial market, however, and\nare\nworth little when of =\nmight be able to harm them. Rather; they will stalk only those too\nfered for sale_\nfeeble (either old, young  sick;\ninjured) to put up much of a\nfight. Carrion is\nregular part of the jackals diet,\nas are occa-\nsional pieces of fruit.\nWhenever a\njackal is afoot, it habitually utters its piercing cry:\nKnown as a pheal, this frightening sound can be heard for quite a\ndistance and is often far more\nterrifying than the animal itself.\nHerbivores (including domesticated ones) will tend\nto become\nfrightened by the pheal of\njackal. There is\na 10 %\nchance per\njackal that the howling will cause a herd of herbivores to panic\nand attempt t0 flee. Horses and similar animals can be calmed by\ntheir keepers, cutting the chance for\nin half.\nDespite its less-than-dangerous nature, the jackal plays a dark\nlong)\ndog\nwill\nkilling\nPart\nthey\nThey\nfor\nquite\nthey\nand\nday;\nthey\ndug\npairs,\npanic",
  "climate_terrain": "Warm plains and deserts",
  "frequency": "Common",
  "organization": "Pack",
  "activity_cycle": "Night",
  "diet": "Scavenger",
  "intelligence": "Semi- (2-4)",
  "treasure_type": "Nil",
  "alignment": "Neutral",
  "number_appearing": "1-6",
  "movement": "12",
  "hit_dice": "1/2 (1-4 hp)",
  "thac0": "20",
  "damage": "172",
  "special_attacks": "Nil",
  "special_defenses": "Nil",
  "magic_resistance": "Nil",
  "size": "S (3'",
  "morale": "Unreliable (2-4)",
  "xp_value": "Jackals are small,",
  "id": "jackal"
}