{
  "name": "Kobold land",
  "source_page": 78,
  "raw_text": "Kobold\nCLIMATETTERRAIN:\nland\nFREQUENCY:\nUncommon\nORGANIZATION:\nTribe\nACTIVITY CYCLE:\nNight\nDIET:\nOmnivore\nINTELLIGENCE:\nAverage (8-10)\nTREASURE:\nJ,0 (Qx5)\nALIGNMENT:\nLawful\nNO. APPEARING:\n5-20 (5d4)\nARMOR CLASS:\n7 (10)\nMOVEMENT:\nHIT DICE:\n1/2 (1-4 hit points)\nTHACO:\n20\nNO. OF ATTACKS:\nDAMAGEIATTACK:\n1-4 or 1-6 (by weapon)\nSPECIAL ATTACKS:\nNil\nSPECIAL DEFENSES:\nNil\nMAGIC RESISTANCE:\nNil\nSIZE:\nS (3' tall)\nMORALE:\nAverage (8-10)\nXP VALUE:\nChiefs / guards\n15\nKobolds are\ncowardly, sadistic race of short humanoids that\nvigorously contest the human and demi-human races for living\nspace and food\nespecially dislike gnomes whom they will\nHabitat Society:\nKobolds   live\nin  dark\ndamp places\nunder-\nattack on sight and in preference to all other enemies_\nground and in overgrown forests. They can be found in almost\nBarely clearing three feet in height, kobolds have scaly hides\nany climate. As kobolds are good miners,\nany area with potential\nthat range from very dark rusty brown to\na rusty black. They\nfor mining is fair game for settlement:\nsmell like & cross between damp dogs and stagnant water: Their\nThe average kobold tribe has 40\n400 (4d1OxlO) adult males\neyes glow like a bright red spark and they have two small horns\nFor every 40 such kobolds in a band there will be one leader and\nranging from tan to white\nBecause of the kobolds' fondness for\ntwo\nbodyguards (AC 6; HD 1-1; hp 4 each; damage 1-6). If en-\nwearing raggedy\nof red and orange; their non-prehensile rat-\ncountered\nin their lair there will be 5-20 (5d4) bodyguards, fe-\nlike tails and their language (which sounds like small dogs yap-\nmales equal to 50%\nof the males,\nyoung equal to 10% of the\nping),\nthese   fell\ncreatures\nare\noften\nnot\ntaken\nseriously by\nmales and 30-300 (3d10xlO) eggs. There will also be a chief and 2-\nhumans\nThis is often a fatal mistake, for what they lack in size\n8 guards (AC 5; HD 1+1; hp 7 each; damage 1-8) in the lair. Fur-\nand strength they make Up in ferocity and tenacity\nther; there is a 65 % chance there will be guard animals: (70 % ) 2-5\nKobolds speak their own language and can often (75 % ) speak\nwild boars (AC 7; HD 3 + 3; damage 3d4 gore) or (30 % ) 1-4 giant\norc and\ngoblin .\nweasels (AC 6; HD 3+3; damage 2d6 bite and blood drain).\nThere may be also one or more tribal shamans_\nCombat:\nThe kobold approach to combat centers around over-\nTheir society is tribal but can be further broken up into\nwar\nwhelming odds or trickery: Kobolds will attack gnomes on sight\nbands based on\nspecific clans. As many as ten families can be part\ndue to their racial hatred of the species but will think twice about\nof a clan; and each clan usually is\nresponsible for controlling the\nattacking humans, elves,\nOr dwarves unless the kobolds outnum-\narea in a ten mile radius from the lair: From this area, the kobolds\nber them by at least two to\none:\nThey often hurl javelins and\nforage for plants, hunt for meat, and waylay humans and demi-\nspears, preferring not to close until they see that their enemies\nhumans. Kobolds recover treasure from the bodies of their vic-\nhave been weakened.\ntims and often carry them back to their lair as food\nsome\nWhen they finally decide to get involved in melee combat, they\ninstances, kobolds will not kill their victims_\nbut will sell them as\n~tend to attack in overwhelming waves. Should the kobolds find\nslaves, though this happens only if they are close to an area which\nthemselves reduced t0 only a three t0 two or less ratio in their fa-\nhas a market for such wares_\nvor\nthey must make\nmorale check. It should be noted that ko-\nKobolds\nare\ndistrustful\nof   strangers\nThey   especially hate\nbolds\nare wary of spellcasters\nand will\naim\nfor\nthem   when\nbrownies, pixies, sprites and gnomes, the latter\nattacked on\npossible.\nsWarm\nof kobolds\ncan\noften overwhelm and drag\nsight. Gnomes are never eaten or taken prisoner:\ndown opponents much\nthan themselves\nKobolds live to conquer land and strip it of all its resources,\nThis diminutive race also enjoys setting Up concealed pits with\ngathering as much power as\npossible in the process.\nBecause of\nspikes,\ncrossbows;\nand other  mechanical traps. They usually\nthis ,\noften come into conflict with gnomes,\nwho compete\nhave view ports and murder holes near these traps s0 that they\nwith kobolds for the same living spaces and mining rights. They\ncan\nfollow them up by pouring flaming oil, firing missile weapons\nhate most other life and delight in\nand torture.\nOr\ndropping poisonous insects on their victims\nKobold war bands are armed with spiked clubs\naxes\njavelins_\nEcology:   Perhaps kobolds are 50 cruel because\nbeing s0\nshort swords and spears. Their shields are seldom made of metal ,\nsmall,\nare easy prey for\nlarger humanoids and hungry monsters.\nbut are normally crafted of wood\nmade of wicker. Chiefs and\nThey have many enemies, and even the dwarves have had to ad-\nguards will tend to have the best weapons available to a tribe_\nmit that at times the numerous\nkobold-goblin\nwars have kept the\nKobolds have 60' infravision but do not see well in bright sun-\nnumber of goblins down to a safe level.\nlight, suffering\n~1 on their attack rolls\nThe average lifespan of the kobold is 135 years.\nAny\nevil\nThey\ngarb\nbeing\nlarger\nthey\nkilling\nthey;",
  "frequency": "Uncommon",
  "organization": "Tribe",
  "activity_cycle": "Night",
  "diet": "Omnivore",
  "intelligence": "Average (8-10)",
  "treasure_type": "J,0 (Qx5)",
  "alignment": "Lawful",
  "number_appearing": "5-20 (5d4)",
  "ac": "7 (10)",
  "hit_dice": "1/2 (1-4 hit points)",
  "thac0": "20",
  "damage": "1-4 or 1-6 (by weapon)",
  "special_attacks": "Nil",
  "special_defenses": "Nil",
  "magic_resistance": "Nil",
  "size": "S (3' tall)",
  "morale": "Average (8-10)",
  "xp_value": "Chiefs / guards",
  "id": "kobold_land"
}