{
  "name": "Lich Lich Demilich",
  "source_page": 80,
  "raw_text": "Lich\nLich\nDemilich\nCLIMATETERRAIN:\nFREQUENCY;\nrare\nrare\nORGANIZATION:\nSolitary\nSolitary\nACTIVITY CYCLE:\nNight\nSee below\nDIET:\nNil\nNil\nINTELLIGENCE:\n~genius\nSupra-genius\n(19-20)\n(19-20)\nTREASURE:\nA\nZ\nALIGNMENT:\nNO: APPEARING:\nARMOR CLASS:\nSee below\nMOVEMENT:\nSee below\nHIT DICE:\n11 +\nSee below\nTHACO:\n10\n10\nNO:\nOF ATTACKS:\nbelow\nDAMAGEIATTACK:\n1-10\nSee below\nSPECIAL ATTACKS:\nSee below\nSee below\nSPECIAL DEFENSES:\n+1 or better magi-\ncal weapon to hit\nSee below\nMAGIC RESISTANCE:\nNil\nSee below\nSIZE:\nM (6' tall)\nM (6' tall)\nMORALE:\nFanatic (17-18)\nFanatic (17-18)\nXP VALUE:\n7000\n900o\nThe lich is, perhaps, the single most powerful form of undead\na lich . In addition, liches are able to use any magical objects\nwhich they might possess just as if\nwere still alive.\nknown to exist\nseek t0 further their own power at all costs\nDefeating a lich in combat is difficult indeed, but managing to\nand have little or no interest in the affairs of the living, except\nactually destroy the creature is harder still. In all cases,\na lich will\nwhere those affairs interfere with their own.\nprotect itself from annihilation with the creation of a phylactery\nA lich greatly resembles a wight or mummy\ngaunt and\nin which it stores its life force. This is similar t0 a magic jar\nskeletal in form. The creature'$ eye sockets are black and empty\nIn order t0 ensure the final destruction of a lich, its body must be\nsave for the fierce pinpoints of light which serve the lich as eyes_\nwholly annihilated and its phylactery must be sought out and de-\nThe lich can see with normal vision in even the darkest of envi-\nAn\nof\nstroyed in some manner. Since the lich will always take great care\nronments but is unaffected by even the brightest light.\naura\nto see to it that its phylactery is well hidden and protected this can\ncold and darkness radiates from the lich which makes it an omi-\nbe an\nundertaking fully as daunting as the defeat of the lich in its\nnous and fearsome\nThey were originally wizards Or priests\nphysical form_\nof at least 18th level.\nLiches are often (75 %\nin the rich clothes of nobility. If\nnot s0 attired, the lich\nbe foundin the robes of its former prO-\nHabitat Society:\nLiches\nare\nusually   solitary\ncreatures .\nwith\nhave cast aside their places as\nbeings by choice and now\nfession . In either case, the clothes will be tattered and rotting\nwant as little to do with the world of men as possible. From time\n25 % chance of\nmagical in some way:\nto time; however;\nlich's interest in the world at\nmay be rea\nCombat:\nAlthough\na lich will seldom engage in actual melee\nwakened by some great event of personal importance\nA lich will make its home in some ominous fortified area, often\ncombat with those it considers enemies, it is more than capable of\nstrong keep or vast subterranean crypt\nholding its own when forced into battle_\nWhen a lich\ndecide to become involved with the world be-\nThe aura of magical power which surrounds a lich is so potent\nthat any creature of fewer than 5 Hit Dice (or Sth level) which sees\nits lair; its keen\nintelligence makes it a dangerous adversary:\nIn some cases, a lich will depend on its\nmagical powers to accom-\nit must save versus\nor flee in terror for 5-20 (5d4) rounds.\nof abso-\nplish its goals. Ifthis is not sufficient, however; the lich is quite ca-\nShould the lich elect to touch a living creature, its aura\npable of animating a force of undead troops to act on its behalf. If\nlute cold will inflict 1-10 points of damage. Further, the victim\nsuch is the case, the lich s endless patience and cunning more than\nmust save versus paralysis or be utterly unable to move. This pa-\nmake up for the inherent disadvantages of the lesser forms of un-\nralysis lasts until dispelled in some manner:\ndead which it commands;\nLiches can themselves be hit only by weapons of at least +1, by\nAlthough the lich has no interest in\nOr\nevil as we under-\nmagical spells, or by monsters with\n6 or more Hit Dice and\nundead\nstand it, the creature will do whatever it must t0 further its own\nmagical properties_\nThe magical nature of the lich and\ncauses. Since it feels that the\nare of little importance, the\nstate make it utterly immune to charm, sleep, enfeeblement, poly-\nlich is often viewed\nas evil by those who encounter it: In rare\nmorph,\ncold\nelectricity; insanity, or death\nPriests of at\ncases, liches of a most unusual nature can be found which are of\nleast 8th level can attempt to turn a lich, as can paladins of no less\nthan IOth level.\nany alignment;\nThe lich can exist for centuries without change. Its will drives it\nA lich is able to employ\njust as it did in life. It still requires\nand similar ob-\nonward to master new magics and harness mystical powers not\nthe use of its\nbooks, magical components,\navailable to it in its previous life. So obsessed does the monster\njects. It is important to note that most, if not all, liches have had a\nbecome with its quest for power that it often forgets its former ex-\ngreat deal of time in which to research and create new magical\nistence utterly Few liches call themselves by their old names when\nand objects. Thus, adventurers should be prepared to face\nthe years have drained the last vestiges of their humanity from\nmagics the likes of which\nhave never seen before when stalk-\nAny\nAny\nVery\nVery\nSupra-\nAny\nAny\nSee\ning\nthey\nThey\nbeing\nspell,\nsight.\ngarbed\nThey\nwill\nliving\nbeing\nlarge\ndoes\nyond\nspell\ngood\nor\nits\nliving\nspells .\nspells\nspell\nspells\nthey",
  "frequency": "rare",
  "organization": "Solitary",
  "activity_cycle": "Night",
  "diet": "Nil",
  "intelligence": "~genius",
  "treasure_type": "A",
  "movement": "See below",
  "hit_dice": "11 +",
  "thac0": "10",
  "damage": "1-10",
  "special_attacks": "See below",
  "special_defenses": "+1 or better magi-",
  "magic_resistance": "Nil",
  "size": "M (6' tall)",
  "morale": "Fanatic (17-18)",
  "xp_value": "7000",
  "id": "lich_lich_demilich"
}