{
  "name": "Lycanthrope, Seawolf Lesser Greater",
  "source_page": 87,
  "raw_text": "Lycanthrope, Seawolf\nLesser\nGreater\nCLIMATETERRAIN:\nSaltwater\nSaltwater\nFREQUENCY:\nVery rare\nrare\nORGANIZATION:\nPack\nPack\nACTIITY CYCLE:\nDIET:\nCarnivore\nCarnivore\nINTELLIGENCE:\nAverage (8-10)\nLow to high (5-14)\nTREASURE:\nNil\nNil\nALIGNMENT:\nNeutral evil\nChaotic evil\nNO:\nAPPEARING:\n3-18\n4-16\nARMOR CLASS:\n6 (7)\nMOVEMENT:\n30, Sw 12\nSw 27\nHIT DICE;\n2+2\n9+2\nTHACO:\n19\nT1\nNO: OF ATTACKS:\n1 (3)\n1 or 2\nDAMAGEATTACK:\n2d4 (1-2/1-2/1-41\n3-12 or 1-2 and by\nweapon type\nSPECIAL ATTACKS:\nNil\nNil\nSPECIAL DEFENSES:\nNil\nHit only by silver,\ncold\nor + or\nbetter magical weap-\nons\nMAGIC RESISTANCE:\nNil\nNil\nSIZE:\nM(6' -7\" )\nL(12'-15' long) or M\nMORALE:\nSteady (11-12)\nElite (13-14)\nXP VALUE:\n175\n2,000\nparental feelings and abandon the cubs. Although the cubs are able to\nThe seawolves are humans who can assume a form combining as-\nswim and hunt from birth, they have difficulty keeping Up with adults\nof\nseal and\nwolf. Their packs roam the seas in search of\nand often drown during the\nif they are at sea\nOnly 5 % of cubs\npects\nreach adulthood;\nThe offspring of a\nand a human are\nships to attack_\nswimmers who feel mysteriously drawn to the sea, but few (25%) be-\nThe monstrous form of the lesser\nhas the 6 t0 7 foot\nbody of a seal_\nThe head and shoulders are those of a wolf. In human\ncome seawolves upon\nreaching adolescence.\nform the lesser seawolves stand 5 t0 6 feet tall . All are thickly muscled\nSeawolves may ally themselves\nother evil aquatic lycan-\nand have\nears and\nhair that covers their head and shoulders\nthropes\nhate selkies, whom they consider allies of the human-\nlike\nmane, The lesser seawolf has a hybrid form of a wolfman;\nhu-\noids. Lesser seawolves attack selkies on sight:\nseawolf's teeth, claws, and fur; statistics\nTheir diet includes a variety of foods, such as shellfish, fish,\nsed-\nmanoid\nthat retains the\nbirds, sea mammals\nand anyone they can sink their teeth into. Occa\nfor this form are given in parentheses above.\nsionally packs may wander into & town and take over a tavern for a\nCombat:\nLesser seawolves approach\nship in seawolf form, then\nround of drinking and wenching:\ninto the hybrid form and climb aboard_\nThere they use their\nSeawolf personalities are a twisted version of their original, human\nchange\npersonalities. It is as if the seawolf persona is a savage;\nmagnified ver-\nteeth and claws to kill their opponents. If the ship looks too heavily\ndefended, the seawolves may gnaw holes in the hull in order to sink\nsion of all the original person s bad traits. Seawolves periodically re-\nturn to their original home port. This may be a subconscious longing\nthe ship.\nseawolves have\nspecial\nfor their old life or a means t0 renew their hatred of those still human-\nUnlike most other lycanthropes, lesser\nno\noid , If & seawolf spots his old selfs mate or child, he may attempt to\nprotection\nnormal weapons. Dead seawolves revert to their\nmake contact_\nhuman form in & single round\nHabitat Society:\nMost seawolves were formerly fishermen or\nEcology:\nSeawolves are the sworn enemies of any humanoid who\nsuch, they also tend t0 be male and human.\ntravel in\nmakes his\nin the sea . They live to destroy shipping, spread ter-\npackssvitcthosepfaheirenntcind Their fierce hatred of their former\nrOr; and spread their curse further:\ncoworkers drives them to seek to kill them or pass on the lycanthropic\ncurse, Victims who acquire the disease become seawolves in 2-5 days.\nGreater Seawolves\nOnce night falls, the new seawolf slips into the water and goes off in\nThe monstrous form of the greater seawolf has a 12 to 15 foot\nsearch of a pack.\nbody but is otherwise identical to the lesser seawolf. In human form,\nSeawolves are nomads constantly roaming the cooler sections of\nseawolves stand 6 to 7 feet tall;\nthe seas.\nneither build lairs nor\ntreasure. During the\nsleep on beaches or in caves or appropriated houses. If\nsurprised\nCombat:\nGreater seawolves assume their human forms t0 get close\non a beach,\nthey pretend to be shipwreck victims\nthen kill the in-\nto their opponents. The typical plan is to bite or strangle one or two\ntruders and take their clothing. If at sea, the seawolves are still able to\ndeckhands, take their weapons, and begin a general assault.\nsleep during the day by floating on their backs; in this case they may\nIn seawolf form, greater seawolves can be harmed only by silver;\nbe mistaken for a cluster of drowning victims. Ifa ship moves close t0\ncold iron , or\nmagical weapons of + 1 or better: Steel weapons have no\ninvestigate, the seawolves wait for the best opportunity to attack and\neffect. Dead seawolves revert t0 their human form in one round\ntake over the ship.\nSeawolves breathe air:\ncan\nremain   submerged for 17-24\n(1d8 + I6) minutes\nFailure t0 surface after that time causes them to\nsuffer\npoints of damage each round until\ndrown,\nFemale seawolves give birth to single cubs. These may appear to be\nhuman infants during the\nOr\nbaby seals at night. Seawolves lack\nVery\nAny\nAny\niron,\nday\nseawolf\ngood\n'seawolf\nlong\nwith\nThey\nlong\ntiny\nshape\nagainst\nsail-\nliving\nThey\nlong\ngreater\nday;\nkeep\nThey\nthey\nThey\nthey\n1-6\nday",
  "climate_terrain": "Saltwater",
  "frequency": "Very rare",
  "organization": "Pack",
  "diet": "Carnivore",
  "intelligence": "Average (8-10)",
  "treasure_type": "Nil",
  "alignment": "Neutral evil",
  "ac": "6 (7)",
  "movement": "30, Sw 12",
  "hit_dice": "2+2",
  "thac0": "19",
  "attacks": "1 (3)",
  "damage": "2d4 (1-2/1-2/1-41",
  "special_attacks": "Nil",
  "special_defenses": "Nil",
  "magic_resistance": "Nil",
  "size": "M(6' -7\" )",
  "morale": "Steady (11-12)",
  "xp_value": "175",
  "id": "lycanthrope_seawolf_lesser_greater"
}