{
  "name": "Lycanthrope,_Weretiger_",
  "source_page": 88,
  "raw_text": "Lycanthrope,_Weretiger_\nCLIMATETERRAIN:\nwilderness\nFREQUENCY:\nrare\nORGANIZATION:\nSolitary\nACTIVITY CYCLE:\nNocturnal\nDIET:\nCarnivore\nINTELLIGENCE:\nAverage (8-10)\nTREASURE:\nD; Q(x5)\nALIGNMENT:\nNeutral\nNO. APPEARING:\n1-6\nARMOR CLASS:\nMOVEMENT:\n12\nHIT DICE:\n6 +2\nTHACO:\n15\nNO: OF ATTACKS:\nDAMAGEIATTACK:\n1-4/1-4/1-12\nSPECIAL ATTACKS:\nRake for 2-5/2-5\nSPECIAL DEFENSES:\nHit only by silver or +1 or\nbetter magical weapon\nMAGIC RESISTANCE:\nStandard\nSIZE:\nM or L (6'-9' )\nMORALE:\nElite (13-14)\nXP VALUE:\n975\nWeretigers are humans, usually female, that have the ability to\ntransform into tigerlike forms.\nhave a strong affinity for all\nfelines\nquickly:\ncan crawl within\nwalk within a month; and\nThe human form tends t0 be sleekly muscular; taller than aver-\nhunt within a year: Their physical size matches that of a human\nage, and very agile. The voices of weretigers are husky and they\nchild of three times the same age. At age six,\nreach adoles-\ntend t0 roll their r'S.\ncence and\nthe ability to transform into a fully human form.\nThe weretiger form is a hybrid between a human and a tiger. It\nAt age 12,\nthe ability to assume a full-tiger form; this is\nis about 25 % larger than the human form, and is covered by tiger-\nconsidered the mark of adulthood\nstriped hide\nA 3-foot tail extends from the spine. The\nare\nIE a male weretiger mates with either\na real tigress or human\nmore feline than human; this form walks on its toes\nThe head is\nwoman; the\ninitially has the same appearance as the\nalso a mixture of features. The ears, nose, muzzle, and teeth are\nmother: Lycanthropic transformations do not begin until the hy-\ntigerlike, but the eyes and overall shape are human. If the human\nbrid reaches adolescence .\nform's hair is\nit is still present. The fingernails grow into\nWeretigers are omnivorous. In the wild\nroam a\nterritory of\nclaws. Despite the changes, the hybrid form can pass for human\n7-10 (1d4 +6) square miles\nTheir homes are usually near human\nat a distance if properly disguised.\nsettlements. These tend to be well kept cabins with small herb and\nThe third form is that of a fully grown tiger without any trace\nvegetable gardens. The only livestock will be a variety of cats and\nof human features.\nsome\npoultry:\nWeretigers speak the languages of all feline breeds, s0 normal\nWeretigers rarely live in confined settings such as cities or\nfelines, including the great cats, have\n75 %   chance of\ntowns because their lycanthropic nature would be hard t0 con-\nFriendly toward\nweretiger:\nEven feline monsters have\n25 %\nceal: If found in such\nsetting; one Or two weretigers in human\nchance of being automatically friendly: However, weretigers are\nform will be on an errand, such as & mission, & revel, Or a simple\nrarely found in the company of real tigers, being only 5 % likely\nshopping trip. In any form, weretigers are very confident and not\nto be accompanied by them\nprone to attack unless provoked\nTreasure varies widely, acquired as payment for past services\nCombat:\nIn either tiger form, the weretiger altacks with a vari-\nplunder from past adventures, Or scavenged from the remains of\nety of punches, raking claws, and bites. The weretiger s punches\nopponents. Weretigers\nan\naffinity for gems and often\nare S0 strong that\ncause 1-4\npoints of damage. Otherwise the\nsmall cache hidden somewhere near their homes.\nclaws can be raked across an opponent, causing 2-5 points of\ndamage: The teeth are the most dreadful weapon. They can tear a\nEcology:\nWeretigers\nare the\nmost   adaptable of\nthe  Iycan -\nvictim apart Or crush a\nwindpipe. Weretigers usually bite only in\nthropes\nare equally at home in human, feline, Or monster\ntheir full tiger form_\ncompany:\nIn human form, the weretiger uses a wide variety of weapons\nwith which it is adept. A weretiger is also\nat unarmed com-\nbat; it retains its deadly punch in this form,\nas\nwell as an\nen-\nhanced sense of smell and night vision.\nHabitat Society:\nFor various reasons\nweretigresses outnumber\nweretigers five to one\nWeretigers travel alone or in\nprides .\ndo not marry\nbut have preferred mates, which may be either humans or tigers.\nWeretigers give birth to one or two cubs. The cubs are the hybrid\nform; they look like fuzzy human babies with tails_\nCubs mature\nAny\nVery\nThey\nThey\ndays,\nthey\ngain\nthey\ngain\nlegs\noffspring\nlong\"\nthey\nlarge\nbeing\nhave\npast\nthey\nkeep\nThey\ngood\nsmall\nThey",
  "climate_terrain": "wilderness",
  "frequency": "rare",
  "organization": "Solitary",
  "activity_cycle": "Nocturnal",
  "diet": "Carnivore",
  "intelligence": "Average (8-10)",
  "treasure_type": "D; Q(x5)",
  "alignment": "Neutral",
  "number_appearing": "1-6",
  "movement": "12",
  "hit_dice": "6 +2",
  "thac0": "15",
  "special_attacks": "Rake for 2-5/2-5",
  "special_defenses": "Hit only by silver or +1 or",
  "magic_resistance": "Standard",
  "size": "M or L (6'-9' )",
  "morale": "Elite (13-14)",
  "xp_value": "975",
  "id": "lycanthrope_weretiger"
}