{
  "name": "Lycanthrope,_Werewolf",
  "source_page": 89,
  "raw_text": "Lycanthrope,_Werewolf\nCLIMATETERRAIN:\nFREQUENCY:\nCommon\nORGANIZATION:\nPack\nACTIVITY CYCLE:\nNocturnal\nDIET:\nCarnivore\nINTELLIGENCE:\nAverage (8-10)\nTREASURE:\nB\nALIGNMENT:\nChaotic evil\nNO\nAPPEARING:\n3-18 (3d6)\nARMOR CLASS:\nMOVEMENT:\n15\nHIT DICE:\n4+3\nTHACO:\n15\nNO. OF ATTACKS:\nDAMAGEIATTACK:\n2-8\nSPECIAL ATTACKS:\nSurprise\nSPECIAL DEFENSES:\nHit only by silver or +1 or\nbetter magical weapon\nMAGIC RESISTANCE:\nStandard\nSIZE:\nM (6' tall)\nMORALE:\nSteady (12)\nXP VALUE:\n420\nWerewolves are the most feared of the lycanthropes, men who\ncan\ntransform into wolflike beasts.\nshould not be confused\nwith wolfweres (q.V.)\nwolves who turn into men. Great enmity\ntreats are used mostly as a sleeping area and a place t0 store their\nexists between werewolves and wolfweres\nhuman possessions\nwerewolf families roam the country\nThe human forms of werewolves have no distinguishing traits.\nside in wagons, much like gypsies. In fact, this has caused many\nThe werewolf form is equally varied. Many have a bipedal form\ngypsies to be accused of being werewolves_\nthat is a\nhybrid of\nand lupine features. These creatures are\nWerewolves live in packs, generally related by bloodlines\nabout one foot taller and stronger than their human forms. The\nWerewolf\nof five to eight individuals\nare  single family\nbodies are fur-covered and have short tails, wolflike\nand\ngroups consisting of a male, female, and three to six cubs, six to\nheads that are combinations in varying degrees of human and lu-\nnine years old. Cubs under six years old are kept in secluded dens\npine features.\nand never encountered by hostile humans_\nA second form of hybrid is more wolflike, and may be mis-\nWhen pregnant, the female retreats with her mate and an older\ntaken for a\nwolf when it runs on all four\nThis hybrid\nfemale who will act as midwife. In a very secluded area\npre-\ncan also walk erect and has humanlike hands.\npare a\nden that\nbe home for the mother and her cubs\nAnother type of werewolf (about 20%) looks exactly like\nfor the next six years. The female gives birth to\na litter of 5-10\nwolf about the size of a bear: This creature has no human\ncubs. The cubs are born in the hybrid form;\nresemble\nfeatures, although the eyes may glow red in the dark:\nhuman babies with wolflike faces_\nInfant mortality is high; 2-4\ncubs of each litter never reach 60% growth: Cubs grow at the\nCombat:\nIn their human forms, werewolves attack with a vari-\nsame rate as humans for their first five years. By the sixth year\nety of weapons, generally those common to their human identity\nattain 60% of their full growth: At this point they develop\nand class. In the werewolf or wolflike forms, the creature attacks\nthe ability to transform into their other forms. Each following\nwith its fearsome teeth. If the form has hands, the werewolf may\nyear brings an increase of an additional 10% growth. Were-\nits prey for a better bite.\nwolves are considered mature at age 10\nIn the wolf form, the werewolf can be harmed only by silver or\nIf a\nwerewolf mates with a woman, the offspring is completely\nmagical weapons of\n+1 or better; Wounds from other weapons\nhuman. The temperament reflects the father; such children are vi-\nheal too quickly to actually injure the werewolf_\nolent, combative, and prone to mental illness. There is\n10 %\nWerewolves  attack\nin packs; packs  including   females   and\nchance each year from the onset of adolescence that such\nchild\nyoung drive the adults to hit harder If the female is attacked, the\nwill spontaneously transform into a true werewolf.\nmale fights at\n+2 to hit and does full damage with each blow. If\nthe young are attacked, the female attacks at +3 to hit and does\nEcology:\nWerewolves are a\npeculiar hybrid of human and lu-\nfull damage. Cubs with 60 % full growth are\nto hit, cubs with\npine personalities. They are savage killers,\nthey are devoted\n70% are -3 to hit; and s0 on_\nAll cubs inflict 2-5 points of damage_\nto their close-knit families. Werewolves are hostile toward Iycan-\nthropes who oppose them, especially werebears.\nHabitat Society:\nWerewolf packs roam the wilderness in search\nof human or other prey: True werewolves tend to be nomadic, al-\nthough infected  werewolves  often\ncontinue to live the life to\nwhich\nwere\naccustomed. Werewolves retreat to their dens\nduring the winter months or the years when the females are rais-\nthe helpless cubs.\nAs humans,  werewolves do\nnot build\nhomes , although\nmay take over existing dwellings, some-\ntimes the home of past victims. Caves and burrows are the dens\nmost commonly used in the wild. These sparsely furnished\nre=\nAny\nThey\nMany\nhuman\npacks\nlegs,\nthey\nlegs .\nlarge\nspecial\nwill\nthey\n(uzzy\nlarge\nthey\ngrab\nyet\nthey\ning\nthey",
  "frequency": "Common",
  "organization": "Pack",
  "activity_cycle": "Nocturnal",
  "diet": "Carnivore",
  "intelligence": "Average (8-10)",
  "treasure_type": "B",
  "alignment": "Chaotic evil",
  "movement": "15",
  "hit_dice": "4+3",
  "thac0": "15",
  "damage": "2-8",
  "special_attacks": "Surprise",
  "special_defenses": "Hit only by silver or +1 or",
  "magic_resistance": "Standard",
  "size": "M (6' tall)",
  "morale": "Steady (12)",
  "xp_value": "420",
  "id": "lycanthrope_werewolf"
}