{
  "name": "Lycanthropez_Werebear",
  "source_page": 85,
  "raw_text": "Lycanthropez_Werebear\nCLIMATETERRAIN:\nCold or temperate regions\nFREQUENCY:\nRare\nORGANIZATION:\nSolitary\nACTIVITY CYCLE:\nNocturnal\nDIET:\nOmnivore\n[NTELLIGENCE:\nExceptional (11-12)\nTREASURE:\nR\nT,X\nALIGNMENT:\nChaotic\nNO: APPEARING:\n1-d\nARMOR CLASS:\n2\nMOVEMENT:\nHIT DICE:\n7+3\nTHACO:\n13\nNO. OF ATTACKS:\nDAMAGEATTACK:\n1-3/1-3/2-8\nSPECIAL ATTACKS:\nfor 2-16\nSPECIAL DEFENSES:\nHit only by silver or +1 or\nbetter magical weapons\nMAGIC RESISTANCE:\nNil\nSIZE:\nL (6'-9')\nMORALE:\nElite (13-14)\nXP VALUE:\n1,400\nWerebears are humans who can transform themselves into\nbrown bears.\nare the best known good-aligned lycan-\nthropes. The ursine form most often resembles\nbrown bear.\nWerebears are closest to forest-dwelling classes like rangers,\nSome have blond, reddish, black, Or ivory fur (the latter is com\ndruids, and wildlife-oriented priests.\nrarely enter villages\nmon in frozen regions)\nand never enter cities except in dire emergencies Or to\nother\nIn human form they are\nstout, well-muscled, and hairy:\ngood-aligned people, especially those threatened by evil lycan-\nTheir brown hair is thick; males usually wear beards. Some have\nthropes. Werebears hate wererats and werewolves_\nreddish, blond, ivory, or black hair; this matches the color of the\nThe average werebear claims a territory 1 to 4 square miles in\nursine form . They dress in simple cloth and leather garments that\nsize .\nFishing areas are open to all werebears_\nA werebear feels\nare easily removed, repaired,\nOr\nreplaced.\nclose bond to its home region, acting as a game warden t0 protect\nits territory andthe animals therein from the ravages of intruders\nCombat:\nIn human form, the werebear uses available weapons,\nWerebears do not travel a great deal. Only the rare individual\npreferring axes, spears, and knives, since these have practical\n(usually young) can be coaxed into joining a band of adventurers.\nplications suitable for woodland life. If attacked in daylight, the\nWerebears may join an adventuring group as guides, provided\nwerebear   usually remains\nhuman   unless   death\nis  likely:\nThe\nthe money is right and the job is agreeable.\nshapechange renders the werebear helpless for & round. In ursine\nTreasure is usually limited to\nvaluable commodities like\nform, the werebear attacks with two swiping claws and a bite. If\ngold, platinum, gems_\nand jewelry: Werebears rarely carry any\nboth claws hit, during the next round the werebear can\nfor an\ntreasure and instead hide it near their homes.\nalso collect\nadditional 2-16 points of damage\nThis subsequent damage con-\nscrolls, potions, and other magical items, often as fees or rewards\ntinues automatically each round thereafter:\nfor past services. Werebears destroy any magical items that spe-\nLike those of other lycanthropes, the werebear's defenses func-\ncifically affect lycanthropes or bears, since such items might be\ntion only in the bear form. Weapons used against the werebear\nused against themselves\nmust be either silver Or\nmagical weapons of + 1 or better Were-\nbears can summon 1-6 brown\nwithin 2-12 turns, provided\nEcology;\nWerebears\nare   omnivorous,  preferring\nfish,   small\nsuch animals are within one mile. Werebears heal at three times\nmammals, and a honey-rich mead. This mead is extremely intoxi-\nthe normal human rate and can cure disease in another creature in\ncating to normal humans. Werebears have few natural enemies.\n1-4 weeks if\nSO desire .\nTheir closest enemies are the werewolves who share their prefer-\nIf a werebear dies, he reverts to his human Form in one round_\nred wilderness regions_\nHabitat Society:\nWerebears are normally solitary creatures_\nAs\nhumans,\nbuild cabins far from settled areas, preferably in a\ndeep forest near well-stocked waters. Werebears do not marry al-\nthough\nhave preferred mates\nmeet on a very irreg-\nular basis.  Females bear\n1-2 children in\nhuman\nform .\nSuch\nchildren are very stout and grow quickly Within eight years\nadolescence\nand\nthe   ability to change\ninto\nwerebears\nShortly after, the mother drives the children out and seeks a mate\nto start the\nanew\nThe newly independent young are dis-\ncreetly guided and assisted by older werebears. Despite their ap-\nparent isolationism and\nindividualism, werebears have a\nsense of community:\nnever attack each other and aid any\nwerebear threatened by another lycanthrope species.\ngood\nHug\nlarge\nThey\nThey\nhelp\nlarge,\nap-\nsmall;\nhug\nThey\nbears\nthey\nthey\nthey\nthey\nmay\nthey\ngain\ncycle\nrugged\nThey",
  "climate_terrain": "Cold or temperate regions",
  "frequency": "Rare",
  "organization": "Solitary",
  "activity_cycle": "Nocturnal",
  "diet": "Omnivore",
  "treasure_type": "R",
  "alignment": "Chaotic",
  "number_appearing": "1-d",
  "ac": "2",
  "hit_dice": "7+3",
  "thac0": "13",
  "damage": "1-3/1-3/2-8",
  "special_attacks": "for 2-16",
  "special_defenses": "Hit only by silver or +1 or",
  "magic_resistance": "Nil",
  "size": "L (6'-9')",
  "morale": "Elite (13-14)",
  "xp_value": "1,400",
  "id": "lycanthropez_werebear"
}