{
  "name": "Lycanthrope,_Wererat",
  "source_page": 86,
  "raw_text": "Lycanthrope,_Wererat\nCLIMATETERRAIN:\nFREQUENCY:\nUncommon\nORGANIZATION:\nPack\nACTIVITY CYCLE:\nNocturnal\nDIET:\nScavenger\nINTELLIGENCE:\nVery (11-12)\nTREASURE:\nC\nALIGNMENT:\nLawful evil\nNO_\nAPPEARING:\n4-24 (4d6)\nARMOR CLASS:\nMOVEMENT:\n12\nHIT DICE:\n3+1\nTHACO:\n17\nNO. OF ATTACKS:\nDAMAGEIATTACK:\nBy weapon\nSPECIAL ATTACKS:\nSurprise\nSPECIAL DEFENSES:\nHit only by silver or\nOr\nbetter weapons\nMAGIC RESISTANCE:\nNil\nSIZE:\nS-M (3'-6')\nMORALE:\nSteady (11-12)\nXP VALUE:\n270\nWererats, also called ratmen, are humans who can transform\nthemselves into three forms-\n-human, human-sized ratman, and\ngiant rat.\nare sly and evil, and usually inhabit tunnel com-\nman form\nThis effectively limits wererats to the less savory sec-\nplexes beneath cities.\ntions of town as well as cutting down on the number of humans\nThe wererat' s human form tends to be a thin, wiry individual of\nwho might unknowingly mate with & wererat:\nshorter than average height. His eyes constantly dart around, and\nWererats see cities as their\nhunting grounds.\ndelight in\nhis nose and mouth may twitch if he is excited. Males often have\nmatching their   superior  intellects and\nmeager   physical   skills\nthin , ragged moustaches.\nagainst the more powerful and numerous humans_\nBut\nare\nThe ratman form is somewhat shorter than the human form\nno fools;\nwill not attack unless\nare sure they can win . If\nThe head, torso, and tail are identical to those of a rat; but the\nbattle is going against them,\nwererats will scatter, transform to\nlimbs remain human.\nrat form;\nand head for the sanctuary of the sewers.\nwon [\nThe third form is that of a giant rat 2 feet from nose to rump.\neven defend their own lairs_\nTheir attitude is that since they had\nThis form is identical to that of the giant rat (q.V.). This is the pre -\nstolen most of their belongings in the first place,\ncan\nalways\nferred form for travel and spying on potential victims.\nreplace them .\nWererats are often followed by 1-6 mice or rats that are instinc-\nWererats are greedy and collect anything\nthink might have\ntively drawn to them but are not controlled by them.\nworth: The resulting trove usually has more junk than treasure,\nbut a thorough search may reveal a wide variety of valuables .\nCombat:\nIn all three forms, wererats rely on weapons for their\nWererats frequent sleazy taverns, both for the\nalcohol\nattacks, preferring shortswords and daggers. Anyone who is in-\nand to follow drunks into the streets to\nthem away for the\njured by a true wererat has a 1 % chance per point of damage of\nnext\n's meal_\nbecoming a wererat. In their ratman and giant rat forms\nwererats\ncan be hurt only by silver or magical weapons\nEcology:\nWererats are parasites_\nrecognize that they are\nWererats prefer to attack\nambush. A favorite tactic is to\nphysically weaker than most species that dominate the surface\nassume human\nand lure unsuspecting victims into a trap.\nhave found and exploited the one niche where\nhave a\nThis is the only time wererats are voluntarily alone_\nVictims are\nchance to dominate, the world beneath the cities.\nfeed on\nthen robbed, held for ransom, Or eaten\nhumans and steal their riches. Humans unknowingly protect the\nEach wererat is able to summon and control 2-12 giant rats.\nwererats\nboth surface dwelling creatures and those who\nmight burrow up from Far below. Besides, the humans pay for the\nHabitat Society:\nWererats live\nin packs,  regardless  of form,\nupkeep of the wererat's sewer realm\nnever\nbeing alone if\ncan help it. Solitary wererats are either\nPsychologically wererats remind humans that no matter how\nsole survivors Or\nengaged in mischief.\ndo not form interper-\nstrongly defended\nthink\nare, monsters can still\nin .\nsonal bonds like love or marriage. In fact; wererats rarely mate\nMothers describe wererats as\nbogeymen to scare unruly children.\nwith their own kind ,\nOffspring of\na wererat and human woman\nare human, although\nare small like their father.\nOffspring of\na female\nwererat resemble giant rats with\nhuman-like paws.\nThese ratlings grow to maturity in two years and\nthe ability\nto transform themselves into human children with an apparent\nage about three times that of the ratling s actual age.\nWererats prefer subterranean lairs hidden among the sewers\nand catacombs beneath\ncities. Nothing can pass through the\nsewers and escape their attention. Unfortunately for the wererat;\nthe sewer $ stains and smells do not vanish when it assumes\nAny\n+1\nThey\nThey\nthey\nthey\nthey\nThey\nthey\nthey\ncheap\ndrag\nday\nThey\nfrom\nshape\nThey\nthey\nThey\nfrom\nthey\nThey\nthey\nthey\nget\nthey\ngain\nhu-",
  "frequency": "Uncommon",
  "organization": "Pack",
  "activity_cycle": "Nocturnal",
  "diet": "Scavenger",
  "intelligence": "Very (11-12)",
  "treasure_type": "C",
  "alignment": "Lawful evil",
  "movement": "12",
  "hit_dice": "3+1",
  "thac0": "17",
  "damage": "By weapon",
  "special_attacks": "Surprise",
  "special_defenses": "Hit only by silver or",
  "magic_resistance": "Nil",
  "size": "S-M (3'-6')",
  "morale": "Steady (11-12)",
  "xp_value": "270",
  "id": "lycanthrope_wererat"
}