{
  "name": "Manticore",
  "source_page": 90,
  "raw_text": "Manticore\nCLIMATETERRAIN:\nFREQUENCY:\nUncommon\nORGANIZATION:\nSolitary\nACTIVITY CYCLE:\nDIET:\nCarnivore\nINTELLIGENCE:\n(5-7)\nTREASURE:\nE\nALIGNMENT:\nLawful evil\nNO. APPEARING:\n1-4\nARMOR CLASS:\nMOVEMENT:\n12, Fl 18 (E)\nHIT DICE:\n6 + 3\nTHACO:\n13\nNO:OF ATTACKS:\nDAMAGEIATTACK:\n1-3/1-3/1-8\nSPECIAL ATTACKS:\nTail spikes\nSPECIAL DEFENSES:\nNil\nMAGIC RESISTANCE:\nNil\nSIZE:\nH (15')\nMORALE:\nElite (13-14)\nXP VALUE:\n1,400\nThe manticore is a true monster, with a leonine torso and\nbatlike\na man's head, a tail\ntipped with iron spikes, and an\nappetite for human flesh.\nThe manticore stands 6 feet\natthe shoulder and measures 15\nManticores normally eat their prey where\nkill it. Males\nfeet in length;\nIt has a 25-foot wingspan . Each section of the man-\nsometimes haul slain prey back to their mates or\nstill-living\nticore closely resembles the creature it imitates. The leonine torso\nprey to their lairs for the cubs to practice killing.\nhas a tawny hide, the mane is a lion's brown-black color, and the\nManticores collect their victims' valuables for a variety of rea-\nbatlike\nare a dark brown with sparse hair.\nAll manticores\nsons;\nincluding curiosity, emulation of other monsters who col-\nheads that resemble human males; the mane resembles\nlect treasure, the man-scent on the\nor\nbecause\nknow\nheavy beard and\nhair.\nhumans value the\nand therefore might come looking for\nthem . Their lack of real hands prevents most manticores from uS-\nCombat:\nThe manticore first fires a volley of 1-6 tail\n(180\ning what magical items fall into their possession . However; man-\nrange as a light crossbow)_\nEach spike causes\npoints of\nticores that have allied with evil humans may possess magical\ndamage. The manticore can fire four such volleys each\n(the\nitems designed specifically for their use. Examples include magi-\nregrow quickly) . Next, the manticore closes with its prey\ncal collars or bracelets that are, in effect, oversized magical rings\nand attacks with its front claws and sharp teeth: In an outdoor\nsetting, the manticore tries to stay in the air t0 minimize its chance\nEcology:\nManticores\nare\nwide-ranging\ncarnivores that\nof\nattacked. It is a clumsy flier, however, and cannot use its\nsuccessfully\nsurvived\nin\nevery\nregion\ninhabited\nby  humans,\nteeth in the air:\nwhether in the wilderness or underground\nare nightmarish\nopponents but invaluable allies if conditions are right: A manti-\nHabitat Society:\nManticores are found in any climate but prefer\ncore $\nis a mark of the most powerful hunters and warriors\nwarm lands t0 cool ones. This reflects the wide climate range of\nAn intact, cured manticore hide complete with wings is worth\ntheir favorite food, humans\nA manticore $ territory\ncover\n10,000 gP _\n20 or more square miles and includes at least one human settle-\nment: Such territories usually overlap with those of other manti-\ncores and other man-eating predators like dragons.\nManticores mate for life:\nThe male remains with the female\ngestation and hunts for her. Manticores bear one or two\ncubs which grow rapidly to adulthood in five years. Cubs are\nborn with\none hit die and\nan additional one each\nIn\ntheir first year; cubs lack flying ability but\nare still small\nenough for an adult to grasp in its\nforelegs. There is a 20 % chance\nshe-manticore's lair holds cubs under one year old. Cubs up to\ntwo years inflict one\npoint of damage per front paw and 1-2\npoints with their bite. Cubs 3-4 years old inflict 1-2, 1-2, and 1-6\npoints of damage.\nManticore cubs can be caught and trained to assist evil hu-\nmans. Such\ntraining is difficult and dangerous, especially since\ndomesticated adults have an 80% chance of reverting to a wild\nstate. Manticores will not allow themselves to be used as mounts.\nWild adults may voluntarily ally themselves with evil humans,\nprovided such allies can provide them with a steady, ample food\nsupply.\nAny\nAny\nLow\nlegs,\nwings,\ntall\nthey\ndrag\nwings\nhave\nthings,\nthey\nlong\nthings\nspikes\nyard\n1-6\nday\nspikes\nhave\nbeing\nThey\npelt\nmay\nduring\ngain\nyear.\nthey",
  "frequency": "Uncommon",
  "organization": "Solitary",
  "diet": "Carnivore",
  "intelligence": "(5-7)",
  "treasure_type": "E",
  "alignment": "Lawful evil",
  "number_appearing": "1-4",
  "movement": "12, Fl 18 (E)",
  "hit_dice": "6 + 3",
  "thac0": "13",
  "special_attacks": "Tail spikes",
  "special_defenses": "Nil",
  "magic_resistance": "Nil",
  "size": "H (15')",
  "morale": "Elite (13-14)",
  "xp_value": "1,400",
  "id": "manticore"
}