{
  "name": "Mind Flayer_ subterranean",
  "source_page": 96,
  "raw_text": "Mind Flayer_\nCLIMATEITERRAIN:\nsubterranean\nFREQUENCY:\nRare\nORGANIZATION:\nCommunity\nACTIITY CYCLE:\nDIET:\nCarnivore (brains)\nINTELLIGENCE:\nGenius (17-18)\nTREASURE:\nS, TX (B)\nALIGNMENT:\nLawful evil\nNO. APPEARING:\n1-4\nARMOR CLASS:\nMOVEMENT:\n12\nHIT DICE;\n8+4\nTHACO:\n11\nNO.OF ATTACKS:\nDAMAGEIATTACK:\nSpecial\nSPECIAL ATTACKS:\nMind blast\nSPECIAL DEFENSES;\nNil\nMAGIC RESISTANCE:\n90 %\nSIZE:\nM (6' tall)\nMORALE:\nChampion (15)\n+Special\nXP VALUE:\n8,000\nOf all the creatures of the Underdark, the illithid, or mind flayer;\nis both the most evil and most inhuman. It is also the most feared,\nfor its powers are formidable and it feeds on the brain of any hu-\nman, demihuman,\nor humanoid creature it encounters. Using\nmind flayers. Due to the powerful mental force of illithids, the\nsheer mental power, it is able to enslave or destroy its foes, which\nelder-brain remains sentient even after their bodies have been de-\ninclude such powerful creatures as drow and kuo-toa.\nstroyed, and the telepathic union of these brains of the dead rules\nMind flayers stand about 6 feet tall, with hideous mauve skin\nthe community: The elder-brain has a telepathic range of two to\nthat glistens with slime\nThe head resembles\nan\noctopus, with\nmiles (depending on the size and age of the community). The\nwhite eyes (no pupils are evident) and four tentacles protruding\nelder-brain cannot attack; but it can telepathically warn the mind\nfrom where a mouth should be. The creature has three fingers and\nof the presence of thinking creatures, so\nmind\na thumb on each hand; its fingers have a reddish cast, though the\nwithin its telepathic radius cannot be surprised, except by nonin-\nrest of the hand is mauve. Mind\ncan communicate with all\ntelligent creatures .\nThe telepathic range of the elder-brain repre-\ncreatures via telepathy;\nhave no spoken language, though\nsents the territory that\ncommunity\nwill claim and defend\nthey have been known to accompany their thoughts with faint\nthough\ncommunity will send raiding parties far beyond this\nhissing and the eager lashing of their tentacles. Mind flayers dress\nlimit. Mind flayers have no family structure\nTheir social activi-\nin\nflowing robes, adorned with symbols of death and despair:\nties are limited to\neating, communicating with the elder-brain,\nand debating on the best tactics to conquer the Underdark. For\nCombat:\nA mind\ncan use its four\ntentacles in combat. If a\namusement;\ninflict pain on their captives and force their\ntentacle hits, it will reach the opponents brain in 1-4 rounds, drawing\nslaves to fight each other in gladiatorial games.\nit forth and killing the victim_\nThe mind flayer then devours the\nMind flayers are extremely arrogant, viewing all other species\nbrain . Even more deadly than this is the mind flayer s mental blast,\nonly as cattle to be fed on.\nprefer to eat the brains of think-\nwhich spreads in a cone 60 feet\n5 feet wide at the base and 20\ncreatures\nfeet wide at its end; all within the area of effect must save versus\nwands at -4 or be stunned for 3-12 (d10 +2) rounds.\nEcology:\nMind flayers have a lifespan of about 125 years.\nThe mind flayer's mental talents also allow it to use the follow\nare\nwarm-blooded amphibians, and\nthe first 10 years of life\npowers, one per round, asa 7th level mage: suggestion, charm\nin a\ntadpole state, swimming in the pool of the elder-brain until\nmonster/ person, ESP levitate, astral projection, and plane shift.\nthey either die (which most do) or grow into a fully developed il-\nMind flayers have infravision_\nAll saving throws against a mind\nlithid . Illithid are sexless; each\nis capable of producing off-\nflayer's mental powers are at-4, due to its powerful mental force.\nspring (twice per lifetime, once every 20 years)\nIF an encounter is going against a mind\nit will immediately\nMind\nichor is an effective ingredient in a potion of ESP\nFlee, seeking to save itself regardless of its treasure or its fellows.\nIn mass combat, the mind\ntries to take as many prisoners\nas\npossible. These prisoners will become slaves, and a source of\nfood in times of shortage.\nHabitat Society:\nMind flayers live in\nunderground com-\nmunities of 200 to 2,000 illithids, plus at least two slaves per il-\nlithid. The minds of the slaves are stripped of any capacity for\nindependent thought (by use of the charm ability) so they obey\ntheir illithid masters without question. Mind\nhate sunlight\nand will avoid it whenever possible_\nThe center of each community is the elder-brain ,\npool of\nbriny brain fluid that contains the brains of the community s dead\nAny\nAny\nfive\nflayers\nflayer\nflayers\nthey\nflayer\nthey\nThey\nlong\"\ning\nThey\nspend\ning \"\nflayer\nflayer,\nflayer\nflayer\nlarge\nflayers",
  "frequency": "Rare",
  "organization": "Community",
  "diet": "Carnivore (brains)",
  "intelligence": "Genius (17-18)",
  "treasure_type": "S, TX (B)",
  "alignment": "Lawful evil",
  "number_appearing": "1-4",
  "movement": "12",
  "hit_dice": "8+4",
  "thac0": "11",
  "damage": "Special",
  "special_attacks": "Mind blast",
  "special_defenses": "Nil",
  "magic_resistance": "90 %",
  "size": "M (6' tall)",
  "morale": "Champion (15)",
  "xp_value": "8,000",
  "id": "mind_flayer_subterranean"
}