{
  "name": "Minotaur",
  "source_page": 97,
  "raw_text": "Minotaur\nCLIMATE TERRAIN:\nTemperate and subtropical\nlabyrinths\nFREQUENCY:\nRare\nORGANIZATION:\nClan\nACTIITY CYCLE:\nNight\nDIET:\nCarnivore (man-eater)\nINTELLIGENCE:\nLow (5-7)\nTREASURE:\n(C)\nALIGNMENT:\nChaotic evil\nNO: APPEARING:\n1-8\nARMOR CLASS:\nMOVEMENT:\n12\nHIT DICE:\n6+3\nTHACO:\n13\nNO: OF ATTACKS:\nDAMAGEIATTACK:\n2-8/2-8 or 1-4/by weapon type\nSPECIAL ATTACKS:\nGrapple, charge\nSPECIAL DEFENSES:\n+2 bonus on\nroll\nMAGIC RESISTANCE:\nNil\nSIZE:\nL (71/2\" tall)\nMORALE:\nElite (13)\nSpecial\nXP VALUE:\n1,400\nElder\n3,000\nMinotaurs are either cursed humans Or the offspring of minotaurs\nand humans\nusually dwell in underground labyrinths, for\nMinotaurs\ntheir own primitive language and are 25 %\nare not confused in these places, which gives them an advan-\nlikely to speak\nhalting form of common_\nhave little cul-\ntage over their prey:\nture; their lives resemble animals more than humans. Their cul-\nMinotaurs are\nwell over 7 feet tall, and quite broad and\nture venerates physical strength above all else and particularly\nmuscular: They have the head of a bull but the body of a human\nstrong human fighters have been known to earn their respect_\nmale. Their fur is brown t0 black while their body coloring varies\nworship crude\nand have weak clerics (maximum 3rd\nas would\na normal human'5.\nClothing is minimal, usually a loin\nlevel shaman) . Rumors persist of more intelligent minotaurs with\ncloth or skirt.\ndeveloped societies\nCombat:\nMinotaurs\nare\nvery strong (equivalent\nhuman\nEcology:\nThe curse which creates minotaurs is unknown, but\nStrength of 18). Against man-sized opponents (minimum\n6 feet\nsages suspect it involves \"crimes\nthe natural order\" Mino-\ntall)\nmay butt\n2-8 points of damage. Against smaller op-\ntaurs are\nalways male. It is also said that the first minotaur was\nponents, they bite for 1-4 points of damage. If a minotaur is 30\noriginally\na great and ill-tempered human fighter; he wanted to\nfeet or more from its opponent, it can lower its head and charge\nbe as strong as a bull andhis wish was granted in the most hideous\nany creature that is at least 6 feet tall. If successful, the\nmanner\npossible.\nMinotaurs breed with human females to pro-\ncharge causes double head-butt damage. In addition to these at-\nduce offspring, which are male minotaurs\nMinotaurs have a life -\ntacks, most minotaurs also carry weapons\nhuge ax (treat as a\nspan of 200 years.\ncan live without food For years at a time,\nhalberd) or flail, with which it inflicts normal damage +2\nbut are always hungry unless they are fed regularly:\nare\nMinotaurs are not particularly intelligent, but are extremely\nmeat-eaters, but their curse causes them to prefer a diet of human\ncunning and have excellent senses. They have &\n+2 bonus on\nflesh . Those transformed into minotaurs by curses may be re-\ntheir surprise rolls, have infravision,and can track prey by scent\nstored to human form by a wish, but those who were born as\nlike a ranger, with 50% accuracy: They always pursue an unfa-\nminotaurs cannot be made human. Gnolls are their natural ene-\nmiliar scent. Minotaurs are immune t0 maze\nattack\nmies;\nwill kill each other on sight.\nany intruder without fear, and will retreat only if the creature is\nMinotaur components are sometimes used in\nand pO-\nobviously beyond their ability to defeat\n+3 t0 morale score in\ntions, and might be used in magical items involving strength, lo-\ncombat) .\ncation, and misdirection\nHabitat Society:\nMinotaurs\nin communities of up to eight\nmembers, If the community contains more than six minotaurs,\none will be an elder minotaur with 18/50 Strength and 8 +4 Hit\nDice. The minotaur elder is the clan leader; he remains in the cen -\nter of the labyrinth and raises young minotaurs while others\nhunt. He is always encountered in the center of a labyrinth:\nA minotaurs labyrinth is rarely natural. Often an evil wizard\nOr a tyrant\nconstruct a labyrinth and place the minotaur fam-\nily there, feeding it prisoners and slaves on a regular basis.\nOccasionally this tyrant will be killed and the minotaurs forced\nto fend for themselves; since creatures rarely enter a labyrinth on\ntheir own accord, these minotaurs will usually be ravenously\nhungry:\nsurprise\nspeak\nThey\nThey\nthey\nhuge,\ngods\nThey\nagainst\nfor\nthey\nagainst\nThey\nThey\nspells .\nThey\nthey\nspells\nlive\nwill",
  "climate_terrain": "Temperate and subtropical",
  "frequency": "Rare",
  "organization": "Clan",
  "diet": "Carnivore (man-eater)",
  "intelligence": "Low (5-7)",
  "treasure_type": "(C)",
  "alignment": "Chaotic evil",
  "number_appearing": "1-8",
  "movement": "12",
  "hit_dice": "6+3",
  "thac0": "13",
  "special_attacks": "Grapple, charge",
  "special_defenses": "+2 bonus on",
  "magic_resistance": "Nil",
  "size": "L (71/2\" tall)",
  "morale": "Elite (13)",
  "xp_value": "1,400",
  "id": "minotaur"
}