{
  "name": "Mud-man",
  "source_page": 98,
  "raw_text": "Mud-man\nCLIMATETERRAIN:\nFREQUENCY:\nrare\nORGANIZATION:\nPack\nACTIVITY CYCLE:\nDIET:\nDweomer\nINTELLIGENCE:\nNon- (0)\nTREASURE:\nNil\nALIGNMENT:\nNeutral\nNO: APPEARING:\n2-12 (2d6)\nARMOR CLASS:\n10\nMOVEMENT:\nHIT DICE:\nTHACO:\n19\nNO: OF ATTACKS:\nDAMAGEIATTACK:\nSpecial\nSPECIAL ATTACKS:\nMud-throwing, suffocation\nSPECIAL DEFENSES:\nSee below\nMAGIC RESISTANCE:\nNil\nSIZE:\nS (4' high)\nMORALE:\nSpecial\nXP VALUE:\n175\nMud-men are formed in\nof mud where enchanted rivers\n(even mildly enchanted ones, such as a stream eroding a magical\nstructure) collect and evaporate and concentrate the dweomer:\nBecause\nare creatures of magic, mud-men\nare sometimes\ninto the depths, return to their dormant state, and wait until the\ncalled\ndweomerlings. Mud-men are unintelligent life forces with\nnext time someone enters the\nbut one\nto\nprotect their pools\nintruders .\nMud-men are affected by all spells that cause damage to living\nWhen aroused into a physical form, mud-men take on the ap-\ncreatures\ncause\nlight wounds, magic missile, fireball, flame\npearance of animated mud in a stocky humanoid\nabout 4\nstrike) . Dispel magic and dig act as fireballs cast at the same level\nfeet tall. Their coloration varies between\nbrown and tar\nas the mage.\nblack.\nhave four thick fingers on each hand\nTheir\nstay\nTransmute mud to rock kills all mud-men within its area of ef-\nsubmerged within the\nand are not usually visible. Their\nfect, with no saving throw allowed:.\neyes are pools of jet black shadow.\nMud-men are immune to all poisons, natural and magical, and\nMud-men speak no languages and are incapable of communi-\nare unaffected by\nthat affect the mind\nhold, charm,\ncating with any living creature.\nand sleep) .\nCombat:\nIn their dormant state, mud-men wait beneath the sur-\nHabitatiSociety:\nMud-men have two states: rest and activity;\nface of the pool, spread on the bottom, feeding on the dweomer:\nthe latter of which solely involves\nintruders. A mud-man's\nIn this state\nare immune to all weapons, even magical ones\nvaries in size between 20 and 200 feet in diameter: Such pools\nSpells that normally harm a mud-man will still affect it, although\nare often found near waterfalls\ndamage is divided evenly among all the mud-men in the\n(the\nentire group counts as one creature for these effects, and fractions\nEcology:\nMud-men are not natural creatures and not part of the\nare\nrounded down)_\nWhen\na creature enters the\nthe mud-\necosystem.\nto kill all natural creatures that encounter\nmen immediately sense its presence and take but a single round to\nthem and have no natural enemies. Over\nlong period of time\ndraw their substance\ntogether and rise to the surface, ready to at-\nabsorb\nflesh,\nwood,\nand bone, extracting\nwhatever\ntack on the following round. Once fully formed and standing, a\ndweomer\ncan\nfrom it,\nSO\nrarely\npossess\nany\nmud-man can be harmed by magical weapons.\ntreasure-_only if\nwere attacked within the last month by\nMud-men attack by hurling mud at their opponents, who are\nsomeone who was\nbearing treasure. Though no uses have been\nconsidered AC 10 (modified by Dexterity) for the purpose of de-\nrecorded for a mud-man'$ mud, it is logical that mages would not\ntermining hits_\nMud hardens on impact and slows the creature'$\nignore its magical properties_\nmovement rate by 1 ifit hits. While hurling mud,\na mud-man will\nalso advance on its victim at its full movement rate_\nOnce within\n10 feet, it will hurl itself (literally) at the victim . A sucessful hit\nmeans the death of the mud-man, but slows the victim's move-\nment by 4. A miss means the mud-man must spend the next round\nre-forming in order to attack\nOnce a victim's movement is brought to 0, he becomes immobi-\nlized and suffocates, suffering 1-8 points of damage per round un-\ntil the mouth or nose is clear. The victim will die of suffocation in\nfive consecutive rounds unless rescued_\nHardened mud can be\ncleared\ncharacter s nose and mouth in one round: Move-\nment can be restored at a rate of 1 per five rounds_\nIf the creature flees the pool, the mud-men will not pursue, as\ntheir senses do not extend beyond the pool. Instead,\nsink\nAny\npool\nVery\nAny\npools\nthey\npool.\ngoal\nagainst\n(e.g ,\nshape,\ndirty\nThey\nlegs\npool,\nspells\n(e.g '\nkilling\nthey\npool\npool\npool\nThey\ntry\nthey\nthey\nthey\nget\nthey\nagain.\nfrom\nthey",
  "frequency": "rare",
  "organization": "Pack",
  "diet": "Dweomer",
  "intelligence": "Non- (0)",
  "treasure_type": "Nil",
  "alignment": "Neutral",
  "number_appearing": "2-12 (2d6)",
  "ac": "10",
  "thac0": "19",
  "special_attacks": "Mud-throwing, suffocation",
  "special_defenses": "See below",
  "magic_resistance": "Nil",
  "size": "S (4' high)",
  "morale": "Special",
  "xp_value": "175",
  "id": "mud_man"
}