{
  "name": "Mummy",
  "source_page": 99,
  "raw_text": "Mummy\nCLIMATETERRAIN:\nDesert subterranean\nFREQUENCY:\nRare\nORGANIZATION:\nPack\nACTIITY CYCLE:\nNight\nDIET:\nNone\nINTELLIGENCE:\nLow (5-7)\nTREASURE:\nP (D)\nALIGNMENT:\nLawful evil\nNO:APPEARING:\n2-8 (2d4)\nARMOR CLASS:\nMOVEMENT:\nHIT DICE:\n6 + 3\nTHACO:\n13\nNO. OF ATTACKS:\nDAMAGEATTACK:\n1-12\nSPECIAL ATTACKS:\nFear, disease\nSPECIAL DEFENSES:\nSee below\nMAGIC RESISTANCE:\nNil\nSIZE:\nM (6')\nMORALE:\nChampion (15)\nXP VALUE:\n3,000\nMummies are corpses native to\ndesert areas, where the dead\nare entombed by a process known as mummification. When their\ntombs are disturbed\nthe corpses become animated into a weird\nunlife state, whose unholy hatred of life causes them to attack liv -\nmies are corpses without magical properties_\nOn occasion , per-\nthings without mercy:\nhaps  due\nto powerful\nevil\nmagic\nor\nperhaps\nbecause the\nMummies are usually (but not always) clothed in rotting strips\nindividual was S0 greedy in life that he refuses t0 give up his trea-\nof linen .\nstand between 5 and 7 feet tall and are supernatu-\nsure, the\nof the mummified person will not die, but taps into\nrally strong:\nenergy from the Positive Material plane and is transformed into\nan undead horror: Most mummies remain dormant until their\nCombat;\nMummies are horrific enemies.\nA single blow from\ntreasure is taken, but then\nbecome aroused and kill without\none$ arm inflicts 1-12\npoints of damage, and worse, its scabrous\nmercy.\ntouch infects the victim with a rotting disease which is fatal in 1-6\nA mummy lives in its ancient burial chamber, usually in the\nmonths. For each month the rot progresses, the victim perma\nheart of\ncrypt Or pyramid.\nThe tomb is\ncomplex series of\nnently loses 2 points of Charisma\nThe disease can be cured only\nchambers filled with relics (mostly nonmagical) . These relics in-\nwith a cure disease spell. Cure wounds\nhave no effect on\nclude models of the mummys possessions, favorite items and\nperson inflicted with mummy rot and his wounds heal at 10% of\ntreasures, the bodies of dead pets, and foodstuffs to feed the spirit\nthe normal rate\nA regenerate\nwill restore damage but will\nafter death. Particularly evil\nwill have slaves\nOr\nfamily\nnot otherwise affect the course of the disease.\nmembers slain when\ndie so the slaves can be buried with\nThe mere sight of a mummy causes such terror in any creature\nthem . Because of their magical properties, mummies exist on both\nthat & saving throw versus\nmust be made or the victim be-\nPrime and Positive Material planes.\ncomes paralyzed with fright for 1 to 4 rounds. Numbers will bol-\nster courage; for each six creatures present, the saving throw is\nEcology:\nTo create a mummy\na corpse should be soaked in\nimproved by\n+1\nHumans save against mummies at\nan addi-\npreserving solution  (typically carbonate\nofsoda)\nfor   several\ntional +2\nweeks and covered with spices and resins. Body organs, such as\nMummies can be harmed only by magical weapons, which in-\nthe heart, brain\nand liver, are typically removed and sealed in\nflict only half damage (all fractions round down) . Sleep, charm,\njars. Sometimes gems are wrapped in the cloth (if the treasure list-\nhold\nand cold-based\nhave no effect. Poison and paralysis\ning for the mummy indicates it possesses gems,\na few may be\ndo not harm them\nA resurrection spell will turn the creature into\nplaced in the wrappings) _\nMummies are not part of the natural\nnormal human (a fighter at Zth level ability) with the memories\necosystem and have no natural enemies.\nof its former life; or\nhave no effect if the mummy is older than\nMummy dust is\ncomponent for rotting and disease magic\nthe maximum age the priest can resurrect: A wish will also restore\nitems:\na mummy to human form but & remove curse will not.\nMummies are vulnerable to fire, even nonmagical varieties. A\nblow witha torch inflicts 1-3\nof damage. A flask of burning\noil inflicts 1-8 points of damage on the first round it hits and 2-16\non the second round. Magical fires are +1 damage/die. Vials of\nholy water inflict 2-8 points of damage per direct hit:\ncreature killed by a mummy rots immediately and cannot\nbe raised from death unless both a cure disease and\na raise dead\nare cast within six rounds\nHabitat Society:\nMummies are the product f an embalming\nprocess used on wealthy and important personages. Most mum-\ndry\ning\nspirit\nThey\nthey\nspells\npeople\nspell\nthey\nspell\nspells\nwill\npoints\nAny\nspell",
  "climate_terrain": "Desert subterranean",
  "frequency": "Rare",
  "organization": "Pack",
  "diet": "None",
  "intelligence": "Low (5-7)",
  "treasure_type": "P (D)",
  "alignment": "Lawful evil",
  "number_appearing": "2-8 (2d4)",
  "hit_dice": "6 + 3",
  "thac0": "13",
  "damage": "1-12",
  "special_attacks": "Fear, disease",
  "special_defenses": "See below",
  "magic_resistance": "Nil",
  "size": "M (6')",
  "morale": "Champion (15)",
  "xp_value": "3,000",
  "id": "mummy"
}