{
  "name": "Nixie",
  "source_page": 100,
  "raw_text": "Nixie\nCLIMATE TERRAIN:\nTemperate lakes\nFREQUENCY:\nRare\nORGANIZATION:\nTribe\nACTIVITY CYCLE:\nDIET:\nFish\nINTELLIGENCE:\nVery (12)\nTREASURE:\nQ (C)\nALIGNMENT:\nNeutral\nNO. APPEARING:\n20-80 (2d8x10)\nARMOR CLASS:\nMOVEMENT:\n6, Sw 12\nHIT DICE:\n1-4 hit points\nTHACO:\n20\nNO. OF ATTACKS:\nDAMAGEIATTACK:\nBy weapon type\nSPECIAL ATTACKS:\nCharm\nSPECIAL DEFENSES:\nNil\nMAGIC RESISTANCE:\n25 %\nSIZE:\n5 (4')\nMORALE:\nAverage (8-10)\nXP VALUE:\n120\nNixies are water sprites that live in fresh water lakes, and while\ncarry no grudge\nagainst humankind,\ndelight in enslav-\nmen as their beasts of burden .\nWith webbed\nand toes, pointed ears, and wide silver\ndistance under 20 feet (it is impossible to detect from farther away\neyes, nixies bear little resemblance to their woodland cousins.\nthan 20 feet) Nixies\ngiant fish as guards, either 1-2 gar\nMost are slim and comely; and\nlightly scaled,\n(20 %\nor 2-5 pike (80 % ) , and these are taught to obey simple\ngreen skin and dark green hair: Females are attractive, often twin-\ncommands. Small ornamental shiners Or rainbow-hued fish are\nshells and\nstrings in their thick hair, and they modestly\nkept as pets and trained to perform elaborate tricks. Trout, bass,\ndress in tight-fitting wraps woven from colorful seaweeds. The\nand catfish are herded as food\nNixies can also summon 10-100\nmales wear loin cloths of the same materials. Nixies are naturally\nsmall fish (this takes 1-3 rounds)_\nable to breathe water and\nalso retain the ability to breathe\nNixie tribes number from 20 t0 80 individuals, with one third of\nair; SO travel on land is possible, although\nprefer not to leave\nthe population being youths. Individual families number from\ntheir lakes except in dire circumstances. Nixies speak their own\nfour to eight members, and the tribe usually includes 10-15 dis-\nlanguage and the common tongue.\ntinct families , each related to the other through a common ances-\ntor, These nixie tribes control an area with a radius of three t0 five\nCombat:\nIE one or more men\napproach within 30 feet of a group\nmiles, and when a tribe\ntoo\ntwo or three families split\nof nixies, the creatures will pool their magic to create a powerful\noff t0 form\nnew tribe.\ncharm\none such\nfor every 10 nixies, which requires the\nNixie tribes are ruled by the Acquar (water mother) who is a di-\nvictim t0 save versus\nat -2 on the die roll. Once a person is\nrect descendant of the original founding ancestor: This is a heredi-\ncharmed but before he enters the water there is a 75 % chance that\nposition. She decides major disputes and chooses the most\ndispel magic\nwill break the charm . Once in the water the\napt warrior to be the S oquar; the warlord of the tribe responsible\nchance of dispelling the magic drops to 10%\nNixies\ntheir\nfor the hunt and defense. The Acquar is advised by a council of el-\ncharmed slaves for one full year, forcing them to do all their\nders, whose spokesperson is called the Luquar, the\nof the\nheavy labor; but thereafter the charm wears off and the victim is\ntribe s oral history: Treasures\nwhether the\nof war or the re-\nset free. During this enslavement, the nixies will\na water\nsults of work or luck, are divided equally by the Acquar: Intertri-\nbreathing\non the human captive, for nixies can cast this\nbal rivalries are often\nand females are sometimes kidnapped\non any creature, Or dispel it, once per day (duration is one day)_\nas brides, for nixies are polygamists, keeping two to three wives.\nMale nixies carry\ndaggers and darts (javelins) which are\nBirth rates in the tribes are high but many children are lost in their\nused as spears under water and missiles above. Usually; each nixie\nfirst years, S0 the overall\npopulation grows slowly: Nixies wor-\nhas one of each weapon . The javelins can be cast a maximum of\nship water and nature powers.\n60 yards (10 yards short range, 30 yards medium) . Occasionally,\nnixies employ their fishing nets in battle, but it takes 10 nixies to\nEcology:\nLakes\nwith\nnixie  tribes\nare\nkept  clean\nand\nwell\nwield the\nnets and their prey must be in the water with them\nstocked, and often the human slaves are worked to improve the\n(rollto hit AC1O t0 ensnare a single man-sized creature, + 2 to the\nenvironment through the removal of trash and obstructions\nAC for each additional victim, Up to five total) . Sometimes nixies\nNixie artifacts include jewelry of shells, pearls and opals, silk\nwill employ their guardian fish or pets in battle (see below).\nfrom waterspiders, and potions of water breathing-\nEven with their 25 % magic resistance, nixies fear fire and very\nbright lights, so a flaming sword or a light\nwill\nthem at\nNixies will try to negate a continual light\nby summon -\nsmall fish to crowd around the light and dim it.\nHabitat Society:\nNixie dwellings are woven from\nsea-\nweed and it is only 5 % likely that their lair will be noticed at any\nDay\nthey\nthey\ning\nfingers\nkeep\nhave\npale\nthey\npearl\ning\nthey\nthey\nJlarge,\ngets\nspell\nspell,\nspell\ntary\nspell\nkeep\nkeeper\nspoils\nkeep\nspell\nfierce\n'spell\nJong\nlarge\nspell\nkeep\nspell\nbay:\ning\nliving",
  "climate_terrain": "Temperate lakes",
  "frequency": "Rare",
  "organization": "Tribe",
  "diet": "Fish",
  "intelligence": "Very (12)",
  "treasure_type": "Q (C)",
  "alignment": "Neutral",
  "number_appearing": "20-80 (2d8x10)",
  "movement": "6, Sw 12",
  "hit_dice": "1-4 hit points",
  "thac0": "20",
  "damage": "By weapon type",
  "special_attacks": "Charm",
  "special_defenses": "Nil",
  "magic_resistance": "25 %",
  "size": "5 (4')",
  "morale": "Average (8-10)",
  "xp_value": "120",
  "id": "nixie"
}