{
  "name": "Nymph",
  "source_page": 101,
  "raw_text": "Nymph\nCLIMATETTERRAIN:\nFREQUENCY:\nrare\nORGANIZATION:\nSolitary\nACTIVITY CYCLE:\nDIET:\nNil\nINTELLIGENCE:\nExceptional (16)\nTREASURE:\nQ (QxlO, X)\nALIGNMENT:\nNeutral (good)\nNO. APPEARING:\n1-4\nARMOR CLASS:\nMOVEMENT:\n12\nHIT DICE:\nTHACO:\n17\nNO: OF ATTACKS:\nDAMAGEIATTACK:\nNil\nSPECIAL ATTACKS:\nSee below\nSPECIAL DEFENSES:\nSee below\nMAGIC RESISTANCE:\n50 %\nSIZE:\nM (4'-6\")\nMORALE:\nUnsteady (7)\nXP VALUE:\n1,400\nSo beautiful that\nglimpse can blind or even kill a\nman, the\nare the embodiment of loveliness,\ntriumph of nature\nA\nnymphs beauty is beyond words\nan ever-young woman\nwith sleek figure and\nthick hair, radiant skin and perfect\nchance) . Since nymphs live for many generations,\ncan pro-\nteeth, full lips and gentle eyes_\nA\nnymph's scent is delightful, and\nvide a wealth of information on the history of an area and often\nher\nrobe glows, hemmed with golden threads and embroi-\nknow secret places, hide-outs, and entrances\nforgotten . If a\ndered with rainbow hues of unearthly magnificence\nA\nnymphs\nman is kissed by a nymph, all painful and troubling memories are\ndemeanor is graceful and charming; her mind quick and witty:\nforgotten for the rest of the\nthis may be a boon to some and\nNymphs speak their own  musical language and the\ncommon\na curse t0 others. A lock of nymph's hair can be used t0 create a\ntongue.\npowerful sleeping potion Or, if enchanted and woven into a cloth\nand sewn into\ngarment, will magically add one point to the\nCombat:\nNeutral in their alliances and cares,\nnymphs do not\nwearer s Charisma. The tears of a nymph can be used as an ingre-\nfight, but flee if confronted by an intruder or danger: Nymphs are\ndient in a philter of love. If a woman bathes in a\nnymphs\nable to cast dimension door once per\nand can employ druidi-\nher Charisma is increased by two points until she bathes\ncal priest\nat Zth ability level, giving a\nfour Ist, two\nZnd, two 3rd, and one 4th level\nonce per day: Looking at a\nnymph will cause permanent blindness unless the onlookers save\nversus\nIf the nymph is nude or disrobes, an onlooker will\ndie unless a saving throw versus\nis successful.\nHabitat Society:\nThese beautiful females inhabit only the love-\nliest of wilderness places, clear lakes and streams, glacier palaces ,\nocean grottoes, and crystalline caverns. Nymphs prefer a solitary\nexistence, but very occasionally a few will gather together in\nplace of spectacular charm, though these rendezvous seldom last\nFor more than\nfew months.\nAnimals of all types flock to\nnymph to be petted and caressed , forgetting their natural enemies\nto gather around the lovely creature\nThere is\na 10% chance that\nwill be friendly if ap\nproached by a\ncreature without the latter first glimpsing the\nnymph, by calling or other\nnotice\nOn the other hand, if a\nnymph sees a human male with 18 Charisma and\nalignment\nbefore he sees her; it is 90% probable that the nymph will be fa-\nvorably inclined toward the man. It is still necessary to make sav-\nthrows upon sighting the nymph\nNymphs hate ugliness and evil and sometimes will help to de-\nfeat it.\ntreasure\npossess has usually been given to them\nby some lovesick man_\nEcology:\nLike a druid, a nymph believes in the sanctity of na-\nture and her environment and will\nto\nher lair safe and\npure. She will heal wounded animals and mend broken trees and\nplants. Sometimes she will even help a human in distress (5%\nAny\nVery\nDay\nnymphs\nthey\nlong,\nlong\nlong\nday\npool,\nagain.\nday;\nnymph\nspells\nspell\nspell.\nspell\nnymph\ngood\nprior\ngood\ning\nthey\nAny\nkeep\ntry",
  "frequency": "rare",
  "organization": "Solitary",
  "diet": "Nil",
  "intelligence": "Exceptional (16)",
  "treasure_type": "Q (QxlO, X)",
  "alignment": "Neutral (good)",
  "number_appearing": "1-4",
  "movement": "12",
  "thac0": "17",
  "special_attacks": "See below",
  "special_defenses": "See below",
  "magic_resistance": "50 %",
  "size": "M (4'-6\")",
  "morale": "Unsteady (7)",
  "xp_value": "1,400",
  "id": "nymph"
}