{
  "name": "Owlbear Temperate forest",
  "source_page": 109,
  "raw_text": "Owlbear\nCLIMATEITERRAIN:\nTemperate forest\nFREQUENCY:\nRare\nORGANIZATION:\nPack\nACTIVITY CYCLE:\nLate afternoon / early evening\nDIET:\nCarnivore\nINTELLIGENCE:\nLow (5-7)\nTREASURE:\n(C)\nALIGNMENT:\nNeutral\nNO. APPEARING:\n1 (2-8)\nJpn\nARMOR CLASS:\nMOVEMENT:\n12\nHIT DICE:\n5 +2\nTHACO:\n15\nNO. OF ATTACKS:\nDAMAGEIATTACK:\n1-6/1-6/2-12\nSPECIAL ATTACKS:\nSPECIAL DEFENSES:\nNil\nMAGIC RESISTANCE:\nNil\nSIZE:\nL (8' tall)\nMORALE:\nSteady (11-12)\n+Special\nXP VALUE:\n420\nOwlbears are probably the crossbred creation of a demented wiz-\nard; given the lethality of this creation, it is\nlikely that the\nwizard who created them is no longer alive. Owlbears are vi-\ncious, ravenous, aggressive, and evil tempered at all times_\nEcology:\nOwlbears have a\nlifespan of 20 years.\nare warm-\nOwlbears are a cross between a giant owl and a bear:\nare\nblooded mammals, but\neggs.\nprey on\nanything,\ncovered with\nthick coat of feathers and fur; brown-black to\nrabbits to bears to trolls to snakes and reptiles. Owlbears prefer\nyellow-brown in color: The 8-foot-tall males, which weigh be-\ntemperate climates, but some thrive in subarctic environments_\ntween 1,300 and 1,500 pounds, are darker colored\nThe beaks of\nAs a hybrid of two animals, one diurnal and the other nocturnal,\nthese creatures are yellow to ivory and their terrifying eyes are\nhave an unusual active time, waking at noon, hunting ani-\nred-rimmed. Owlbears speak their own language, which consists\nmals active during the day; then hunting nocturnal creatures be-\nof very loud screeches of varying length and pitch.\nfore   going\nto  sleep\nat  midnight.\nOwlbears\nare  active\nin the\nsummer months and hibernate during the cold season. There are\nCombat:\nThe owlbear attacks prey on sight, always fighting to\nrumors of white arctic owlbears\na cross between arctic owls and\nthe death (ignore morale rating for purposes of determining re-\npolar bears, but no specimens have ever been captured.\ntreat) . It attacks with its claws and snapping beak: If an owlbear\nAn owlbear does not actively seek treasure but the remains of\nscores a claw hit with a roll of 18or better; it drags its victim into a\nvictims may be found buried in shallow holes around an owlbear\nsubsequently squeezing its opponent for 2-16 points of dam-\nlair: Owlbear eggs are\n2,000 silver pieces and\nhatchlings are\nage per round until either the victim Or the owlbear is slain_\nThe\nworth 5,000 silver pieces on the open market\nThese are typically\nowlbear can also use its beak attack on victims caught in its grasp;\nbought by wizards; while\nare\nimpossible to domesticate,\nbut cannot use its claws\nA single attempt at a bend\n'lift\nmake formidable guardians and wizards sometimes place\nroll\nbe made to break\nthe grasp of an owlbear\nNote\nthem in locations of strategic importance (it has been said that an\nthat if the Armor Class of a victim is high enough that 18 is insuf-\nowlbear is a less subtle version ofa \"keep out\" sign). Owlbears in\nficient to hit, the\nis not effective and no damage is taken\ndungeons and ruins almost always\nbeen placed there by\nsomeone.\nHabitat Society:\nOwlbears inhabit the depths of tangled forests\nin temperate climes, as well as subterranean labyrinths,\nin\ncaves or hollow stumps.\nOwlbears live in mated pairs; the male is slightly\nand\nheavier than the female. If encountered in their lair there is a 25 %\nchance that there will be\neggs (20 %\nor young (80 %\nin addi-\ntion t0 the adults\nThe offspring\nbe 40 % to 70 % grown and\nfight as creatures with three or four Hit Dice, depending on their\ngrowth. They have hit points based on their adjusted Hit Dice\nImmature offspring inflict 1-4/1-4/2-8 points of damage\ntheir attacks and\na character has\n+20% to\nbend bars /lift\nroll to escape the\nof an immature owlbear:\nAn owlbear\nclaims a territory of one Or two square miles\nand will vigorously defend this territory against all intruders.\nAn owlbear s main weakness is also its greatest strength-_its fe-\nrocity: Because owlbears are so bad-tempered,\nstop at noth-\nto kill\ntarget: It is not difficult to trick an owlbear into\nhurling itself off a cliff or into a trap, provided you can find one.\nHug\nquite\nThey\nThey\nJay\nThey\nfrom\nthey\nworth\nhug,\nthey\nbars\ngates\nthey\nfrom\nmay\n'have\nhug\nliving\nlarger\n1-6\nwill\nwith\nhis\nhug\ngates\npair\nthey\ning",
  "frequency": "Rare",
  "organization": "Pack",
  "activity_cycle": "Late afternoon / early evening",
  "diet": "Carnivore",
  "intelligence": "Low (5-7)",
  "treasure_type": "(C)",
  "alignment": "Neutral",
  "number_appearing": "1 (2-8)",
  "movement": "12",
  "hit_dice": "5 +2",
  "thac0": "15",
  "damage": "1-6/1-6/2-12",
  "special_defenses": "Nil",
  "magic_resistance": "Nil",
  "size": "L (8' tall)",
  "morale": "Steady (11-12)",
  "xp_value": "420",
  "id": "owlbear_temperate_forest"
}