{
  "name": "Pegasus",
  "source_page": 110,
  "raw_text": "Pegasus\nCLIMATETERRAIN:\nTemperate and subtropical\nforests\nFREQUENCY:\nrare\nORGANIZATION:\nHerd\nACTIVITY CYCLE:\nDay\nDIET:\nHerbivore\nINTELLIGENCE:\nAverage (8-10)\nTREASURE:\nNil\nALIGNMENT:\nChaotic\nNO: APPEARING:\n1-10\nARMOR CLASS:\nMOVEMENT:\n24, FI 48 (C, D mounted)\nHIT DICE:\nTHACO:\n17\nNO: OF ATTACKS:\nDAMAGEIATTACK:\n1-8/1-8/1-3\nSPECIAL ATTACKS:\nDive, rear kick\nSPECIAL DEFENSES:\nNil\nMAGIC RESISTANCE:\nNil\nSIZE:\nL (51/2' at the shoulder)\nMORALE:\nSteady (11)\nXP VALUE:\n175\nGreater\n975\nPegasi are\nmagnificent winged steeds that often serve the cause of\nThese intelligent creatures are very shy and wild, not easily\nPegasi are intelligent creatures. They can detect\nand de-\ntamed. They serve only\ncharacters, but if\ndo,\nwill\ntect evil at will (60\nrange) . They use these powers on those\nserve their master with absolute faithfulness for the rest of his life.\nwho would ride them;\nto throw anyone of non-\nA pegasus is a thoroughbred which resembles an Arabian horse\nalignments who would tame them. If provoked, pegasi will not\n(though slightly larger) with two\nfeathered\nPegasi are\nhesitate to attack creatures whom\nperceive as evil.\nusually white, but brown pegasi are not unknown, and rumors per-\nTo tame\npegasus,\nperson of\nalignment must locate a\nsist of black pegasi\nAs should be expected, alignments do not vary\npegasus herd. Then, at night, he can\nto sneak Up on a pegasus\naccording to color (all pegasi are chaotic\nPegasi are 17 hands\nand surprise it. The character must have the airborne\ntall (five feet at the shoulder) and weigh over 1,500 pounds. Pegasi\nciency: There is an initial + 10 penalty to the roll; pegasi do not\nmust be ridden bareback; they will not accept saddles\nlike to be tamed. A magical bridle enchanted for the purpose will\nPegasi speak their own language and can communicate with\nremove this penalty If the character successfully makes his roll;\nhorses. They can understand common, and will\ntheir master' $\nthen the pegasus\nbe tamed\ncommands if they are given in that language.\nA tamed pegasus will\nthe commands of its master for as\nas it lives, if the master remains of\nalignment.\nCombat:\nA pegasus attacks with its\nand teeth. It can at-\ntack an opponent who is behind it with its rear hooves, inflicting\nEcology:\nPegasi feed on grass, fruits, and other plants. Griffons\n2-12 points of damage; butit cannot use any ofits other attacks in\nand hippogriffs are the natural enemies of a pegasus. Pegasi have\nthat round\nA pegasus can also dive at an opponent from heights\nlifespan of about 40 years.\nof 50 feet or higher and use its hoof attacks; each attack roll is\nand does double damage\nGreater\nPegasus\nIn battle,\na pegasus will try to lure larger opponents (such as\nLegend has it that if a medusa is slain and beheaded, there is\ndragons) into tight spaces. As the opponent struggles to maneu-\ninto attack\nthe\nclimbs and attacks with its\nsmall (5 %\nchance that a greater pegasus will be born, springing\nver\nrange,\npegasus\nfully born from the medusa's cloven neck. These pegasi have the\nhooves from above. Against creatures their own size, such as\nsame attacks and movement rate of\nnormal pegasus but are\nfons, pegasi use their superior speed to outrun them. If griffons\nif\nworth 6 Hit Dice and have 20 % magic resistance\nalso have\nare close to a pegasus nest (especially\nare young present) ,\na +1 bonus to their morale rating. There is a 5 % chance that the\none parent will attack aggressively,\nthe griffon 5 attention, and\nleader of a herd of pegasi will be a greater pegasus. Greater pegasi\nthen fly away: By doing this,\nhope to lure enemies away\ncan be tamed only by the noblest and greatest of heroes, and\nfrom the nest and tire them out over a\ndistance before return-\n~lifespan of 100 years.\nhome\nHabitatiSociety:\nPegasi\nare egg-laying mammals. If encoun -\ntered in their lair, there will be one nest for every\nof pegasi.\nThere is a 20% chance per nest that there will be 1-2 eggs (30 %\nchance) or young (70 %\nof 20-50% maturity Each egg is worth\n3,000 silver pieces, while the young are worth 5,000 silver pieces\nper head on the open market.\nA pegasus can be used as a warhorse;\nmale can carry weight\nas a medium warhorse (220/330/440) , while\nfemale can carry\nweight as a light warhorse (170/255/340) .\nVery\ngood\ngood\ngood .\nthey\nthey\ngood\nyard\nthey\ngood\ntry\nlarge\nwings\nthey\ngood\ntry\ngood).\nriding\nprofi-\nobey\nwill\nobey\ngood\nlong\nhooves\n+2\ngrif-\nThey\nthere\nget\nthey\nhave\nlong\ning\npair",
  "climate_terrain": "Temperate and subtropical",
  "frequency": "rare",
  "organization": "Herd",
  "activity_cycle": "Day",
  "diet": "Herbivore",
  "intelligence": "Average (8-10)",
  "treasure_type": "Nil",
  "alignment": "Chaotic",
  "number_appearing": "1-10",
  "movement": "24, FI 48 (C, D mounted)",
  "thac0": "17",
  "special_attacks": "Dive, rear kick",
  "special_defenses": "Nil",
  "magic_resistance": "Nil",
  "size": "L (51/2' at the shoulder)",
  "morale": "Steady (11)",
  "xp_value": "175",
  "id": "pegasus"
}