{
  "name": "Piercer",
  "source_page": 111,
  "raw_text": "Piercer\nCLIMATE TERRAIN:\nsubterranean\nFREQUENCY:\nUncommon\nORGANIZATION:\nColony\nACTIVITY CYCLE:\nDIET:\nCarnivore\nINTELLIGENCE:\nNon- (0)\nTREASURE:\nNil\nALIGNMENT:\nNeutral\nNO: APPEARING:\n3-18 (3d6)\nARMOR CLASS:\nMOVEMENT:\nHIT DICE:\n1-4\nTHACO:\n19 (1-2 HD)\n17 (3-4 HD)\nNO:OF ATTACKS:\nDAMAGEIATTACK:\n1-6 (1 HD),\n2-12 (2 HD);\n3-18 (3 HD)\n4-24 (4 HD)\nSPECIAL ATTACKS:\nSurprise\nSPECIAL DEFENSES:\nNil\nMAGIC RESISTANCE:\nNil\nSIZE:\nTM (1-6' tall)\nMORALE:\nAverage (8-10)\nXP VALUE:\n1 HD\n35\npiercers are not social creatures\nThere are rumored to be great\n2 HD\n65\ncaverns\nunderground that contain colonies of hundreds of\n3 HD\n120\npiercers. Piercers are not attracted to treasure, only to food\n4 HD\n420\nEcology:\nThe piercer is & mollusk, hatched from a hen-sized egg\nPiercers resemble stalactites found on cave roofs.\nare actu-\nwhich the parent\nin clutches of six to eight in isolated areas of\nally\nspecies of gastropods that, without their shells, resemble\nthe cavern . When\nhatch, the young appear to be slugs feed-\nwith\ntails\nA piercer climbs onto the ceiling of a cavern\non fungi. After several months,\nclimb the cavern walls,\nand waits patiently; when it detects prey beneath it, it drops from\nsecrete a chemical that hardens into the familiar stalactite\nthe ceiling and impales the victim with the sharp end of its shell.\nand then wait for prey t0 come.\nPiercers look like limestone growths on the ceiling of a cavern ,\nA piercer has a lifespan of four years and grows one Hit Die per\njust like ordinary stalactites. They come in the following sizes:\nyear: In any group of piercers, the number of creatures with one,\none foot\n(1 Hit Die) , three feet\n(2 Hit Dice) , four and\ntwo, three, and four Hit Dice will be nearly evenly divided\none-half feet\n(3 Hit Dice) , and six feet\n(4 Hit Dice) .\nin a group of 12 piercers, there will be three one Hit Die piercers,\nPiercers can be identified on very close inspection by a\nof\nthree with two Hit Dice , three with three Hit Dice, and three with\neyestalks that curl along the side of the stalactite\nfour Hit Dice) .\nA piercer can g0 without food for months. It stores food in &\nCombat:\nPiercers have only one chance to hit; if an attack fails\nsecond stomach that can preserve food for long periods of time;\nto score a kill, the piercer cannot attack again until it slowly scales\nsome alchemists seek out piercers to extract a substance from this\nwall to resume its position . Piercers can hear noises and detect\norgan and refine it for human use, as it can\nfoodstuffs and\nheat sources in a 120-yard radius; these heat sources include hu-\nprecious ingredients fresh for weeks. Piercers also store\nsup-\nmans. If the noise and light are stationary for many minutes at a\nplies of water, extracted from their victims. Piercers can maintain\ntime, piercers will slowly edge into attack position\nover  the\nthis water supply for months:\nsource of the stimulus. Piercers are virtually indistinguishable\nThe taste of a piercer is said to resemble that of a snail, but with\nfrom natural phenomena. A group of characters has a\nmodifier\na bitter aftertaste_\nTheir eggs and offspring are not traded on the\non its\nsurprise roll against a piercer (this guarantees that the group\nopen market.\nbe surprised unless it has some positive modifiers)_\nA piercer, after it has fallen, is slow and fairly easily slain . Its\nsoft underbelly has one defense mechanism; when exposed to air\nit covers itself in a corrosive\nwhich inflicts 1 point of damage\non contact with flesh;\nThis is usually enough to dissuade natural\npredators from disturbing it.\nHabitat Society:\nWhile piercers are nonintelligent, the piercers\nin a\ncolony are aware of each other:\noften fall simultane-\nously; to feed on those killed by other piercers (which makes the\narea\nsuddenly very dangerous) _\nPiercers dwell in caverns, where they live in groups of about 10\nmembers. They prefer to\nover\nhigh traffic areas, so\nusually be found near cave entrances. Aside from mating, the\nAny\nAny\ndeep\nThey\nJays\nthey\nthey\ning\n~slugs\nlong\nshape,\nlong\n(e.g\nlong\nlong\nlong\ntiny\npair\nkeep\nlarge\nwill\nacid\nThey\nthey\nwill\nhang",
  "climate_terrain": "subterranean",
  "frequency": "Uncommon",
  "organization": "Colony",
  "diet": "Carnivore",
  "intelligence": "Non- (0)",
  "treasure_type": "Nil",
  "alignment": "Neutral",
  "number_appearing": "3-18 (3d6)",
  "hit_dice": "1-4",
  "thac0": "19 (1-2 HD)",
  "special_attacks": "Surprise",
  "special_defenses": "Nil",
  "magic_resistance": "Nil",
  "size": "TM (1-6' tall)",
  "morale": "Average (8-10)",
  "xp_value": "1 HD",
  "id": "piercer"
}