{
  "name": "Pseudodragon",
  "source_page": 112,
  "raw_text": "Pseudodragon\nCLIMATE TERRAIN:\nTemperate\nOT\nsubtropical\nforests and caves\nFREQUENCY;\nVery rare\nORGANIZATION:\nSolitary\nACTIITY CYCLE:\nDay\nDIET:\nOmnivore\nINTELLIGENCE:\nAverage (8-10)\nTREASURE:\nQ (x1O)\nALIGNMENT:\nNeutral (good)\nNO:APPEARING:\n1 (50% chance of 1-8 in nests)\nARMOR CLASS:\nMOVEMENT:\n6 , FI 24 (B)\nHIT DICE:\nTHACO:\n19\nNO. OF ATTACKS:\nDAMAGEIATTACK:\n1-3 + special\nSPECIAL ATTACKS:\nPoison\nSPECIAL DEFENSES:\nChameleon power\nMAGIC RESISTANCE:\n35 %\nSIZE:\nT (11/2' long)\nMORALE:\nChampion (15)\nXP VALUE:\n975\nPseudodragons are\nspecies of\nflying lizard that inhabits\nheavily forested wilderness areas. These playful, benign creatures\nhave magical powers that\ncan share with others\nSo\nare\ncompanionship will stalk\na candidate silently for\nreading\noften sought as companions.\nhis thoughts via telepathy; judging his deeds to be\nor evil. If\nPseudodragons resemble miniature red dragons.\nhave\nthe candidate is found to be good, the pseudodragon will present\nfine scales and sharp horns and teeth. A pseudodragon's colora-\nitself to the human as a\ntraveling companion and observe the hu-\ntion is red-brown as opposed to the\nred of red dragons. Its\nman $ reaction\nIf the human seems overjoyed and promises to\ntail is about 2 feet\n(longer than the pseudodragon itself) ,\ntake very\ncare of it, the pseudodragon will accept. If not, it\nbarbed, and very flexible.\nwill fly away:\nPseudodragons communicate via a limited form of telepathy. If\nThe personality of a pseudodragon has been described by some\none elects to takea human companion, it can transmit what it sees\nas catlike\nA pseudodragon is willing to serve, provided that it is\nand hears at a distance of up to 240 yards. Pseudodragons can vo-\nwell-fed\ngroomed, and receives lots of attention.\nAt times\ncalize animal noises such as a rasping purr (pleasure), a hiss (un-\npseudodragon seems arrogant, demanding, and less than willing\npleasant surprise) ,\n(desire), or a growl (anger) .\nto help. In order to\nits full cooperation, the companion must\npamper the pseudodragon and make it feel as though it were the\nCombat:\nThe pseudodragon can deliver a vicious bite with its\nmost important\nin his life. If the pseudodragon is mistreated\nsmall, dragonlike jaws, but its major weapon is its sting-equipped\nor insulted it will\nor worse, play pranks when least ex-\ntail, The creature can move it with flashing speed and strikes at\npected . Pseudodragons particularly dislike cruelty and will not\n+4 on attack rolls:\ncreature struck must save versus poison\nserve cruel masters.\nor g0 into a state of\ncatalepsy that lasts 1-6 days.\nThe victim ap-\npears quite dead, but at the end of that time the character will ei-\nEcology:\nPseudodragons\nare\nomnivorous\nbut  prefer\nto\neat\nther wake Up unharmed (75 % chance) or die (25 % chance) _\nmeat. Their diet consists chiefly of rodents and\nbirds with\nPseudodragons have a chameleonlike power that allows them\noccasional leaves, fruits, and berries. In the wild, pseudodragons\nto alter their coloration to blend with their surroundings.\nlive solitary lives , protecting small personal hoards in their nests_\ncan blend into any typical forest background with an 80 % chance\ngather to mate once per year, in early spring, when gather-\nof\nundetected by creatures which cannot see invisible ob-\nof dozens of pseudodragons are not uncommon . After mat-\njects . Pseudodragons have infravision with\n60 foot range and\nmales and females separate; females\nspeckled brown eggs\ncan see invisible objects\nin clutches of four to six which hatch in mid-summer; females\nA pseudodragon is highly magic resistant and can transmit this\nraise the young by themselves. Pseudodragons hibernate in win-\nmagic resistance to its human companion via physical contact (a\nter; the young leave the nest in spring to mate.\npseudodragon likes to be perched\non the top of one's head or\nPseudodragons have\nlifespan of 10-15 years: Like dragons,\ncurled around the shoulders and upper back)\nare attracted to bright shiny objects. Pseudodragon eggs can\nbe resold for up to 10,000\npieces while a hatchling is worth as\nHabitatiSociety:\nThese   forest-dwelling\ncreatures\nplace\ntheir\nmuch as 20,000\npieces .\nlairs in the hollows of great trees Or in large caves.\nA pseudodragon will very rarely take a human or demihuman\nas its\ncompanion. Some view these pseudodragons as the human's\npet; the pseudodragon will be sure to correct this misunderstand-\nThere are two ways to become a pseudodragon's companion;\none is t0 use magic t0 summon it (a find familiar\nAnother\nway is to find the pseudodragon on an adventure and pursuade it\nto become\ncompanion. The pseudodragon that searches for\nsting\nsmall\nthey\nthey\ndays,\ngood\nThey\ndeep\nlong\ngood\nchirp\ngain\nthing\nleave,\nAny\nsmall\nThey\nThey\nbeing\nings\ning,\nlay\nthey\ngold\ngold\ning\nspell) .",
  "climate_terrain": "Temperate",
  "frequency": "Very rare",
  "organization": "Solitary",
  "diet": "Omnivore",
  "intelligence": "Average (8-10)",
  "treasure_type": "Q (x1O)",
  "alignment": "Neutral (good)",
  "number_appearing": "1 (50% chance of 1-8 in nests)",
  "movement": "6 , FI 24 (B)",
  "thac0": "19",
  "damage": "1-3 + special",
  "special_attacks": "Poison",
  "special_defenses": "Chameleon power",
  "magic_resistance": "35 %",
  "size": "T (11/2' long)",
  "morale": "Champion (15)",
  "xp_value": "975",
  "id": "pseudodragon"
}