{
  "name": "Rakshasa Rakshasa Rakshasa, Greater",
  "source_page": 114,
  "raw_text": "Rakshasa\nRakshasa\nRakshasa, Greater\nCLIMATETERRAIN:\nTropical or sub\nTropical or sub-\ntropical forest;,\ntropical forest ,\njungle, or swamp\njungle,\nOr-swamp\nFREQUENCY:\nRare\nVery rare\nORGANIZATION:\nSolitary\nSolitary\nACTMITY CYCLE:\nNight\nNight\nDIET:\nCarnivore\nCarnivore\nINTELLIGENCE:\n(11-12)\nHigh (13 - 14)\nTREASURE:\nF\nB,F\nALIGNMENT:\nLawful evil\nLawful evil\nNO APPEARING:\n14\n1\nARMOR CLASS:\nF5\nMOVEMENT:\n15\n18\nHIT DICE;\n8 +1o\nTHACO:\n13\n11\nNO: OF ATTACKS:\nDAMAGEIATTACK:\n1-3/1-3/2-5\n1-6/1-6/2-10\nSPECIAL ATTACKS:\nIllusion\nIllusion\nSPECIAL DEFENSES:\n+1 or better\n+2 or better\nmagical weapon\nmagical weapon\nto hit\nto hit\nMAGIC RESISTANCE:   Special\nSpecial\nSIZE:\nM (6' tall)\nM (61/2' tall)\nMORALE:\nChampion (15-16)  Fanatic (17-18)\nXP VALUE:\n4,000\nhonor: If confronted by humans who recognize their true ap-\nRuhk\n7,000\npearance,\nare\ninsufferably arrogant:\nRajah\n7,000\nA rakshasa' s life varies in\nof wild self-indulgence in times\nMaharajah\n10,000\nof prosperity and strict fasting and sacrifice in times of trouble or\nbefore battle.\nare honorable creatures but will twist the\nwording of an agreement to suit their purposes\nprefer to\nRakshasas are a race of malevolent spirits encased in flesh that\ndeal with humanity by using their illusion powers to deceive and\nhunt and torment humanity No one knows where these creatures\nmanipulate them, but are brave and forthright in battle.\noriginate; some say they are the embodiment of nightmares.\nRakshasas stand 6 t0 7 feet tall and weigh between 250 and 300\nEcology:\nAs  spirits,  rakshasas\nare  virtually immortal.\npounds.\nhave no uniform appearance but appear as human-\nproduce\na new\ngeneration every century t0 replace the rakshasas\noid creatures with the bodily features of various beasts (most\nthat have been slain in battle. No creatures prey on rakshasas ex-\ncommonly tigers and apes) . Hands whose palms curve backward,\ncept those who would avenge their victims. Rakshasa essence can\naway from the body; seem to be common. Rakshasas of the high-\nbe an\ningredient in a potion of delusion:\nest\nstanding sometimes have several heads. All rakshasas wear\nhuman clothing of the highest quality:\nRakshasa Ruhks\nCombat:\nRakshasas savor fresh human meat and use illusions\nAbout 15 % of all rakshasas are ruhks,\nOr\nknights. These warriors\nto\nit,\nhave a limited form of ESP which allows them to\nare the guardians of a rakshasa community\nare hit only by\ndisguise themselves as someone the victim trusts; the rakshasa\nmagical weapons of + 2 or better; any weapon below\n+4 inflicts\nuses this illusion as a lure and strikes when the victim is most un-\nonly half damage against them. Their spells are castat 9th level of\nprepared.\nThe rakshasa must\nthe illusion when it attacks\nability:\nNormally rakshasas can have magical abilities, Up to the follow-\nlimits: four Ist level wizard spells, three Znd level wizard\nRakshasa Rajahs\nspells, two 3rd level wizard spells, and three Ist level priest\nAbout 15 % of all rakshasa ruhks are rakshasa rajahs, or lords.\nThese are cast at Zth level ability Rakshasas are immune to all\nEach rajah is the leader (patriarch) of his local clan. These rulers\nlower than 8th level. An attacker needs at least a\n+1 magi-\nof rakshasadom have the same abilities as a ruhk, but also\ncal weapon t0 harm a rakshasa; any weapon below\n+3 inflicts\nthe\ncasting abilities of both a 6th level priest and an\nlevel\nonly half damage. However,\na hit by any blessed crossbow bolt\nwizard\ncast at Ilth level of ability:\nkills a rakshasa instantly:\nRakshasa Maharajahs\nHabitatiSociety:\nRakshasa   society\nis bound by\ncastes\nEach rakshasa is born into a particular role in life and cannot ad-\nAbout 5% of all rakshasa rajahs are rakshasa maharajahs; or\nvance . Females (known as rakshasi) are fit to be consorts, hon-\ndukes_\nMaharajahs have the same abilities as a ruhk, but have\nored only by their faithfulness and the fighting ability of their\n13 + 39 Hit Dice, and the\ncasting abilities of a 13th level wiz -\nchildren . There are 1-3 females per male.\nard and %th level priest\nA maharajah is the leader of either sev-\nRakshasa society is led by & rajah or maharajah, whose com-\neral small, related clans, or a single powerful clan\nMaharajahs\nmands are t0 be obeyed without question\nreside on the outer planes, where\nrule island communities of\nRakshasas wage war on humanity constantly not only to feed\nhundreds of rakshasas, and serve as minions to even greater\nthemselves but because\nbelieve that battle is the only way to\npowers.\nVery\ngain\nthey\ncycles\nThey\nThey\nThey\nThey\nThey\nThey\nget\ndrop\ning\nspells\nspells\nhave\nspell\n8th\nrigid\nspell\nthey\nthey",
  "climate_terrain": "Tropical or sub",
  "frequency": "Rare",
  "organization": "Solitary",
  "diet": "Carnivore",
  "intelligence": "(11-12)",
  "treasure_type": "F",
  "alignment": "Lawful evil",
  "number_appearing": "14",
  "ac": "F5",
  "movement": "15",
  "hit_dice": "8 +1o",
  "thac0": "13",
  "special_attacks": "Illusion",
  "special_defenses": "+1 or better",
  "magic_resistance": "Special",
  "size": "M (6' tall)",
  "morale": "Champion (15-16)  Fanatic (17-18)",
  "xp_value": "4,000",
  "id": "rakshasa_rakshasa_rakshasa_greater"
}