{
  "name": "Remorhaz",
  "source_page": 117,
  "raw_text": "Remorhaz\nCLIMATE TERRAIN:\nArctic plain\nFREQUENCY:\nrare\nORGANIZATION:\nSolitary\nACTIITY CYCLE:\nDay\nDIET:\nCarnivore\nINTELLIGENCE:\nAnimal (1)\nTREASURE:\nD\nALIGNMENT:\nNeutral\nNO. APPEARING:\nARMOR CLASS:\nOverall 0, head 2, underbelly\nMOVEMENT:\n12\nHIT DICE:\n7-14\nTHACO:\n13 (7-8 HD)\n11 (9-10 HD);\n(11-12 HD)\n7 (13-14 HD)\nNO.OF ATTACKS:\nDAMAGEATTACK:\nBite: (7-8 HD) 4-24;\n(9-12 HD) 5-30;\n(13-14 HD) 6-36\nSPECIAL ATTACKS:\nSwallow whole, heat lash\nSPECIAL DEFENSES:\nMelt metal\nMAGIC RESISTANCE:\n75 %\nSIZE:\nG (21'-42\"'\nMORALE:\nElite (13-14)\nXP VALUE:\nmelts the snow, leaving it to refreeze. The central chamber is only\n7 HD\n4,000 ( +1000 per Hit Die)\nabout twice the size of a remorhaz, while the central chamber of a\nnes\nis about four times their size and may contain\nsta-\nRemorhaz, sometimes known as polar worms, inhabit only chill\nlactites\narctic wastes. They are very aggressive predators that devour any\nRemorhaz have a hunting range of 60 miles. Except where the\nanimal matter, including humans, demihumans, and humanoids;\ngame has\nhunted to extinction, these creatures tolerate the\nhave even been known to attack frost giants.\npresence of other remorhaz in their hunting grounds_\nA remorhaz has\nsegmented body with\nwinged head and\nneck, standing on dozens of chitinous\nRemorhaz have an ice\nEcology:\nRemorhaz are carnivores, sustaining themselves with\nblue color everywhere except on their backs, where a streak of\ndiet of deer, elk\nand even\npolar\nmate in late sum-\nwhite sets off the many protrusions located there. The size of a re-\nmer and\ntogether for two months before departing to\nsol-\nmorhaz is determined by its Hit Dice: a 7 Hit Dice remorhaz is 21\nitary existences. Remorhaz\nmate every year but\ncan\nproduce\nfeet\nan 8 Hit Dice creature is 24 feet\netc. Their lan-\noffspring only three or four times in a lifetime; the female\nguage consists of roaring, bellowing, and howling:\nclutch of one or two\ngrey-blue eggs, remaining with the eggs at all\ntimes, coiling around them to keep them warm; ifthe eggs are left\nCombat:\nIn combat the remorhaz beats its\nwings, raising\nin the freezing cold for only one minute;\nwill never hatch.\nup the front quarter ofits body. It then snaps itself forward, strik-\nYoung remorhaz have 1 Hit Die at birth and grow to 7 Hit Dice af-\nwith blinding\nThey are able to swallow prey whole on\nter four months, when they leave the nest . Immature remorhaz\nan unmodified attack roll of 20; any victim swallowed is killed in-\nhave weaker armor (+2 AC in all locations); 1-3 Hit Dice re-\nstantly by the intense heat inside the creature: When aroused, the\nmorhaz can only bite for 2-12 points of damage, while 4-6 Hit\nremorhaz secretes a substance that causes its intestines to become\nDice creatures inflict 3-18 points of damage. From birth, the\nvery hot and its back protrusions actually glow cherry red from\nyoung remorhaz have all the powers of an adult.\nexcess heat: Any nonmagical weapon melts from contact with its\nRemorhaz have\nlifespans of 30 years. Their eggs are valued at\nback and any creature touched by these surfaces suffers 10-100\n500\npieces and are eagerly sought because these creatures can\npoints of damage.\nbe trained to be excellent guards. However,\nremorhaz can be\nTo determine where\na blow has struck\nremorhaz, consider\ntrained t0 obey only one Or two masters, and\nattack its mas-\nwhere the attacker is in respect to the remorhaz. While the re-\nter if\nenough. The heat secretion of a rhemorhaz,\nmorhaz is rearing to attack,\nblow from the front hits the rela-\nis valuable as a component for heat-related magical items and can\ntively soft underbelly: When the remorhaz is attacking a creature,\nbe sold to alchemists for 5-10\npieces per flask. The remorhaz\nany blow inflicted hits the head unless the underside is specifically\nwill contain 10 flasks worth of thrym per Hit Die.\nstated as the object of the attack. In all other cases, the body is the\nobject of the attack, subject to adjudication by the DM:\nRemorhaz are slower than most\ndwellers, so\nprefer\nto burrow into the snow and surface when they hear prey nearby;\nhoping to achieve surprise. Remorhaz have infravision to 60 feet:\nHabitat Society:\nA remorhaz lair usually consists of a number\nof\nsmoothly rounded tunnels in ice and snow or rock,\nually descending to\ncentral chamber; Tunnels in ice and\nsnow will be very slippery, as the remorhazs hot back repeatedly\nVery\nlong)\nicy\nsting\npair\nbeen\nthey\nlegs.\nbears.\nThey\nlive\nstay\nJays\nlong,\nlong:\nthey\nsmall\nspeed.\ning -\ngold\nwill\nthrym;\nhungry\ngold\npolar\nthey\ngrad-\nlarge,\nlarge",
  "climate_terrain": "Arctic plain",
  "frequency": "rare",
  "organization": "Solitary",
  "diet": "Carnivore",
  "intelligence": "Animal (1)",
  "treasure_type": "D",
  "alignment": "Neutral",
  "ac": "Overall 0, head 2, underbelly",
  "movement": "12",
  "hit_dice": "7-14",
  "thac0": "13 (7-8 HD)",
  "damage": "Bite: (7-8 HD) 4-24;",
  "special_attacks": "Swallow whole, heat lash",
  "special_defenses": "Melt metal",
  "magic_resistance": "75 %",
  "size": "G (21'-42\"'",
  "morale": "Elite (13-14)",
  "xp_value": "melts the snow, leaving it to refreeze. The central chamber is only",
  "id": "remorhaz"
}