{
  "name": "Selkie Cold to subarctic waters",
  "source_page": 120,
  "raw_text": "Selkie\nCLIMATEITERRAIN:\nCold to subarctic waters\nFREQUENCY:\nrare\nORGANIZATION:\nSolitary or tribal\nACTIVITY CYCLE:\nDIET:\nOmnivore\nINTELLIGENCE:\nAverage to exceptional (8-16)\nTREASURE:\nA (magic only) _\nR\nALIGNMENT:\nNeutral (good)\nNO. APPEARING:\nTor 12-30\nARMOR CLASS:\n5 (10 base in human form)\nMOVEMENT:\n12 , Sw 36\nHIT DICE:\n3+3\nTHACO:\n17\nNO. OF ATTACKS:\nDAMAGEIATTACK:\n1-6 or by weapon type\nSPECIAL ATTACKS:\nNil\nSPECIAL DEFENSES:\nCan change into human form\nMAGIC RESISTANCE:\nNil\nSIZE:\nM (5'-6' in either form\nMORALE:\nSteady (11-12)\nXP VALUE:\n120\nLeader\n420\nSelkies are seal-like beings that have the ability to change into hu-\nman form for a few days at a time.\nWhen in their true, seal-like forms, they are nearly indistin-\nselkies who have visited the overworld many times have ever ac-\nguishable\nnormal seals. Close inspection of their arms, how\nquired\na taste for ornamenting themselves like overworlders, and\never; will reveal the presence of slightly webbed hands instead of\ncan be\ndistinguished from more traditional selkies immediately:\nfore flippers and\ninstead of a tapering body and rear flippers.\nFor obvious reasons, these more experienced selkies are often the\nOnce\nmonth; each selkie is able to assume human form for\nbest representatives t0 deal with if one is an overworlder: Selkies\nabout\na week. Usually selkies prefer to briefly visit the realm of\ncan be hired and have a limited knowledge of overworlder cus-\nmen (which\ncall the\n'overworld\nout of curiosity but some-\ntoms\nAll magical treasure recovered by selkies is immediately\ntimes\nare  ordered\nto go forth and purchase desperately\ncommandeered for the\nof the community and the lair s de-\nneeded\nor information, When in human form, selkies are\nfense\nvery attractive indeed and their\nlooks have broken more than\na few overworlders' hearts. Their eyes are particularly noticeable\nEcology:\nSelkies are omnivorous, preferring t0 eat fish, shell-\nas\nare always either a bright emerald green or startling light\nfish, crustaceans, and various forms of seaweed. Those that have\nblue. Since the selkie transformation is not a\nor\nmagical ef-\nvisited the surface are often partial to human fare as well. Selkies\nfect, only\nlike true seeing will reveal\na selkie $ true nature\nare\nparticularly susceptible to\nwine, which is to be expected\nalthough their peculiar mannerisms and predilection for seafood\nsince these intoxicants are unknown below the seas\nalso might.\nSelkies are sensitive about their environment and harvest only\nwhat they need to survive. It is worth noting that selkie represent-\nCombat:\nSince selkies are unable to swim quickly while carry-\natives lobby heavily whenever local overworlder environmental\nweapons, 90 % of selkies encountered underwater will be un-\nissues threaten selkie existence\nMost selkie communities have\narmed. They use their sharp teeth whenever\nare cornered but\nlearned the value of dropping a few pearls here and there in order\nprefer to use their impressive\nunderwater to escape superior\nto\nwhat\nwant from men .\nodds. If encountered on land, selkies are wise enough to bear hu-\nWhile selkies in human form are quite beautiful;\nare fortu-\nman weapons, most likely swords scavenged\nthe wrecks of\nnate indeed that their\nhave little value in overworlder\nmar -\nships (see below)\nkets .\nare, therefore, without any special enemies besides\nthose common to seals and all ocean dwelling beings.\nHabitat Society:\nSelkie communities are divided between male\nand female, with females usually outnumbering males, as male\nSelkie, Leader\nselkies are the hunter / gatherers throughout the often dangerous\nwaters nearby: However; both aspects of selkie \"community\" (do-\nEach venerable leader of a selkie community can cast the follow-\nmestic and provider) are equally respected within the lair; and no\nonce per\none\nper round: augury, cure light\nwounds, and cure disease. Leaders can also cast weather\nSum -\nsex is accorded undue privileges\nSelkies inhabit only colder waters and there are both saltwater\nmoning and control weather\nonce per week. Selkies fear the\nand freshwater varieties. Selkies almost always build their lairs in\nwrath of the sea should they ever use their powers for ill.\nunderwater caverns and grottos containing both air and\nwater-filled regions\nselkie young must be raised in an air-filled\nenvironment for about their first\nAs mentioned earlier, selkies often find and explore wrecks of\nsunken treasure. Most selkie communities have hoarded at least\nsome booty (especially pearls) , keeping those otherwise useless\ntrinkets only for purposes of trade with the overworld.\nOnly\nVery\nAny\nfrom\nlegs\nthey\nthey\ngood\nsupplies\nfine\nthey\nspell\nspells\nfine\ning\nthey\nspeed\nthey\nget\nthey\nfrom\npelts\nThey\nspells\nday;\nspell\ning\nhuge ,\nyear;",
  "frequency": "rare",
  "organization": "Solitary or tribal",
  "diet": "Omnivore",
  "intelligence": "Average to exceptional (8-16)",
  "treasure_type": "A (magic only) _",
  "alignment": "Neutral (good)",
  "number_appearing": "Tor 12-30",
  "ac": "5 (10 base in human form)",
  "movement": "12 , Sw 36",
  "hit_dice": "3+3",
  "thac0": "17",
  "damage": "1-6 or by weapon type",
  "special_attacks": "Nil",
  "special_defenses": "Can change into human form",
  "magic_resistance": "Nil",
  "size": "M (5'-6' in either form",
  "morale": "Steady (11-12)",
  "xp_value": "120",
  "id": "selkie_cold_to_subarctic_waters"
}