{
  "name": "Spectre",
  "source_page": 125,
  "raw_text": "Spectre\nCLIMATETERRAIN:\nDesolate dungeons and ruins\nFREQUENCY:\nRare\nORGANIZATION:\nSolitary\nACTIVITY CYCLE:\nDarkness and night\nDIET:\nNil\nINTELLIGENCE:\nHigh (13-14)\nTREASURE:\nQ(x3), X, Y\nALIGNMENT:\nLawful evil\nNO:\nAPPEARING:\n1-6\nARMOR CLASS:\n2\nMOVEMENT:\n15, FI 30 (B)\nHIT DICE:\n7+3\nTHACO:\n13\nNO. OF ATTACKS:\nDAMAGEIATTACK:\n1-8\nSPECIAL ATTACKS:\nEnergy drain\nSPECIAL DEFENSES:\n+1 or better weapon to hit\nMAGIC RESISTANCE:\nSee below\nSIZE:\nM (6' tall)\nMORALE:\nChampion (15)\nXP VALUE:\n3,000\nSpectres are powerful undead that haunt the most desolate and\nto drain mortals of life. This lead spectre is known as the master\ndeserted of places\nhate all life and light.\nspectre (always with maximum hit points per die), while the oth-\nSpectres appear as semitransparent beings and are often mis-\ners are known collectively as the followers. In this arrangement\ntaken for haunts or\nghosts. Unlike most undead, spectres retain\nthe master spectre almost never engages enemies personally but\nthe semblance and manner of dress of their former life and can be\ninstead sends his minions in for the kill. Mortals drained of life by\nrecognized by old friends or through paintings of the persons they\nfollower spectres are subservient to the master spectre, not the\nused to be.\nfollowers. Note that if the master spectre is slain, all followers be-\ncome independent and can travel anywhere they wish in\nof\nCombat:\nSpectres\nexist  primarily\non   the Negative Material\nbecoming master spectres themselves. Once a character becomes\nplane and can therefore be attacked by beings on the Prime Mate-\nspectre\nrecovery is nearly impossible, requiring a special quest .\nrial plane only with magical weapons\nDaylight makes spectres\nSpectres hate light and all\nas both remind them of their un-\npowerless by weakening their ties to the Negative Material plane_\ndead existence. They are therefore encountered only in places of\nThe chilling touch of a spectre drains energy from\ncrea-\nextreme darkness and desolation, like long-abandoned ruins,\ntures. A successful attack inflicts 1-8 points of damage and drains\ndungeons, and subterranean sewers_\ntwo life energy levels from the victim . Any being totally drained of\nContrary to\nmythology; spectres remain highly intelli-\nlife energy by a spectre becomes a full-strength spectre under the\ngent and generally rational after the transformation to undeath\ncontrol of the spectre which drained him. The victim loses all con -\nLife makes them lament their unlife, and\nbear a strong hatred\ntrol of his personality and may become more or less powerful than\nfor all those lucky\nenough to live and truly die.\nbefore, depending on his level and class before becoming a spectre.\nSpectres have enough cunning to plan their attacks, and rival\nSpectres are immune to all sleep, charm, hold, and cold-based\nvampires in their skill at remaining hidden from the general popu-\nspells, as well as poisons and paralyzation attacks. Holy water in -\nlace\nflicts 2-8 points of damage when it strikes a spectre. The water can\nbe splashed on\nspectre successfully:\nA raise dead\nappar-\nEcology:\nNo one knows who the first spectre was\nOr\nhow it\nently reverses the undead status, destroying the spectre immedi-\ncame t0\nthe few facts detailed above are all that is known with\nately if a saving throw versus\nis failed.\nany\ndegree of certainty:\nHabitat Society:\nMost spectres are solitary; but some enclaves\nexist where a particularly powerful or lucky spectre has managed\nThey\nhopes\nlife ,\nliving\npopular\nthey\nspell\nbe;\nspell",
  "climate_terrain": "Desolate dungeons and ruins",
  "frequency": "Rare",
  "organization": "Solitary",
  "activity_cycle": "Darkness and night",
  "diet": "Nil",
  "intelligence": "High (13-14)",
  "treasure_type": "Q(x3), X, Y",
  "alignment": "Lawful evil",
  "ac": "2",
  "movement": "15, FI 30 (B)",
  "hit_dice": "7+3",
  "thac0": "13",
  "damage": "1-8",
  "special_attacks": "Energy drain",
  "special_defenses": "+1 or better weapon to hit",
  "magic_resistance": "See below",
  "size": "M (6' tall)",
  "morale": "Champion (15)",
  "xp_value": "3,000",
  "id": "spectre"
}