{
  "name": "Sprite Meadows and woods",
  "source_page": 127,
  "raw_text": "Sprite\nCLIMATEITERRAIN:\nMeadows and woods\nFREQUENCY;\nRare\nORGANIZATION:\nTribal\nACTIVITY CYCLE:\nDIET:\nOmnivore\nINTELLIGENCE:\nVery (11-12)\nTREASURE:\nC\nALIGNMENT:\nNeutral (good)\nNO: APPEARING:\n10-100 (10d10)\nARMOR CLASS:\nMOVEMENT:\nFl 18 (B)\nHIT DICE:\nTHACO:\n19\nNO: OF ATTACKS:\nDAMAGEIATTACK:\n1-4 (sword) or 1-3 (arrow)\nSPECIAL ATTACKS:\nSee below\nSPECIAL DEFENSES:\nSee below\nMAGIC RESISTANCE:\nNil\nSIZE:\nS (2' tall)\nMORALE:\nSteady (11-12)\nXP VALUE:\n420\nSprites are shy and reclusive faerie people who dwell in meadows\nand wooded glens.\nhave distinctly elven features and small,\nsemitransparent wings\nTheir\nointment is concocted from forest mushrooms. The\nCombat:\nSprites hate all evil and ugliness and are quite capable\nointment must be left to sit in the sun for seven\nand the\nof stout militancy should their secluded homes be invaded by orcs\nsprites\nhollowed out many tree stumps as containers for this\nOr worse .\nfight with\nslim swords which do damage as\nrare substance.\nhuman-size dagger, or their own\nbows which have\nSprites never die unless\nare killed, as\nare one of the\nrange half that of a human short bow and do only half as much\nfew races that are truly immortal\nTheir small size and dangerous\ndamage (i.e., 1-3 points). The tips of their arrows, however, are\nenvironment\nthe sprite population to\na minimum.\ncoated  with\nspecial   ointment\nconcocted   especially by\nthe\nFortunately; the sprites keep a watch on their fellow sprites, for\nsprites.\ncreature struck by these arrows,\nregardless of level\nthe inevitable gatherings, celebrations, and parties, and\na de-\nor magic resistance, must save versus poison or fall into a deep\nserted meadow or glen is never deserted for more than a decade\nsleep lasting 1-6 hours. Normally sprites won't do anything more\nbefore a new clan of sprites moves in.\nthan remove their victims to a place very far away (often dispos-\nSprites usually speak only their own language, common , and\nsessing them of weapons in the process) , but evil creatures may be\nelven , but seem to get along with woodland mammals and other\nslain .\ncreatures anyway: In the human world, sprites are sometimes\nSprites can become invisible at will and detect good/evil within\nmistaken for butterflies at a distance, S0 it is guessed that perhaps\n50 yards, so\nare hard to deceive, evade, Or capture. When in-\nthe majority of forest creatures likewise think of the fair sprites in\nvisible, sprites\n+2 to hit against their bewildered opponents\nthis way:\nand are attacked with a\n4 penalty to hit.\nSprites are very flighty like most faerie-kind\nand are hard to\nwith once\nare found. Even the elves\nare not fast allies with the sprites, for sprites find elves much too\nserious about most woodland affairs.\nOnly druids, who are sometimes able to magically summon\nsprites, deal with these creatures on a\nbasis. Some druids\neven receive at least some of their training in the company of a\nfew sprites. In fact, most sprites love druids, for their neutral\nalignment and views on evil make them see the forest much the\nsame\nSprites are loosely tribal, electing the best warrior among the\ngroup (male or female) as the group spokesman. This leader is\nrecognized as the one who makes major decisions and bargains\nwith druids and elves. Sprites rarely wait for their leader's deci-\nsion when\nshould,\nas any\nwandering orc starts\na race\nfor\nglory after the offensive beast\nThe leader is often left in the back-\nwash; just beginning to order the attack\nIn the typical sylvan setting, sprites have assumed the\ntask\nEs?lofmonitorigpeadowsandegleng, andthe open espaneses oâ‚¬\nforests_\nDay\nThey\nsleep\ndays,\nhave\nlong,\nThey\nspecial\nthey\nthey\nkeep\nAny\nthey\nget\nHabitat Soce   bargain\nthey\nregular\nthey",
  "frequency": "Rare",
  "organization": "Tribal",
  "diet": "Omnivore",
  "intelligence": "Very (11-12)",
  "treasure_type": "C",
  "alignment": "Neutral (good)",
  "number_appearing": "10-100 (10d10)",
  "movement": "Fl 18 (B)",
  "thac0": "19",
  "special_attacks": "See below",
  "special_defenses": "See below",
  "magic_resistance": "Nil",
  "size": "S (2' tall)",
  "morale": "Steady (11-12)",
  "xp_value": "420",
  "id": "sprite_meadows_and_woods"
}