{
  "name": "Treant",
  "source_page": 129,
  "raw_text": "Treant\nCLIMATE TERRAIN:\nforest\nFREQUENCY;\nRare\nORGANIZATION:\nGrove\nACTIVITY CYCLE:\nDIET:\nPhotosynthesis\nINTELLIGENCE:\n(11-12)\nTREASURE:\nQ (x5) X\nALIGNMENT:\nChaotic\nNO. APPEARING:\n1-20\nARMOR CLASS:\nMOVEMENT:\n12\nHIT DICE;\n7-12\nTHACO:\n13 (7-8 HD)\n11 (9-10 HD)\n9 (11-12 HD)\nNO.OF ATTACKS:\nDAMAGEIATTACK:\nVariable\nSPECIAL ATTACKS:\nSee below\nSPECIAL DEFENSES:\nNever surprised\nMAGIC RESISTANCE:\nNil\nSIZE:\nH (13'-18' )\nMORALE:\nChampion (15-16)\nXP VALUE:\n7 HD\n2,000 ( +1000 per Hit Die)\nTreants are strangely related to both humans and trees, combin-\nwith the more transient lifeforms (anything with a lifespan of 500\nfeatures of both species. Peaceful by nature, treants can cause\nyears\nOr\nless)_\nHumans   and\ndemihumans have  only\nslight\ngreat damage when roused to anger:\nhate evil\nand the\nchance of spotting\na treant who is trying to blend in with the\nunrestrained use of fire\ntrees. Rangers have\na fair chance of spotting a treant (10% per\nTreants are almost indistinguishable from trees. Their skin is a\nlevel)\nthick; textured, brown bark. Their arms are\ngnarled like branches\nTreants are intolerant of evil, particularly when fire and the\nand their\nfit together when standing like the trunk of a tree_\nwanton destruction of trees is involved\nhate orcs and\nAbove the eyes and along the head are dozens of smaller branches\nlins with a passion and tend to be suspicious of anyone carrying\nfrom which\nleaves . In winter the leaves of\na treant\nan ax\nchange color but rarely fall out. Treants are very intelligent and\nTreants have no use for treasure, and usually place all such\noften  speak\nnumber of languages including their\nown, elf ,\nitems somewhere out of sight, such as under a great rock: Occa-\ndwarf, common, and a smattering of just about all other human-\nsionally a treant can be convinced t0 give up his treasure but only\noid tongues (at least enough to say\n'Get out of my treesl\")\nwhen some great\nwill be\naccomplished by this generosity:\nCombat:\nThe combat ability of treants varies with their size_\nEcology:\nTreants, like all trees ,\nsustenance via photosyn-\ntreants (13 or 14 feet) have 7 or 8 Hit Dice and inflict 2-16\nthesis _\nTreants often sleep for\nperiods of time (anywhere\npoints of damage per attack. Middle-aged treants (15 or 16 feet)\nfrom a few days to several years)\nwhich short roots grow\nhave 9 or 10 Hit Dice, respectively; and inflict 3-18 points of dam-\ninto the ground beneath them gathering water and minerals from\nage per attack: Elder treants (17 or 18 feet) have 1l or 12 Hit Dice\nthe soil. Reproduction is via off-shoot stalks which the female\nand inflict 4-24 points of damage per attack:\ntreants then protect and care for until the stalks are grown.\nDue to their tough, barklike skin, treants have & superior Ar-\nThe lifespan of a treant is not known, but is several thousand\nmor Class\nalmost all weapons\nTheir only weak-\nyears at least. As\ngrow older; treants become slower and less\nness is fire.\nfire-based attack against a treant is at\n+4 to hit\nagile, sleeping for longer periods and talking less of things that are\nand\n+1 damage. In addition, treants save against all fire-based\nand more of\nthat were. Eventually an old treant will not\nattacks at\n4\nThis weakness t0 fire also\nto animated trees\nwake Up,\ntaking permanent root in the spot where he sleeps and\ncontrolled by a treant:\nout the rest of his life as a normal tree.\nTreants have the ability to animate normal trees.\ntreant\ncan animate Up to two trees. It takes one round for a normal tree\nto uproot itself. Thereafter the animated tree can move ata rate of\n3 per turn and fights as a full-grown treant (12 Hit Dice, two at-\ntacks, 4-24 points of damage per attack):\nA treant must be within\n60 yards of the tree it is attempting to animate. Animated trees\nlose their\nability to move if the treant who animated them is inca-\npacitated or moves more than 60 yards away:\nTreants (regardless of size) and treant-controlled trees can in-\nflict structural damage when attacking a building or fortification.\nHabitat Society:\nTreants   live  in\ncommunities,\nusually\namidst old hardwood forests (oak, maple, mahogany; etc.). In the\nforest treants rarely reveal themselves, preferring not to interact\nAny\nAny\nVery\ngood\ning\nthings\nThey\nThey\nlegs\ngob-\nhang\ngreat\ngood\ngain\nlong\nYoung\nduring\nthey\nrating\nagainst\nAny\nthings\napplies\nliving\nOne\nsmall",
  "climate_terrain": "forest",
  "frequency": "Rare",
  "organization": "Grove",
  "diet": "Photosynthesis",
  "intelligence": "(11-12)",
  "treasure_type": "Q (x5) X",
  "alignment": "Chaotic",
  "number_appearing": "1-20",
  "movement": "12",
  "hit_dice": "7-12",
  "thac0": "13 (7-8 HD)",
  "damage": "Variable",
  "special_attacks": "See below",
  "special_defenses": "Never surprised",
  "magic_resistance": "Nil",
  "size": "H (13'-18' )",
  "morale": "Champion (15-16)",
  "xp_value": "7 HD",
  "id": "treant"
}