{
  "name": "Unicorn",
  "source_page": 133,
  "raw_text": "Unicorn\nCLIMATETERRAIN:\nTemperate sylvan woodlands\nFREQUENCY:\nORGANIZATION:\nFamily\nACTIVITY CYCLE:\nDIET:\nHerbivorous\nINTELLIGENCE:\nAverage (8-10)\nTREASURE:\nX\nALIGNMENT:\nChaotic\nNO: APPEARING:\n1-6\nARMOR CLASS:\n2\nMOVEMENT:\n24\nHIT DICE:\n4+4\nTHACO:\n15\nNO:\nOF ATTACKS:\nDAMAGEIATTACK:\n1-6/1-6/1-12\nSPECIAL ATTACKS:\nCharge\nSPECIAL DEFENSES:\nSee below\nMAGIC RESISTANCE:\nNil\nSIZE:\nL\nMORALE:\nElite (14)\nXP VALUE:\n650\nUnicorns dwell only in temperate woodlands, away from human\nhabitation. These fierce but\ncreatures shun contact with all\nbut sylvan creatures (dryads, pixies, sprites,\nand the like); how-\never, they will show themselves to defend their woodland home\nTravelers may pass through a unicorn's forest freely and even\nPowerful steeds with gleaming coats of pure white hair, uni-\nhunt there, but anyone killing for sport or damaging the forest\ncorn eyes are usually deep sea blue or\npink\nsilky\nmaliciously   will\nbe   attacked\nif the   unicorn\nis   nearby (10%\nwhite strands of hair\ndown From the mane and forelock\nchance) . The ferocity of this attack is determined by the evil of the\nsingle ivory-colored horn , 2 to 3 feet in length, grows from the\ntrespasser: Truant youths throwing stones at animals, for exam-\ncenter of each unicorn's forehead. Males are distinguished by the\nple, would be driven off with just a few bruises as\nreminder;\nwhite beard beneath the chin; females by their more elegant and\nwhile pillaging orcs would be hunted down and slain\nslimmer musculature. The hooves of\na unicorn are cloven and\nLone unicorns occasionally allow themselves to be tamed and\nyellow-ivory in color: Unicorns speak their own language as well\nridden by a\nor elf maiden of pure heart and\nalign -\nas those of other sylvan creatures and elves.\nment_\nA unicorn that submits once and is treated kindly will act\nas the maiden's steed for life, even carrying her beyond the realm\nCombat:\nUnicorns can sense an enemy\n240 yards away:\nof his forest if she s0 desires. Unicorns make exceptionally loyal\nLikewise , unicorns move very silently so opponents are\nmounts and will protect their riders even unto death:\nized -6 on their\nsurprise rolls. Unicorns can kick with their front\nhooves and thrust with the horn each round\nDue to the horn's\nEcology:\nUnicorns are herbivores, living on tender leaves and\nmagical nature, it always has\n+2 bonus to hit. Unicorns can\ngrasses. Their only enemies are griffons and those creatures who\ncharge into battle,  using the horn like\na lance .\nTo make this\ndestroy forests, in particular red dragons and orcs.\ncharge, there must be at least 30 feet of open space between the\nThe life span of unicorns has never been recorded but is known\nunicorn and his opponent. Opponents struck by\ncharging uni-\nto surpass 1,000 years. They are believed to maintain their youth\ncorn suffer 3-36 points of damage from impaling; Unicorns may\nuntil death is only weeks away: The secret to this longevity is the\nnot attack with their front hooves in the round\ncharge.\nstrong magical nature of the horn. Unicorn horns are highly\nOnce per\na unicorn can use a\nteleport\nof limited range.\nsought after; since possession ofone is a sovereign remedy against\nThis\nwill transport the unicorn (and its rider) to any place\nall poisons. Alternately\nsingle horn can be used, by an alche-\nthat the unicorn desires, up to 360 yards away: Unicorns often use\nmist, to manufacture 2-12 potions of healing: Unicorn horns sell\nthis ability as a last resort to avoid death or capture:\nfor 1,500\npieces Or more on the open market.\nIn addition , unicorns can never be charmed or held by magic.\nThey are immune to death\nand make all saving throws\nagainst\nas if\nwere wizards of lth level. Unicorns are\nimmune t0 poison.\nHabitat Society:\nUnicorns mate for life and make their home in\nan open dell of the forest\nhave chosen to protect. There, in\nthe boles of the trees, unicorns etch a\nglyph, recognizable to syl-\nvan creatures, indicating that the forest is under unicorn protec-\ntion. Rangers   have\n10 %\nchance\nper   level\nof   determining\ncorrectly whether a forest is guarded by unicorns\nOnce & wood-\nland has & unicorn protector; no other unicorn will enter that for-\nest unless the forest is very large. Each family of unicorns stakes\nout\nterritory approximately 400 square miles (20 miles by 20\nmiles) .\nRare\nDay\ngood\ngood\nLong;\nfiery\nhang\ngood\nhuman\nfrom\npenal-\nthey\nspell\nday\nspell\ngold\nspells\nspells\nthey\nthey",
  "climate_terrain": "Temperate sylvan woodlands",
  "organization": "Family",
  "diet": "Herbivorous",
  "intelligence": "Average (8-10)",
  "treasure_type": "X",
  "alignment": "Chaotic",
  "number_appearing": "1-6",
  "ac": "2",
  "movement": "24",
  "hit_dice": "4+4",
  "thac0": "15",
  "damage": "1-6/1-6/1-12",
  "special_attacks": "Charge",
  "special_defenses": "See below",
  "magic_resistance": "Nil",
  "size": "L",
  "morale": "Elite (14)",
  "xp_value": "650",
  "id": "unicorn"
}