{
  "name": "Vampire Any land",
  "source_page": 134,
  "raw_text": "Vampire\nCLIMATEITERRAIN:\nAny land\nFREQUENCY:\nRare\nORGANIZATION:\nSolitary\nACTIITY CYCLE:\nNight\nDIET:\nSpecial\nINTELLIGENCE:\nExceptional (15-16)\nTREASURE:\nF\nALIGNMENT:\nChaotic evil\nNO. APPEARING:\n1-4\nARMOR CLASS:\nMOVEMENT:\n12 , Fl 18 (C)\nHIT DICE:\n8 +3\nTHACO:\n13\nNO. OF ATTACKS:\nDAMAGEIATTACK:\n5-10\nSPECIAL ATTACKS:\nEnergy drain\nSPECIAL DEFENSES:\n+1 or better magical weapon\nto hit\nMAGIC RESISTANCE:\nSee below\nSIZE:\nM (51/2'-61/2')\nMORALE:\nChampion (16)\nXP VALUE:\nWestern\n3,000\nEastern\n4,000\nOf all the chaotic\nundead creatures that stalk the world, none\nable to reach its coffin within 12 turns, however; its essence\nis more dreadful than the vampire. Moving silently through the\nbreaks Up and the creature is truly destroyed.\nnight, vampires prey upon the\nwithout mercy Or compas-\ncharm, and hold\ndo not affect vampires. Similarly;\nsion . Unless\nunderground,\nmust return to the coffins in\nare unharmed by poisons and immune to paralysis. Spells\nwhich\npass the daylight hours, and even in the former case\nthat are based on cold or\nelectricity cause only half damage\nmust occasionally return t0 such to rest, for their power is re-\nAtwill, vampires are able to disperse their bodies into clouds of\nnewed by contact with soil from their graves.\nelemental vapor and assume gaseous form. In this state, they are\nOne aspect that makes the vampire far more fearful than many\nall but immune to attack and can escape from almost any confine-\nofits undead kindred is its appearance. Unlike other undead crea\nment. In addition, vampires can shape change s0 as to take on the\ntures, the vampire can easily pass among normal\nmen\nwithout\nform of a\nbat (hence the flying movement rate given above).\ndrawing attention to itself for, although its facial features are\nVampires can summon lesser creatures for aid. In a subterra-\nsharp and feral,\ndo not seem inhuman. In many cases,\nnean environment,\nwill typically\nforth\na swarm of 10-\ntrue nature is revealed only when it attacks.\n100 rats or bats. In the case of the latter; these do not physically\nThere are ways in which\nvampire may be detected by the\nattack but serve t0 confuse and obscure the vision of the\nVam-\ncareful observer, however. Vampires cast no reflection in a glass,\npire s foes. In the wilderness\nvampire will normally call upon 3-\ncast no shadows, and move in complete silence.\n18 wolves for assistance. In all cases, the summoned animals\narrive in 2-12 rounds\nCombat:\nWhen engaging in combat, vampires are savage and\nAt will, a\ncan use a\nspider climb ability and scale sheer\nfearsome opponents.\nare physically very powerful;\nwith\nsurfaces\nOften ,\nwill employ this power to\naccess to\nStrength score of 18/76, receiving a bonus of +2 to hit and +4to\nrooms on upper\nwithout alerting those on watch down-\ndamage. The crushing blows of a vampire s attack are so fierce\nstairs. This power also permits the\nto seek\nin\nthat\ninflict 5-10 points of damage.\nplaces which are all but beyond the reach of mortal men.\nThe gaze of a vampire is one of its most powerful and danger-\nDespite the great powers which vampires obviously possess\nous weapons\nperson who allows the vampire to look into\nare not without weaknesses of their own. The odor of strong\nhis eyes will be affected as if by a charm person\nDue to the\ngarlic_\nthem and\nwill not approach it. Further; they will\npower of this enchantment,\na -2 is\napplied to the victim'$ saving\nrecoil from the face of a mirror or lawful\nholy symbol if ei-\nthrow versus\nIn this manner,\nvampires are often able to pass\nther of these is presented to them with courage and conviction. It\nposted sentries and\ntheir chosen victims.\nis important to understand, however; that this will not actually\nLike all undead creatures, vampires exist in both the Positive\nthe vampire in any way nor drive it off. Garlic will prevent\nMaterial and Negative Material planes at the same time\nTheir\nthe creature from\nattacking or entering the area, while mirrors\npowerful negative essence allows them to drain two life energy\nand holy symbols force the vampire to find some means of re-\nlevels from anyone\nstrike. If the vampire is making use of\nmoving the offending object before it can be bypassed. In most\nsome form of weapon in the attack, it cannot employ this power:\ncases, the vampire will seek to overcome these hazards with the\nWeapons of less than +1 enchantment pass through vampires\naid ofits minions. For example, a charmed person might be called\nwithout harming them in any way: Even if attacked with and\nupon to attack someone who is holding the\nvampire at\nwith a\nharmed by magical weapons, vampires regenerate 3 hit points per\nholy symbol.\nAnother important point to\nin mind is that a\nround. If reduced to zero hit points, & vampire is not destroyed,\nlawful\nholy symbol will affect the vampire regardless of the\nbut is forced to assume gaseous form. Once in this state, it will at-\nvampire $   original religious background. Vampires   which\nare\ntempt to flee and return to its coffin where, after eight hours of\nsplashed with a vial of holy water or struck with lawful\nholy\nrest, it\nregains its corporeal form. If the defeated vampire is un-\nsymbols are burned by them, suffering 2-7\nof damage.\nevil\nspells\nliving\nSleep,\nthey\nthey\ndeep\nthey\nthey\nlarge\ncall\nthey\nthey\nvampire $\nvampire\ngain\nthey\nThey\nfloors\nrefuge\nvampire\nthey\nthey\nAny\nspell .\nrepels\nthey\ngood\nspell.\nsurprise\nharm\nthey\nbay\nkeep\ngood\ngood\npoints",
  "frequency": "Rare",
  "organization": "Solitary",
  "diet": "Special",
  "intelligence": "Exceptional (15-16)",
  "treasure_type": "F",
  "alignment": "Chaotic evil",
  "number_appearing": "1-4",
  "movement": "12 , Fl 18 (C)",
  "hit_dice": "8 +3",
  "thac0": "13",
  "damage": "5-10",
  "special_attacks": "Energy drain",
  "special_defenses": "+1 or better magical weapon",
  "magic_resistance": "See below",
  "size": "M (51/2'-61/2')",
  "morale": "Champion (16)",
  "xp_value": "Western",
  "id": "vampire_any_land"
}