{
  "name": "Wight",
  "source_page": 136,
  "raw_text": "Wight\nCLIMATETERRAIN:\nland\nFREQUENCY;\nUncommon\nORGANIZATION:\nSolitary\nACTIVITY CYCLE:\nNight\nDIET:\nSee below\nINTELLIGENCE:\nAverage (8-10)\nTREASURE:\nB\nALIGNMENT:\nLawful evil\nNO. APPEARING:\n2-16 (2d8)\nARMOR CLASS:\nMOVEMENT:\n12\nHIT DICE:\n4+3\nTHACO:\n15\nNO. OF ATTACKS:\nDAMAGEIATTACK:\n1-4\nSPECIAL ATTACKS:\nEnergy drain\nSPECIAL DEFENSES:\nHit only by silver or +1 or\nbetter\nmagical weapon\nMAGIC RESISTANCE:\nSee below\nSIZE:\nM (4'-7\"')\nMORALE:\nElite (14)\nXP VALUE:\n975\nIn ages\npast, the word \"wight\" meant simply\n'man:\" As the\ncenturies have passed, though, it has come to be associated only\nwith those undead that typically inhabit barrow mounds and cat-\nHabitat Society:\nLike the other undead that infest the world,\nacombs.\nwights live in barrow mounds, catacombs, and other sepulchral\nFrom a distance, wights can easily be mistaken for any number\nplaces.\ndespise light and places which are vibrant with liv-\nof humanoid races. Upon closer examination, however, their true\ning things. As a rule, the wight is hateful and evil, seeking to sat-\nnature becomes apparent: As undead creatures, wights are night-\nisfy its hatred of life by killing all those it encounters.\nmarish reflections of their former selves, with cruel, burning eyes\nAlthough wights are often found in small groups,\nare ac-\nset in mummified flesh over\ntwisted skeleton with hands that\ntually solitary\ncreatures\nWithout exception, encounters with\nend in sharp claws:\nmultiple wights\nbe a single leader and a number of lesser crea-\ntures which it has created t0 serve it. In these cases, the leader of\nCombat:\nWights are\nand deadly foes in combat: When at-\nthe group will be more than willing to sacrifice some or all of its\ntacked,\nare\nunharmed by any weapons that are not forged\nminions to assure its own survival or victory:\nfrom silver or enchanted in some manner:\nThe wight attacks with its jagged claws and powerful blows, in-\nEcology:\nLike all undead, wights exist on both the Prime Mate-\nflicting 1-4 points of damage with each successful strike: In addi-\nrial and Negative Material planes simultaneously It is this power-\ntion to this physical harm, the wight is able to feed on the life\nful link\nto the negative world that gives them their fearsome\nessence of its foes. Each blow that the wight lands drains one level\nlevel-draining ability: Further; it is this draining which provides\nfrom the victim , reducing Hit Dice, class bonuses,\nabilities\nthem with sustenance.\nand s0 forth. Thus,\nOth-level wizard struck by a wight loses 1-4\nAs they are not living creatures and have no\nrightful place in\nhit\nand becomes an 8th-level wizard; he has the\nand hit\nour\nworld\nmany animals can sense the wights presence.\npoints of an 8th-level wizard and he fights as an 8th-level wizard.\nwill growl or howl with alarm\nhorses will refuse t0 enter an area\nPersons who are slain by the energy draining powers of a wight\nwhich wights inhabit, and birds and insects will grow silent when\nare doomed to rise again as wights under the direct control of\nthe creature passes near them. In addition, their presence will\ntheir slayer. In their new form,\nhave all the powers and abili-\ngradually cause the plant life around their lairs to wither and die,\nties of a normal wight but half their Hit Dice. If the wight who\nmarking the region as unclean.\n\"created\" them is slain;\nwill instantly be freed of its control\nand\nportion of its power, acquiring the normal 4 +3 Hit\nDice of their kind, Once a character becomes a wight, recovery is\nnearly impossible, requiring & special quest.\nWights are unaffected by sleep, charm, hold or cold-based\nspells. In addition ,\nare not harmed by poisons Or paralyza-\ntion attacks\nWights can be engaged and defeated by individuals who are\nwell prepared for battle with them . Physical contact with holy\nwater is deadly to wights and each vial splashed on one burns it\nfor 2-8 points of damage. In addition, a raise dead\nbecomes a\npowerful weapon if used\nthe wight. Such magic is in-\nstantly fatal to the creature, utterly annihilating it.\nWights cannot tolerate bright light, including sunlight, and\nit at all costs. It is important to note, however; that wights\nare not harmed by exposure to sunlight as vampires are.\nAny\nlong\nThey\nthey\nwill\nfierce\nthey\nspell\nDogs\nspells\npoints\nthey\nthey\ngain\nthey\nspell\nagainst\navoid",
  "climate_terrain": "land",
  "frequency": "Uncommon",
  "organization": "Solitary",
  "activity_cycle": "Night",
  "diet": "See below",
  "intelligence": "Average (8-10)",
  "treasure_type": "B",
  "alignment": "Lawful evil",
  "number_appearing": "2-16 (2d8)",
  "movement": "12",
  "hit_dice": "4+3",
  "thac0": "15",
  "damage": "1-4",
  "special_attacks": "Energy drain",
  "special_defenses": "Hit only by silver or +1 or",
  "magic_resistance": "See below",
  "size": "M (4'-7\"')",
  "morale": "Elite (14)",
  "xp_value": "975",
  "id": "wight"
}