{
  "name": "Will 0'wisp",
  "source_page": 137,
  "raw_text": "Will 0'wisp\nCLIMATETERRAIN:\nswamp\nFREQUENCY:\nUncommon\nORGANIZATION:\nSolitary\nACTIVITY CYCLE:\nNight\nDIET:\nSee below\nINTELLIGENCE:\nExceptional (15-16)\nTREASURE:\nZ\nALIGNMENT:\nChaotic evil\nNO: APPEARING:\n1 or 1-3\nARMOR CLASS:\n-8\nMOVEMENT:\nFl 18 (A)\nHIT DICE:\nTHACO:\n11\nNO. OF ATTACKS:\nDAMAGEIATTACK:\n2-16\nSPECIAL ATTACKS:\nSee below\nSPECIAL DEFENSES:\nSee below\nMAGIC RESISTANCE:\nSee below\nSIZE:\nS (2'-4')\nMORALE:\nFanatic (17)\nXP VALUE:\n3,000\nThe will 0'\nis\nmalevolent entity that makes its home in\nswamps,\nand\nmoors.\nIt subsists by\nunsuspecting\ncreatures t0 their deaths amid the natural hazards of such places\nand feeding on the energies which their death struggles release\nany treasure which it may have. It is important to note, however,\nWhen encountered in the wild , will 0\nnormally appear as\nthat the chaotic alignment of the will 0\ncan make any agree-\nfaintly glowing balls of light: They can alter their own color;\nment with the creature uncertain.\nand size t0 some extent and can be easily mistaken for lan -\nterns,\nlight spells, and similar sources of artificial illumination.\nHabitatiSociety:\nFor the most part, will 0\nwill be found\nIf they do not attack; will 0' wisps are able to utterly blank out\non their own . On rare occasions (10 % ofthe time) groups of up to\ntheir glows, rendering them invisible to all those who cannot spot\nthree may be found near a particularly fertile hunting ground. In\ninvisible objects, for 2-8 melee rounds.\nthe latter case ,\nwill work together to trick victims into the\nThe will 0\nlanguage is a most unusual one, being purely\ntraps which they have arranged\noptical in nature\nAll communication between will 0'wisps is by\nmeans of\nchanges in color or brightness, many of which are far\nEcology:\nAlthough difficult to say with certainty; evidence indi-\ntoo subtle for the average observer t0 notice. Because this form of\ncates that the will 0\nfeeds on the\nof electrical activity\nexchange is almost impossible to mimic, it is very difficult for\ngiven off by the brains of panic stricken individuals as\nrealize\ntravelers to communicate with these creatures. Exceptional exam-\nthat death is inescapable. In order to prolong the suffering of their\nples of this race\nmastered\na very simple sound-based lan -\nvictims and increase the amount of\n'food\" which\ngive off,\nguage.\nproduce sounds by vibrating very rapidly and thus\nwill typically lure their victims into areas like quick-\nhave a shallow and ghostly-sounding voice when\n\"speak\nsand pits which promise a slow and frightening death.\nIt seems certain that the unusual environment found in\nCombat:\nAs a rule, will 0\nseek to avoid physical combat\nand swamps is important to the creature $ existence in some way;\nwith other creatures, preferring to lead them to their deaths in the\nbut the exact nature of this link is uncertain. It seems probable\nswamps around them instead\nWhen pressed, however,\nare\nthat the ominous and haunting nature of these places increases\ndangerous adversaries who must be attacked with the greatest\nthe fear and dread which their victims feel, and thus the energy\ncare\nIn combat,\nglow blue, violet, or pale green .\nwhich\ngive off prior to death:\nWill 0'wisps are very versatile flyers.\ncan hover in place\nwithout effort, often looking like lanterns Or similar beacons to\nlure others toward them. When they decide to move, they can do\nso with rapid bursts of speed or slow drifting movements\nA will 0 wisp's main weapon in combat is its ability to manifest\npowerful electric\nIn melee, it swoops at its foe and at-\ntempts to brush against the victim, discharging the stored energy:\nA\nsuccessful strike by one of these creatures\ncause 2-16 points\nof damage.\nThose   attacking\nwill\nwith any form\nof physical\nweapon are able to inflict damage normally: Persons making use\nof magical attacks, however, will find their powers almost inef-\nfective against them. As a rule, the only\nwhich have any ef-\nfect on the will 0\nare\nprotection from evil, magic missile, and\nmaze.\nA will 05\nwhich is reduced to 5 or fewer hit points\nattempt to escape. If it is unable to flee, the creature will sur-\nrender to its attackers and attempt to\nits safety by offering up\nAny\n'wisp\nbogs,\nluring\n'wisps\n\"wisp\nshape,\n'wisps\nthey\n'wisp\nfury\nwisp\nthey\n'have\nthey\nThey\nwill\n\"wisps\nthey\nbogs\n\"wisps\nthey\nthey\nthey\nThey\ncharge.\nwill\n'wisp\nspells\n) wisp\n'wisp\nwill\nbuy",
  "climate_terrain": "swamp",
  "frequency": "Uncommon",
  "organization": "Solitary",
  "activity_cycle": "Night",
  "diet": "See below",
  "intelligence": "Exceptional (15-16)",
  "treasure_type": "Z",
  "alignment": "Chaotic evil",
  "number_appearing": "1 or 1-3",
  "ac": "-8",
  "movement": "Fl 18 (A)",
  "thac0": "11",
  "damage": "2-16",
  "special_attacks": "See below",
  "special_defenses": "See below",
  "magic_resistance": "See below",
  "size": "S (2'-4')",
  "morale": "Fanatic (17)",
  "xp_value": "3,000",
  "id": "will_0_wisp"
}