{
  "name": "Wolfwere forest",
  "source_page": 139,
  "raw_text": "Wolfwere\nCLIMATEITERRAIN:\nforest\nFREQUENCY:\nRare\nORGANIZATION:\nSolitary\nACTIVITY CYCLE:\nAny\nDIET:\nCarnivore\nINTELLIGENCE:\nHigh to exceptional (13-16)\nTREASURE:\nB, 50 % of S, T\nALIGNMENT:\nChaotic evil\nNO. APPEARING:\n1-3\nARMOR CLASS:\nMOVEMENT:\n15\nHIT DICE:\n5+1\nTHACO:\n15\nNO_\nOF ATTACKS:\n1 or 2\nDAMAGEATTACK:\n2-12 and weapon\nSPECIAL ATTACKS:\nSinging\non\nlethargy\nSPECIAL DEFENSES:\nor +1 or\nweapon to\nhit\nMAGIC RESISTANCE:\n10 %\nSIZE:\nM (4'-7\")\nMORALE:\nElite (14)\nXP VALUE:\n2,000\nThe wolfwere is an evil and hateful creature that delights in the\nbrutal slaying of humans and demihumans alike. In many cases_\nthe wolfwere is able to attack its victims with utter surprise be-\ntered, wolfweres tend toward axes, swords, and similar cutting\ncause of its\nability to assume the shape of a human of exceptional\nedges.\ncharisma\nIF the creature is forced to engage in battle while in its human-\nThe wolfwere is able to assume a wide variety of shapes at will.\noid form, it will be forced t0 rely wholly on its weapons for de-\nTransformation from\none form to another takes only\nsingle\nfense\nIn such cases, it normally seeks to escape and transform\nround_\nIts true shape, and that in which it prefers to\nthe\nits half-humanoid state before returning to battle:\nvast majority of its time, is that ofa\nwolf\nWhen in this state,\nThe magical nature of the wolfwere makes it immune t0 dam-\nit is almost indistinguishable from\ndire woll.\nage   inflicted by\nany weapon\nwhich\nis\nnot\nmade   from\ncold\nWhen a wolfwere is attempting to lure humans or demihumans\nwrought iron or enchanted to +1 or better: All other weapons are\ninto an ambush, it will assume the shape of member of their race.\nsimply turned aside by the creature s hide.\nAlmost without exception, the new persona will not be of the\nIt is possible to protect oneself from\nattacks by wolfweres,\nsame sex as the potential victim. Thus, a wolfwere which is stalk-\nhowever, for\nare\ndisgusted by wolfsbane and will avoid it\nmale elf will transform itself into & female elf. In all cases\nwhenever possible_\nthe newly disguised\nwolfwere  will have exceptional physical\nbeauty:\nHabitatiSociety:\nThe wolfwere is generally fairly solitary in na-\nture. When encountered in the wild, it is rare that more than three\nCombat:\nThe wolfwere is a sly and dangerous adversary: In ad-\nof these creatures will be found_\nIn almost all cases, encounters\ndition to its great\nand fighting prowess, its high intelligence\nwith more than one wolfwere will be with a mated pair Or a group\nmust not be overlooked or underestimated.\nwhich has decided to work together to increase the success of\nWhen a wolfwere first\nunsuspecting humans or demihu-\ntheir hunting.\nmans in its territory; it will change into its fully humanoid form\nand assume the\nof a pilgrim, minstrel;\nor similar wanderer.\nThere is a 75 % chance that any encountered wolfwere\nThe wolfwere will normally carry some form of stringed instru-\nwill be running with a\nof wild wolves . In such cases, the ani-\nment which it seems to absent-mindedly play at while it travels\nmals will be Worgs 70 % of the time. If\nare not worgS,\nThe true nature of its song, however, is terrible and often fatal_\nwill be common wolves . In all cases, the influence of the wolfwere\nAnyone who hears the wolfwere $ song and then fails a saving\nwill make the creatures far more vicious and evil than\nmight\nthrow versus spell will be overcome with lethargy. The effects of\nnormally be_\nthis enchantment are the same as those of the slow\nOnce this\nDespite their fondness for wolves and worgs, wolfweres loathe\neffect begins, it cannot be countered and lasts for 5-8 rounds_\nthe company of werewolves. The enmity between these two mon-\nWhen a wolfwere is ready to attack, the creature\nchanges\nsters is S0 great that\nwill often attack each other on sight.\nits\nNow, in a form which is half-wolf and half-human (or\ndemihuman), it strikes. The wolfwere will almost always change\ninto this Form when it engages in combat because it has the ability\nto bite like a wolf and also wield & weapon of some type.\nIn any form but its fully humanoid one, the creature can deliver\nsavage bite with its powerful jaws. It is this mode of attack\nwhich the monster prefers to employ above all others.\nWhen in its humanoid or half-humanoid state, it is also able to\ncarry and employ weapons. Although the exact type of weapon\nused will depend upon the specific tastes of the creature encoun-\nAny\nbrings\nbetter\nIron\nspend\ninto\nlarge\nthey\ning\nfury\nspots\nguise\nEcology:\npack\nthey\nthey\nthey\nspell.\nagain\nthey\nshape",
  "frequency": "Rare",
  "organization": "Solitary",
  "activity_cycle": "Any",
  "diet": "Carnivore",
  "intelligence": "High to exceptional (13-16)",
  "treasure_type": "B, 50 % of S, T",
  "alignment": "Chaotic evil",
  "number_appearing": "1-3",
  "movement": "15",
  "hit_dice": "5+1",
  "thac0": "15",
  "damage": "2-12 and weapon",
  "special_attacks": "Singing",
  "special_defenses": "or +1 or",
  "magic_resistance": "10 %",
  "size": "M (4'-7\")",
  "morale": "Elite (14)",
  "xp_value": "2,000",
  "id": "wolfwere_forest"
}