{
  "name": "Wraith",
  "source_page": 140,
  "raw_text": "Wraith\nCLIMATETERRAIN:\nFREQUENCY:\nUncommon\nORGANIZATION:\nPack\nACTIVITY CYCLE:\nNight\nDIET:\nSpecial\nINTELLIGENCE:\n(11-12)\nTREASURE:\nE\nALIGNMENT:\nLawful evil\nNO. APPEARING:\n2-12 (2d6)\nARMOR CLASS:\nMOVEMENT:\n12, FI 24 (B)\nHIT DICE:\n5+3\nTHAC:\n15\nNO:\nATTACKS:\nDAMAGEIATTACK:\n1-6\nSPECIAL ATTACKS:\nEnergy drain\nSPECIAL DEFENSES:\nHit only by silver or + 1 or\nbetter magical weapon\nMAGIC RESISTANCE:\nNil\nSIZE:\nM (6' tall)\nMORALE:\nChampion (15)\nXP VALUE:\n3,000\nThe wraith is an evil undead spirit of a powerful human that seeks\nto absorb human life energy:\nThese horrible creatures are usually seen as black, vaguely\nHabitat Society:\nA wraith is an undead\nof a\npowerful, evil\nman-shaped clouds.\nhave no true substance, but tend to\nhuman, As such, it is usually found in tombs or places where such\nshape themselves with two upper limbs,\na torso, and a head with\nmen and women would have died_\nSince such men and women\ntwo glowing red eyes. This\nis & convenience born from the\nare frequently buried together; in the case of the wealthy, or with\nhabit of once having a human body\ntheir families , wraiths are most commonly encountered in packs.\nThose that died or were buried alone might still be encountered in\nCombat:\nThe touch of a wraith does damage in two ways.\npacks, because a human who dies from the touch of a wraith be-\nthe chilling effect of the touch inflicts 1-6 points of damage, even\ncomes a\nwraith under the sway of its slayer: The treasure of the\nto creatures immune to cold. Second, such a hit drains a level of\nwraith is usually its possessions in life, now buried with it, or\nexperience from its victim: This includes hit\nand all abili-\nthose of its victims. Wraiths exist only to perpetuate evil by ab-\nties associated with that level ,\nsuch as\ncasting Or combat\nsorbing the life force of as many people as possible. A character\nability: The damage from the chill can be healed normally but the\nwho becomes a wraith is nearly impossible to recover; requiring a\nexperience\nare gone forever and must be earned again or\nspecial quest:\nmagically restored.\nThe wraith cannot communicate, except through a\nwith\nWraiths are immune to normal weapons. An attack with such a\ndead\ndo not even seem t0 communicate with each\nweapon merely passes through its body with no effect. Silver\nother, except as master to slave for combat strategy:\nattempt\nweapons cause only half normal damage. Magical weapons in-\nto\nto a\nwraith is met with scorn, unless by a very powerful\nFlict their full damage, causing a black vapor to boil away from\nparty: In that case, the wraith desires only to flee: Wraiths can be\nthe body of the wraith_\nA wraith slowly regains its full hit\ndominated by powerful evil creatures, particularly other undead,\nif left alone for at least a week (recovering one point every eight\npriests, and wizards, and made to serve their\nhours) . Like most undead, wraiths are immune to\ncharm;\nhold, death and cold-based\nThey are immune to poison\nEcology:\nThe wraith has no proper niche, serving no useful pur-\nand paralyzation _\nA vial of holy water causes 2-8 points of dam-\npose in nature and providing no byproducts that others can use\nage (as acid) upon striking the body ofa wraith_\nAraise dead\nit requires no nourishment, killing only for the sheer hatred of\nwill utterly destroy one if a saving throw versus\nis failed\nlife. All creatures close to nature will shun the presence of\nWraiths attack humans or demihumans in preference to other\nwraith. It exists more in the Negative Material plane than in the\ncreatures. However; animals will sense their presence within 30\nPrime Material plane, and thus is not a natural part of this world.\nfeet and refuse to advance further; panicking if forced. A\nof\nwraiths will try to get surprise when attacking, and will wait and\nposition themselves for the most advantageous moment to at-\ntack. Wraiths are very intelligent and tend to cluster around the\nweaker members,\nor stragglers, when attacking:\nhuman\nkilled by a wraith becomes a half-strength wraith under its con-\ntrol (e.g.,\n1Oth-level fighter will become a 5 Hit Die wraith un-\nder the control of the wraith that slew him)_\nThis foul creature has no power in direct sunlight and will flee\nfrom it. Sunlight cannot destroy the wraith, but the undead crea-\nture cannot attack in sunlight. It shuns bright (e.g , continual)\nlight sources in general, but will occasionally attack if the com-\npulsion to do so is strong:\nAny\nVery\nOF\nspirit\nThey\nshape\nFirst ,\npoints\nspell\npoints\nspeak\nThey\nspell ,\nAny\nspeak\npoints\nwill;\nsleep,\nspells .\nspell\nspell\npack\nAny",
  "frequency": "Uncommon",
  "organization": "Pack",
  "activity_cycle": "Night",
  "diet": "Special",
  "intelligence": "(11-12)",
  "treasure_type": "E",
  "alignment": "Lawful evil",
  "number_appearing": "2-12 (2d6)",
  "movement": "12, FI 24 (B)",
  "hit_dice": "5+3",
  "damage": "1-6",
  "special_attacks": "Energy drain",
  "special_defenses": "Hit only by silver or + 1 or",
  "magic_resistance": "Nil",
  "size": "M (6' tall)",
  "morale": "Champion (15)",
  "xp_value": "3,000",
  "id": "wraith"
}