{
  "name": "Wyvern",
  "source_page": 141,
  "raw_text": "Wyvern\nCLIMATETERRAIN:\nTemperate mountain forests\nand jungles\nFREQUENCY:\nUncommon\nCC\nORGANIZATION:\nSolitary\nACTIITY CYCLE:\nDusk and dawn\nDIET:\nCarnivore\nINTELLIGENCE:\nLow (5-7)\nTREASURE:\nE\nALIGNMENT:\nNeutral (evil)\nNO. APPEARING:\n1-6\nARMOR CLASS:\nMOVEMENT:\n6, Fl 24 (E)\nHIT DICE:\n7+7\nTHACO:\n13\nNO: OF ATTACKS:\nDAMAGEIATTACK:\n2-16/1-6\nSPECIAL ATTACKS:\nPoison\nSPECIAL DEFENSES:\nNil\nMAGIC RESISTANCE:\nNil\nSIZE:\nG (35' long)\nMORALE:\nsteady (14)\nXP VALUE:\n2,000\nA distant cousin to the dragon, the wyvern is a\nflying lizard\nwith a poisonous stinger in its tail.\nThe 35-foot-long dark brown to gray body of the wyvern is\nstrike, and is willing to let prey g0 that is too powerful or within\nhalf tail . Its leathery batlike\nare over 50 feet from tip to tip.\neasy reach of cover: Such a wyvern understands that men, partic-\nThe head alone is 4 feet\nand filled with\nsharp teeth. Un-\nularly those armed in bright metal, are stronger than their size\nthe dragon, it has only hind\nusing them the same way a\nwould indicate. Given\nperfect opportunity it will attempt to\n'hunting bird would_\nThe tip of the tail is a thick knot of cartilage\nsnatch up an unarmored member and fly out of range.\nfrom which a 2 -\nfoot-long stinger protrudes, very much like that\nof a scorpion. The eyes are red or orange.\nA wyvern does not\nHabitat Society:\nThe wyvern is a solitary creature, nesting only\nhave & strong odor, although its lair might smell of a recent kill.\nwith its mate and young: It tends to lair on mountainsides that\nThese beasts can make two sounds; a loud hiss, which sounds like\noverlook forests, jungles, or sometimes plains. A wyvern makes\na hot sword plunged into water; and a low, deep-throated growl,\nits lair in\ncaverns that can be found in such places, staking\nmuch like that of a bull crocodile\nout a\nterritory about 25 miles across. If game is sparse, it will hunt\nwith a small group of its own kind: Only young wyverns attack\nCombat:\nRather stupid, but aggressive, wyverns will nearly al-\nothers of their kind, usually to establish new territory:\nOlder\nways attack: In combat, the wyvern always prefers to be flying,\nwyverns settle disputes in\nan unknown manner without actual\nand will seize any opportunity to take flight and continue com-\ncombat.\nbat. If trapped on the ground it will bite (2-16 points of damage)\nSome wyverns have been known to work with evil dragons.\nand use its stinger (1-6 points of damage), attacking the most con-\nUsually these   dragons   completely\ndominate the\nweaker   and\nvenient target Or targets. The tail is very mobile, easily striking\nsmaller wyverns\nover the back of the wyvern to hit an opponent to its front. The\nstinger injects poison (type F) into the wound, against which the\nEcology:\nAn adult wyvern consumes the equivalent of a man-\nvictim must make a save versus poison Or die. Even if the saving\nsized to\ncreature once per day. This could translate to\nthrow is successful, the victim suffers\npoints of physical dam-\nhorse, pig, Or a handful of sheep. While it eats them whole, the\nage from the sting:\nbones are not\ndigested, and neither are metal objects. The wyvern\nFrom the air the wyvern is a far more deadly opponent. It dives\neats carrion only if desperate.\nupon ground targets, attempting t0 snatch them up in its two tal-\nThe wyvern has no natural enemies, although it would not be a\noned claws (1-6 points of damage each) and fly off. Man-sized\nmatch for certain powerful creatures. It is noted for the foul taste\nvictims are snatched if at least one talon hits for damage.\nof its flesh. No one has found a way t0 cure its hide and the bones\nvictims require both talons to hit in order to snatch them up\nThe\nare\nlight and brittle to aid in flying. Certain body parts are used\nwyvern cannot fly while carrying anything\nAfter a dive, it\nby\ncasters as\ncomponents, for which\nwill pay a\ntakes the wyvern a full round to circle around. On the next round\nreasonable price.\nit can dive\nOnce  airborne with prey in its talons, the\nwyvern\nand bites each round, both at +4 to hit,\nthe\nvictim is motionless. In aerial combat, the wyvern will make a\npass during which it will either bite or sting. Then it will land and\nfeast, not hunting\nuntil the next\nAs\nhunter, the wyvern is cunning. It will avoid letting its\nshadow fall across its prey as a warning. The final approach of\nthe dive is done in complete silence, imposing a -2 surprise modi-\non the target: It trails its prey from downwind whenever pos-\nsible.\nA\nmature wyvern often waits for the right\nmoment\nto\nVery\nhuge\nwings\nlong\nlong'\nlike\nlegs,\nlarge\nlarge\n1-6\nLarge\nbigger:\nspell\nspell\nthey\nagain.\nstings\nuntil\nagain\nday:\nfier",
  "climate_terrain": "Temperate mountain forests",
  "frequency": "Uncommon",
  "organization": "Solitary",
  "diet": "Carnivore",
  "intelligence": "Low (5-7)",
  "treasure_type": "E",
  "alignment": "Neutral (evil)",
  "number_appearing": "1-6",
  "movement": "6, Fl 24 (E)",
  "hit_dice": "7+7",
  "thac0": "13",
  "special_attacks": "Poison",
  "special_defenses": "Nil",
  "magic_resistance": "Nil",
  "size": "G (35' long)",
  "morale": "steady (14)",
  "xp_value": "2,000",
  "id": "wyvern"
}