{
  "name": "Yeti",
  "source_page": 142,
  "raw_text": "Yeti\nCLIMATE TERRAIN:\nArctic hills and mountains\nFREQUENCY:\nrare\nORGANIZATION:\nClan\nACTIVITY CYCLE:\nDIET:\nCarnivore\nINTELLIGENCE:\nAverage (8-10)\nTREASURE:\nD\nALIGNMENT:\nNeutral\nNO: APPEARING:\n1-6\nARMOR CLASS:\nMOVEMENT:\n15\nHIT DICE:\n4+4\nTHACO:\n15\nNO. OF ATTACKS:\nDAMAGEIATTACK:\n1-6/1-6\nSPECIAL ATTACKS:\nSqueeze\nSPECIAL DEFENSES:\nImmune to normal cold,\ninvisible in snow and ice\nMAGIC RESISTANCE:\nNil\nSIZE:\nL (8' tall)\nMORALE:\nElite (13)\nXP VALUE:\n420\nSometimes confused with the abominable snowman , the\nis a\ndistant cousin to the\ncarnivorous apes of warmer climates.\nAn adult\nstands 8 feet tall and is covered in\nwhite fur:\nmade weapons, but will not make any themselves. Yeti live in ice\nTheir feet and hands are wide and flat, which helps to disperse\ncaves in hills and mountains. Sometimes these are natural, some-\ntheir\nweight (about 300 pounds) on treacherous snow fields_\ntimes\nare excavated by the\nor enlarged to accommodate\ntravel on all fours like the apes, but fight very comfortably\nthe family Most\ntreasure consists of items recovered\nthe\nstanding erect. Unlike most apes and gorillas, the\ndoes not\nbodies of explorers.\ntoe on its feet. They wear no clothing Or orna-\nLife is harsh in the arctic, and friends and food are hard to find,\nhaeretatiopp\n0PPChebleooe or stsetetofh\nis very subtle in cold cli-\nmaking survival and reproduction the\nonly goals. The\nmates, but in confined or warm areas, they have a strong, musky\nassociate only with its immediate family the young leaving\nThe\nof\nare\nblue or almost colorless. Their\nto fend for themselves as soon as\nmature, A family usually\nodor;\neyes\nwhite. Unlike\narctic creatures, the\nconsists of an adult male with one to three females and a 50%\nclaws and flesh are ivory\nmany\ndoes not have a thick\nof body fat to keep it warm\nIn-\nchance of 1-6 young if females are present. In an attacking group,\nstead, it relies upon the special properties of its thick, warm fur: It\nthe largest\nis the male, the next largest ones are his mates.\nsecond eyelid, which allows the creature to see\nothers are small males or females that are due to leave the\nhas a transparent\nin blowing snow, and prevents its eyes from freezing in extreme\nfamily soon.\ntemperatures.\nEcology:\nliving creature not of its family is considered po-\nCombat:\nThe\nis a fierce hunter of the\nregions. It stalks\ntential food, including other\nThis does not make them fool-\nits\nand\nan ambush, attempting to\nsurprise_\nA favor-\nhardy; only\nstarving\nwill attack\nan\nobviously stronger\nite Prickaisao\nahead of its prey and lie in a depression in the\nparty: Their typical diet consists of herd creatures, such as cari-\nSnow, or dig a shallow pit and cover itself with snow\nSuch works\nbou, bears, wolves, and other creatures inhabiting the snowy\ncan be detected only by natives of the arctic regions, and then\nmountains in which\nlive. The\nmay turn t0 scavenging in\nonly 25 % of the time. Against the snow\nthe\nis invisible due\nhard times\nrange across a wide area in search of food,\nusU=\nto its coloration until its prey is 10 yards away Under a thin\nally 15 miles in all directions from their lair:\ninvisible\nYeti claws and teeth have value only because of the rarity of the\nof snow it is completely\nsurprised\nmust save versus paralyza-\ncreature. They sell for about a\npiece a tooth or claw on the\ntion\ngorgienvith TPigted Or threetounds indicatingthat he has\nopen market. Yeti fur is another story: It is prized by those living\ntooked {otogie'\nblue depths of the\neyes.\nopponent\nin cold climates for its extraordinary ability to keep its wearer\nthat is paralyzed in this way can be automatically hit by both\nwarm. A full grown\ncan fetch up to 300 .\npieces on the\nclaws and squeezed\nopen market_\nAlthough the\ndoes have fangs (1-4 points of damage) , it\ndoes not usually attack with them , preferring to use its formida-\nble claws. If any hit with claws is made with a natural 20, the vic-\ntim is pulled in for a chilling squeeze. The creature s fur actually\nabsorbs heat, making it extraordinarily cold if contacted (2-16\npoints of damage if squeezed) . The heat-absorbing property of\nthe\nfur can work against it; damage from heat is 50 %\ngreater than normal.\nHabitat/Society:\nAlthough the\nis of average intelligence, it\nhas no civilization.\ncan use\nsimple tools, including man-\nVery\nDay\nyeti\ngreat\nlong,\nyeti\nyeti\nthey\ngreat\nfrom\nyeti\nThey\nyeti\nyeti\nyeti's\nyeti\nwill\nthey\nyeti\nicy\nlayer\nyeti\nyeti\nAny\nAny\nyeti.\npolar\nyeti\nyeti\ngain\nJays\nget\nyeti\nthey\nThey\nyeti\nlayer\ngold\nby\nyeti\nAny\nyeti's\nAny\nicy\ngold\npelt\nyeti\nyeti\nyeti's\nyeti\nThey",
  "climate_terrain": "Arctic hills and mountains",
  "frequency": "rare",
  "organization": "Clan",
  "diet": "Carnivore",
  "intelligence": "Average (8-10)",
  "treasure_type": "D",
  "alignment": "Neutral",
  "number_appearing": "1-6",
  "movement": "15",
  "hit_dice": "4+4",
  "thac0": "15",
  "damage": "1-6/1-6",
  "special_attacks": "Squeeze",
  "special_defenses": "Immune to normal cold,",
  "magic_resistance": "Nil",
  "size": "L (8' tall)",
  "morale": "Elite (13)",
  "xp_value": "420",
  "id": "yeti"
}