{
  "name": "Yuan-ti",
  "source_page": 143,
  "raw_text": "Yuan-ti\nCLIMATE TERRAIN:\nTropical jungles\nFREQUENCY:\nrare\nORGANIZATION:\nTribe or nation\nACTIVITY CYCLE:\nAny\nDIET:\nCarnivore\nINTELLIGENCE:\nGenius (17-18)\nTREASURE:\nC\nALIGNMENT:\nChaotic evil\nNO: APPEARING:\n1-4\nARMOR CLASS:\n4/0\nMOVEMENT:\n12, slither 0\nHIT DICE:\nTHACO:\n15 (6 HD)\n13 (7-8 HD) ,\n11 (9 HD)\nNO. OF ATTACKS:\nDAMAGEIATTACK:\nSee below\nSPECIAL ATTACKS:\nSpells\nSPECIAL DEFENSES:\nNil\nMAGIC RESISTANCE:\n20 %\nSIZE:\nM or L (10'\nMORALE:\nElite (14)\nAbominations\nChampion (15)\nXP VALUE:\nVariable\nDescendants of humans whose blood has been fouled, yuan-ti\nbefore the abominations. The group leader may order particular\nhave varying degrees of snakelike body parts .\nare\nhighly in -\nmembers forward before others if it provides for a better strategy:\ntelligent and evil, always plotting to advance their causes_\nWhen encountered outside their temple area, only one t0 four of\nThere\nare\nthree\nmajor\nvarieties\nof  yuan-ti:\npurebloods ,\nthem are in a group. In the temple area\ncan be found in much\nhalfbreeds, and abominations\nA pureblood can pass for human\ngroups.\n80% of the time. It has only slight differences from true humans,\nPurebloods have 6 Hit Dice, half-breeds have 7 or 8 Hit\nsuch as slit eyes,\nOT\nforked tongue,\nmaybe even small\nand abominations have\n9 Hit Dice. All yuan-ti, if\nhave\nHalfbreeds are\nhuman and part snake. Roll a d6 twice on the\nhands, always use weapons, preferring those with an edge.\ntable below;\nduplicate roll produces no result, but is not re-\nuse\npoison , particularly slow acting types, but in traps, not on\nrolled . Ignore unworkable combinations. This is a general guide;\nweapons.\nthe DM can invent his own combinations of snake and human.\nyuan-ti with\nhuman head can cast the following\nRoll\nFeature\nEffect\nonce per\ncause fear; darkness (15 foot radius), snake charm,\nSnake head\nBites for 1-10 points dam-\nsticks to snakes, neutralize poison, suggestion, and polymorph\nother;\nage\n2\nFlexible torso\n+1to saves\nusing Dexterity\nNo\nsnake tail\nConstricts\n1-4 points of\nHabitat Society:\nYuan-ti are devout\nworshippers of evil.\ndamage\nalso hold all reptiles in high esteem. The center of yuan-ti life is\nSnakes instead of arms\nEach bites for 1-6 points\nthe temple:\ntend toward old ruins far away from man, but\ndamage\nhave even been known t0 build underneath human cities_\nTheir\nScales instead of skin\nArmor Class 0\nown works tend toward circles, with ramps and poles replacing\nand a snake tail\nConstricts for 1-4 points of\nstairs. In all cases\nare secretive about the location of their\ndamage\nor\ntemple. The abominations rule over the yuan-ti, and are\nthe leaders of the temple, with the high priest (human headed) rul-\nAbominations are either all snake (50 %\nor have only a single hu-\nover all. Their rituals often involve bloody sacrifices. The\nman feature, either head or arms, and are of\nsize (10 feet\npurebloods take care of all outside negotiations, always pretend-\nHalfbreeds  and\nabominations\ndisdain   wearing human\nto be human. Yuan-ti speak their own language and common .\nclothing\nor  armor;\nwhile purebloods do not.\nAll yuan-ti\nuse\nweapons and other items\nYuan-ti do not give off an odor that hu-\nEcology:\nag0,\na cult of humans\nworshiping a reptilian el-\nmans can detect. However, animals will detect a dry, musty smell\nder\nrecieved a \"blessing'\nfrom their dark lord: their offspring\non them. The snake features of these foul creatures vary greatly\nall were part snake. Since then the breeding line has been polluted\nfrom simple green and brown scales to wild patterns of stripes, di-\nand mixed;\nproducing purebloods (those\nfavored) , half-\namonds, and whorls in reds and blues. Yuan-ti speak their own\nbreeds, and abominations (the truly blessed) . They are strictly\nlanguage.\ncan also speak with any snake or snakelike crea-\ncarnivorous, eating any warm-blooded creature\ncan catch,\nture\nThose with human heads speak common besides .\nhave\nspecial taste for birds and human flesh.\nare\nclever enough about their\nnot t0 overhunt any particular\nCombat:\nYuan-ti are geniuses, and fight as such.\nplan\nregion.\ngroups\ncaptive herds of wingless birds or\nelaborate traps and utilize their surroundings superbly in combat:\nother warm-blooded creatures.\nprefer ambushes to direct confrontation_\nIn\nmixed group,\nthe least valuable and powerful attack the opponent first. This\nmeans that the purebloods go before the half-breeds, which g0\nVery\nlong)\nThey\nthey\nlarger\nDice ,\nfangs\nthey\npart\nThey\nAny\nspells\nday;\nThey\nlegs,\nfor\nThey\nthey\nLegs\ncity\ning\nlarge\ning\nlong)\nAges\ngod\nleast\nthey\nThey\nThey\nThey\necology\nLarger\nkeep\nThey\nThey",
  "climate_terrain": "Tropical jungles",
  "frequency": "rare",
  "organization": "Tribe or nation",
  "activity_cycle": "Any",
  "diet": "Carnivore",
  "intelligence": "Genius (17-18)",
  "treasure_type": "C",
  "alignment": "Chaotic evil",
  "number_appearing": "1-4",
  "ac": "4/0",
  "movement": "12, slither 0",
  "thac0": "15 (6 HD)",
  "damage": "See below",
  "special_attacks": "Spells",
  "special_defenses": "Nil",
  "magic_resistance": "20 %",
  "size": "M or L (10'",
  "morale": "Elite (14)",
  "xp_value": "Variable",
  "id": "yuan_ti"
}